Workbook

Sheet About
A1: EIaE BAU Imported Electricity | B1: North Dakota | C1: 46185 | K1: Alabama | L1: AL | M1: EIA
A2: EIaE BAU Exported Electricity | B2: =LOOKUP(B1,K1:L50,L1:L50) -> ND | K2: Alaska | L2: AK | M2: EIA
A3: EIaE Imported Electricity Price | K3: Arizona | L3: AZ | M3: EIA
A4: EIaE BAU Exported Electricity Price | K4: Arkansas | L4: AR | M4: EIA
K5: California | L5: CA | M5: EIA
A6: Source: | B6: Quantity of Imports and Exports | K6: Colorado | L6: CO | M6: EIA
B7: Energy Information Administration | E7: State Imports Weighted by Fuel Mix of External States | K7: Connecticut | L7: CT | M7: EIA
B8: 2024 | E8: From EPS Outputs from TCAMRB | K8: Delaware | L8: DE | M8: EIA
B9: Annual Energy Outlook 2021 and 2022 | E9: ReEDs generation by resource (Mid-case) | K9: Florida | L9: FL | M9: EIA
B10: https://www.eia.gov/outlooks/aeo/tables_side.php | K10: Georgia | L10: GA | M10: EIA
B11: Table 10 | K11: Hawaii | L11: HI | M11: EIA
K12: Idaho | L12: ID | M12: EIA
B13: Canadian Electricity Generation by Type | K13: Illinois | L13: IL | M13: EIA
B14: National Energy Board, Government of Canada | E14: Imports and Export EIA SEDS | K14: Indiana | L14: IN | M14: EIA
B15: 2024 | E15: Energy Information Administration | K15: Iowa | L15: IA | M15: EIA
B16: Canada's Energy Future 2021, Appendices | E16: 2024 | K16: Kansas | L16: KS | M16: EIA
B17: https://apps.neb-one.gc.ca/ftrppndc/dflt.aspx?GoCTemplateCulture=en-CA | E17: Example Link: https://www.eia.gov/electricity/state/virginia/state_tables.php | K17: Kentucky | L17: KY | M17: EIA
B18: Table "Electricity Generation," Reference Case, Canada | E18: Tab 10: Imports and Exports (lines 15,28) | K18: Louisiana | L18: LA | M18: EIA
K19: Maine | L19: ME | M19: EIA
B20: Imported and Exported Electricity Prices | K20: Maryland | L20: MD | M20: EIA
B21: Energy Information Administration | E21: Mexican Electricity Generation by Type | K21: Massachusetts | L21: MA | M21: EIA
B22: May 2026 | E22: Energy Information Agency | K22: Michigan | L22: MI | M22: EIA
B23: Short-Term Energy Outlook | E23: 2016 | K23: Minnesota | L23: MN | M23: EIA
B24: https://www.eia.gov/outlooks/steo/tables/pdf/7atab.pdf | E24: Mexico Analysis | K24: Mississippi | L24: MS | M24: EIA
B25: Table 7 | E25: https://www.eia.gov/international/analysis/country/MEX | K25: Missouri | L25: MO | M25: EIA
E26: Table 12, 14 | K26: Montana | L26: MT | M26: EIA
B27: Canada NG Generation by Turbine Type | K27: Nebraska | L27: NE | M27: EIA
B28: Statistics Canada | K28: Nevada | L28: NV | M28: EIA
B29: 2022 | K29: New Hampshire | L29: NH | M29: EIA
B30: Electric power generation, monthly generation by type of electricity | K30: New Jersey | L30: NJ | M30: EIA
B31: https://www150.statcan.gc.ca/t1/tbl1/en/tv.action?pid=2510001501&pickMembers%5B0%5D=1.1&pickMembers%5B1%5D=2.2&cubeTimeFrame.startMonth=01&cubeTimeFrame.startYear=2015&cubeTimeFrame.endMonth=12&cubeTimeFrame.endYear=2015&referencePeriods=20150101%2C20151201 | K31: New Mexico | L31: NM | M31: EIA
B32: Data after 2015 does not break out turbine types, so we use data from 2015. | K32: New York | L32: NY | M32: EIA
K33: North Carolina | L33: NC | M33: EIA
B34: NREL REEDS Scenario Viewer | K34: North Dakota | L34: ND | M34: EIA
B35: NREL | K35: Ohio | L35: OH | M35: EIA
B36: 2023 | K36: Oklahoma | L36: OK | M36: EIA
B37: Cambium 2022 Mid-Case | K37: Oregon | L37: OR | M37: EIA
B38: https://scenarioviewer.nrel.gov/?project=82460f06-548c-4954-b2d9-b84ba92d63e2&mode=download&layout=Default | K38: Pennsylvania | L38: PA | M38: EIA
K39: Rhode Island | L39: RI | M39: EIA
K40: South Carolina | L40: SC | M40: EIA
K41: South Dakota | L41: SD | M41: EIA
A42: Notes | K42: Tennessee | L42: TN | M42: EIA
A43: West Virginia: adjusted to reduce exports when coal power plants retire | K43: Texas | L43: TX | M43: EIA
K44: Utah | L44: UT | M44: EIA
A45: We need to know the mix of imported electricity types if we will be including | K45: Vermont | L45: VT | M45: EIA
A46: pollutant emissions associated with imported electricity into the totals, which | K46: Virginia | L46: VA | M46: EIA
A47: is managed by a control lever. If these emissions will not be included in the | K47: Washington | L47: WA | M47: EIA
A48: emissions totals, the breakdown is unimportant, and you may assign all | K48: West Virginia | L48: WV | M48: EIA
A49: imported electricity emissions to any one electricity source, if you prefer. | K49: Wisconsin | L49: WI | M49: EIA
K50: Wyoming | L50: WY | M50: EIA
A51: Electricity exports are supplied by power plants in the modeled region and
A52: hence do not need their electricity source to be specified here.
A54: Since electricity imported to the U.S. comes overwhelmingly from Canada,
A55: we use Canada's electricity generation mix to approximate the mix
A56: of all imported electricity.
A58: All Canadian natural gas was assigned to the "natural gas nonpeaker" plant type
A59: because the breakdown between NG peaker and NG nonpeaker for imported
A60: electricity is not important.
A62: Electricity Prices
A63: We do not have explicit data on the prices of electricity imported to or exported
A64: from the United States (i.e. via transmission lines to Canada and Mexico), so we
A65: use the average U.S. electricity price to all consumers from AEO Table 3.
A67: Conversion Factors
A68: 2.931e-07 | B68: MWh/BTU
A69: 0.88711067 | B69: 2012 USD/2020 USD
A70: 0.84730413 | B70: 2012 USD/2021 USD
A71: 0.75350342 | B71: 2012 USD/2023 USD
A72: 0.74296375 | B72: 2012 USD/2024 USD
A73: 0.72252462 | B73: 2012 USD/2025 USD
A74: weighed by the capacity of transmission available between each surrounding state. Only states that are net exporters are qualified.
A76: More detailed documentation of this data can be found in SYC (Start Year Capacity)
A77: and TCAMRB (Transmission Capacity Across Modeled Border Region)
A79: State Import and Export Prices (VA ONLY)
A80: Prices are equivalent for imports and exports, with changes over time derived from the national AEO projections
A81: Wholesale prices are approximated by taking the average retail price and the national fraction of generation costs versus transmission and distribution
A83: International Imports/Exports
A85: Canadian and mexican imports are approximated based on their aggregate generation mix.
A86: Attribute NM, AZ, and NV imports are attributed to the average energy generation profile of Mexico

Sheet Table 7_Wholesale prices
A1: Wholesale Electricity Prices (dollars per megawatthour) | B1: 2025$ | F1: 2012$
B2: 2025 | C2: 2026 | D2: 2027 | F2: 2025 | G2: 2026 | H2: 2027
A3: ERCOT | B3: 37.33 | C3: 37.61 | D3: 39.44 | F3: =B3*About!$A$73 -> 26.971844 | G3: =C3*About!$A$73 -> 27.174151 | H3: =D3*About!$A$73 -> 28.496371
A4: CAISO | B4: 28.56 | C4: 23.01 | D4: 25.86 | F4: =B4*About!$A$73 -> 20.635303 | G4: =C4*About!$A$73 -> 16.625291 | H4: =D4*About!$A$73 -> 18.684487
A5: ISO-NE | B5: 75.58 | C5: 72.09 | D5: 55.03 | F5: =B5*About!$A$73 -> 54.608411 | G5: =C5*About!$A$73 -> 52.0868 | H5: =D5*About!$A$73 -> 39.76053
A6: NYISO | B6: 72.1 | C6: 74.28 | D6: 57.96 | F6: =B6*About!$A$73 -> 52.094025 | G6: =C6*About!$A$73 -> 53.669129 | H6: =D6*About!$A$73 -> 41.877527
A7: PJM | B7: 60.09 | C7: 73.16 | D7: 67.35 | F7: =B7*About!$A$73 -> 43.416504 | G7: =C7*About!$A$73 -> 52.859901 | H7: =D7*About!$A$73 -> 48.662033
A8: MISO | B8: 46.82 | C8: 46.21 | D8: 45.05 | F8: =B8*About!$A$73 -> 33.828603 | G8: =C8*About!$A$73 -> 33.387863 | H8: =D8*About!$A$73 -> 32.549734
A9: SPP | B9: 37.91 | C9: 34.42 | D9: 34.26 | F9: =B9*About!$A$73 -> 27.390908 | G9: =C9*About!$A$73 -> 24.869297 | H9: =D9*About!$A$73 -> 24.753693
A10: SERC | B10: 41.41 | C10: 44.42 | D10: 41.3 | F10: =B10*About!$A$73 -> 29.919744 | G10: =C10*About!$A$73 -> 32.094544 | H10: =D10*About!$A$73 -> 29.840267
A11: FRCC | B11: 44.6 | C11: 47.32 | D11: 42 | F11: =B11*About!$A$73 -> 32.224598 | G11: =C11*About!$A$73 -> 34.189865 | H11: =D11*About!$A$73 -> 30.346034
A12: Northwest | B12: 45.57 | C12: 28.63 | D12: 29.7 | F12: =B12*About!$A$73 -> 32.925447 | G12: =C12*About!$A$73 -> 20.68588 | H12: =D12*About!$A$73 -> 21.458981
A13: Southwest | B13: 31.43 | C13: 25.37 | D13: 28.43 | F13: =B13*About!$A$73 -> 22.708949 | G13: =C13*About!$A$73 -> 18.33045 | H13: =D13*About!$A$73 -> 20.541375
D17: 2025 | E17: 2026 | F17: 2027
A18: Alabama | B18: AL | C18: SERC | D18: =SUMIFS(F$3:F$13,$A$3:$A$13,$C18) -> 29.919744 | E18: =SUMIFS(G$3:G$13,$A$3:$A$13,$C18) -> 32.094544 | F18: =SUMIFS(H$3:H$13,$A$3:$A$13,$C18) -> 29.840267
A19: Arizona | B19: AZ | C19: Southwest | D19: =SUMIFS(F$3:F$13,$A$3:$A$13,$C19) -> 22.708949 | E19: =SUMIFS(G$3:G$13,$A$3:$A$13,$C19) -> 18.33045 | F19: =SUMIFS(H$3:H$13,$A$3:$A$13,$C19) -> 20.541375
A20: Arkansas | B20: AR | C20: MISO | D20: =SUMIFS(F$3:F$13,$A$3:$A$13,$C20) -> 33.828603 | E20: =SUMIFS(G$3:G$13,$A$3:$A$13,$C20) -> 33.387863 | F20: =SUMIFS(H$3:H$13,$A$3:$A$13,$C20) -> 32.549734
A21: California | B21: CA | C21: CAISO | D21: =SUMIFS(F$3:F$13,$A$3:$A$13,$C21) -> 20.635303 | E21: =SUMIFS(G$3:G$13,$A$3:$A$13,$C21) -> 16.625291 | F21: =SUMIFS(H$3:H$13,$A$3:$A$13,$C21) -> 18.684487
A22: Colorado | B22: CO | C22: Southwest | D22: =SUMIFS(F$3:F$13,$A$3:$A$13,$C22) -> 22.708949 | E22: =SUMIFS(G$3:G$13,$A$3:$A$13,$C22) -> 18.33045 | F22: =SUMIFS(H$3:H$13,$A$3:$A$13,$C22) -> 20.541375
A23: Connecticut | B23: CT | C23: ISO-NE | D23: =SUMIFS(F$3:F$13,$A$3:$A$13,$C23) -> 54.608411 | E23: =SUMIFS(G$3:G$13,$A$3:$A$13,$C23) -> 52.0868 | F23: =SUMIFS(H$3:H$13,$A$3:$A$13,$C23) -> 39.76053
A24: Delaware | B24: DE | C24: PJM | D24: =SUMIFS(F$3:F$13,$A$3:$A$13,$C24) -> 43.416504 | E24: =SUMIFS(G$3:G$13,$A$3:$A$13,$C24) -> 52.859901 | F24: =SUMIFS(H$3:H$13,$A$3:$A$13,$C24) -> 48.662033
A25: Florida | B25: FL | C25: SERC | D25: =SUMIFS(F$3:F$13,$A$3:$A$13,$C25) -> 29.919744 | E25: =SUMIFS(G$3:G$13,$A$3:$A$13,$C25) -> 32.094544 | F25: =SUMIFS(H$3:H$13,$A$3:$A$13,$C25) -> 29.840267
A26: Georgia | B26: GA | C26: SERC | D26: =SUMIFS(F$3:F$13,$A$3:$A$13,$C26) -> 29.919744 | E26: =SUMIFS(G$3:G$13,$A$3:$A$13,$C26) -> 32.094544 | F26: =SUMIFS(H$3:H$13,$A$3:$A$13,$C26) -> 29.840267
A27: Idaho | B27: ID | C27: Northwest | D27: =SUMIFS(F$3:F$13,$A$3:$A$13,$C27) -> 32.925447 | E27: =SUMIFS(G$3:G$13,$A$3:$A$13,$C27) -> 20.68588 | F27: =SUMIFS(H$3:H$13,$A$3:$A$13,$C27) -> 21.458981
A28: Illinois | B28: IL | C28: MISO | D28: =SUMIFS(F$3:F$13,$A$3:$A$13,$C28) -> 33.828603 | E28: =SUMIFS(G$3:G$13,$A$3:$A$13,$C28) -> 33.387863 | F28: =SUMIFS(H$3:H$13,$A$3:$A$13,$C28) -> 32.549734
A29: Indiana | B29: IN | C29: MISO | D29: =SUMIFS(F$3:F$13,$A$3:$A$13,$C29) -> 33.828603 | E29: =SUMIFS(G$3:G$13,$A$3:$A$13,$C29) -> 33.387863 | F29: =SUMIFS(H$3:H$13,$A$3:$A$13,$C29) -> 32.549734
... A65: Wyoming | B65: WY | C65: Northwest | D65: =SUMIFS(F$3:F$13,$A$3:$A$13,$C65) -> 32.925447 | E65: =SUMIFS(G$3:G$13,$A$3:$A$13,$C65) -> 20.68588 | F65: =SUMIFS(H$3:H$13,$A$3:$A$13,$C65) -> 21.458981

Sheet Intl Imports
D1: Import Mexico? | E1: Import from Canada?
B2: Alabama | C2: AL | D2: FALSE | E2: FALSE
B3: Alaska | C3: AK | D3: FALSE | E3: FALSE
B4: Arizona | C4: AZ | D4: FALSE | E4: FALSE
B5: Arkansas | C5: AR | D5: FALSE | E5: FALSE
B6: California | C6: CA | D6: TRUE | E6: FALSE
B7: Colorado | C7: CO | D7: FALSE | E7: FALSE
B8: Connecticut | C8: CT | D8: FALSE | E8: FALSE
B9: Delaware | C9: DE | D9: FALSE | E9: FALSE
B10: Florida | C10: FL | D10: FALSE | E10: FALSE
B11: Georgia | C11: GA | D11: FALSE | E11: FALSE
B12: Hawaii | C12: HI | D12: FALSE | E12: FALSE
B13: Idaho | C13: ID | D13: FALSE | E13: FALSE
... B51: Wyoming | C51: WY | D51: FALSE | E51: FALSE

Sheet IRA-BIL_IRA-BIL - Mid_annual_st
W1: =INDEX('REEDS crosswalk'!$C:$C,MATCH(W$2,'REEDS crosswalk'!$B:$B,0)) -> battery | X1: =INDEX('REEDS crosswalk'!$C:$C,MATCH(X$2,'REEDS crosswalk'!$B:$B,0)) -> biomass | Y1: =INDEX('REEDS crosswalk'!$C:$C,MATCH(Y$2,'REEDS crosswalk'!$B:$B,0)) -> 0 | Z1: =INDEX('REEDS crosswalk'!$C:$C,MATCH(Z$2,'REEDS crosswalk'!$B:$B,0)) -> hard coal | AA1: =INDEX('REEDS crosswalk'!$C:$C,MATCH(AA$2,'REEDS crosswalk'!$B:$B,0)) -> hard coal | AB1: =INDEX('REEDS crosswalk'!$C:$C,MATCH(AB$2,'REEDS crosswalk'!$B:$B,0)) -> solar pv | AC1: =INDEX('REEDS crosswalk'!$C:$C,MATCH(AC$2,'REEDS crosswalk'!$B:$B,0)) -> 0 | AD1: =INDEX('REEDS crosswalk'!$C:$C,MATCH(AD$2,'REEDS crosswalk'!$B:$B,0)) -> natural gas steam turbine | ... AR1: =INDEX('REEDS crosswalk'!$C:$C,MATCH(AR$2,'REEDS crosswalk'!$B:$B,0)) -> 0
A2: state year | B2: state | C2: t | D2: battery_MW | E2: bio_MW | F2: coal_ccs_MW | G2: coal_MW | H2: csp_MW | I2: distpv_MW | J2: gas_cc_ccs_MW | K2: gas_cc_MW | L2: gas_ct_MW | M2: geo_MW | N2: hydro_MW | O2: nuclear_MW | P2: nuclear_smr_MW | Q2: o-g-s_MW | R2: pumped-hydro_MW | S2: re_ct_MW | T2: upv_MW | U2: wind_offshore_MW | V2: wind_onshore_MW | W2: battery_MWh | X2: bio_MWh | Y2: canada_MWh | Z2: coal_ccs_MWh | AA2: coal_MWh | AB2: csp_MWh | AC2: distpv_MWh | AD2: gas_cc_ccs_MWh | AE2: gas_cc_MWh | AF2: gas_ct_MWh | AG2: geo_MWh | AH2: hydro_MWh | AI2: nuclear_MWh | AJ2: nuclear_smr_MWh | AK2: o-g-s_MWh | AL2: pumped-hydro_MWh | AM2: re_ct_MWh | AN2: upv_MWh | AO2: wind_offshore_MWh | AP2: wind_onshore_MWh | AQ2: generation | AR2: co2_c_mmt
A3: =B3&"_"&C3 -> AL_2022 | B3: AL | C3: 2022 | D3: 0 | E3: 6.4 | F3: 0 | G3: 5790.7 | H3: 0 | I3: 31.2 | J3: 0 | K3: 9689 | L3: 2618.2 | M3: 0 | N3: 3334 | O3: 5544.5 | P3: 0 | Q3: 1738.7 | R3: 0 | S3: 0 | T3: 673.9 | U3: 0 | V3: 0 | W3: 0 | X3: 29415 | Y3: 0 | Z3: 0 | AA3: 33823351 | AB3: 0 | AC3: 47339 | AD3: 0 | AE3: 38649334 | AF3: 1743037 | AG3: 0 | AH3: 9704302 | AI3: 44519210 | AJ3: 0 | AK3: 1243712 | AL3: 0 | AM3: 0 | AN3: 1208752 | AO3: 0 | AP3: 0 | AQ3: 130968453 | AR3: 52
A4: =B4&"_"&C4 -> AL_2023 | B4: AL | C4: 2023 | D4: 0 | E4: 6.4 | F4: 0 | G4: 5790.7 | H4: 0 | I4: 46.8 | J4: 0 | K4: 11004 | L4: 2618.2 | M4: 0 | N4: 3334 | O4: 5544.5 | P4: 0 | Q4: 1738.7 | R4: 0 | S4: 0 | T4: 753.6 | U4: 0 | V4: 0 | W4: 0 | X4: 29415 | Y4: 0 | Z4: 0 | AA4: 32487520 | AB4: 0 | AC4: 70959 | AD4: 0 | AE4: 56967892 | AF4: 1990173 | AG4: 0 | AH4: 9703029 | AI4: 44519210 | AJ4: 0 | AK4: 1402943 | AL4: 0 | AM4: 0 | AN4: 1577345 | AO4: 0 | AP4: 0 | AQ4: 148748486 | AR4: 57.8
A5: =B5&"_"&C5 -> AL_2024 | B5: AL | C5: 2024 | D5: 0 | E5: 6.4 | F5: 0 | G5: 5750.2 | H5: 0 | I5: 62.4 | J5: 0 | K5: 11004 | L5: 1415 | M5: 0 | N5: 3337.2 | O5: 5544.5 | P5: 0 | Q5: 413.8 | R5: 0 | S5: 0 | T5: 757.2 | U5: 0 | V5: 0 | W5: 0 | X5: 29415 | Y5: 0 | Z5: 0 | AA5: 32487156 | AB5: 0 | AC5: 94580 | AD5: 0 | AE5: 63535342 | AF5: 1882275 | AG5: 0 | AH5: 9713363 | AI5: 44519210 | AJ5: 0 | AK5: 441841 | AL5: 0 | AM5: 0 | AN5: 1708516 | AO5: 0 | AP5: 0 | AQ5: 154411698 | AR5: 59.8
A6: =B6&"_"&C6 -> AL_2025 | B6: AL | C6: 2025 | D6: 0 | E6: 6.4 | F6: 3.1 | G6: 5697.6 | H6: 0 | I6: 107.8 | J6: 4.6 | K6: 10996.1 | L6: 1415 | M6: 0 | N6: 3425.3 | O6: 5544.5 | P6: 0 | Q6: 413.8 | R6: 0 | S6: 0 | T6: 758 | U6: 0 | V6: 0 | W6: 0 | X6: 29415 | Y6: 0 | Z6: 20504 | AA6: 32081701 | AB6: 0 | AC6: 163384 | AD6: 30115 | AE6: 59563016 | AF6: 2054863 | AG6: 0 | AH6: 10024547 | AI6: 44519210 | AJ6: 0 | AK6: 472991 | AL6: 0 | AM6: 0 | AN6: 1719481 | AO6: 0 | AP6: 0 | AQ6: 150679227 | AR6: 57.8
A7: =B7&"_"&C7 -> AL_2026 | B7: AL | C7: 2026 | D7: 3.1 | E7: 6.4 | F7: 6.2 | G7: 5643.9 | H7: 0 | I7: 153.2 | J7: 9.2 | K7: 10988.2 | L7: 1415 | M7: 0 | N7: 3428.5 | O7: 5544.5 | P7: 0 | Q7: 413.8 | R7: 0 | S7: 0 | T7: 1606.7 | U7: 0 | V7: 0 | W7: -1439 | X7: 29415 | Y7: 0 | Z7: 41007 | AA7: 31528190 | AB7: 0 | AC7: 95463 | AD7: 60230 | AE7: 52709144 | AF7: 2723312 | AG7: 0 | AH7: 10034680 | AI7: 44519210 | AJ7: 0 | AK7: 685367 | AL7: 0 | AM7: 0 | AN7: 2801553 | AO7: 0 | AP7: 0 | AQ7: 145226132 | AR7: 55
A8: =B8&"_"&C8 -> AL_2027 | B8: AL | C8: 2027 | D8: 61.6 | E8: 6.4 | F8: 9.4 | G8: 5581.4 | H8: 0 | I8: 263.4 | J8: 13.7 | K8: 10969.7 | L8: 1415 | M8: 0 | N8: 3461.7 | O8: 5544.5 | P8: 0 | Q8: 413.8 | R8: 0 | S8: 0 | T8: 3351 | U8: 0 | V8: 0 | W8: -26160 | X8: 29415 | Y8: 0 | Z8: 61511 | AA8: 29644436 | AB8: 0 | AC8: 2783 | AD8: 90345 | AE8: 48386136 | AF8: 2805653 | AG8: 0 | AH8: 10141830 | AI8: 44519210 | AJ8: 0 | AK8: 695939 | AL8: 0 | AM8: 0 | AN8: 6098368 | AO8: 0 | AP8: 0 | AQ8: 142449466 | AR8: 51.4
A9: =B9&"_"&C9 -> AL_2028 | B9: AL | C9: 2028 | D9: 450.2 | E9: 6.4 | F9: 3351.4 | G9: 1342.7 | H9: 0 | I9: 373.6 | J9: 18.3 | K9: 10951.2 | L9: 1415 | M9: 0 | N9: 3486.9 | O9: 5544.5 | P9: 0 | Q9: 413.8 | R9: 0 | S9: 0 | T9: 4790.9 | U9: 0 | V9: 0 | W9: -193341 | X9: 29415 | Y9: 0 | Z9: 23768654 | AA9: 1957399 | AB9: 0 | AC9: 445155 | AD9: 120461 | AE9: 39980532 | AF9: 3306552 | AG9: 0 | AH9: 10194938 | AI9: 44519210 | AJ9: 0 | AK9: 1121991 | AL9: 0 | AM9: 0 | AN9: 10000893 | AO9: 0 | AP9: 0 | AQ9: 135251859 | AR9: 23.7
A10: =B10&"_"&C10 -> AL_2029 | B10: AL | C10: 2029 | D10: 501.7 | E10: 6.4 | F10: 3524.5 | G10: 1326.4 | H10: 0 | I10: 572.1 | J10: 18.3 | K10: 10940.2 | L10: 1415 | M10: 0 | N10: 3490 | O10: 5544.5 | P10: 0 | Q10: 413.8 | R10: 0 | S10: 0 | T10: 8085.4 | U10: 0 | V10: 0 | W10: -150763 | X10: 29415 | Y10: 0 | Z10: 24996353 | AA10: 2293425 | AB10: 0 | AC10: 657804 | AD10: 120461 | AE10: 34593311 | AF10: 4535810 | AG10: 0 | AH10: 10201313 | AI10: 44519210 | AJ10: 0 | AK10: 909000 | AL10: 0 | AM10: 0 | AN10: 17513523 | AO10: 0 | AP10: 0 | AQ10: 140218861 | AR10: 22.6
A11: =B11&"_"&C11 -> AL_2030 | B11: AL | C11: 2030 | D11: 704.6 | E11: 6.4 | F11: 3524.5 | G11: 1306.1 | H11: 0 | I11: 770.5 | J11: 18.3 | K11: 10889.2 | L11: 1415 | M11: 0 | N11: 3493.2 | O11: 5544.5 | P11: 0 | Q11: 413.8 | R11: 0 | S11: 0 | T11: 9523 | U11: 0 | V11: 0 | W11: -255395 | X11: 29415 | Y11: 0 | Z11: 24996353 | AA11: 3113993 | AB11: 0 | AC11: 942856 | AD11: 120461 | AE11: 21979273 | AF11: 4215241 | AG11: 0 | AH11: 10213940 | AI11: 44519210 | AJ11: 0 | AK11: 1086251 | AL11: 0 | AM11: 0 | AN11: 21062677 | AO11: 0 | AP11: 0 | AQ11: 132024275 | AR11: 18.3
A12: =B12&"_"&C12 -> AR_2022 | B12: AR | C12: 2022 | D12: 0 | E12: 16.8 | F12: 0 | G12: 5128.1 | H12: 0 | I12: 87.6 | J12: 0 | K12: 4597 | L12: 715.6 | M12: 0 | N12: 1265.8 | O12: 1817.8 | P12: 0 | Q12: 787 | R12: 30 | S12: 0 | T12: 306.7 | U12: 0 | V12: 0 | W12: 0 | X12: 40369 | Y12: 0 | Z12: 0 | AA12: 29909120 | AB12: 0 | AC12: 129118 | AD12: 0 | AE12: 11577177 | AF12: 789123 | AG12: 0 | AH12: 2917131 | AI12: 14613013 | AJ12: 0 | AK12: 281525 | AL12: -6597 | AM12: 0 | AN12: 573458 | AO12: 0 | AP12: 0 | AQ12: 60823436 | AR12: 35.8
A13: =B13&"_"&C13 -> AR_2023 | B13: AR | C13: 2023 | D13: 0 | E13: 16.8 | F13: 0 | G13: 5128.1 | H13: 0 | I13: 181 | J13: 0 | K13: 4597 | L13: 715.6 | M13: 0 | N13: 1265.8 | O13: 1817.8 | P13: 0 | Q13: 787 | R13: 30 | S13: 0 | T13: 306.7 | U13: 0 | V13: 0 | W13: 0 | X13: 40369 | Y13: 0 | Z13: 0 | AA13: 15368075 | AB13: 0 | AC13: 266673 | AD13: 0 | AE13: 11735490 | AF13: 924812 | AG13: 0 | AH13: 2917131 | AI13: 14613013 | AJ13: 0 | AK13: 281525 | AL13: -4914 | AM13: 0 | AN13: 674270 | AO13: 0 | AP13: 0 | AQ13: 46816445 | AR13: 20.5
A14: =B14&"_"&C14 -> AR_2024 | B14: AR | C14: 2024 | D14: 0 | E14: 16.8 | F14: 0 | G14: 5124.4 | H14: 0 | I14: 274.4 | J14: 0 | K14: 4597 | L14: 705.4 | M14: 0 | N14: 1266.8 | O14: 1817.8 | P14: 0 | Q14: 352.4 | R14: 30 | S14: 0 | T14: 455.2 | U14: 0 | V14: 0 | W14: 0 | X14: 40369 | Y14: 0 | Z14: 0 | AA14: 13411216 | AB14: 0 | AC14: 383985 | AD14: 0 | AE14: 12566671 | AF14: 800487 | AG14: 0 | AH14: 2919630 | AI14: 14613013 | AJ14: 0 | AK14: 150536 | AL14: -4361 | AM14: 0 | AN14: 990857 | AO14: 0 | AP14: 0 | AQ14: 45872404 | AR14: 18.7
... A434: =B434&"_"&C434 -> WY_2030 | B434: WY | C434: 2030 | D434: 200.9 | E434: 0 | F434: 1550.5 | G434: 2419.2 | H434: 0 | I434: 37.5 | J434: 36.6 | K434: 93.4 | L434: 0 | M434: 0 | N434: 307.4 | O434: 0 | P434: 345 | Q434: 0 | R434: 0 | S434: 0 | T434: 92 | U434: 0 | V434: 17550.3 | W434: -44004 | X434: 0 | Y434: 0 | Z434: 10996147 | AA434: 1396334 | AB434: 0 | AC434: 43766 | AD434: 240921 | AE434: 56414 | AF434: 0 | AG434: 0 | AH434: 1037875 | AI434: 0 | AJ434: 1969158 | AK434: 0 | AL434: 0 | AM434: 0 | AN434: 139007 | AO434: 0 | AP434: 69156087 | AQ434: 84991706 | AR434: 3.1

Sheet REEDS crosswalk
B2: state
B3: t
B4: battery_MW | C4: battery
B5: bio_MW | C5: biomass
B6: coal_ccs_MW | C6: hard coal
B7: coal_MW | C7: hard coal
B8: csp_MW | C8: solar pv
B9: distpv_MW
B10: gas_cc_ccs_MW | C10: natural gas steam turbine
B11: gas_cc_MW | C11: natural gas steam turbine
B12: gas_ct_MW | C12: natural gas steam turbine
B13: geo_MW | C13: geothermal
B14: hydro_MW | C14: hydro
B15: nuclear_MW | C15: nuclear
B16: nuclear_smr_MW | C16: nuclear
B17: o-g-s_MW | C17: petroleum
B18: pumped-hydro_MW | C18: pumped hydro
B19: re_ct_MW
B20: upv_MW | C20: solar pv
B21: wind_offshore_MW | C21: offshore wind
B22: wind_onshore_MW | C22: onshore wind
B23: battery_MWh | C23: battery
B24: bio_MWh | C24: biomass
B25: canada_MWh
B26: coal_ccs_MWh | C26: hard coal
B27: coal_MWh | C27: hard coal
B28: csp_MWh | C28: solar pv
B29: distpv_MWh
B30: gas_cc_ccs_MWh | C30: natural gas steam turbine
B31: gas_cc_MWh | C31: natural gas steam turbine
B32: gas_ct_MWh | C32: natural gas steam turbine
B33: geo_MWh | C33: geothermal
B34: hydro_MWh | C34: hydro
B35: nuclear_MWh | C35: nuclear
B36: nuclear_smr_MWh | C36: nuclear
B37: o-g-s_MWh | C37: petroleum
B38: pumped-hydro_MWh | C38: pumped hydro
B39: re_ct_MWh
B40: upv_MWh | C40: solar pv
B41: wind_offshore_MWh | C41: offshore wind
B42: wind_onshore_MWh | C42: onshore wind
B43: generation
B44: co2_c_mmt

Sheet REEDS summary
A1: REEDS Data Summarized | M1: Percent of Total
A2: AL | C2: =$A2&"_"&C3 -> AL_2022 | D2: =$A2&"_"&D3 -> AL_2023 | E2: =$A2&"_"&E3 -> AL_2024 | F2: =$A2&"_"&F3 -> AL_2025 | G2: =$A2&"_"&G3 -> AL_2026 | H2: =$A2&"_"&H3 -> AL_2027 | I2: =$A2&"_"&I3 -> AL_2028 | J2: =$A2&"_"&J3 -> AL_2029 | K2: =$A2&"_"&K3 -> AL_2030 | M2: =$A2&"_"&M3 -> AL_2022 | N2: =$A2&"_"&N3 -> AL_2023 | O2: =$A2&"_"&O3 -> AL_2024 | P2: =$A2&"_"&P3 -> AL_2025 | Q2: =$A2&"_"&Q3 -> AL_2026 | R2: =$A2&"_"&R3 -> AL_2027 | S2: =$A2&"_"&S3 -> AL_2028 | T2: =$A2&"_"&T3 -> AL_2029 | U2: =$A2&"_"&U3 -> AL_2030
C3: 2022 | D3: 2023 | E3: 2024 | F3: 2025 | G3: 2026 | H3: 2027 | I3: 2028 | J3: 2029 | K3: 2030 | M3: 2022 | N3: 2023 | O3: 2024 | P3: 2025 | Q3: 2026 | R3: 2027 | S3: 2028 | T3: 2029 | U3: 2030
A4: =A2 -> AL | B4: battery | C4: 0 | D4: 0 | E4: 0 | F4: 0 | G4: 0 | H4: 0 | I4: 0 | J4: 0 | K4: 0 | M4: 0 | N4: 0 | O4: 0 | P4: 0 | Q4: 0 | R4: 0 | S4: 0 | T4: 0 | U4: 0
A5: =A4 -> AL | B5: biomass | C5: =SUMIFS(INDEX('IRA-BIL_IRA-BIL - Mid_annual_st'!$W$3:$AR$434,MATCH(C2,'IRA-BIL_IRA-BIL - Mid_annual_st'!$A$3:$A$434,0),),'IRA-BIL_IRA-BIL - Mid_annual_st'!$W$1:$AR$1,$B5) -> 29415 | D5: =SUMIFS(INDEX('IRA-BIL_IRA-BIL - Mid_annual_st'!$W$3:$AR$434,MATCH(D2,'IRA-BIL_IRA-BIL - Mid_annual_st'!$A$3:$A$434,0),),'IRA-BIL_IRA-BIL - Mid_annual_st'!$W$1:$AR$1,$B5) -> 29415 | E5: =SUMIFS(INDEX('IRA-BIL_IRA-BIL - Mid_annual_st'!$W$3:$AR$434,MATCH(E2,'IRA-BIL_IRA-BIL - Mid_annual_st'!$A$3:$A$434,0),),'IRA-BIL_IRA-BIL - Mid_annual_st'!$W$1:$AR$1,$B5) -> 29415 | F5: =SUMIFS(INDEX('IRA-BIL_IRA-BIL - Mid_annual_st'!$W$3:$AR$434,MATCH(F2,'IRA-BIL_IRA-BIL - Mid_annual_st'!$A$3:$A$434,0),),'IRA-BIL_IRA-BIL - Mid_annual_st'!$W$1:$AR$1,$B5) -> 29415 | G5: =SUMIFS(INDEX('IRA-BIL_IRA-BIL - Mid_annual_st'!$W$3:$AR$434,MATCH(G2,'IRA-BIL_IRA-BIL - Mid_annual_st'!$A$3:$A$434,0),),'IRA-BIL_IRA-BIL - Mid_annual_st'!$W$1:$AR$1,$B5) -> 29415 | H5: =SUMIFS(INDEX('IRA-BIL_IRA-BIL - Mid_annual_st'!$W$3:$AR$434,MATCH(H2,'IRA-BIL_IRA-BIL - Mid_annual_st'!$A$3:$A$434,0),),'IRA-BIL_IRA-BIL - Mid_annual_st'!$W$1:$AR$1,$B5) -> 29415 | I5: =SUMIFS(INDEX('IRA-BIL_IRA-BIL - Mid_annual_st'!$W$3:$AR$434,MATCH(I2,'IRA-BIL_IRA-BIL - Mid_annual_st'!$A$3:$A$434,0),),'IRA-BIL_IRA-BIL - Mid_annual_st'!$W$1:$AR$1,$B5) -> 29415 | J5: =SUMIFS(INDEX('IRA-BIL_IRA-BIL - Mid_annual_st'!$W$3:$AR$434,MATCH(J2,'IRA-BIL_IRA-BIL - Mid_annual_st'!$A$3:$A$434,0),),'IRA-BIL_IRA-BIL - Mid_annual_st'!$W$1:$AR$1,$B5) -> 29415 | K5: =SUMIFS(INDEX('IRA-BIL_IRA-BIL - Mid_annual_st'!$W$3:$AR$434,MATCH(K2,'IRA-BIL_IRA-BIL - Mid_annual_st'!$A$3:$A$434,0),),'IRA-BIL_IRA-BIL - Mid_annual_st'!$W$1:$AR$1,$B5) -> 29415 | M5: =C5/SUM(C4:C15) -> 0.00022467728 | N5: =D5/SUM(D4:D15) -> 0.00019784429 | O5: =E5/SUM(E4:E15) -> 0.00019061398 | P5: =F5/SUM(F4:F15) -> 0.00019542793 | Q5: =G5/SUM(G4:G15) -> 0.00020267741 | R5: =H5/SUM(H4:H15) -> 0.0002064604 | S5: =I5/SUM(I4:I15) -> 0.00021788882 | T5: =J5/SUM(J4:J15) -> 0.00021054052 | U5: =K5/SUM(K4:K15) -> 0.00022396615
A6: =A5 -> AL | B6: hard coal | C6: =SUMIFS(INDEX('IRA-BIL_IRA-BIL - Mid_annual_st'!$W$3:$AR$434,MATCH(C2,'IRA-BIL_IRA-BIL - Mid_annual_st'!$A$3:$A$434,0),),'IRA-BIL_IRA-BIL - Mid_annual_st'!$W$1:$AR$1,$B6) -> 33823351 | D6: =SUMIFS(INDEX('IRA-BIL_IRA-BIL - Mid_annual_st'!$W$3:$AR$434,MATCH(D2,'IRA-BIL_IRA-BIL - Mid_annual_st'!$A$3:$A$434,0),),'IRA-BIL_IRA-BIL - Mid_annual_st'!$W$1:$AR$1,$B6) -> 32487520 | E6: =SUMIFS(INDEX('IRA-BIL_IRA-BIL - Mid_annual_st'!$W$3:$AR$434,MATCH(E2,'IRA-BIL_IRA-BIL - Mid_annual_st'!$A$3:$A$434,0),),'IRA-BIL_IRA-BIL - Mid_annual_st'!$W$1:$AR$1,$B6) -> 32487156 | F6: =SUMIFS(INDEX('IRA-BIL_IRA-BIL - Mid_annual_st'!$W$3:$AR$434,MATCH(F2,'IRA-BIL_IRA-BIL - Mid_annual_st'!$A$3:$A$434,0),),'IRA-BIL_IRA-BIL - Mid_annual_st'!$W$1:$AR$1,$B6) -> 32102205 | G6: =SUMIFS(INDEX('IRA-BIL_IRA-BIL - Mid_annual_st'!$W$3:$AR$434,MATCH(G2,'IRA-BIL_IRA-BIL - Mid_annual_st'!$A$3:$A$434,0),),'IRA-BIL_IRA-BIL - Mid_annual_st'!$W$1:$AR$1,$B6) -> 31569197 | H6: =SUMIFS(INDEX('IRA-BIL_IRA-BIL - Mid_annual_st'!$W$3:$AR$434,MATCH(H2,'IRA-BIL_IRA-BIL - Mid_annual_st'!$A$3:$A$434,0),),'IRA-BIL_IRA-BIL - Mid_annual_st'!$W$1:$AR$1,$B6) -> 29705947 | I6: =SUMIFS(INDEX('IRA-BIL_IRA-BIL - Mid_annual_st'!$W$3:$AR$434,MATCH(I2,'IRA-BIL_IRA-BIL - Mid_annual_st'!$A$3:$A$434,0),),'IRA-BIL_IRA-BIL - Mid_annual_st'!$W$1:$AR$1,$B6) -> 25726053 | J6: =SUMIFS(INDEX('IRA-BIL_IRA-BIL - Mid_annual_st'!$W$3:$AR$434,MATCH(J2,'IRA-BIL_IRA-BIL - Mid_annual_st'!$A$3:$A$434,0),),'IRA-BIL_IRA-BIL - Mid_annual_st'!$W$1:$AR$1,$B6) -> 27289778 | K6: =SUMIFS(INDEX('IRA-BIL_IRA-BIL - Mid_annual_st'!$W$3:$AR$434,MATCH(K2,'IRA-BIL_IRA-BIL - Mid_annual_st'!$A$3:$A$434,0),),'IRA-BIL_IRA-BIL - Mid_annual_st'!$W$1:$AR$1,$B6) -> 28110346 | M6: =C6/SUM(C4:C15) -> 0.25834909 | N6: =D6/SUM(D4:D15) -> 0.21850996 | O6: =E6/SUM(E4:E15) -> 0.21052205 | P6: =F6/SUM(F4:F15) -> 0.21328124 | Q6: =G6/SUM(G4:G15) -> 0.21752042 | R6: =H6/SUM(H4:H15) -> 0.20850252 | S6: =I6/SUM(I4:I15) -> 0.19056329 | T6: =J6/SUM(J4:J15) -> 0.19532906 | U6: =K6/SUM(K4:K15) -> 0.2140325
A7: =A6 -> AL | B7: geothermal | C7: =SUMIFS(INDEX('IRA-BIL_IRA-BIL - Mid_annual_st'!$W$3:$AR$434,MATCH(C2,'IRA-BIL_IRA-BIL - Mid_annual_st'!$A$3:$A$434,0),),'IRA-BIL_IRA-BIL - Mid_annual_st'!$W$1:$AR$1,$B7) -> 0 | D7: =SUMIFS(INDEX('IRA-BIL_IRA-BIL - Mid_annual_st'!$W$3:$AR$434,MATCH(D2,'IRA-BIL_IRA-BIL - Mid_annual_st'!$A$3:$A$434,0),),'IRA-BIL_IRA-BIL - Mid_annual_st'!$W$1:$AR$1,$B7) -> 0 | E7: =SUMIFS(INDEX('IRA-BIL_IRA-BIL - Mid_annual_st'!$W$3:$AR$434,MATCH(E2,'IRA-BIL_IRA-BIL - Mid_annual_st'!$A$3:$A$434,0),),'IRA-BIL_IRA-BIL - Mid_annual_st'!$W$1:$AR$1,$B7) -> 0 | F7: =SUMIFS(INDEX('IRA-BIL_IRA-BIL - Mid_annual_st'!$W$3:$AR$434,MATCH(F2,'IRA-BIL_IRA-BIL - Mid_annual_st'!$A$3:$A$434,0),),'IRA-BIL_IRA-BIL - Mid_annual_st'!$W$1:$AR$1,$B7) -> 0 | G7: =SUMIFS(INDEX('IRA-BIL_IRA-BIL - Mid_annual_st'!$W$3:$AR$434,MATCH(G2,'IRA-BIL_IRA-BIL - Mid_annual_st'!$A$3:$A$434,0),),'IRA-BIL_IRA-BIL - Mid_annual_st'!$W$1:$AR$1,$B7) -> 0 | H7: =SUMIFS(INDEX('IRA-BIL_IRA-BIL - Mid_annual_st'!$W$3:$AR$434,MATCH(H2,'IRA-BIL_IRA-BIL - Mid_annual_st'!$A$3:$A$434,0),),'IRA-BIL_IRA-BIL - Mid_annual_st'!$W$1:$AR$1,$B7) -> 0 | I7: =SUMIFS(INDEX('IRA-BIL_IRA-BIL - Mid_annual_st'!$W$3:$AR$434,MATCH(I2,'IRA-BIL_IRA-BIL - Mid_annual_st'!$A$3:$A$434,0),),'IRA-BIL_IRA-BIL - Mid_annual_st'!$W$1:$AR$1,$B7) -> 0 | J7: =SUMIFS(INDEX('IRA-BIL_IRA-BIL - Mid_annual_st'!$W$3:$AR$434,MATCH(J2,'IRA-BIL_IRA-BIL - Mid_annual_st'!$A$3:$A$434,0),),'IRA-BIL_IRA-BIL - Mid_annual_st'!$W$1:$AR$1,$B7) -> 0 | K7: =SUMIFS(INDEX('IRA-BIL_IRA-BIL - Mid_annual_st'!$W$3:$AR$434,MATCH(K2,'IRA-BIL_IRA-BIL - Mid_annual_st'!$A$3:$A$434,0),),'IRA-BIL_IRA-BIL - Mid_annual_st'!$W$1:$AR$1,$B7) -> 0 | M7: =C7/SUM(C4:C15) -> 0 | N7: =D7/SUM(D4:D15) -> 0 | O7: =E7/SUM(E4:E15) -> 0 | P7: =F7/SUM(F4:F15) -> 0 | Q7: =G7/SUM(G4:G15) -> 0 | R7: =H7/SUM(H4:H15) -> 0 | S7: =I7/SUM(I4:I15) -> 0 | T7: =J7/SUM(J4:J15) -> 0 | U7: =K7/SUM(K4:K15) -> 0
A8: =A7 -> AL | B8: hydro | C8: =SUMIFS(INDEX('IRA-BIL_IRA-BIL - Mid_annual_st'!$W$3:$AR$434,MATCH(C2,'IRA-BIL_IRA-BIL - Mid_annual_st'!$A$3:$A$434,0),),'IRA-BIL_IRA-BIL - Mid_annual_st'!$W$1:$AR$1,$B8) -> 9704302 | D8: =SUMIFS(INDEX('IRA-BIL_IRA-BIL - Mid_annual_st'!$W$3:$AR$434,MATCH(D2,'IRA-BIL_IRA-BIL - Mid_annual_st'!$A$3:$A$434,0),),'IRA-BIL_IRA-BIL - Mid_annual_st'!$W$1:$AR$1,$B8) -> 9703029 | E8: =SUMIFS(INDEX('IRA-BIL_IRA-BIL - Mid_annual_st'!$W$3:$AR$434,MATCH(E2,'IRA-BIL_IRA-BIL - Mid_annual_st'!$A$3:$A$434,0),),'IRA-BIL_IRA-BIL - Mid_annual_st'!$W$1:$AR$1,$B8) -> 9713363 | F8: =SUMIFS(INDEX('IRA-BIL_IRA-BIL - Mid_annual_st'!$W$3:$AR$434,MATCH(F2,'IRA-BIL_IRA-BIL - Mid_annual_st'!$A$3:$A$434,0),),'IRA-BIL_IRA-BIL - Mid_annual_st'!$W$1:$AR$1,$B8) -> 10024547 | G8: =SUMIFS(INDEX('IRA-BIL_IRA-BIL - Mid_annual_st'!$W$3:$AR$434,MATCH(G2,'IRA-BIL_IRA-BIL - Mid_annual_st'!$A$3:$A$434,0),),'IRA-BIL_IRA-BIL - Mid_annual_st'!$W$1:$AR$1,$B8) -> 10034680 | H8: =SUMIFS(INDEX('IRA-BIL_IRA-BIL - Mid_annual_st'!$W$3:$AR$434,MATCH(H2,'IRA-BIL_IRA-BIL - Mid_annual_st'!$A$3:$A$434,0),),'IRA-BIL_IRA-BIL - Mid_annual_st'!$W$1:$AR$1,$B8) -> 10141830 | I8: =SUMIFS(INDEX('IRA-BIL_IRA-BIL - Mid_annual_st'!$W$3:$AR$434,MATCH(I2,'IRA-BIL_IRA-BIL - Mid_annual_st'!$A$3:$A$434,0),),'IRA-BIL_IRA-BIL - Mid_annual_st'!$W$1:$AR$1,$B8) -> 10194938 | J8: =SUMIFS(INDEX('IRA-BIL_IRA-BIL - Mid_annual_st'!$W$3:$AR$434,MATCH(J2,'IRA-BIL_IRA-BIL - Mid_annual_st'!$A$3:$A$434,0),),'IRA-BIL_IRA-BIL - Mid_annual_st'!$W$1:$AR$1,$B8) -> 10201313 | K8: =SUMIFS(INDEX('IRA-BIL_IRA-BIL - Mid_annual_st'!$W$3:$AR$434,MATCH(K2,'IRA-BIL_IRA-BIL - Mid_annual_st'!$A$3:$A$434,0),),'IRA-BIL_IRA-BIL - Mid_annual_st'!$W$1:$AR$1,$B8) -> 10213940 | M8: =C8/SUM(C4:C15) -> 0.074123278 | N8: =D8/SUM(D4:D15) -> 0.065262244 | O8: =E8/SUM(E4:E15) -> 0.062944171 | P8: =F8/SUM(F4:F15) -> 0.066601275 | Q8: =G8/SUM(G4:G15) -> 0.069141695 | R8: =H8/SUM(H4:H15) -> 0.071184303 | S8: =I8/SUM(I4:I15) -> 0.075518034 | T8: =J8/SUM(J4:J15) -> 0.073016821 | U8: =K8/SUM(K4:K15) -> 0.077769056
A9: =A8 -> AL | B9: natural gas steam turbine | C9: =SUMIFS(INDEX('IRA-BIL_IRA-BIL - Mid_annual_st'!$W$3:$AR$434,MATCH(C2,'IRA-BIL_IRA-BIL - Mid_annual_st'!$A$3:$A$434,0),),'IRA-BIL_IRA-BIL - Mid_annual_st'!$W$1:$AR$1,$B9) -> 40392371 | D9: =SUMIFS(INDEX('IRA-BIL_IRA-BIL - Mid_annual_st'!$W$3:$AR$434,MATCH(D2,'IRA-BIL_IRA-BIL - Mid_annual_st'!$A$3:$A$434,0),),'IRA-BIL_IRA-BIL - Mid_annual_st'!$W$1:$AR$1,$B9) -> 58958065 | E9: =SUMIFS(INDEX('IRA-BIL_IRA-BIL - Mid_annual_st'!$W$3:$AR$434,MATCH(E2,'IRA-BIL_IRA-BIL - Mid_annual_st'!$A$3:$A$434,0),),'IRA-BIL_IRA-BIL - Mid_annual_st'!$W$1:$AR$1,$B9) -> 65417617 | F9: =SUMIFS(INDEX('IRA-BIL_IRA-BIL - Mid_annual_st'!$W$3:$AR$434,MATCH(F2,'IRA-BIL_IRA-BIL - Mid_annual_st'!$A$3:$A$434,0),),'IRA-BIL_IRA-BIL - Mid_annual_st'!$W$1:$AR$1,$B9) -> 61647994 | G9: =SUMIFS(INDEX('IRA-BIL_IRA-BIL - Mid_annual_st'!$W$3:$AR$434,MATCH(G2,'IRA-BIL_IRA-BIL - Mid_annual_st'!$A$3:$A$434,0),),'IRA-BIL_IRA-BIL - Mid_annual_st'!$W$1:$AR$1,$B9) -> 55492686 | H9: =SUMIFS(INDEX('IRA-BIL_IRA-BIL - Mid_annual_st'!$W$3:$AR$434,MATCH(H2,'IRA-BIL_IRA-BIL - Mid_annual_st'!$A$3:$A$434,0),),'IRA-BIL_IRA-BIL - Mid_annual_st'!$W$1:$AR$1,$B9) -> 51282134 | I9: =SUMIFS(INDEX('IRA-BIL_IRA-BIL - Mid_annual_st'!$W$3:$AR$434,MATCH(I2,'IRA-BIL_IRA-BIL - Mid_annual_st'!$A$3:$A$434,0),),'IRA-BIL_IRA-BIL - Mid_annual_st'!$W$1:$AR$1,$B9) -> 43407545 | J9: =SUMIFS(INDEX('IRA-BIL_IRA-BIL - Mid_annual_st'!$W$3:$AR$434,MATCH(J2,'IRA-BIL_IRA-BIL - Mid_annual_st'!$A$3:$A$434,0),),'IRA-BIL_IRA-BIL - Mid_annual_st'!$W$1:$AR$1,$B9) -> 39249582 | K9: =SUMIFS(INDEX('IRA-BIL_IRA-BIL - Mid_annual_st'!$W$3:$AR$434,MATCH(K2,'IRA-BIL_IRA-BIL - Mid_annual_st'!$A$3:$A$434,0),),'IRA-BIL_IRA-BIL - Mid_annual_st'!$W$1:$AR$1,$B9) -> 26314975 | M9: =C9/SUM(C4:C15) -> 0.3085245 | N9: =D9/SUM(D4:D15) -> 0.39654994 | O9: =E9/SUM(E4:E15) -> 0.42391679 | P9: =F9/SUM(F4:F15) -> 0.40957811 | Q9: =G9/SUM(G4:G15) -> 0.38235982 | R9: =H9/SUM(H4:H15) -> 0.35994322 | S9: =I9/SUM(I4:I15) -> 0.32153726 | T9: =J9/SUM(J4:J15) -> 0.28093243 | U9: =K9/SUM(K4:K15) -> 0.20036252
A10: =A9 -> AL | B10: nuclear | C10: =SUMIFS(INDEX('IRA-BIL_IRA-BIL - Mid_annual_st'!$W$3:$AR$434,MATCH(C2,'IRA-BIL_IRA-BIL - Mid_annual_st'!$A$3:$A$434,0),),'IRA-BIL_IRA-BIL - Mid_annual_st'!$W$1:$AR$1,$B10) -> 44519210 | D10: =SUMIFS(INDEX('IRA-BIL_IRA-BIL - Mid_annual_st'!$W$3:$AR$434,MATCH(D2,'IRA-BIL_IRA-BIL - Mid_annual_st'!$A$3:$A$434,0),),'IRA-BIL_IRA-BIL - Mid_annual_st'!$W$1:$AR$1,$B10) -> 44519210 | E10: =SUMIFS(INDEX('IRA-BIL_IRA-BIL - Mid_annual_st'!$W$3:$AR$434,MATCH(E2,'IRA-BIL_IRA-BIL - Mid_annual_st'!$A$3:$A$434,0),),'IRA-BIL_IRA-BIL - Mid_annual_st'!$W$1:$AR$1,$B10) -> 44519210 | F10: =SUMIFS(INDEX('IRA-BIL_IRA-BIL - Mid_annual_st'!$W$3:$AR$434,MATCH(F2,'IRA-BIL_IRA-BIL - Mid_annual_st'!$A$3:$A$434,0),),'IRA-BIL_IRA-BIL - Mid_annual_st'!$W$1:$AR$1,$B10) -> 44519210 | G10: =SUMIFS(INDEX('IRA-BIL_IRA-BIL - Mid_annual_st'!$W$3:$AR$434,MATCH(G2,'IRA-BIL_IRA-BIL - Mid_annual_st'!$A$3:$A$434,0),),'IRA-BIL_IRA-BIL - Mid_annual_st'!$W$1:$AR$1,$B10) -> 44519210 | H10: =SUMIFS(INDEX('IRA-BIL_IRA-BIL - Mid_annual_st'!$W$3:$AR$434,MATCH(H2,'IRA-BIL_IRA-BIL - Mid_annual_st'!$A$3:$A$434,0),),'IRA-BIL_IRA-BIL - Mid_annual_st'!$W$1:$AR$1,$B10) -> 44519210 | I10: =SUMIFS(INDEX('IRA-BIL_IRA-BIL - Mid_annual_st'!$W$3:$AR$434,MATCH(I2,'IRA-BIL_IRA-BIL - Mid_annual_st'!$A$3:$A$434,0),),'IRA-BIL_IRA-BIL - Mid_annual_st'!$W$1:$AR$1,$B10) -> 44519210 | J10: =SUMIFS(INDEX('IRA-BIL_IRA-BIL - Mid_annual_st'!$W$3:$AR$434,MATCH(J2,'IRA-BIL_IRA-BIL - Mid_annual_st'!$A$3:$A$434,0),),'IRA-BIL_IRA-BIL - Mid_annual_st'!$W$1:$AR$1,$B10) -> 44519210 | K10: =SUMIFS(INDEX('IRA-BIL_IRA-BIL - Mid_annual_st'!$W$3:$AR$434,MATCH(K2,'IRA-BIL_IRA-BIL - Mid_annual_st'!$A$3:$A$434,0),),'IRA-BIL_IRA-BIL - Mid_annual_st'!$W$1:$AR$1,$B10) -> 44519210 | M10: =C10/SUM(C4:C15) -> 0.34004607 | N10: =D10/SUM(D4:D15) -> 0.2994347 | O10: =E10/SUM(E4:E15) -> 0.28849171 | P10: =F10/SUM(F4:F15) -> 0.29577757 | Q10: =G10/SUM(G4:G15) -> 0.30674956 | R10: =H10/SUM(H4:H15) -> 0.31247506 | S10: =I10/SUM(I4:I15) -> 0.32977182 | T10: =J10/SUM(J4:J15) -> 0.31865027 | U10: =K10/SUM(K4:K15) -> 0.33896977
A11: =A10 -> AL | B11: offshore wind | C11: =SUMIFS(INDEX('IRA-BIL_IRA-BIL - Mid_annual_st'!$W$3:$AR$434,MATCH(C2,'IRA-BIL_IRA-BIL - Mid_annual_st'!$A$3:$A$434,0),),'IRA-BIL_IRA-BIL - Mid_annual_st'!$W$1:$AR$1,$B11) -> 0 | D11: =SUMIFS(INDEX('IRA-BIL_IRA-BIL - Mid_annual_st'!$W$3:$AR$434,MATCH(D2,'IRA-BIL_IRA-BIL - Mid_annual_st'!$A$3:$A$434,0),),'IRA-BIL_IRA-BIL - Mid_annual_st'!$W$1:$AR$1,$B11) -> 0 | E11: =SUMIFS(INDEX('IRA-BIL_IRA-BIL - Mid_annual_st'!$W$3:$AR$434,MATCH(E2,'IRA-BIL_IRA-BIL - Mid_annual_st'!$A$3:$A$434,0),),'IRA-BIL_IRA-BIL - Mid_annual_st'!$W$1:$AR$1,$B11) -> 0 | F11: =SUMIFS(INDEX('IRA-BIL_IRA-BIL - Mid_annual_st'!$W$3:$AR$434,MATCH(F2,'IRA-BIL_IRA-BIL - Mid_annual_st'!$A$3:$A$434,0),),'IRA-BIL_IRA-BIL - Mid_annual_st'!$W$1:$AR$1,$B11) -> 0 | G11: =SUMIFS(INDEX('IRA-BIL_IRA-BIL - Mid_annual_st'!$W$3:$AR$434,MATCH(G2,'IRA-BIL_IRA-BIL - Mid_annual_st'!$A$3:$A$434,0),),'IRA-BIL_IRA-BIL - Mid_annual_st'!$W$1:$AR$1,$B11) -> 0 | H11: =SUMIFS(INDEX('IRA-BIL_IRA-BIL - Mid_annual_st'!$W$3:$AR$434,MATCH(H2,'IRA-BIL_IRA-BIL - Mid_annual_st'!$A$3:$A$434,0),),'IRA-BIL_IRA-BIL - Mid_annual_st'!$W$1:$AR$1,$B11) -> 0 | I11: =SUMIFS(INDEX('IRA-BIL_IRA-BIL - Mid_annual_st'!$W$3:$AR$434,MATCH(I2,'IRA-BIL_IRA-BIL - Mid_annual_st'!$A$3:$A$434,0),),'IRA-BIL_IRA-BIL - Mid_annual_st'!$W$1:$AR$1,$B11) -> 0 | J11: =SUMIFS(INDEX('IRA-BIL_IRA-BIL - Mid_annual_st'!$W$3:$AR$434,MATCH(J2,'IRA-BIL_IRA-BIL - Mid_annual_st'!$A$3:$A$434,0),),'IRA-BIL_IRA-BIL - Mid_annual_st'!$W$1:$AR$1,$B11) -> 0 | K11: =SUMIFS(INDEX('IRA-BIL_IRA-BIL - Mid_annual_st'!$W$3:$AR$434,MATCH(K2,'IRA-BIL_IRA-BIL - Mid_annual_st'!$A$3:$A$434,0),),'IRA-BIL_IRA-BIL - Mid_annual_st'!$W$1:$AR$1,$B11) -> 0 | M11: =C11/SUM(C4:C15) -> 0 | N11: =D11/SUM(D4:D15) -> 0 | O11: =E11/SUM(E4:E15) -> 0 | P11: =F11/SUM(F4:F15) -> 0 | Q11: =G11/SUM(G4:G15) -> 0 | R11: =H11/SUM(H4:H15) -> 0 | S11: =I11/SUM(I4:I15) -> 0 | T11: =J11/SUM(J4:J15) -> 0 | U11: =K11/SUM(K4:K15) -> 0
A12: =A11 -> AL | B12: petroleum | C12: =SUMIFS(INDEX('IRA-BIL_IRA-BIL - Mid_annual_st'!$W$3:$AR$434,MATCH(C2,'IRA-BIL_IRA-BIL - Mid_annual_st'!$A$3:$A$434,0),),'IRA-BIL_IRA-BIL - Mid_annual_st'!$W$1:$AR$1,$B12) -> 1243712 | D12: =SUMIFS(INDEX('IRA-BIL_IRA-BIL - Mid_annual_st'!$W$3:$AR$434,MATCH(D2,'IRA-BIL_IRA-BIL - Mid_annual_st'!$A$3:$A$434,0),),'IRA-BIL_IRA-BIL - Mid_annual_st'!$W$1:$AR$1,$B12) -> 1402943 | E12: =SUMIFS(INDEX('IRA-BIL_IRA-BIL - Mid_annual_st'!$W$3:$AR$434,MATCH(E2,'IRA-BIL_IRA-BIL - Mid_annual_st'!$A$3:$A$434,0),),'IRA-BIL_IRA-BIL - Mid_annual_st'!$W$1:$AR$1,$B12) -> 441841 | F12: =SUMIFS(INDEX('IRA-BIL_IRA-BIL - Mid_annual_st'!$W$3:$AR$434,MATCH(F2,'IRA-BIL_IRA-BIL - Mid_annual_st'!$A$3:$A$434,0),),'IRA-BIL_IRA-BIL - Mid_annual_st'!$W$1:$AR$1,$B12) -> 472991 | G12: =SUMIFS(INDEX('IRA-BIL_IRA-BIL - Mid_annual_st'!$W$3:$AR$434,MATCH(G2,'IRA-BIL_IRA-BIL - Mid_annual_st'!$A$3:$A$434,0),),'IRA-BIL_IRA-BIL - Mid_annual_st'!$W$1:$AR$1,$B12) -> 685367 | H12: =SUMIFS(INDEX('IRA-BIL_IRA-BIL - Mid_annual_st'!$W$3:$AR$434,MATCH(H2,'IRA-BIL_IRA-BIL - Mid_annual_st'!$A$3:$A$434,0),),'IRA-BIL_IRA-BIL - Mid_annual_st'!$W$1:$AR$1,$B12) -> 695939 | I12: =SUMIFS(INDEX('IRA-BIL_IRA-BIL - Mid_annual_st'!$W$3:$AR$434,MATCH(I2,'IRA-BIL_IRA-BIL - Mid_annual_st'!$A$3:$A$434,0),),'IRA-BIL_IRA-BIL - Mid_annual_st'!$W$1:$AR$1,$B12) -> 1121991 | J12: =SUMIFS(INDEX('IRA-BIL_IRA-BIL - Mid_annual_st'!$W$3:$AR$434,MATCH(J2,'IRA-BIL_IRA-BIL - Mid_annual_st'!$A$3:$A$434,0),),'IRA-BIL_IRA-BIL - Mid_annual_st'!$W$1:$AR$1,$B12) -> 909000 | K12: =SUMIFS(INDEX('IRA-BIL_IRA-BIL - Mid_annual_st'!$W$3:$AR$434,MATCH(K2,'IRA-BIL_IRA-BIL - Mid_annual_st'!$A$3:$A$434,0),),'IRA-BIL_IRA-BIL - Mid_annual_st'!$W$1:$AR$1,$B12) -> 1086251 | M12: =C12/SUM(C4:C15) -> 0.0094997054 | N12: =D12/SUM(D4:D15) -> 0.009436147 | O12: =E12/SUM(E4:E15) -> 0.0028632015 | P12: =F12/SUM(F4:F15) -> 0.0031424665 | Q12: =G12/SUM(G4:G15) -> 0.0047223665 | R12: =H12/SUM(H4:H15) -> 0.0048847134 | S12: =I12/SUM(I4:I15) -> 0.0083110417 | T12: =J12/SUM(J4:J15) -> 0.0065062497 | U12: =K12/SUM(K4:K15) -> 0.0082707275
A13: =A12 -> AL | B13: onshore wind | C13: =SUMIFS(INDEX('IRA-BIL_IRA-BIL - Mid_annual_st'!$W$3:$AR$434,MATCH(C2,'IRA-BIL_IRA-BIL - Mid_annual_st'!$A$3:$A$434,0),),'IRA-BIL_IRA-BIL - Mid_annual_st'!$W$1:$AR$1,$B13) -> 0 | D13: =SUMIFS(INDEX('IRA-BIL_IRA-BIL - Mid_annual_st'!$W$3:$AR$434,MATCH(D2,'IRA-BIL_IRA-BIL - Mid_annual_st'!$A$3:$A$434,0),),'IRA-BIL_IRA-BIL - Mid_annual_st'!$W$1:$AR$1,$B13) -> 0 | E13: =SUMIFS(INDEX('IRA-BIL_IRA-BIL - Mid_annual_st'!$W$3:$AR$434,MATCH(E2,'IRA-BIL_IRA-BIL - Mid_annual_st'!$A$3:$A$434,0),),'IRA-BIL_IRA-BIL - Mid_annual_st'!$W$1:$AR$1,$B13) -> 0 | F13: =SUMIFS(INDEX('IRA-BIL_IRA-BIL - Mid_annual_st'!$W$3:$AR$434,MATCH(F2,'IRA-BIL_IRA-BIL - Mid_annual_st'!$A$3:$A$434,0),),'IRA-BIL_IRA-BIL - Mid_annual_st'!$W$1:$AR$1,$B13) -> 0 | G13: =SUMIFS(INDEX('IRA-BIL_IRA-BIL - Mid_annual_st'!$W$3:$AR$434,MATCH(G2,'IRA-BIL_IRA-BIL - Mid_annual_st'!$A$3:$A$434,0),),'IRA-BIL_IRA-BIL - Mid_annual_st'!$W$1:$AR$1,$B13) -> 0 | H13: =SUMIFS(INDEX('IRA-BIL_IRA-BIL - Mid_annual_st'!$W$3:$AR$434,MATCH(H2,'IRA-BIL_IRA-BIL - Mid_annual_st'!$A$3:$A$434,0),),'IRA-BIL_IRA-BIL - Mid_annual_st'!$W$1:$AR$1,$B13) -> 0 | I13: =SUMIFS(INDEX('IRA-BIL_IRA-BIL - Mid_annual_st'!$W$3:$AR$434,MATCH(I2,'IRA-BIL_IRA-BIL - Mid_annual_st'!$A$3:$A$434,0),),'IRA-BIL_IRA-BIL - Mid_annual_st'!$W$1:$AR$1,$B13) -> 0 | J13: =SUMIFS(INDEX('IRA-BIL_IRA-BIL - Mid_annual_st'!$W$3:$AR$434,MATCH(J2,'IRA-BIL_IRA-BIL - Mid_annual_st'!$A$3:$A$434,0),),'IRA-BIL_IRA-BIL - Mid_annual_st'!$W$1:$AR$1,$B13) -> 0 | K13: =SUMIFS(INDEX('IRA-BIL_IRA-BIL - Mid_annual_st'!$W$3:$AR$434,MATCH(K2,'IRA-BIL_IRA-BIL - Mid_annual_st'!$A$3:$A$434,0),),'IRA-BIL_IRA-BIL - Mid_annual_st'!$W$1:$AR$1,$B13) -> 0 | M13: =C13/SUM(C4:C15) -> 0 | N13: =D13/SUM(D4:D15) -> 0 | O13: =E13/SUM(E4:E15) -> 0 | P13: =F13/SUM(F4:F15) -> 0 | Q13: =G13/SUM(G4:G15) -> 0 | R13: =H13/SUM(H4:H15) -> 0 | S13: =I13/SUM(I4:I15) -> 0 | T13: =J13/SUM(J4:J15) -> 0 | U13: =K13/SUM(K4:K15) -> 0
A14: =A13 -> AL | B14: pumped hydro | C14: 0 | D14: 0 | E14: 0 | F14: 0 | G14: 0 | H14: 0 | I14: 0 | J14: 0 | K14: 0 | M14: 0 | N14: 0 | O14: 0 | P14: 0 | Q14: 0 | R14: 0 | S14: 0 | T14: 0 | U14: 0
A15: =A14 -> AL | B15: solar pv | C15: =SUMIFS(INDEX('IRA-BIL_IRA-BIL - Mid_annual_st'!$W$3:$AR$434,MATCH(C2,'IRA-BIL_IRA-BIL - Mid_annual_st'!$A$3:$A$434,0),),'IRA-BIL_IRA-BIL - Mid_annual_st'!$W$1:$AR$1,$B15) -> 1208752 | D15: =SUMIFS(INDEX('IRA-BIL_IRA-BIL - Mid_annual_st'!$W$3:$AR$434,MATCH(D2,'IRA-BIL_IRA-BIL - Mid_annual_st'!$A$3:$A$434,0),),'IRA-BIL_IRA-BIL - Mid_annual_st'!$W$1:$AR$1,$B15) -> 1577345 | E15: =SUMIFS(INDEX('IRA-BIL_IRA-BIL - Mid_annual_st'!$W$3:$AR$434,MATCH(E2,'IRA-BIL_IRA-BIL - Mid_annual_st'!$A$3:$A$434,0),),'IRA-BIL_IRA-BIL - Mid_annual_st'!$W$1:$AR$1,$B15) -> 1708516 | F15: =SUMIFS(INDEX('IRA-BIL_IRA-BIL - Mid_annual_st'!$W$3:$AR$434,MATCH(F2,'IRA-BIL_IRA-BIL - Mid_annual_st'!$A$3:$A$434,0),),'IRA-BIL_IRA-BIL - Mid_annual_st'!$W$1:$AR$1,$B15) -> 1719481 | G15: =SUMIFS(INDEX('IRA-BIL_IRA-BIL - Mid_annual_st'!$W$3:$AR$434,MATCH(G2,'IRA-BIL_IRA-BIL - Mid_annual_st'!$A$3:$A$434,0),),'IRA-BIL_IRA-BIL - Mid_annual_st'!$W$1:$AR$1,$B15) -> 2801553 | H15: =SUMIFS(INDEX('IRA-BIL_IRA-BIL - Mid_annual_st'!$W$3:$AR$434,MATCH(H2,'IRA-BIL_IRA-BIL - Mid_annual_st'!$A$3:$A$434,0),),'IRA-BIL_IRA-BIL - Mid_annual_st'!$W$1:$AR$1,$B15) -> 6098368 | I15: =SUMIFS(INDEX('IRA-BIL_IRA-BIL - Mid_annual_st'!$W$3:$AR$434,MATCH(I2,'IRA-BIL_IRA-BIL - Mid_annual_st'!$A$3:$A$434,0),),'IRA-BIL_IRA-BIL - Mid_annual_st'!$W$1:$AR$1,$B15) -> 10000893 | J15: =SUMIFS(INDEX('IRA-BIL_IRA-BIL - Mid_annual_st'!$W$3:$AR$434,MATCH(J2,'IRA-BIL_IRA-BIL - Mid_annual_st'!$A$3:$A$434,0),),'IRA-BIL_IRA-BIL - Mid_annual_st'!$W$1:$AR$1,$B15) -> 17513523 | K15: =SUMIFS(INDEX('IRA-BIL_IRA-BIL - Mid_annual_st'!$W$3:$AR$434,MATCH(K2,'IRA-BIL_IRA-BIL - Mid_annual_st'!$A$3:$A$434,0),),'IRA-BIL_IRA-BIL - Mid_annual_st'!$W$1:$AR$1,$B15) -> 21062677 | M15: =C15/SUM(C4:C15) -> 0.0092326743 | N15: =D15/SUM(D4:D15) -> 0.010609169 | O15: =E15/SUM(E4:E15) -> 0.011071461 | P15: =F15/SUM(F4:F15) -> 0.01142392 | Q15: =G15/SUM(G4:G15) -> 0.019303468 | R15: =H15/SUM(H4:H15) -> 0.042803722 | S15: =I15/SUM(I4:I15) -> 0.074080664 | T15: =J15/SUM(J4:J15) -> 0.12535463 | U15: =K15/SUM(K4:K15) -> 0.16037146
A16: AZ | C16: =$A16&"_"&C17 -> AZ_2022 | D16: =$A16&"_"&D17 -> AZ_2023 | E16: =$A16&"_"&E17 -> AZ_2024 | F16: =$A16&"_"&F17 -> AZ_2025 | G16: =$A16&"_"&G17 -> AZ_2026 | H16: =$A16&"_"&H17 -> AZ_2027 | I16: =$A16&"_"&I17 -> AZ_2028 | J16: =$A16&"_"&J17 -> AZ_2029 | K16: =$A16&"_"&K17 -> AZ_2030 | M16: =$A16&"_"&M17 -> AZ_2022 | N16: =$A16&"_"&N17 -> AZ_2023 | O16: =$A16&"_"&O17 -> AZ_2024 | P16: =$A16&"_"&P17 -> AZ_2025 | Q16: =$A16&"_"&Q17 -> AZ_2026 | R16: =$A16&"_"&R17 -> AZ_2027 | S16: =$A16&"_"&S17 -> AZ_2028 | T16: =$A16&"_"&T17 -> AZ_2029 | U16: =$A16&"_"&U17 -> AZ_2030
C17: 2022 | D17: 2023 | E17: 2024 | F17: 2025 | G17: 2026 | H17: 2027 | I17: 2028 | J17: 2029 | K17: 2030 | M17: 2022 | N17: 2023 | O17: 2024 | P17: 2025 | Q17: 2026 | R17: 2027 | S17: 2028 | T17: 2029 | U17: 2030
A18: =A16 -> AZ | B18: battery | C18: 0 | D18: 0 | E18: 0 | F18: 0 | G18: 0 | H18: 0 | I18: 0 | J18: 0 | K18: 0 | M18: 0 | N18: 0 | O18: 0 | P18: 0 | Q18: 0 | R18: 0 | S18: 0 | T18: 0 | U18: 0
A19: =A18 -> AZ | B19: biomass | C19: =SUMIFS(INDEX('IRA-BIL_IRA-BIL - Mid_annual_st'!$W$3:$AR$434,MATCH(C16,'IRA-BIL_IRA-BIL - Mid_annual_st'!$A$3:$A$434,0),),'IRA-BIL_IRA-BIL - Mid_annual_st'!$W$1:$AR$1,$B19) -> 27577 | D19: =SUMIFS(INDEX('IRA-BIL_IRA-BIL - Mid_annual_st'!$W$3:$AR$434,MATCH(D16,'IRA-BIL_IRA-BIL - Mid_annual_st'!$A$3:$A$434,0),),'IRA-BIL_IRA-BIL - Mid_annual_st'!$W$1:$AR$1,$B19) -> 27577 | E19: =SUMIFS(INDEX('IRA-BIL_IRA-BIL - Mid_annual_st'!$W$3:$AR$434,MATCH(E16,'IRA-BIL_IRA-BIL - Mid_annual_st'!$A$3:$A$434,0),),'IRA-BIL_IRA-BIL - Mid_annual_st'!$W$1:$AR$1,$B19) -> 27577 | F19: =SUMIFS(INDEX('IRA-BIL_IRA-BIL - Mid_annual_st'!$W$3:$AR$434,MATCH(F16,'IRA-BIL_IRA-BIL - Mid_annual_st'!$A$3:$A$434,0),),'IRA-BIL_IRA-BIL - Mid_annual_st'!$W$1:$AR$1,$B19) -> 27577 | G19: =SUMIFS(INDEX('IRA-BIL_IRA-BIL - Mid_annual_st'!$W$3:$AR$434,MATCH(G16,'IRA-BIL_IRA-BIL - Mid_annual_st'!$A$3:$A$434,0),),'IRA-BIL_IRA-BIL - Mid_annual_st'!$W$1:$AR$1,$B19) -> 27577 | H19: =SUMIFS(INDEX('IRA-BIL_IRA-BIL - Mid_annual_st'!$W$3:$AR$434,MATCH(H16,'IRA-BIL_IRA-BIL - Mid_annual_st'!$A$3:$A$434,0),),'IRA-BIL_IRA-BIL - Mid_annual_st'!$W$1:$AR$1,$B19) -> 27577 | I19: =SUMIFS(INDEX('IRA-BIL_IRA-BIL - Mid_annual_st'!$W$3:$AR$434,MATCH(I16,'IRA-BIL_IRA-BIL - Mid_annual_st'!$A$3:$A$434,0),),'IRA-BIL_IRA-BIL - Mid_annual_st'!$W$1:$AR$1,$B19) -> 27577 | J19: =SUMIFS(INDEX('IRA-BIL_IRA-BIL - Mid_annual_st'!$W$3:$AR$434,MATCH(J16,'IRA-BIL_IRA-BIL - Mid_annual_st'!$A$3:$A$434,0),),'IRA-BIL_IRA-BIL - Mid_annual_st'!$W$1:$AR$1,$B19) -> 25707 | K19: =SUMIFS(INDEX('IRA-BIL_IRA-BIL - Mid_annual_st'!$W$3:$AR$434,MATCH(K16,'IRA-BIL_IRA-BIL - Mid_annual_st'!$A$3:$A$434,0),),'IRA-BIL_IRA-BIL - Mid_annual_st'!$W$1:$AR$1,$B19) -> 25707 | M19: =C19/SUM(C18:C29) -> 0.00027121217 | N19: =D19/SUM(D18:D29) -> 0.00030667645 | O19: =E19/SUM(E18:E29) -> 0.0002950779 | P19: =F19/SUM(F18:F29) -> 0.00029907087 | Q19: =G19/SUM(G18:G29) -> 0.00029518933 | R19: =H19/SUM(H18:H29) -> 0.00029945835 | S19: =I19/SUM(I18:I29) -> 0.00029667341 | T19: =J19/SUM(J18:J29) -> 0.00026591537 | U19: =K19/SUM(K18:K29) -> 0.00026756319
A20: =A19 -> AZ | B20: hard coal | C20: =SUMIFS(INDEX('IRA-BIL_IRA-BIL - Mid_annual_st'!$W$3:$AR$434,MATCH(C16,'IRA-BIL_IRA-BIL - Mid_annual_st'!$A$3:$A$434,0),),'IRA-BIL_IRA-BIL - Mid_annual_st'!$W$1:$AR$1,$B20) -> 20872123 | D20: =SUMIFS(INDEX('IRA-BIL_IRA-BIL - Mid_annual_st'!$W$3:$AR$434,MATCH(D16,'IRA-BIL_IRA-BIL - Mid_annual_st'!$A$3:$A$434,0),),'IRA-BIL_IRA-BIL - Mid_annual_st'!$W$1:$AR$1,$B20) -> 19029980 | E20: =SUMIFS(INDEX('IRA-BIL_IRA-BIL - Mid_annual_st'!$W$3:$AR$434,MATCH(E16,'IRA-BIL_IRA-BIL - Mid_annual_st'!$A$3:$A$434,0),),'IRA-BIL_IRA-BIL - Mid_annual_st'!$W$1:$AR$1,$B20) -> 18467787 | F20: =SUMIFS(INDEX('IRA-BIL_IRA-BIL - Mid_annual_st'!$W$3:$AR$434,MATCH(F16,'IRA-BIL_IRA-BIL - Mid_annual_st'!$A$3:$A$434,0),),'IRA-BIL_IRA-BIL - Mid_annual_st'!$W$1:$AR$1,$B20) -> 17363540 | G20: =SUMIFS(INDEX('IRA-BIL_IRA-BIL - Mid_annual_st'!$W$3:$AR$434,MATCH(G16,'IRA-BIL_IRA-BIL - Mid_annual_st'!$A$3:$A$434,0),),'IRA-BIL_IRA-BIL - Mid_annual_st'!$W$1:$AR$1,$B20) -> 15864171 | H20: =SUMIFS(INDEX('IRA-BIL_IRA-BIL - Mid_annual_st'!$W$3:$AR$434,MATCH(H16,'IRA-BIL_IRA-BIL - Mid_annual_st'!$A$3:$A$434,0),),'IRA-BIL_IRA-BIL - Mid_annual_st'!$W$1:$AR$1,$B20) -> 15377456 | I20: =SUMIFS(INDEX('IRA-BIL_IRA-BIL - Mid_annual_st'!$W$3:$AR$434,MATCH(I16,'IRA-BIL_IRA-BIL - Mid_annual_st'!$A$3:$A$434,0),),'IRA-BIL_IRA-BIL - Mid_annual_st'!$W$1:$AR$1,$B20) -> 7898588 | J20: =SUMIFS(INDEX('IRA-BIL_IRA-BIL - Mid_annual_st'!$W$3:$AR$434,MATCH(J16,'IRA-BIL_IRA-BIL - Mid_annual_st'!$A$3:$A$434,0),),'IRA-BIL_IRA-BIL - Mid_annual_st'!$W$1:$AR$1,$B20) -> 8012938 | K20: =SUMIFS(INDEX('IRA-BIL_IRA-BIL - Mid_annual_st'!$W$3:$AR$434,MATCH(K16,'IRA-BIL_IRA-BIL - Mid_annual_st'!$A$3:$A$434,0),),'IRA-BIL_IRA-BIL - Mid_annual_st'!$W$1:$AR$1,$B20) -> 6519503 | M20: =C20/SUM(C18:C29) -> 0.20527156 | N20: =D20/SUM(D18:D29) -> 0.21162733 | O20: =E20/SUM(E18:E29) -> 0.197608 | P20: =F20/SUM(F18:F29) -> 0.18830653 | Q20: =G20/SUM(G18:G29) -> 0.16981303 | R20: =H20/SUM(H18:H29) -> 0.16698363 | S20: =I20/SUM(I18:I29) -> 0.084973021 | T20: =J20/SUM(J18:J29) -> 0.082886503 | U20: =K20/SUM(K18:K29) -> 0.067856187
A21: =A20 -> AZ | B21: geothermal | C21: =SUMIFS(INDEX('IRA-BIL_IRA-BIL - Mid_annual_st'!$W$3:$AR$434,MATCH(C16,'IRA-BIL_IRA-BIL - Mid_annual_st'!$A$3:$A$434,0),),'IRA-BIL_IRA-BIL - Mid_annual_st'!$W$1:$AR$1,$B21) -> 0 | D21: =SUMIFS(INDEX('IRA-BIL_IRA-BIL - Mid_annual_st'!$W$3:$AR$434,MATCH(D16,'IRA-BIL_IRA-BIL - Mid_annual_st'!$A$3:$A$434,0),),'IRA-BIL_IRA-BIL - Mid_annual_st'!$W$1:$AR$1,$B21) -> 0 | E21: =SUMIFS(INDEX('IRA-BIL_IRA-BIL - Mid_annual_st'!$W$3:$AR$434,MATCH(E16,'IRA-BIL_IRA-BIL - Mid_annual_st'!$A$3:$A$434,0),),'IRA-BIL_IRA-BIL - Mid_annual_st'!$W$1:$AR$1,$B21) -> 0 | F21: =SUMIFS(INDEX('IRA-BIL_IRA-BIL - Mid_annual_st'!$W$3:$AR$434,MATCH(F16,'IRA-BIL_IRA-BIL - Mid_annual_st'!$A$3:$A$434,0),),'IRA-BIL_IRA-BIL - Mid_annual_st'!$W$1:$AR$1,$B21) -> 0 | G21: =SUMIFS(INDEX('IRA-BIL_IRA-BIL - Mid_annual_st'!$W$3:$AR$434,MATCH(G16,'IRA-BIL_IRA-BIL - Mid_annual_st'!$A$3:$A$434,0),),'IRA-BIL_IRA-BIL - Mid_annual_st'!$W$1:$AR$1,$B21) -> 0 | H21: =SUMIFS(INDEX('IRA-BIL_IRA-BIL - Mid_annual_st'!$W$3:$AR$434,MATCH(H16,'IRA-BIL_IRA-BIL - Mid_annual_st'!$A$3:$A$434,0),),'IRA-BIL_IRA-BIL - Mid_annual_st'!$W$1:$AR$1,$B21) -> 0 | I21: =SUMIFS(INDEX('IRA-BIL_IRA-BIL - Mid_annual_st'!$W$3:$AR$434,MATCH(I16,'IRA-BIL_IRA-BIL - Mid_annual_st'!$A$3:$A$434,0),),'IRA-BIL_IRA-BIL - Mid_annual_st'!$W$1:$AR$1,$B21) -> 0 | J21: =SUMIFS(INDEX('IRA-BIL_IRA-BIL - Mid_annual_st'!$W$3:$AR$434,MATCH(J16,'IRA-BIL_IRA-BIL - Mid_annual_st'!$A$3:$A$434,0),),'IRA-BIL_IRA-BIL - Mid_annual_st'!$W$1:$AR$1,$B21) -> 0 | K21: =SUMIFS(INDEX('IRA-BIL_IRA-BIL - Mid_annual_st'!$W$3:$AR$434,MATCH(K16,'IRA-BIL_IRA-BIL - Mid_annual_st'!$A$3:$A$434,0),),'IRA-BIL_IRA-BIL - Mid_annual_st'!$W$1:$AR$1,$B21) -> 0 | M21: =C21/SUM(C18:C29) -> 0 | N21: =D21/SUM(D18:D29) -> 0 | O21: =E21/SUM(E18:E29) -> 0 | P21: =F21/SUM(F18:F29) -> 0 | Q21: =G21/SUM(G18:G29) -> 0 | R21: =H21/SUM(H18:H29) -> 0 | S21: =I21/SUM(I18:I29) -> 0 | T21: =J21/SUM(J18:J29) -> 0 | U21: =K21/SUM(K18:K29) -> 0
A22: =A21 -> AZ | B22: hydro | C22: =SUMIFS(INDEX('IRA-BIL_IRA-BIL - Mid_annual_st'!$W$3:$AR$434,MATCH(C16,'IRA-BIL_IRA-BIL - Mid_annual_st'!$A$3:$A$434,0),),'IRA-BIL_IRA-BIL - Mid_annual_st'!$W$1:$AR$1,$B22) -> 7246652 | D22: =SUMIFS(INDEX('IRA-BIL_IRA-BIL - Mid_annual_st'!$W$3:$AR$434,MATCH(D16,'IRA-BIL_IRA-BIL - Mid_annual_st'!$A$3:$A$434,0),),'IRA-BIL_IRA-BIL - Mid_annual_st'!$W$1:$AR$1,$B22) -> 7246652 | E22: =SUMIFS(INDEX('IRA-BIL_IRA-BIL - Mid_annual_st'!$W$3:$AR$434,MATCH(E16,'IRA-BIL_IRA-BIL - Mid_annual_st'!$A$3:$A$434,0),),'IRA-BIL_IRA-BIL - Mid_annual_st'!$W$1:$AR$1,$B22) -> 7246804 | F22: =SUMIFS(INDEX('IRA-BIL_IRA-BIL - Mid_annual_st'!$W$3:$AR$434,MATCH(F16,'IRA-BIL_IRA-BIL - Mid_annual_st'!$A$3:$A$434,0),),'IRA-BIL_IRA-BIL - Mid_annual_st'!$W$1:$AR$1,$B22) -> 8628376 | G22: =SUMIFS(INDEX('IRA-BIL_IRA-BIL - Mid_annual_st'!$W$3:$AR$434,MATCH(G16,'IRA-BIL_IRA-BIL - Mid_annual_st'!$A$3:$A$434,0),),'IRA-BIL_IRA-BIL - Mid_annual_st'!$W$1:$AR$1,$B22) -> 8628528 | H22: =SUMIFS(INDEX('IRA-BIL_IRA-BIL - Mid_annual_st'!$W$3:$AR$434,MATCH(H16,'IRA-BIL_IRA-BIL - Mid_annual_st'!$A$3:$A$434,0),),'IRA-BIL_IRA-BIL - Mid_annual_st'!$W$1:$AR$1,$B22) -> 8637626 | I22: =SUMIFS(INDEX('IRA-BIL_IRA-BIL - Mid_annual_st'!$W$3:$AR$434,MATCH(I16,'IRA-BIL_IRA-BIL - Mid_annual_st'!$A$3:$A$434,0),),'IRA-BIL_IRA-BIL - Mid_annual_st'!$W$1:$AR$1,$B22) -> 8630449 | J22: =SUMIFS(INDEX('IRA-BIL_IRA-BIL - Mid_annual_st'!$W$3:$AR$434,MATCH(J16,'IRA-BIL_IRA-BIL - Mid_annual_st'!$A$3:$A$434,0),),'IRA-BIL_IRA-BIL - Mid_annual_st'!$W$1:$AR$1,$B22) -> 8636154 | K22: =SUMIFS(INDEX('IRA-BIL_IRA-BIL - Mid_annual_st'!$W$3:$AR$434,MATCH(K16,'IRA-BIL_IRA-BIL - Mid_annual_st'!$A$3:$A$434,0),),'IRA-BIL_IRA-BIL - Mid_annual_st'!$W$1:$AR$1,$B22) -> 8616548 | M22: =C22/SUM(C18:C29) -> 0.07126882 | N22: =D22/SUM(D18:D29) -> 0.080588082 | O22: =E22/SUM(E18:E29) -> 0.077541854 | P22: =F22/SUM(F18:F29) -> 0.093574208 | Q22: =G22/SUM(G18:G29) -> 0.092361366 | R22: =H22/SUM(H18:H29) -> 0.09379589 | S22: =I22/SUM(I18:I29) -> 0.092846383 | T22: =J22/SUM(J18:J29) -> 0.089333102 | U22: =K22/SUM(K18:K29) -> 0.089682618
A23: =A22 -> AZ | B23: natural gas steam turbine | C23: =SUMIFS(INDEX('IRA-BIL_IRA-BIL - Mid_annual_st'!$W$3:$AR$434,MATCH(C16,'IRA-BIL_IRA-BIL - Mid_annual_st'!$A$3:$A$434,0),),'IRA-BIL_IRA-BIL - Mid_annual_st'!$W$1:$AR$1,$B23) -> 31617311 | D23: =SUMIFS(INDEX('IRA-BIL_IRA-BIL - Mid_annual_st'!$W$3:$AR$434,MATCH(D16,'IRA-BIL_IRA-BIL - Mid_annual_st'!$A$3:$A$434,0),),'IRA-BIL_IRA-BIL - Mid_annual_st'!$W$1:$AR$1,$B23) -> 20325118 | E23: =SUMIFS(INDEX('IRA-BIL_IRA-BIL - Mid_annual_st'!$W$3:$AR$434,MATCH(E16,'IRA-BIL_IRA-BIL - Mid_annual_st'!$A$3:$A$434,0),),'IRA-BIL_IRA-BIL - Mid_annual_st'!$W$1:$AR$1,$B23) -> 18395143 | F23: =SUMIFS(INDEX('IRA-BIL_IRA-BIL - Mid_annual_st'!$W$3:$AR$434,MATCH(F16,'IRA-BIL_IRA-BIL - Mid_annual_st'!$A$3:$A$434,0),),'IRA-BIL_IRA-BIL - Mid_annual_st'!$W$1:$AR$1,$B23) -> 16093789 | G23: =SUMIFS(INDEX('IRA-BIL_IRA-BIL - Mid_annual_st'!$W$3:$AR$434,MATCH(G16,'IRA-BIL_IRA-BIL - Mid_annual_st'!$A$3:$A$434,0),),'IRA-BIL_IRA-BIL - Mid_annual_st'!$W$1:$AR$1,$B23) -> 16074622 | H23: =SUMIFS(INDEX('IRA-BIL_IRA-BIL - Mid_annual_st'!$W$3:$AR$434,MATCH(H16,'IRA-BIL_IRA-BIL - Mid_annual_st'!$A$3:$A$434,0),),'IRA-BIL_IRA-BIL - Mid_annual_st'!$W$1:$AR$1,$B23) -> 12969138 | I23: =SUMIFS(INDEX('IRA-BIL_IRA-BIL - Mid_annual_st'!$W$3:$AR$434,MATCH(I16,'IRA-BIL_IRA-BIL - Mid_annual_st'!$A$3:$A$434,0),),'IRA-BIL_IRA-BIL - Mid_annual_st'!$W$1:$AR$1,$B23) -> 9178381 | J23: =SUMIFS(INDEX('IRA-BIL_IRA-BIL - Mid_annual_st'!$W$3:$AR$434,MATCH(J16,'IRA-BIL_IRA-BIL - Mid_annual_st'!$A$3:$A$434,0),),'IRA-BIL_IRA-BIL - Mid_annual_st'!$W$1:$AR$1,$B23) -> 8495528 | K23: =SUMIFS(INDEX('IRA-BIL_IRA-BIL - Mid_annual_st'!$W$3:$AR$434,MATCH(K16,'IRA-BIL_IRA-BIL - Mid_annual_st'!$A$3:$A$434,0),),'IRA-BIL_IRA-BIL - Mid_annual_st'!$W$1:$AR$1,$B23) -> 8387745 | M23: =C23/SUM(C18:C29) -> 0.31094752 | N23: =D23/SUM(D18:D29) -> 0.22603021 | O23: =E23/SUM(E18:E29) -> 0.1968307 | P23: =F23/SUM(F18:F29) -> 0.17453615 | Q23: =G23/SUM(G18:G29) -> 0.17206574 | R23: =H23/SUM(H18:H29) -> 0.14083173 | S23: =I23/SUM(I18:I29) -> 0.098741036 | T23: =J23/SUM(J18:J29) -> 0.087878455 | U23: =K23/SUM(K18:K29) -> 0.087301194
A24: =A23 -> AZ | B24: nuclear | C24: =SUMIFS(INDEX('IRA-BIL_IRA-BIL - Mid_annual_st'!$W$3:$AR$434,MATCH(C16,'IRA-BIL_IRA-BIL - Mid_annual_st'!$A$3:$A$434,0),),'IRA-BIL_IRA-BIL - Mid_annual_st'!$W$1:$AR$1,$B24) -> 31618584 | D24: =SUMIFS(INDEX('IRA-BIL_IRA-BIL - Mid_annual_st'!$W$3:$AR$434,MATCH(D16,'IRA-BIL_IRA-BIL - Mid_annual_st'!$A$3:$A$434,0),),'IRA-BIL_IRA-BIL - Mid_annual_st'!$W$1:$AR$1,$B24) -> 31618584 | E24: =SUMIFS(INDEX('IRA-BIL_IRA-BIL - Mid_annual_st'!$W$3:$AR$434,MATCH(E16,'IRA-BIL_IRA-BIL - Mid_annual_st'!$A$3:$A$434,0),),'IRA-BIL_IRA-BIL - Mid_annual_st'!$W$1:$AR$1,$B24) -> 31618584 | F24: =SUMIFS(INDEX('IRA-BIL_IRA-BIL - Mid_annual_st'!$W$3:$AR$434,MATCH(F16,'IRA-BIL_IRA-BIL - Mid_annual_st'!$A$3:$A$434,0),),'IRA-BIL_IRA-BIL - Mid_annual_st'!$W$1:$AR$1,$B24) -> 31618584 | G24: =SUMIFS(INDEX('IRA-BIL_IRA-BIL - Mid_annual_st'!$W$3:$AR$434,MATCH(G16,'IRA-BIL_IRA-BIL - Mid_annual_st'!$A$3:$A$434,0),),'IRA-BIL_IRA-BIL - Mid_annual_st'!$W$1:$AR$1,$B24) -> 31618584 | H24: =SUMIFS(INDEX('IRA-BIL_IRA-BIL - Mid_annual_st'!$W$3:$AR$434,MATCH(H16,'IRA-BIL_IRA-BIL - Mid_annual_st'!$A$3:$A$434,0),),'IRA-BIL_IRA-BIL - Mid_annual_st'!$W$1:$AR$1,$B24) -> 31618584 | I24: =SUMIFS(INDEX('IRA-BIL_IRA-BIL - Mid_annual_st'!$W$3:$AR$434,MATCH(I16,'IRA-BIL_IRA-BIL - Mid_annual_st'!$A$3:$A$434,0),),'IRA-BIL_IRA-BIL - Mid_annual_st'!$W$1:$AR$1,$B24) -> 30552162 | J24: =SUMIFS(INDEX('IRA-BIL_IRA-BIL - Mid_annual_st'!$W$3:$AR$434,MATCH(J16,'IRA-BIL_IRA-BIL - Mid_annual_st'!$A$3:$A$434,0),),'IRA-BIL_IRA-BIL - Mid_annual_st'!$W$1:$AR$1,$B24) -> 30552162 | K24: =SUMIFS(INDEX('IRA-BIL_IRA-BIL - Mid_annual_st'!$W$3:$AR$434,MATCH(K16,'IRA-BIL_IRA-BIL - Mid_annual_st'!$A$3:$A$434,0),),'IRA-BIL_IRA-BIL - Mid_annual_st'!$W$1:$AR$1,$B24) -> 30449033 | M24: =C24/SUM(C18:C29) -> 0.31096004 | N24: =D24/SUM(D18:D29) -> 0.35162183 | O24: =E24/SUM(E18:E29) -> 0.33832344 | P24: =F24/SUM(F18:F29) -> 0.3429016 | Q24: =G24/SUM(G18:G29) -> 0.33845119 | R24: =H24/SUM(H18:H29) -> 0.34334587 | S24: =I24/SUM(I18:I29) -> 0.3286802 | T24: =J24/SUM(J18:J29) -> 0.31603413 | U24: =K24/SUM(K18:K29) -> 0.31691914
A25: =A24 -> AZ | B25: offshore wind | C25: =SUMIFS(INDEX('IRA-BIL_IRA-BIL - Mid_annual_st'!$W$3:$AR$434,MATCH(C16,'IRA-BIL_IRA-BIL - Mid_annual_st'!$A$3:$A$434,0),),'IRA-BIL_IRA-BIL - Mid_annual_st'!$W$1:$AR$1,$B25) -> 0 | D25: =SUMIFS(INDEX('IRA-BIL_IRA-BIL - Mid_annual_st'!$W$3:$AR$434,MATCH(D16,'IRA-BIL_IRA-BIL - Mid_annual_st'!$A$3:$A$434,0),),'IRA-BIL_IRA-BIL - Mid_annual_st'!$W$1:$AR$1,$B25) -> 0 | E25: =SUMIFS(INDEX('IRA-BIL_IRA-BIL - Mid_annual_st'!$W$3:$AR$434,MATCH(E16,'IRA-BIL_IRA-BIL - Mid_annual_st'!$A$3:$A$434,0),),'IRA-BIL_IRA-BIL - Mid_annual_st'!$W$1:$AR$1,$B25) -> 0 | F25: =SUMIFS(INDEX('IRA-BIL_IRA-BIL - Mid_annual_st'!$W$3:$AR$434,MATCH(F16,'IRA-BIL_IRA-BIL - Mid_annual_st'!$A$3:$A$434,0),),'IRA-BIL_IRA-BIL - Mid_annual_st'!$W$1:$AR$1,$B25) -> 0 | G25: =SUMIFS(INDEX('IRA-BIL_IRA-BIL - Mid_annual_st'!$W$3:$AR$434,MATCH(G16,'IRA-BIL_IRA-BIL - Mid_annual_st'!$A$3:$A$434,0),),'IRA-BIL_IRA-BIL - Mid_annual_st'!$W$1:$AR$1,$B25) -> 0 | H25: =SUMIFS(INDEX('IRA-BIL_IRA-BIL - Mid_annual_st'!$W$3:$AR$434,MATCH(H16,'IRA-BIL_IRA-BIL - Mid_annual_st'!$A$3:$A$434,0),),'IRA-BIL_IRA-BIL - Mid_annual_st'!$W$1:$AR$1,$B25) -> 0 | I25: =SUMIFS(INDEX('IRA-BIL_IRA-BIL - Mid_annual_st'!$W$3:$AR$434,MATCH(I16,'IRA-BIL_IRA-BIL - Mid_annual_st'!$A$3:$A$434,0),),'IRA-BIL_IRA-BIL - Mid_annual_st'!$W$1:$AR$1,$B25) -> 0 | J25: =SUMIFS(INDEX('IRA-BIL_IRA-BIL - Mid_annual_st'!$W$3:$AR$434,MATCH(J16,'IRA-BIL_IRA-BIL - Mid_annual_st'!$A$3:$A$434,0),),'IRA-BIL_IRA-BIL - Mid_annual_st'!$W$1:$AR$1,$B25) -> 0 | K25: =SUMIFS(INDEX('IRA-BIL_IRA-BIL - Mid_annual_st'!$W$3:$AR$434,MATCH(K16,'IRA-BIL_IRA-BIL - Mid_annual_st'!$A$3:$A$434,0),),'IRA-BIL_IRA-BIL - Mid_annual_st'!$W$1:$AR$1,$B25) -> 0 | M25: =C25/SUM(C18:C29) -> 0 | N25: =D25/SUM(D18:D29) -> 0 | O25: =E25/SUM(E18:E29) -> 0 | P25: =F25/SUM(F18:F29) -> 0 | Q25: =G25/SUM(G18:G29) -> 0 | R25: =H25/SUM(H18:H29) -> 0 | S25: =I25/SUM(I18:I29) -> 0 | T25: =J25/SUM(J18:J29) -> 0 | U25: =K25/SUM(K18:K29) -> 0
A26: =A25 -> AZ | B26: petroleum | C26: =SUMIFS(INDEX('IRA-BIL_IRA-BIL - Mid_annual_st'!$W$3:$AR$434,MATCH(C16,'IRA-BIL_IRA-BIL - Mid_annual_st'!$A$3:$A$434,0),),'IRA-BIL_IRA-BIL - Mid_annual_st'!$W$1:$AR$1,$B26) -> 1113957 | D26: =SUMIFS(INDEX('IRA-BIL_IRA-BIL - Mid_annual_st'!$W$3:$AR$434,MATCH(D16,'IRA-BIL_IRA-BIL - Mid_annual_st'!$A$3:$A$434,0),),'IRA-BIL_IRA-BIL - Mid_annual_st'!$W$1:$AR$1,$B26) -> 1113957 | E26: =SUMIFS(INDEX('IRA-BIL_IRA-BIL - Mid_annual_st'!$W$3:$AR$434,MATCH(E16,'IRA-BIL_IRA-BIL - Mid_annual_st'!$A$3:$A$434,0),),'IRA-BIL_IRA-BIL - Mid_annual_st'!$W$1:$AR$1,$B26) -> 587621 | F26: =SUMIFS(INDEX('IRA-BIL_IRA-BIL - Mid_annual_st'!$W$3:$AR$434,MATCH(F16,'IRA-BIL_IRA-BIL - Mid_annual_st'!$A$3:$A$434,0),),'IRA-BIL_IRA-BIL - Mid_annual_st'!$W$1:$AR$1,$B26) -> 587621 | G26: =SUMIFS(INDEX('IRA-BIL_IRA-BIL - Mid_annual_st'!$W$3:$AR$434,MATCH(G16,'IRA-BIL_IRA-BIL - Mid_annual_st'!$A$3:$A$434,0),),'IRA-BIL_IRA-BIL - Mid_annual_st'!$W$1:$AR$1,$B26) -> 587621 | H26: =SUMIFS(INDEX('IRA-BIL_IRA-BIL - Mid_annual_st'!$W$3:$AR$434,MATCH(H16,'IRA-BIL_IRA-BIL - Mid_annual_st'!$A$3:$A$434,0),),'IRA-BIL_IRA-BIL - Mid_annual_st'!$W$1:$AR$1,$B26) -> 450965 | I26: =SUMIFS(INDEX('IRA-BIL_IRA-BIL - Mid_annual_st'!$W$3:$AR$434,MATCH(I16,'IRA-BIL_IRA-BIL - Mid_annual_st'!$A$3:$A$434,0),),'IRA-BIL_IRA-BIL - Mid_annual_st'!$W$1:$AR$1,$B26) -> 440453 | J26: =SUMIFS(INDEX('IRA-BIL_IRA-BIL - Mid_annual_st'!$W$3:$AR$434,MATCH(J16,'IRA-BIL_IRA-BIL - Mid_annual_st'!$A$3:$A$434,0),),'IRA-BIL_IRA-BIL - Mid_annual_st'!$W$1:$AR$1,$B26) -> 384739 | K26: =SUMIFS(INDEX('IRA-BIL_IRA-BIL - Mid_annual_st'!$W$3:$AR$434,MATCH(K16,'IRA-BIL_IRA-BIL - Mid_annual_st'!$A$3:$A$434,0),),'IRA-BIL_IRA-BIL - Mid_annual_st'!$W$1:$AR$1,$B26) -> 307476 | M26: =C26/SUM(C18:C29) -> 0.010955459 | N26: =D26/SUM(D18:D29) -> 0.012388018 | O26: =E26/SUM(E18:E29) -> 0.0062876299 | P26: =F26/SUM(F18:F29) -> 0.0063727137 | Q26: =G26/SUM(G18:G29) -> 0.0062900043 | R26: =H26/SUM(H18:H29) -> 0.0048970242 | S26: =I26/SUM(I18:I29) -> 0.004738394 | T26: =J26/SUM(J18:J29) -> 0.0039797725 | U26: =K26/SUM(K18:K29) -> 0.0032002668
A27: =A26 -> AZ | B27: onshore wind | C27: =SUMIFS(INDEX('IRA-BIL_IRA-BIL - Mid_annual_st'!$W$3:$AR$434,MATCH(C16,'IRA-BIL_IRA-BIL - Mid_annual_st'!$A$3:$A$434,0),),'IRA-BIL_IRA-BIL - Mid_annual_st'!$W$1:$AR$1,$B27) -> 1676683 | D27: =SUMIFS(INDEX('IRA-BIL_IRA-BIL - Mid_annual_st'!$W$3:$AR$434,MATCH(D16,'IRA-BIL_IRA-BIL - Mid_annual_st'!$A$3:$A$434,0),),'IRA-BIL_IRA-BIL - Mid_annual_st'!$W$1:$AR$1,$B27) -> 1688417 | E27: =SUMIFS(INDEX('IRA-BIL_IRA-BIL - Mid_annual_st'!$W$3:$AR$434,MATCH(E16,'IRA-BIL_IRA-BIL - Mid_annual_st'!$A$3:$A$434,0),),'IRA-BIL_IRA-BIL - Mid_annual_st'!$W$1:$AR$1,$B27) -> 1685885 | F27: =SUMIFS(INDEX('IRA-BIL_IRA-BIL - Mid_annual_st'!$W$3:$AR$434,MATCH(F16,'IRA-BIL_IRA-BIL - Mid_annual_st'!$A$3:$A$434,0),),'IRA-BIL_IRA-BIL - Mid_annual_st'!$W$1:$AR$1,$B27) -> 1701411 | G27: =SUMIFS(INDEX('IRA-BIL_IRA-BIL - Mid_annual_st'!$W$3:$AR$434,MATCH(G16,'IRA-BIL_IRA-BIL - Mid_annual_st'!$A$3:$A$434,0),),'IRA-BIL_IRA-BIL - Mid_annual_st'!$W$1:$AR$1,$B27) -> 1989930 | H27: =SUMIFS(INDEX('IRA-BIL_IRA-BIL - Mid_annual_st'!$W$3:$AR$434,MATCH(H16,'IRA-BIL_IRA-BIL - Mid_annual_st'!$A$3:$A$434,0),),'IRA-BIL_IRA-BIL - Mid_annual_st'!$W$1:$AR$1,$B27) -> 2008713 | I27: =SUMIFS(INDEX('IRA-BIL_IRA-BIL - Mid_annual_st'!$W$3:$AR$434,MATCH(I16,'IRA-BIL_IRA-BIL - Mid_annual_st'!$A$3:$A$434,0),),'IRA-BIL_IRA-BIL - Mid_annual_st'!$W$1:$AR$1,$B27) -> 2693408 | J27: =SUMIFS(INDEX('IRA-BIL_IRA-BIL - Mid_annual_st'!$W$3:$AR$434,MATCH(J16,'IRA-BIL_IRA-BIL - Mid_annual_st'!$A$3:$A$434,0),),'IRA-BIL_IRA-BIL - Mid_annual_st'!$W$1:$AR$1,$B27) -> 2762852 | K27: =SUMIFS(INDEX('IRA-BIL_IRA-BIL - Mid_annual_st'!$W$3:$AR$434,MATCH(K16,'IRA-BIL_IRA-BIL - Mid_annual_st'!$A$3:$A$434,0),),'IRA-BIL_IRA-BIL - Mid_annual_st'!$W$1:$AR$1,$B27) -> 2764866 | M27: =C27/SUM(C18:C29) -> 0.016489714 | N27: =D27/SUM(D18:D29) -> 0.018776435 | O27: =E27/SUM(E18:E29) -> 0.018039214 | P27: =F27/SUM(F18:F29) -> 0.018451698 | Q27: =G27/SUM(G18:G29) -> 0.02130058 | R27: =H27/SUM(H18:H29) -> 0.021812593 | S27: =I27/SUM(I18:I29) -> 0.028975687 | T27: =J27/SUM(J18:J29) -> 0.028579173 | U27: =K27/SUM(K18:K29) -> 0.028777234
A28: =A27 -> AZ | B28: pumped hydro | C28: 0 | D28: 0 | E28: 0 | F28: 0 | G28: 0 | H28: 0 | I28: 0 | J28: 0 | K28: 0 | M28: 0 | N28: 0 | O28: 0 | P28: 0 | Q28: 0 | R28: 0 | S28: 0 | T28: 0 | U28: 0
A29: =A28 -> AZ | B29: solar pv | C29: =SUMIFS(INDEX('IRA-BIL_IRA-BIL - Mid_annual_st'!$W$3:$AR$434,MATCH(C16,'IRA-BIL_IRA-BIL - Mid_annual_st'!$A$3:$A$434,0),),'IRA-BIL_IRA-BIL - Mid_annual_st'!$W$1:$AR$1,$B29) -> 7507652 | D29: =SUMIFS(INDEX('IRA-BIL_IRA-BIL - Mid_annual_st'!$W$3:$AR$434,MATCH(D16,'IRA-BIL_IRA-BIL - Mid_annual_st'!$A$3:$A$434,0),),'IRA-BIL_IRA-BIL - Mid_annual_st'!$W$1:$AR$1,$B29) -> 8871845 | E29: =SUMIFS(INDEX('IRA-BIL_IRA-BIL - Mid_annual_st'!$W$3:$AR$434,MATCH(E16,'IRA-BIL_IRA-BIL - Mid_annual_st'!$A$3:$A$434,0),),'IRA-BIL_IRA-BIL - Mid_annual_st'!$W$1:$AR$1,$B29) -> 15427276 | F29: =SUMIFS(INDEX('IRA-BIL_IRA-BIL - Mid_annual_st'!$W$3:$AR$434,MATCH(F16,'IRA-BIL_IRA-BIL - Mid_annual_st'!$A$3:$A$434,0),),'IRA-BIL_IRA-BIL - Mid_annual_st'!$W$1:$AR$1,$B29) -> 16188015 | G29: =SUMIFS(INDEX('IRA-BIL_IRA-BIL - Mid_annual_st'!$W$3:$AR$434,MATCH(G16,'IRA-BIL_IRA-BIL - Mid_annual_st'!$A$3:$A$434,0),),'IRA-BIL_IRA-BIL - Mid_annual_st'!$W$1:$AR$1,$B29) -> 18630366 | H29: =SUMIFS(INDEX('IRA-BIL_IRA-BIL - Mid_annual_st'!$W$3:$AR$434,MATCH(H16,'IRA-BIL_IRA-BIL - Mid_annual_st'!$A$3:$A$434,0),),'IRA-BIL_IRA-BIL - Mid_annual_st'!$W$1:$AR$1,$B29) -> 20999541 | I29: =SUMIFS(INDEX('IRA-BIL_IRA-BIL - Mid_annual_st'!$W$3:$AR$434,MATCH(I16,'IRA-BIL_IRA-BIL - Mid_annual_st'!$A$3:$A$434,0),),'IRA-BIL_IRA-BIL - Mid_annual_st'!$W$1:$AR$1,$B29) -> 33533050 | J29: =SUMIFS(INDEX('IRA-BIL_IRA-BIL - Mid_annual_st'!$W$3:$AR$434,MATCH(J16,'IRA-BIL_IRA-BIL - Mid_annual_st'!$A$3:$A$434,0),),'IRA-BIL_IRA-BIL - Mid_annual_st'!$W$1:$AR$1,$B29) -> 37803536 | K29: =SUMIFS(INDEX('IRA-BIL_IRA-BIL - Mid_annual_st'!$W$3:$AR$434,MATCH(K16,'IRA-BIL_IRA-BIL - Mid_annual_st'!$A$3:$A$434,0),),'IRA-BIL_IRA-BIL - Mid_annual_st'!$W$1:$AR$1,$B29) -> 39007361 | M29: =C29/SUM(C18:C29) -> 0.073835683 | N29: =D29/SUM(D18:D29) -> 0.09866142 | O29: =E29/SUM(E18:E29) -> 0.16507409 | P29: =F29/SUM(F18:F29) -> 0.17555803 | Q29: =G29/SUM(G18:G29) -> 0.1994229 | R29: =H29/SUM(H18:H29) -> 0.2280338 | S29: =I29/SUM(I18:I29) -> 0.3607486 | T29: =J29/SUM(J18:J29) -> 0.39104295 | U29: =K29/SUM(K18:K29) -> 0.40599579
A30: AR | C30: =$A30&"_"&C31 -> AR_2022 | D30: =$A30&"_"&D31 -> AR_2023 | E30: =$A30&"_"&E31 -> AR_2024 | F30: =$A30&"_"&F31 -> AR_2025 | G30: =$A30&"_"&G31 -> AR_2026 | H30: =$A30&"_"&H31 -> AR_2027 | I30: =$A30&"_"&I31 -> AR_2028 | J30: =$A30&"_"&J31 -> AR_2029 | K30: =$A30&"_"&K31 -> AR_2030 | M30: =$A30&"_"&M31 -> AR_2022 | N30: =$A30&"_"&N31 -> AR_2023 | O30: =$A30&"_"&O31 -> AR_2024 | P30: =$A30&"_"&P31 -> AR_2025 | Q30: =$A30&"_"&Q31 -> AR_2026 | R30: =$A30&"_"&R31 -> AR_2027 | S30: =$A30&"_"&S31 -> AR_2028 | T30: =$A30&"_"&T31 -> AR_2029 | U30: =$A30&"_"&U31 -> AR_2030
C31: 2022 | D31: 2023 | E31: 2024 | F31: 2025 | G31: 2026 | H31: 2027 | I31: 2028 | J31: 2029 | K31: 2030 | M31: 2022 | N31: 2023 | O31: 2024 | P31: 2025 | Q31: 2026 | R31: 2027 | S31: 2028 | T31: 2029 | U31: 2030
A32: =A30 -> AR | B32: battery | C32: 0 | D32: 0 | E32: 0 | F32: 0 | G32: 0 | H32: 0 | I32: 0 | J32: 0 | K32: 0 | M32: 0 | N32: 0 | O32: 0 | P32: 0 | Q32: 0 | R32: 0 | S32: 0 | T32: 0 | U32: 0
A33: =A32 -> AR | B33: biomass | C33: =SUMIFS(INDEX('IRA-BIL_IRA-BIL - Mid_annual_st'!$W$3:$AR$434,MATCH(C30,'IRA-BIL_IRA-BIL - Mid_annual_st'!$A$3:$A$434,0),),'IRA-BIL_IRA-BIL - Mid_annual_st'!$W$1:$AR$1,$B33) -> 40369 | D33: =SUMIFS(INDEX('IRA-BIL_IRA-BIL - Mid_annual_st'!$W$3:$AR$434,MATCH(D30,'IRA-BIL_IRA-BIL - Mid_annual_st'!$A$3:$A$434,0),),'IRA-BIL_IRA-BIL - Mid_annual_st'!$W$1:$AR$1,$B33) -> 40369 | E33: =SUMIFS(INDEX('IRA-BIL_IRA-BIL - Mid_annual_st'!$W$3:$AR$434,MATCH(E30,'IRA-BIL_IRA-BIL - Mid_annual_st'!$A$3:$A$434,0),),'IRA-BIL_IRA-BIL - Mid_annual_st'!$W$1:$AR$1,$B33) -> 40369 | F33: =SUMIFS(INDEX('IRA-BIL_IRA-BIL - Mid_annual_st'!$W$3:$AR$434,MATCH(F30,'IRA-BIL_IRA-BIL - Mid_annual_st'!$A$3:$A$434,0),),'IRA-BIL_IRA-BIL - Mid_annual_st'!$W$1:$AR$1,$B33) -> 40369 | G33: =SUMIFS(INDEX('IRA-BIL_IRA-BIL - Mid_annual_st'!$W$3:$AR$434,MATCH(G30,'IRA-BIL_IRA-BIL - Mid_annual_st'!$A$3:$A$434,0),),'IRA-BIL_IRA-BIL - Mid_annual_st'!$W$1:$AR$1,$B33) -> 40369 | H33: =SUMIFS(INDEX('IRA-BIL_IRA-BIL - Mid_annual_st'!$W$3:$AR$434,MATCH(H30,'IRA-BIL_IRA-BIL - Mid_annual_st'!$A$3:$A$434,0),),'IRA-BIL_IRA-BIL - Mid_annual_st'!$W$1:$AR$1,$B33) -> 39462 | I33: =SUMIFS(INDEX('IRA-BIL_IRA-BIL - Mid_annual_st'!$W$3:$AR$434,MATCH(I30,'IRA-BIL_IRA-BIL - Mid_annual_st'!$A$3:$A$434,0),),'IRA-BIL_IRA-BIL - Mid_annual_st'!$W$1:$AR$1,$B33) -> 37633 | J33: =SUMIFS(INDEX('IRA-BIL_IRA-BIL - Mid_annual_st'!$W$3:$AR$434,MATCH(J30,'IRA-BIL_IRA-BIL - Mid_annual_st'!$A$3:$A$434,0),),'IRA-BIL_IRA-BIL - Mid_annual_st'!$W$1:$AR$1,$B33) -> 35302 | K33: =SUMIFS(INDEX('IRA-BIL_IRA-BIL - Mid_annual_st'!$W$3:$AR$434,MATCH(K30,'IRA-BIL_IRA-BIL - Mid_annual_st'!$A$3:$A$434,0),),'IRA-BIL_IRA-BIL - Mid_annual_st'!$W$1:$AR$1,$B33) -> 34429 | M33: =C33/SUM(C32:C43) -> 0.00066504762 | N33: =D33/SUM(D32:D43) -> 0.00086713077 | O33: =E33/SUM(E32:E43) -> 0.0008873716 | P33: =F33/SUM(F32:F43) -> 0.00088826399 | Q33: =G33/SUM(G32:G43) -> 0.00094251453 | R33: =H33/SUM(H32:H43) -> 0.00090508958 | S33: =I33/SUM(I32:I43) -> 0.00098234714 | T33: =J33/SUM(J32:J43) -> 0.00091660161 | U33: =K33/SUM(K32:K43) -> 0.00089582352
A34: =A33 -> AR | B34: hard coal | C34: =SUMIFS(INDEX('IRA-BIL_IRA-BIL - Mid_annual_st'!$W$3:$AR$434,MATCH(C30,'IRA-BIL_IRA-BIL - Mid_annual_st'!$A$3:$A$434,0),),'IRA-BIL_IRA-BIL - Mid_annual_st'!$W$1:$AR$1,$B34) -> 29909120 | D34: =SUMIFS(INDEX('IRA-BIL_IRA-BIL - Mid_annual_st'!$W$3:$AR$434,MATCH(D30,'IRA-BIL_IRA-BIL - Mid_annual_st'!$A$3:$A$434,0),),'IRA-BIL_IRA-BIL - Mid_annual_st'!$W$1:$AR$1,$B34) -> 15368075 | E34: =SUMIFS(INDEX('IRA-BIL_IRA-BIL - Mid_annual_st'!$W$3:$AR$434,MATCH(E30,'IRA-BIL_IRA-BIL - Mid_annual_st'!$A$3:$A$434,0),),'IRA-BIL_IRA-BIL - Mid_annual_st'!$W$1:$AR$1,$B34) -> 13411216 | F34: =SUMIFS(INDEX('IRA-BIL_IRA-BIL - Mid_annual_st'!$W$3:$AR$434,MATCH(F30,'IRA-BIL_IRA-BIL - Mid_annual_st'!$A$3:$A$434,0),),'IRA-BIL_IRA-BIL - Mid_annual_st'!$W$1:$AR$1,$B34) -> 12010296 | G34: =SUMIFS(INDEX('IRA-BIL_IRA-BIL - Mid_annual_st'!$W$3:$AR$434,MATCH(G30,'IRA-BIL_IRA-BIL - Mid_annual_st'!$A$3:$A$434,0),),'IRA-BIL_IRA-BIL - Mid_annual_st'!$W$1:$AR$1,$B34) -> 8654116 | H34: =SUMIFS(INDEX('IRA-BIL_IRA-BIL - Mid_annual_st'!$W$3:$AR$434,MATCH(H30,'IRA-BIL_IRA-BIL - Mid_annual_st'!$A$3:$A$434,0),),'IRA-BIL_IRA-BIL - Mid_annual_st'!$W$1:$AR$1,$B34) -> 6521246 | I34: =SUMIFS(INDEX('IRA-BIL_IRA-BIL - Mid_annual_st'!$W$3:$AR$434,MATCH(I30,'IRA-BIL_IRA-BIL - Mid_annual_st'!$A$3:$A$434,0),),'IRA-BIL_IRA-BIL - Mid_annual_st'!$W$1:$AR$1,$B34) -> 2399368 | J34: =SUMIFS(INDEX('IRA-BIL_IRA-BIL - Mid_annual_st'!$W$3:$AR$434,MATCH(J30,'IRA-BIL_IRA-BIL - Mid_annual_st'!$A$3:$A$434,0),),'IRA-BIL_IRA-BIL - Mid_annual_st'!$W$1:$AR$1,$B34) -> 1421779 | K34: =SUMIFS(INDEX('IRA-BIL_IRA-BIL - Mid_annual_st'!$W$3:$AR$434,MATCH(K30,'IRA-BIL_IRA-BIL - Mid_annual_st'!$A$3:$A$434,0),),'IRA-BIL_IRA-BIL - Mid_annual_st'!$W$1:$AR$1,$B34) -> 952771 | M34: =C34/SUM(C32:C43) -> 0.4927293 | N34: =D34/SUM(D32:D43) -> 0.33010802 | O34: =E34/SUM(E32:E43) -> 0.29479879 | P34: =F34/SUM(F32:F43) -> 0.26426994 | Q34: =G34/SUM(G32:G43) -> 0.20205182 | R34: =H34/SUM(H32:H43) -> 0.14956951 | S34: =I34/SUM(I32:I43) -> 0.062631528 | T34: =J34/SUM(J32:J43) -> 0.036915895 | U34: =K34/SUM(K32:K43) -> 0.024790574
A35: =A34 -> AR | B35: geothermal | C35: =SUMIFS(INDEX('IRA-BIL_IRA-BIL - Mid_annual_st'!$W$3:$AR$434,MATCH(C30,'IRA-BIL_IRA-BIL - Mid_annual_st'!$A$3:$A$434,0),),'IRA-BIL_IRA-BIL - Mid_annual_st'!$W$1:$AR$1,$B35) -> 0 | D35: =SUMIFS(INDEX('IRA-BIL_IRA-BIL - Mid_annual_st'!$W$3:$AR$434,MATCH(D30,'IRA-BIL_IRA-BIL - Mid_annual_st'!$A$3:$A$434,0),),'IRA-BIL_IRA-BIL - Mid_annual_st'!$W$1:$AR$1,$B35) -> 0 | E35: =SUMIFS(INDEX('IRA-BIL_IRA-BIL - Mid_annual_st'!$W$3:$AR$434,MATCH(E30,'IRA-BIL_IRA-BIL - Mid_annual_st'!$A$3:$A$434,0),),'IRA-BIL_IRA-BIL - Mid_annual_st'!$W$1:$AR$1,$B35) -> 0 | F35: =SUMIFS(INDEX('IRA-BIL_IRA-BIL - Mid_annual_st'!$W$3:$AR$434,MATCH(F30,'IRA-BIL_IRA-BIL - Mid_annual_st'!$A$3:$A$434,0),),'IRA-BIL_IRA-BIL - Mid_annual_st'!$W$1:$AR$1,$B35) -> 0 | G35: =SUMIFS(INDEX('IRA-BIL_IRA-BIL - Mid_annual_st'!$W$3:$AR$434,MATCH(G30,'IRA-BIL_IRA-BIL - Mid_annual_st'!$A$3:$A$434,0),),'IRA-BIL_IRA-BIL - Mid_annual_st'!$W$1:$AR$1,$B35) -> 0 | H35: =SUMIFS(INDEX('IRA-BIL_IRA-BIL - Mid_annual_st'!$W$3:$AR$434,MATCH(H30,'IRA-BIL_IRA-BIL - Mid_annual_st'!$A$3:$A$434,0),),'IRA-BIL_IRA-BIL - Mid_annual_st'!$W$1:$AR$1,$B35) -> 0 | I35: =SUMIFS(INDEX('IRA-BIL_IRA-BIL - Mid_annual_st'!$W$3:$AR$434,MATCH(I30,'IRA-BIL_IRA-BIL - Mid_annual_st'!$A$3:$A$434,0),),'IRA-BIL_IRA-BIL - Mid_annual_st'!$W$1:$AR$1,$B35) -> 0 | J35: =SUMIFS(INDEX('IRA-BIL_IRA-BIL - Mid_annual_st'!$W$3:$AR$434,MATCH(J30,'IRA-BIL_IRA-BIL - Mid_annual_st'!$A$3:$A$434,0),),'IRA-BIL_IRA-BIL - Mid_annual_st'!$W$1:$AR$1,$B35) -> 0 | K35: =SUMIFS(INDEX('IRA-BIL_IRA-BIL - Mid_annual_st'!$W$3:$AR$434,MATCH(K30,'IRA-BIL_IRA-BIL - Mid_annual_st'!$A$3:$A$434,0),),'IRA-BIL_IRA-BIL - Mid_annual_st'!$W$1:$AR$1,$B35) -> 0 | M35: =C35/SUM(C32:C43) -> 0 | N35: =D35/SUM(D32:D43) -> 0 | O35: =E35/SUM(E32:E43) -> 0 | P35: =F35/SUM(F32:F43) -> 0 | Q35: =G35/SUM(G32:G43) -> 0 | R35: =H35/SUM(H32:H43) -> 0 | S35: =I35/SUM(I32:I43) -> 0 | T35: =J35/SUM(J32:J43) -> 0 | U35: =K35/SUM(K32:K43) -> 0
A36: =A35 -> AR | B36: hydro | C36: =SUMIFS(INDEX('IRA-BIL_IRA-BIL - Mid_annual_st'!$W$3:$AR$434,MATCH(C30,'IRA-BIL_IRA-BIL - Mid_annual_st'!$A$3:$A$434,0),),'IRA-BIL_IRA-BIL - Mid_annual_st'!$W$1:$AR$1,$B36) -> 2917131 | D36: =SUMIFS(INDEX('IRA-BIL_IRA-BIL - Mid_annual_st'!$W$3:$AR$434,MATCH(D30,'IRA-BIL_IRA-BIL - Mid_annual_st'!$A$3:$A$434,0),),'IRA-BIL_IRA-BIL - Mid_annual_st'!$W$1:$AR$1,$B36) -> 2917131 | E36: =SUMIFS(INDEX('IRA-BIL_IRA-BIL - Mid_annual_st'!$W$3:$AR$434,MATCH(E30,'IRA-BIL_IRA-BIL - Mid_annual_st'!$A$3:$A$434,0),),'IRA-BIL_IRA-BIL - Mid_annual_st'!$W$1:$AR$1,$B36) -> 2919630 | F36: =SUMIFS(INDEX('IRA-BIL_IRA-BIL - Mid_annual_st'!$W$3:$AR$434,MATCH(F30,'IRA-BIL_IRA-BIL - Mid_annual_st'!$A$3:$A$434,0),),'IRA-BIL_IRA-BIL - Mid_annual_st'!$W$1:$AR$1,$B36) -> 2921353 | G36: =SUMIFS(INDEX('IRA-BIL_IRA-BIL - Mid_annual_st'!$W$3:$AR$434,MATCH(G30,'IRA-BIL_IRA-BIL - Mid_annual_st'!$A$3:$A$434,0),),'IRA-BIL_IRA-BIL - Mid_annual_st'!$W$1:$AR$1,$B36) -> 2921865 | H36: =SUMIFS(INDEX('IRA-BIL_IRA-BIL - Mid_annual_st'!$W$3:$AR$434,MATCH(H30,'IRA-BIL_IRA-BIL - Mid_annual_st'!$A$3:$A$434,0),),'IRA-BIL_IRA-BIL - Mid_annual_st'!$W$1:$AR$1,$B36) -> 2918929 | I36: =SUMIFS(INDEX('IRA-BIL_IRA-BIL - Mid_annual_st'!$W$3:$AR$434,MATCH(I30,'IRA-BIL_IRA-BIL - Mid_annual_st'!$A$3:$A$434,0),),'IRA-BIL_IRA-BIL - Mid_annual_st'!$W$1:$AR$1,$B36) -> 2963510 | J36: =SUMIFS(INDEX('IRA-BIL_IRA-BIL - Mid_annual_st'!$W$3:$AR$434,MATCH(J30,'IRA-BIL_IRA-BIL - Mid_annual_st'!$A$3:$A$434,0),),'IRA-BIL_IRA-BIL - Mid_annual_st'!$W$1:$AR$1,$B36) -> 2963318 | K36: =SUMIFS(INDEX('IRA-BIL_IRA-BIL - Mid_annual_st'!$W$3:$AR$434,MATCH(K30,'IRA-BIL_IRA-BIL - Mid_annual_st'!$A$3:$A$434,0),),'IRA-BIL_IRA-BIL - Mid_annual_st'!$W$1:$AR$1,$B36) -> 2963598 | M36: =C36/SUM(C32:C43) -> 0.048057446 | N36: =D36/SUM(D32:D43) -> 0.06266031 | O36: =E36/SUM(E32:E43) -> 0.064177878 | P36: =F36/SUM(F32:F43) -> 0.06428033 | Q36: =G36/SUM(G32:G43) -> 0.068218192 | R36: =H36/SUM(H32:H43) -> 0.066947753 | S36: =I36/SUM(I32:I43) -> 0.077357521 | T36: =J36/SUM(J32:J43) -> 0.076941308 | U36: =K36/SUM(K32:K43) -> 0.07711118
A37: =A36 -> AR | B37: natural gas steam turbine | C37: =SUMIFS(INDEX('IRA-BIL_IRA-BIL - Mid_annual_st'!$W$3:$AR$434,MATCH(C30,'IRA-BIL_IRA-BIL - Mid_annual_st'!$A$3:$A$434,0),),'IRA-BIL_IRA-BIL - Mid_annual_st'!$W$1:$AR$1,$B37) -> 12366300 | D37: =SUMIFS(INDEX('IRA-BIL_IRA-BIL - Mid_annual_st'!$W$3:$AR$434,MATCH(D30,'IRA-BIL_IRA-BIL - Mid_annual_st'!$A$3:$A$434,0),),'IRA-BIL_IRA-BIL - Mid_annual_st'!$W$1:$AR$1,$B37) -> 12660302 | E37: =SUMIFS(INDEX('IRA-BIL_IRA-BIL - Mid_annual_st'!$W$3:$AR$434,MATCH(E30,'IRA-BIL_IRA-BIL - Mid_annual_st'!$A$3:$A$434,0),),'IRA-BIL_IRA-BIL - Mid_annual_st'!$W$1:$AR$1,$B37) -> 13367158 | F37: =SUMIFS(INDEX('IRA-BIL_IRA-BIL - Mid_annual_st'!$W$3:$AR$434,MATCH(F30,'IRA-BIL_IRA-BIL - Mid_annual_st'!$A$3:$A$434,0),),'IRA-BIL_IRA-BIL - Mid_annual_st'!$W$1:$AR$1,$B37) -> 11151416 | G37: =SUMIFS(INDEX('IRA-BIL_IRA-BIL - Mid_annual_st'!$W$3:$AR$434,MATCH(G30,'IRA-BIL_IRA-BIL - Mid_annual_st'!$A$3:$A$434,0),),'IRA-BIL_IRA-BIL - Mid_annual_st'!$W$1:$AR$1,$B37) -> 10608346 | H37: =SUMIFS(INDEX('IRA-BIL_IRA-BIL - Mid_annual_st'!$W$3:$AR$434,MATCH(H30,'IRA-BIL_IRA-BIL - Mid_annual_st'!$A$3:$A$434,0),),'IRA-BIL_IRA-BIL - Mid_annual_st'!$W$1:$AR$1,$B37) -> 7613467 | I37: =SUMIFS(INDEX('IRA-BIL_IRA-BIL - Mid_annual_st'!$W$3:$AR$434,MATCH(I30,'IRA-BIL_IRA-BIL - Mid_annual_st'!$A$3:$A$434,0),),'IRA-BIL_IRA-BIL - Mid_annual_st'!$W$1:$AR$1,$B37) -> 2664205 | J37: =SUMIFS(INDEX('IRA-BIL_IRA-BIL - Mid_annual_st'!$W$3:$AR$434,MATCH(J30,'IRA-BIL_IRA-BIL - Mid_annual_st'!$A$3:$A$434,0),),'IRA-BIL_IRA-BIL - Mid_annual_st'!$W$1:$AR$1,$B37) -> 1071846 | K37: =SUMIFS(INDEX('IRA-BIL_IRA-BIL - Mid_annual_st'!$W$3:$AR$434,MATCH(K30,'IRA-BIL_IRA-BIL - Mid_annual_st'!$A$3:$A$434,0),),'IRA-BIL_IRA-BIL - Mid_annual_st'!$W$1:$AR$1,$B37) -> 538205 | M37: =C37/SUM(C32:C43) -> 0.2037251 | N37: =D37/SUM(D32:D43) -> 0.27194475 | O37: =E37/SUM(E32:E43) -> 0.29383032 | P37: =F37/SUM(F32:F43) -> 0.24537148 | Q37: =G37/SUM(G32:G43) -> 0.24767817 | R37: =H37/SUM(H32:H43) -> 0.17462039 | S37: =I37/SUM(I32:I43) -> 0.06954466 | T37: =J37/SUM(J32:J43) -> 0.027830031 | U37: =K37/SUM(K32:K43) -> 0.014003796
A38: =A37 -> AR | B38: nuclear | C38: =SUMIFS(INDEX('IRA-BIL_IRA-BIL - Mid_annual_st'!$W$3:$AR$434,MATCH(C30,'IRA-BIL_IRA-BIL - Mid_annual_st'!$A$3:$A$434,0),),'IRA-BIL_IRA-BIL - Mid_annual_st'!$W$1:$AR$1,$B38) -> 14613013 | D38: =SUMIFS(INDEX('IRA-BIL_IRA-BIL - Mid_annual_st'!$W$3:$AR$434,MATCH(D30,'IRA-BIL_IRA-BIL - Mid_annual_st'!$A$3:$A$434,0),),'IRA-BIL_IRA-BIL - Mid_annual_st'!$W$1:$AR$1,$B38) -> 14613013 | E38: =SUMIFS(INDEX('IRA-BIL_IRA-BIL - Mid_annual_st'!$W$3:$AR$434,MATCH(E30,'IRA-BIL_IRA-BIL - Mid_annual_st'!$A$3:$A$434,0),),'IRA-BIL_IRA-BIL - Mid_annual_st'!$W$1:$AR$1,$B38) -> 14613013 | F38: =SUMIFS(INDEX('IRA-BIL_IRA-BIL - Mid_annual_st'!$W$3:$AR$434,MATCH(F30,'IRA-BIL_IRA-BIL - Mid_annual_st'!$A$3:$A$434,0),),'IRA-BIL_IRA-BIL - Mid_annual_st'!$W$1:$AR$1,$B38) -> 14613013 | G38: =SUMIFS(INDEX('IRA-BIL_IRA-BIL - Mid_annual_st'!$W$3:$AR$434,MATCH(G30,'IRA-BIL_IRA-BIL - Mid_annual_st'!$A$3:$A$434,0),),'IRA-BIL_IRA-BIL - Mid_annual_st'!$W$1:$AR$1,$B38) -> 14613013 | H38: =SUMIFS(INDEX('IRA-BIL_IRA-BIL - Mid_annual_st'!$W$3:$AR$434,MATCH(H30,'IRA-BIL_IRA-BIL - Mid_annual_st'!$A$3:$A$434,0),),'IRA-BIL_IRA-BIL - Mid_annual_st'!$W$1:$AR$1,$B38) -> 14613013 | I38: =SUMIFS(INDEX('IRA-BIL_IRA-BIL - Mid_annual_st'!$W$3:$AR$434,MATCH(I30,'IRA-BIL_IRA-BIL - Mid_annual_st'!$A$3:$A$434,0),),'IRA-BIL_IRA-BIL - Mid_annual_st'!$W$1:$AR$1,$B38) -> 14613013 | J38: =SUMIFS(INDEX('IRA-BIL_IRA-BIL - Mid_annual_st'!$W$3:$AR$434,MATCH(J30,'IRA-BIL_IRA-BIL - Mid_annual_st'!$A$3:$A$434,0),),'IRA-BIL_IRA-BIL - Mid_annual_st'!$W$1:$AR$1,$B38) -> 14120622 | K38: =SUMIFS(INDEX('IRA-BIL_IRA-BIL - Mid_annual_st'!$W$3:$AR$434,MATCH(K30,'IRA-BIL_IRA-BIL - Mid_annual_st'!$A$3:$A$434,0),),'IRA-BIL_IRA-BIL - Mid_annual_st'!$W$1:$AR$1,$B38) -> 14017535 | M38: =C38/SUM(C32:C43) -> 0.24073793 | N38: =D38/SUM(D32:D43) -> 0.3138892 | O38: =E38/SUM(E32:E43) -> 0.3212161 | P38: =F38/SUM(F32:F43) -> 0.32153913 | Q38: =G38/SUM(G32:G43) -> 0.34117707 | R38: =H38/SUM(H32:H43) -> 0.33516005 | S38: =I38/SUM(I32:I43) -> 0.3814485 | T38: =J38/SUM(J32:J43) -> 0.36663602 | U38: =K38/SUM(K32:K43) -> 0.3647285
A39: =A38 -> AR | B39: offshore wind | C39: =SUMIFS(INDEX('IRA-BIL_IRA-BIL - Mid_annual_st'!$W$3:$AR$434,MATCH(C30,'IRA-BIL_IRA-BIL - Mid_annual_st'!$A$3:$A$434,0),),'IRA-BIL_IRA-BIL - Mid_annual_st'!$W$1:$AR$1,$B39) -> 0 | D39: =SUMIFS(INDEX('IRA-BIL_IRA-BIL - Mid_annual_st'!$W$3:$AR$434,MATCH(D30,'IRA-BIL_IRA-BIL - Mid_annual_st'!$A$3:$A$434,0),),'IRA-BIL_IRA-BIL - Mid_annual_st'!$W$1:$AR$1,$B39) -> 0 | E39: =SUMIFS(INDEX('IRA-BIL_IRA-BIL - Mid_annual_st'!$W$3:$AR$434,MATCH(E30,'IRA-BIL_IRA-BIL - Mid_annual_st'!$A$3:$A$434,0),),'IRA-BIL_IRA-BIL - Mid_annual_st'!$W$1:$AR$1,$B39) -> 0 | F39: =SUMIFS(INDEX('IRA-BIL_IRA-BIL - Mid_annual_st'!$W$3:$AR$434,MATCH(F30,'IRA-BIL_IRA-BIL - Mid_annual_st'!$A$3:$A$434,0),),'IRA-BIL_IRA-BIL - Mid_annual_st'!$W$1:$AR$1,$B39) -> 0 | G39: =SUMIFS(INDEX('IRA-BIL_IRA-BIL - Mid_annual_st'!$W$3:$AR$434,MATCH(G30,'IRA-BIL_IRA-BIL - Mid_annual_st'!$A$3:$A$434,0),),'IRA-BIL_IRA-BIL - Mid_annual_st'!$W$1:$AR$1,$B39) -> 0 | H39: =SUMIFS(INDEX('IRA-BIL_IRA-BIL - Mid_annual_st'!$W$3:$AR$434,MATCH(H30,'IRA-BIL_IRA-BIL - Mid_annual_st'!$A$3:$A$434,0),),'IRA-BIL_IRA-BIL - Mid_annual_st'!$W$1:$AR$1,$B39) -> 0 | I39: =SUMIFS(INDEX('IRA-BIL_IRA-BIL - Mid_annual_st'!$W$3:$AR$434,MATCH(I30,'IRA-BIL_IRA-BIL - Mid_annual_st'!$A$3:$A$434,0),),'IRA-BIL_IRA-BIL - Mid_annual_st'!$W$1:$AR$1,$B39) -> 0 | J39: =SUMIFS(INDEX('IRA-BIL_IRA-BIL - Mid_annual_st'!$W$3:$AR$434,MATCH(J30,'IRA-BIL_IRA-BIL - Mid_annual_st'!$A$3:$A$434,0),),'IRA-BIL_IRA-BIL - Mid_annual_st'!$W$1:$AR$1,$B39) -> 0 | K39: =SUMIFS(INDEX('IRA-BIL_IRA-BIL - Mid_annual_st'!$W$3:$AR$434,MATCH(K30,'IRA-BIL_IRA-BIL - Mid_annual_st'!$A$3:$A$434,0),),'IRA-BIL_IRA-BIL - Mid_annual_st'!$W$1:$AR$1,$B39) -> 0 | M39: =C39/SUM(C32:C43) -> 0 | N39: =D39/SUM(D32:D43) -> 0 | O39: =E39/SUM(E32:E43) -> 0 | P39: =F39/SUM(F32:F43) -> 0 | Q39: =G39/SUM(G32:G43) -> 0 | R39: =H39/SUM(H32:H43) -> 0 | S39: =I39/SUM(I32:I43) -> 0 | T39: =J39/SUM(J32:J43) -> 0 | U39: =K39/SUM(K32:K43) -> 0
A40: =A39 -> AR | B40: petroleum | C40: =SUMIFS(INDEX('IRA-BIL_IRA-BIL - Mid_annual_st'!$W$3:$AR$434,MATCH(C30,'IRA-BIL_IRA-BIL - Mid_annual_st'!$A$3:$A$434,0),),'IRA-BIL_IRA-BIL - Mid_annual_st'!$W$1:$AR$1,$B40) -> 281525 | D40: =SUMIFS(INDEX('IRA-BIL_IRA-BIL - Mid_annual_st'!$W$3:$AR$434,MATCH(D30,'IRA-BIL_IRA-BIL - Mid_annual_st'!$A$3:$A$434,0),),'IRA-BIL_IRA-BIL - Mid_annual_st'!$W$1:$AR$1,$B40) -> 281525 | E40: =SUMIFS(INDEX('IRA-BIL_IRA-BIL - Mid_annual_st'!$W$3:$AR$434,MATCH(E30,'IRA-BIL_IRA-BIL - Mid_annual_st'!$A$3:$A$434,0),),'IRA-BIL_IRA-BIL - Mid_annual_st'!$W$1:$AR$1,$B40) -> 150536 | F40: =SUMIFS(INDEX('IRA-BIL_IRA-BIL - Mid_annual_st'!$W$3:$AR$434,MATCH(F30,'IRA-BIL_IRA-BIL - Mid_annual_st'!$A$3:$A$434,0),),'IRA-BIL_IRA-BIL - Mid_annual_st'!$W$1:$AR$1,$B40) -> 0 | G40: =SUMIFS(INDEX('IRA-BIL_IRA-BIL - Mid_annual_st'!$W$3:$AR$434,MATCH(G30,'IRA-BIL_IRA-BIL - Mid_annual_st'!$A$3:$A$434,0),),'IRA-BIL_IRA-BIL - Mid_annual_st'!$W$1:$AR$1,$B40) -> 0 | H40: =SUMIFS(INDEX('IRA-BIL_IRA-BIL - Mid_annual_st'!$W$3:$AR$434,MATCH(H30,'IRA-BIL_IRA-BIL - Mid_annual_st'!$A$3:$A$434,0),),'IRA-BIL_IRA-BIL - Mid_annual_st'!$W$1:$AR$1,$B40) -> 0 | I40: =SUMIFS(INDEX('IRA-BIL_IRA-BIL - Mid_annual_st'!$W$3:$AR$434,MATCH(I30,'IRA-BIL_IRA-BIL - Mid_annual_st'!$A$3:$A$434,0),),'IRA-BIL_IRA-BIL - Mid_annual_st'!$W$1:$AR$1,$B40) -> 0 | J40: =SUMIFS(INDEX('IRA-BIL_IRA-BIL - Mid_annual_st'!$W$3:$AR$434,MATCH(J30,'IRA-BIL_IRA-BIL - Mid_annual_st'!$A$3:$A$434,0),),'IRA-BIL_IRA-BIL - Mid_annual_st'!$W$1:$AR$1,$B40) -> 0 | K40: =SUMIFS(INDEX('IRA-BIL_IRA-BIL - Mid_annual_st'!$W$3:$AR$434,MATCH(K30,'IRA-BIL_IRA-BIL - Mid_annual_st'!$A$3:$A$434,0),),'IRA-BIL_IRA-BIL - Mid_annual_st'!$W$1:$AR$1,$B40) -> 0 | M40: =C40/SUM(C32:C43) -> 0.0046379037 | N40: =D40/SUM(D32:D43) -> 0.0060471895 | O40: =E40/SUM(E32:E43) -> 0.0033090087 | P40: =F40/SUM(F32:F43) -> 0 | Q40: =G40/SUM(G32:G43) -> 0 | R40: =H40/SUM(H32:H43) -> 0 | S40: =I40/SUM(I32:I43) -> 0 | T40: =J40/SUM(J32:J43) -> 0 | U40: =K40/SUM(K32:K43) -> 0
A41: =A40 -> AR | B41: onshore wind | C41: =SUMIFS(INDEX('IRA-BIL_IRA-BIL - Mid_annual_st'!$W$3:$AR$434,MATCH(C30,'IRA-BIL_IRA-BIL - Mid_annual_st'!$A$3:$A$434,0),),'IRA-BIL_IRA-BIL - Mid_annual_st'!$W$1:$AR$1,$B41) -> 0 | D41: =SUMIFS(INDEX('IRA-BIL_IRA-BIL - Mid_annual_st'!$W$3:$AR$434,MATCH(D30,'IRA-BIL_IRA-BIL - Mid_annual_st'!$A$3:$A$434,0),),'IRA-BIL_IRA-BIL - Mid_annual_st'!$W$1:$AR$1,$B41) -> 0 | E41: =SUMIFS(INDEX('IRA-BIL_IRA-BIL - Mid_annual_st'!$W$3:$AR$434,MATCH(E30,'IRA-BIL_IRA-BIL - Mid_annual_st'!$A$3:$A$434,0),),'IRA-BIL_IRA-BIL - Mid_annual_st'!$W$1:$AR$1,$B41) -> 0 | F41: =SUMIFS(INDEX('IRA-BIL_IRA-BIL - Mid_annual_st'!$W$3:$AR$434,MATCH(F30,'IRA-BIL_IRA-BIL - Mid_annual_st'!$A$3:$A$434,0),),'IRA-BIL_IRA-BIL - Mid_annual_st'!$W$1:$AR$1,$B41) -> 0 | G41: =SUMIFS(INDEX('IRA-BIL_IRA-BIL - Mid_annual_st'!$W$3:$AR$434,MATCH(G30,'IRA-BIL_IRA-BIL - Mid_annual_st'!$A$3:$A$434,0),),'IRA-BIL_IRA-BIL - Mid_annual_st'!$W$1:$AR$1,$B41) -> 0 | H41: =SUMIFS(INDEX('IRA-BIL_IRA-BIL - Mid_annual_st'!$W$3:$AR$434,MATCH(H30,'IRA-BIL_IRA-BIL - Mid_annual_st'!$A$3:$A$434,0),),'IRA-BIL_IRA-BIL - Mid_annual_st'!$W$1:$AR$1,$B41) -> 0 | I41: =SUMIFS(INDEX('IRA-BIL_IRA-BIL - Mid_annual_st'!$W$3:$AR$434,MATCH(I30,'IRA-BIL_IRA-BIL - Mid_annual_st'!$A$3:$A$434,0),),'IRA-BIL_IRA-BIL - Mid_annual_st'!$W$1:$AR$1,$B41) -> 0 | J41: =SUMIFS(INDEX('IRA-BIL_IRA-BIL - Mid_annual_st'!$W$3:$AR$434,MATCH(J30,'IRA-BIL_IRA-BIL - Mid_annual_st'!$A$3:$A$434,0),),'IRA-BIL_IRA-BIL - Mid_annual_st'!$W$1:$AR$1,$B41) -> 0 | K41: =SUMIFS(INDEX('IRA-BIL_IRA-BIL - Mid_annual_st'!$W$3:$AR$434,MATCH(K30,'IRA-BIL_IRA-BIL - Mid_annual_st'!$A$3:$A$434,0),),'IRA-BIL_IRA-BIL - Mid_annual_st'!$W$1:$AR$1,$B41) -> 0 | M41: =C41/SUM(C32:C43) -> 0 | N41: =D41/SUM(D32:D43) -> 0 | O41: =E41/SUM(E32:E43) -> 0 | P41: =F41/SUM(F32:F43) -> 0 | Q41: =G41/SUM(G32:G43) -> 0 | R41: =H41/SUM(H32:H43) -> 0 | S41: =I41/SUM(I32:I43) -> 0 | T41: =J41/SUM(J32:J43) -> 0 | U41: =K41/SUM(K32:K43) -> 0
A42: =A41 -> AR | B42: pumped hydro | C42: 0 | D42: 0 | E42: 0 | F42: 0 | G42: 0 | H42: 0 | I42: 0 | J42: 0 | K42: 0 | M42: 0 | N42: 0 | O42: 0 | P42: 0 | Q42: 0 | R42: 0 | S42: 0 | T42: 0 | U42: 0
A43: =A42 -> AR | B43: solar pv | C43: =SUMIFS(INDEX('IRA-BIL_IRA-BIL - Mid_annual_st'!$W$3:$AR$434,MATCH(C30,'IRA-BIL_IRA-BIL - Mid_annual_st'!$A$3:$A$434,0),),'IRA-BIL_IRA-BIL - Mid_annual_st'!$W$1:$AR$1,$B43) -> 573458 | D43: =SUMIFS(INDEX('IRA-BIL_IRA-BIL - Mid_annual_st'!$W$3:$AR$434,MATCH(D30,'IRA-BIL_IRA-BIL - Mid_annual_st'!$A$3:$A$434,0),),'IRA-BIL_IRA-BIL - Mid_annual_st'!$W$1:$AR$1,$B43) -> 674270 | E43: =SUMIFS(INDEX('IRA-BIL_IRA-BIL - Mid_annual_st'!$W$3:$AR$434,MATCH(E30,'IRA-BIL_IRA-BIL - Mid_annual_st'!$A$3:$A$434,0),),'IRA-BIL_IRA-BIL - Mid_annual_st'!$W$1:$AR$1,$B43) -> 990857 | F43: =SUMIFS(INDEX('IRA-BIL_IRA-BIL - Mid_annual_st'!$W$3:$AR$434,MATCH(F30,'IRA-BIL_IRA-BIL - Mid_annual_st'!$A$3:$A$434,0),),'IRA-BIL_IRA-BIL - Mid_annual_st'!$W$1:$AR$1,$B43) -> 4710628 | G43: =SUMIFS(INDEX('IRA-BIL_IRA-BIL - Mid_annual_st'!$W$3:$AR$434,MATCH(G30,'IRA-BIL_IRA-BIL - Mid_annual_st'!$A$3:$A$434,0),),'IRA-BIL_IRA-BIL - Mid_annual_st'!$W$1:$AR$1,$B43) -> 5993461 | H43: =SUMIFS(INDEX('IRA-BIL_IRA-BIL - Mid_annual_st'!$W$3:$AR$434,MATCH(H30,'IRA-BIL_IRA-BIL - Mid_annual_st'!$A$3:$A$434,0),),'IRA-BIL_IRA-BIL - Mid_annual_st'!$W$1:$AR$1,$B43) -> 11893987 | I43: =SUMIFS(INDEX('IRA-BIL_IRA-BIL - Mid_annual_st'!$W$3:$AR$434,MATCH(I30,'IRA-BIL_IRA-BIL - Mid_annual_st'!$A$3:$A$434,0),),'IRA-BIL_IRA-BIL - Mid_annual_st'!$W$1:$AR$1,$B43) -> 15631539 | J43: =SUMIFS(INDEX('IRA-BIL_IRA-BIL - Mid_annual_st'!$W$3:$AR$434,MATCH(J30,'IRA-BIL_IRA-BIL - Mid_annual_st'!$A$3:$A$434,0),),'IRA-BIL_IRA-BIL - Mid_annual_st'!$W$1:$AR$1,$B43) -> 18901139 | K43: =SUMIFS(INDEX('IRA-BIL_IRA-BIL - Mid_annual_st'!$W$3:$AR$434,MATCH(K30,'IRA-BIL_IRA-BIL - Mid_annual_st'!$A$3:$A$434,0),),'IRA-BIL_IRA-BIL - Mid_annual_st'!$W$1:$AR$1,$B43) -> 19926255 | M43: =C43/SUM(C32:C43) -> 0.0094472709 | N43: =D43/SUM(D32:D43) -> 0.014483397 | O43: =E43/SUM(E32:E43) -> 0.021780534 | P43: =F43/SUM(F32:F43) -> 0.10365085 | Q43: =G43/SUM(G32:G43) -> 0.13993223 | R43: =H43/SUM(H32:H43) -> 0.27279722 | S43: =I43/SUM(I32:I43) -> 0.40803544 | T43: =J43/SUM(J32:J43) -> 0.49076014 | U43: =K43/SUM(K32:K43) -> 0.51847013
A44: CA | C44: =$A44&"_"&C45 -> CA_2022 | D44: =$A44&"_"&D45 -> CA_2023 | E44: =$A44&"_"&E45 -> CA_2024 | F44: =$A44&"_"&F45 -> CA_2025 | G44: =$A44&"_"&G45 -> CA_2026 | H44: =$A44&"_"&H45 -> CA_2027 | I44: =$A44&"_"&I45 -> CA_2028 | J44: =$A44&"_"&J45 -> CA_2029 | K44: =$A44&"_"&K45 -> CA_2030 | M44: =$A44&"_"&M45 -> CA_2022 | N44: =$A44&"_"&N45 -> CA_2023 | O44: =$A44&"_"&O45 -> CA_2024 | P44: =$A44&"_"&P45 -> CA_2025 | Q44: =$A44&"_"&Q45 -> CA_2026 | R44: =$A44&"_"&R45 -> CA_2027 | S44: =$A44&"_"&S45 -> CA_2028 | T44: =$A44&"_"&T45 -> CA_2029 | U44: =$A44&"_"&U45 -> CA_2030
C45: 2022 | D45: 2023 | E45: 2024 | F45: 2025 | G45: 2026 | H45: 2027 | I45: 2028 | J45: 2029 | K45: 2030 | M45: 2022 | N45: 2023 | O45: 2024 | P45: 2025 | Q45: 2026 | R45: 2027 | S45: 2028 | T45: 2029 | U45: 2030
A46: =A44 -> CA | B46: battery | C46: 0 | D46: 0 | E46: 0 | F46: 0 | G46: 0 | H46: 0 | I46: 0 | J46: 0 | K46: 0 | M46: 0 | N46: 0 | O46: 0 | P46: 0 | Q46: 0 | R46: 0 | S46: 0 | T46: 0 | U46: 0
A47: =A46 -> CA | B47: biomass | C47: =SUMIFS(INDEX('IRA-BIL_IRA-BIL - Mid_annual_st'!$W$3:$AR$434,MATCH(C44,'IRA-BIL_IRA-BIL - Mid_annual_st'!$A$3:$A$434,0),),'IRA-BIL_IRA-BIL - Mid_annual_st'!$W$1:$AR$1,$B47) -> 2221389 | D47: =SUMIFS(INDEX('IRA-BIL_IRA-BIL - Mid_annual_st'!$W$3:$AR$434,MATCH(D44,'IRA-BIL_IRA-BIL - Mid_annual_st'!$A$3:$A$434,0),),'IRA-BIL_IRA-BIL - Mid_annual_st'!$W$1:$AR$1,$B47) -> 1535504 | E47: =SUMIFS(INDEX('IRA-BIL_IRA-BIL - Mid_annual_st'!$W$3:$AR$434,MATCH(E44,'IRA-BIL_IRA-BIL - Mid_annual_st'!$A$3:$A$434,0),),'IRA-BIL_IRA-BIL - Mid_annual_st'!$W$1:$AR$1,$B47) -> 1666675 | F47: =SUMIFS(INDEX('IRA-BIL_IRA-BIL - Mid_annual_st'!$W$3:$AR$434,MATCH(F44,'IRA-BIL_IRA-BIL - Mid_annual_st'!$A$3:$A$434,0),),'IRA-BIL_IRA-BIL - Mid_annual_st'!$W$1:$AR$1,$B47) -> 1494705 | G47: =SUMIFS(INDEX('IRA-BIL_IRA-BIL - Mid_annual_st'!$W$3:$AR$434,MATCH(G44,'IRA-BIL_IRA-BIL - Mid_annual_st'!$A$3:$A$434,0),),'IRA-BIL_IRA-BIL - Mid_annual_st'!$W$1:$AR$1,$B47) -> 1494705 | H47: =SUMIFS(INDEX('IRA-BIL_IRA-BIL - Mid_annual_st'!$W$3:$AR$434,MATCH(H44,'IRA-BIL_IRA-BIL - Mid_annual_st'!$A$3:$A$434,0),),'IRA-BIL_IRA-BIL - Mid_annual_st'!$W$1:$AR$1,$B47) -> 1491136 | I47: =SUMIFS(INDEX('IRA-BIL_IRA-BIL - Mid_annual_st'!$W$3:$AR$434,MATCH(I44,'IRA-BIL_IRA-BIL - Mid_annual_st'!$A$3:$A$434,0),),'IRA-BIL_IRA-BIL - Mid_annual_st'!$W$1:$AR$1,$B47) -> 1440320 | J47: =SUMIFS(INDEX('IRA-BIL_IRA-BIL - Mid_annual_st'!$W$3:$AR$434,MATCH(J44,'IRA-BIL_IRA-BIL - Mid_annual_st'!$A$3:$A$434,0),),'IRA-BIL_IRA-BIL - Mid_annual_st'!$W$1:$AR$1,$B47) -> 1415959 | K47: =SUMIFS(INDEX('IRA-BIL_IRA-BIL - Mid_annual_st'!$W$3:$AR$434,MATCH(K44,'IRA-BIL_IRA-BIL - Mid_annual_st'!$A$3:$A$434,0),),'IRA-BIL_IRA-BIL - Mid_annual_st'!$W$1:$AR$1,$B47) -> 1391348 | M47: =C47/SUM(C46:C57) -> 0.010931221 | N47: =D47/SUM(D46:D57) -> 0.00793214 | O47: =E47/SUM(E46:E57) -> 0.0081141313 | P47: =F47/SUM(F46:F57) -> 0.0075456887 | Q47: =G47/SUM(G46:G57) -> 0.0076088211 | R47: =H47/SUM(H46:H57) -> 0.0073539963 | S47: =I47/SUM(I46:I57) -> 0.0076081442 | T47: =J47/SUM(J46:J57) -> 0.0078166351 | U47: =K47/SUM(K46:K57) -> 0.0068409117
A48: =A47 -> CA | B48: hard coal | C48: =SUMIFS(INDEX('IRA-BIL_IRA-BIL - Mid_annual_st'!$W$3:$AR$434,MATCH(C44,'IRA-BIL_IRA-BIL - Mid_annual_st'!$A$3:$A$434,0),),'IRA-BIL_IRA-BIL - Mid_annual_st'!$W$1:$AR$1,$B48) -> 0 | D48: =SUMIFS(INDEX('IRA-BIL_IRA-BIL - Mid_annual_st'!$W$3:$AR$434,MATCH(D44,'IRA-BIL_IRA-BIL - Mid_annual_st'!$A$3:$A$434,0),),'IRA-BIL_IRA-BIL - Mid_annual_st'!$W$1:$AR$1,$B48) -> 0 | E48: =SUMIFS(INDEX('IRA-BIL_IRA-BIL - Mid_annual_st'!$W$3:$AR$434,MATCH(E44,'IRA-BIL_IRA-BIL - Mid_annual_st'!$A$3:$A$434,0),),'IRA-BIL_IRA-BIL - Mid_annual_st'!$W$1:$AR$1,$B48) -> 0 | F48: =SUMIFS(INDEX('IRA-BIL_IRA-BIL - Mid_annual_st'!$W$3:$AR$434,MATCH(F44,'IRA-BIL_IRA-BIL - Mid_annual_st'!$A$3:$A$434,0),),'IRA-BIL_IRA-BIL - Mid_annual_st'!$W$1:$AR$1,$B48) -> 41007 | G48: =SUMIFS(INDEX('IRA-BIL_IRA-BIL - Mid_annual_st'!$W$3:$AR$434,MATCH(G44,'IRA-BIL_IRA-BIL - Mid_annual_st'!$A$3:$A$434,0),),'IRA-BIL_IRA-BIL - Mid_annual_st'!$W$1:$AR$1,$B48) -> 82014 | H48: =SUMIFS(INDEX('IRA-BIL_IRA-BIL - Mid_annual_st'!$W$3:$AR$434,MATCH(H44,'IRA-BIL_IRA-BIL - Mid_annual_st'!$A$3:$A$434,0),),'IRA-BIL_IRA-BIL - Mid_annual_st'!$W$1:$AR$1,$B48) -> 123022 | I48: =SUMIFS(INDEX('IRA-BIL_IRA-BIL - Mid_annual_st'!$W$3:$AR$434,MATCH(I44,'IRA-BIL_IRA-BIL - Mid_annual_st'!$A$3:$A$434,0),),'IRA-BIL_IRA-BIL - Mid_annual_st'!$W$1:$AR$1,$B48) -> 0 | J48: =SUMIFS(INDEX('IRA-BIL_IRA-BIL - Mid_annual_st'!$W$3:$AR$434,MATCH(J44,'IRA-BIL_IRA-BIL - Mid_annual_st'!$A$3:$A$434,0),),'IRA-BIL_IRA-BIL - Mid_annual_st'!$W$1:$AR$1,$B48) -> 0 | K48: =SUMIFS(INDEX('IRA-BIL_IRA-BIL - Mid_annual_st'!$W$3:$AR$434,MATCH(K44,'IRA-BIL_IRA-BIL - Mid_annual_st'!$A$3:$A$434,0),),'IRA-BIL_IRA-BIL - Mid_annual_st'!$W$1:$AR$1,$B48) -> 0 | M48: =C48/SUM(C46:C57) -> 0 | N48: =D48/SUM(D46:D57) -> 0 | O48: =E48/SUM(E46:E57) -> 0 | P48: =F48/SUM(F46:F57) -> 0.0002070148 | Q48: =G48/SUM(G46:G57) -> 0.00041749365 | R48: =H48/SUM(H46:H57) -> 0.00060672087 | S48: =I48/SUM(I46:I57) -> 0 | T48: =J48/SUM(J46:J57) -> 0 | U48: =K48/SUM(K46:K57) -> 0
A49: =A48 -> CA | B49: geothermal | C49: =SUMIFS(INDEX('IRA-BIL_IRA-BIL - Mid_annual_st'!$W$3:$AR$434,MATCH(C44,'IRA-BIL_IRA-BIL - Mid_annual_st'!$A$3:$A$434,0),),'IRA-BIL_IRA-BIL - Mid_annual_st'!$W$1:$AR$1,$B49) -> 670989 | D49: =SUMIFS(INDEX('IRA-BIL_IRA-BIL - Mid_annual_st'!$W$3:$AR$434,MATCH(D44,'IRA-BIL_IRA-BIL - Mid_annual_st'!$A$3:$A$434,0),),'IRA-BIL_IRA-BIL - Mid_annual_st'!$W$1:$AR$1,$B49) -> 670989 | E49: =SUMIFS(INDEX('IRA-BIL_IRA-BIL - Mid_annual_st'!$W$3:$AR$434,MATCH(E44,'IRA-BIL_IRA-BIL - Mid_annual_st'!$A$3:$A$434,0),),'IRA-BIL_IRA-BIL - Mid_annual_st'!$W$1:$AR$1,$B49) -> 670989 | F49: =SUMIFS(INDEX('IRA-BIL_IRA-BIL - Mid_annual_st'!$W$3:$AR$434,MATCH(F44,'IRA-BIL_IRA-BIL - Mid_annual_st'!$A$3:$A$434,0),),'IRA-BIL_IRA-BIL - Mid_annual_st'!$W$1:$AR$1,$B49) -> 670989 | G49: =SUMIFS(INDEX('IRA-BIL_IRA-BIL - Mid_annual_st'!$W$3:$AR$434,MATCH(G44,'IRA-BIL_IRA-BIL - Mid_annual_st'!$A$3:$A$434,0),),'IRA-BIL_IRA-BIL - Mid_annual_st'!$W$1:$AR$1,$B49) -> 670989 | H49: =SUMIFS(INDEX('IRA-BIL_IRA-BIL - Mid_annual_st'!$W$3:$AR$434,MATCH(H44,'IRA-BIL_IRA-BIL - Mid_annual_st'!$A$3:$A$434,0),),'IRA-BIL_IRA-BIL - Mid_annual_st'!$W$1:$AR$1,$B49) -> 9216362 | I49: =SUMIFS(INDEX('IRA-BIL_IRA-BIL - Mid_annual_st'!$W$3:$AR$434,MATCH(I44,'IRA-BIL_IRA-BIL - Mid_annual_st'!$A$3:$A$434,0),),'IRA-BIL_IRA-BIL - Mid_annual_st'!$W$1:$AR$1,$B49) -> 9381313 | J49: =SUMIFS(INDEX('IRA-BIL_IRA-BIL - Mid_annual_st'!$W$3:$AR$434,MATCH(J44,'IRA-BIL_IRA-BIL - Mid_annual_st'!$A$3:$A$434,0),),'IRA-BIL_IRA-BIL - Mid_annual_st'!$W$1:$AR$1,$B49) -> 9546264 | K49: =SUMIFS(INDEX('IRA-BIL_IRA-BIL - Mid_annual_st'!$W$3:$AR$434,MATCH(K44,'IRA-BIL_IRA-BIL - Mid_annual_st'!$A$3:$A$434,0),),'IRA-BIL_IRA-BIL - Mid_annual_st'!$W$1:$AR$1,$B49) -> 9546264 | M49: =C49/SUM(C46:C57) -> 0.0033018662 | N49: =D49/SUM(D46:D57) -> 0.0034662096 | O49: =E49/SUM(E46:E57) -> 0.0032666794 | P49: =F49/SUM(F46:F57) -> 0.00338734 | Q49: =G49/SUM(G46:G57) -> 0.0034156808 | R49: =H49/SUM(H46:H57) -> 0.045453327 | S49: =I49/SUM(I46:I57) -> 0.049554531 | T49: =J49/SUM(J46:J57) -> 0.052699028 | U49: =K49/SUM(K46:K57) -> 0.046936603
A50: =A49 -> CA | B50: hydro | C50: =SUMIFS(INDEX('IRA-BIL_IRA-BIL - Mid_annual_st'!$W$3:$AR$434,MATCH(C44,'IRA-BIL_IRA-BIL - Mid_annual_st'!$A$3:$A$434,0),),'IRA-BIL_IRA-BIL - Mid_annual_st'!$W$1:$AR$1,$B50) -> 29045873 | D50: =SUMIFS(INDEX('IRA-BIL_IRA-BIL - Mid_annual_st'!$W$3:$AR$434,MATCH(D44,'IRA-BIL_IRA-BIL - Mid_annual_st'!$A$3:$A$434,0),),'IRA-BIL_IRA-BIL - Mid_annual_st'!$W$1:$AR$1,$B50) -> 29045873 | E50: =SUMIFS(INDEX('IRA-BIL_IRA-BIL - Mid_annual_st'!$W$3:$AR$434,MATCH(E44,'IRA-BIL_IRA-BIL - Mid_annual_st'!$A$3:$A$434,0),),'IRA-BIL_IRA-BIL - Mid_annual_st'!$W$1:$AR$1,$B50) -> 29081950 | F50: =SUMIFS(INDEX('IRA-BIL_IRA-BIL - Mid_annual_st'!$W$3:$AR$434,MATCH(F44,'IRA-BIL_IRA-BIL - Mid_annual_st'!$A$3:$A$434,0),),'IRA-BIL_IRA-BIL - Mid_annual_st'!$W$1:$AR$1,$B50) -> 29926687 | G50: =SUMIFS(INDEX('IRA-BIL_IRA-BIL - Mid_annual_st'!$W$3:$AR$434,MATCH(G44,'IRA-BIL_IRA-BIL - Mid_annual_st'!$A$3:$A$434,0),),'IRA-BIL_IRA-BIL - Mid_annual_st'!$W$1:$AR$1,$B50) -> 30031576 | H50: =SUMIFS(INDEX('IRA-BIL_IRA-BIL - Mid_annual_st'!$W$3:$AR$434,MATCH(H44,'IRA-BIL_IRA-BIL - Mid_annual_st'!$A$3:$A$434,0),),'IRA-BIL_IRA-BIL - Mid_annual_st'!$W$1:$AR$1,$B50) -> 30839968 | I50: =SUMIFS(INDEX('IRA-BIL_IRA-BIL - Mid_annual_st'!$W$3:$AR$434,MATCH(I44,'IRA-BIL_IRA-BIL - Mid_annual_st'!$A$3:$A$434,0),),'IRA-BIL_IRA-BIL - Mid_annual_st'!$W$1:$AR$1,$B50) -> 31160126 | J50: =SUMIFS(INDEX('IRA-BIL_IRA-BIL - Mid_annual_st'!$W$3:$AR$434,MATCH(J44,'IRA-BIL_IRA-BIL - Mid_annual_st'!$A$3:$A$434,0),),'IRA-BIL_IRA-BIL - Mid_annual_st'!$W$1:$AR$1,$B50) -> 31292832 | K50: =SUMIFS(INDEX('IRA-BIL_IRA-BIL - Mid_annual_st'!$W$3:$AR$434,MATCH(K44,'IRA-BIL_IRA-BIL - Mid_annual_st'!$A$3:$A$434,0),),'IRA-BIL_IRA-BIL - Mid_annual_st'!$W$1:$AR$1,$B50) -> 31462972 | M50: =C50/SUM(C46:C57) -> 0.14293168 | N50: =D50/SUM(D46:D57) -> 0.1500458 | O50: =E50/SUM(E46:E57) -> 0.14158415 | P50: =F50/SUM(F46:F57) -> 0.15107828 | Q50: =G50/SUM(G46:G57) -> 0.15287625 | R50: =H50/SUM(H46:H57) -> 0.1520968 | S50: =I50/SUM(I46:I57) -> 0.16459588 | T50: =J50/SUM(J46:J57) -> 0.1727484 | U50: =K50/SUM(K46:K57) -> 0.1546956
A51: =A50 -> CA | B51: natural gas steam turbine | C51: =SUMIFS(INDEX('IRA-BIL_IRA-BIL - Mid_annual_st'!$W$3:$AR$434,MATCH(C44,'IRA-BIL_IRA-BIL - Mid_annual_st'!$A$3:$A$434,0),),'IRA-BIL_IRA-BIL - Mid_annual_st'!$W$1:$AR$1,$B51) -> 92014589 | D51: =SUMIFS(INDEX('IRA-BIL_IRA-BIL - Mid_annual_st'!$W$3:$AR$434,MATCH(D44,'IRA-BIL_IRA-BIL - Mid_annual_st'!$A$3:$A$434,0),),'IRA-BIL_IRA-BIL - Mid_annual_st'!$W$1:$AR$1,$B51) -> 83708204 | E51: =SUMIFS(INDEX('IRA-BIL_IRA-BIL - Mid_annual_st'!$W$3:$AR$434,MATCH(E44,'IRA-BIL_IRA-BIL - Mid_annual_st'!$A$3:$A$434,0),),'IRA-BIL_IRA-BIL - Mid_annual_st'!$W$1:$AR$1,$B51) -> 75294834 | F51: =SUMIFS(INDEX('IRA-BIL_IRA-BIL - Mid_annual_st'!$W$3:$AR$434,MATCH(F44,'IRA-BIL_IRA-BIL - Mid_annual_st'!$A$3:$A$434,0),),'IRA-BIL_IRA-BIL - Mid_annual_st'!$W$1:$AR$1,$B51) -> 67449029 | G51: =SUMIFS(INDEX('IRA-BIL_IRA-BIL - Mid_annual_st'!$W$3:$AR$434,MATCH(G44,'IRA-BIL_IRA-BIL - Mid_annual_st'!$A$3:$A$434,0),),'IRA-BIL_IRA-BIL - Mid_annual_st'!$W$1:$AR$1,$B51) -> 65539556 | H51: =SUMIFS(INDEX('IRA-BIL_IRA-BIL - Mid_annual_st'!$W$3:$AR$434,MATCH(H44,'IRA-BIL_IRA-BIL - Mid_annual_st'!$A$3:$A$434,0),),'IRA-BIL_IRA-BIL - Mid_annual_st'!$W$1:$AR$1,$B51) -> 56551666 | I51: =SUMIFS(INDEX('IRA-BIL_IRA-BIL - Mid_annual_st'!$W$3:$AR$434,MATCH(I44,'IRA-BIL_IRA-BIL - Mid_annual_st'!$A$3:$A$434,0),),'IRA-BIL_IRA-BIL - Mid_annual_st'!$W$1:$AR$1,$B51) -> 41451679 | J51: =SUMIFS(INDEX('IRA-BIL_IRA-BIL - Mid_annual_st'!$W$3:$AR$434,MATCH(J44,'IRA-BIL_IRA-BIL - Mid_annual_st'!$A$3:$A$434,0),),'IRA-BIL_IRA-BIL - Mid_annual_st'!$W$1:$AR$1,$B51) -> 37893169 | K51: =SUMIFS(INDEX('IRA-BIL_IRA-BIL - Mid_annual_st'!$W$3:$AR$434,MATCH(K44,'IRA-BIL_IRA-BIL - Mid_annual_st'!$A$3:$A$434,0),),'IRA-BIL_IRA-BIL - Mid_annual_st'!$W$1:$AR$1,$B51) -> 24700632 | M51: =C51/SUM(C46:C57) -> 0.4527941 | N51: =D51/SUM(D46:D57) -> 0.43242166 | O51: =E51/SUM(E46:E57) -> 0.36656947 | P51: =F51/SUM(F46:F57) -> 0.34050155 | Q51: =G51/SUM(G46:G57) -> 0.33363022 | R51: =H51/SUM(H46:H57) -> 0.27890195 | S51: =I51/SUM(I46:I57) -> 0.21895853 | T51: =J51/SUM(J46:J57) -> 0.20918478 | U51: =K51/SUM(K46:K57) -> 0.12144686
A52: =A51 -> CA | B52: nuclear | C52: =SUMIFS(INDEX('IRA-BIL_IRA-BIL - Mid_annual_st'!$W$3:$AR$434,MATCH(C44,'IRA-BIL_IRA-BIL - Mid_annual_st'!$A$3:$A$434,0),),'IRA-BIL_IRA-BIL - Mid_annual_st'!$W$1:$AR$1,$B52) -> 17891898 | D52: =SUMIFS(INDEX('IRA-BIL_IRA-BIL - Mid_annual_st'!$W$3:$AR$434,MATCH(D44,'IRA-BIL_IRA-BIL - Mid_annual_st'!$A$3:$A$434,0),),'IRA-BIL_IRA-BIL - Mid_annual_st'!$W$1:$AR$1,$B52) -> 17891898 | E52: =SUMIFS(INDEX('IRA-BIL_IRA-BIL - Mid_annual_st'!$W$3:$AR$434,MATCH(E44,'IRA-BIL_IRA-BIL - Mid_annual_st'!$A$3:$A$434,0),),'IRA-BIL_IRA-BIL - Mid_annual_st'!$W$1:$AR$1,$B52) -> 17891898 | F52: =SUMIFS(INDEX('IRA-BIL_IRA-BIL - Mid_annual_st'!$W$3:$AR$434,MATCH(F44,'IRA-BIL_IRA-BIL - Mid_annual_st'!$A$3:$A$434,0),),'IRA-BIL_IRA-BIL - Mid_annual_st'!$W$1:$AR$1,$B52) -> 17891898 | G52: =SUMIFS(INDEX('IRA-BIL_IRA-BIL - Mid_annual_st'!$W$3:$AR$434,MATCH(G44,'IRA-BIL_IRA-BIL - Mid_annual_st'!$A$3:$A$434,0),),'IRA-BIL_IRA-BIL - Mid_annual_st'!$W$1:$AR$1,$B52) -> 17891898 | H52: =SUMIFS(INDEX('IRA-BIL_IRA-BIL - Mid_annual_st'!$W$3:$AR$434,MATCH(H44,'IRA-BIL_IRA-BIL - Mid_annual_st'!$A$3:$A$434,0),),'IRA-BIL_IRA-BIL - Mid_annual_st'!$W$1:$AR$1,$B52) -> 17891898 | I52: =SUMIFS(INDEX('IRA-BIL_IRA-BIL - Mid_annual_st'!$W$3:$AR$434,MATCH(I44,'IRA-BIL_IRA-BIL - Mid_annual_st'!$A$3:$A$434,0),),'IRA-BIL_IRA-BIL - Mid_annual_st'!$W$1:$AR$1,$B52) -> 17505782 | J52: =SUMIFS(INDEX('IRA-BIL_IRA-BIL - Mid_annual_st'!$W$3:$AR$434,MATCH(J44,'IRA-BIL_IRA-BIL - Mid_annual_st'!$A$3:$A$434,0),),'IRA-BIL_IRA-BIL - Mid_annual_st'!$W$1:$AR$1,$B52) -> 8627139 | K52: =SUMIFS(INDEX('IRA-BIL_IRA-BIL - Mid_annual_st'!$W$3:$AR$434,MATCH(K44,'IRA-BIL_IRA-BIL - Mid_annual_st'!$A$3:$A$434,0),),'IRA-BIL_IRA-BIL - Mid_annual_st'!$W$1:$AR$1,$B52) -> 0 | M52: =C52/SUM(C46:C57) -> 0.088044145 | N52: =D52/SUM(D46:D57) -> 0.092426356 | O52: =E52/SUM(E46:E57) -> 0.08710589 | P52: =F52/SUM(F46:F57) -> 0.090323303 | Q52: =G52/SUM(G46:G57) -> 0.091079009 | R52: =H52/SUM(H46:H57) -> 0.088239404 | S52: =I52/SUM(I46:I57) -> 0.092470086 | T52: =J52/SUM(J46:J57) -> 0.047625106 | U52: =K52/SUM(K46:K57) -> 0
A53: =A52 -> CA | B53: offshore wind | C53: =SUMIFS(INDEX('IRA-BIL_IRA-BIL - Mid_annual_st'!$W$3:$AR$434,MATCH(C44,'IRA-BIL_IRA-BIL - Mid_annual_st'!$A$3:$A$434,0),),'IRA-BIL_IRA-BIL - Mid_annual_st'!$W$1:$AR$1,$B53) -> 0 | D53: =SUMIFS(INDEX('IRA-BIL_IRA-BIL - Mid_annual_st'!$W$3:$AR$434,MATCH(D44,'IRA-BIL_IRA-BIL - Mid_annual_st'!$A$3:$A$434,0),),'IRA-BIL_IRA-BIL - Mid_annual_st'!$W$1:$AR$1,$B53) -> 0 | E53: =SUMIFS(INDEX('IRA-BIL_IRA-BIL - Mid_annual_st'!$W$3:$AR$434,MATCH(E44,'IRA-BIL_IRA-BIL - Mid_annual_st'!$A$3:$A$434,0),),'IRA-BIL_IRA-BIL - Mid_annual_st'!$W$1:$AR$1,$B53) -> 0 | F53: =SUMIFS(INDEX('IRA-BIL_IRA-BIL - Mid_annual_st'!$W$3:$AR$434,MATCH(F44,'IRA-BIL_IRA-BIL - Mid_annual_st'!$A$3:$A$434,0),),'IRA-BIL_IRA-BIL - Mid_annual_st'!$W$1:$AR$1,$B53) -> 0 | G53: =SUMIFS(INDEX('IRA-BIL_IRA-BIL - Mid_annual_st'!$W$3:$AR$434,MATCH(G44,'IRA-BIL_IRA-BIL - Mid_annual_st'!$A$3:$A$434,0),),'IRA-BIL_IRA-BIL - Mid_annual_st'!$W$1:$AR$1,$B53) -> 0 | H53: =SUMIFS(INDEX('IRA-BIL_IRA-BIL - Mid_annual_st'!$W$3:$AR$434,MATCH(H44,'IRA-BIL_IRA-BIL - Mid_annual_st'!$A$3:$A$434,0),),'IRA-BIL_IRA-BIL - Mid_annual_st'!$W$1:$AR$1,$B53) -> 0 | I53: =SUMIFS(INDEX('IRA-BIL_IRA-BIL - Mid_annual_st'!$W$3:$AR$434,MATCH(I44,'IRA-BIL_IRA-BIL - Mid_annual_st'!$A$3:$A$434,0),),'IRA-BIL_IRA-BIL - Mid_annual_st'!$W$1:$AR$1,$B53) -> 2338100 | J53: =SUMIFS(INDEX('IRA-BIL_IRA-BIL - Mid_annual_st'!$W$3:$AR$434,MATCH(J44,'IRA-BIL_IRA-BIL - Mid_annual_st'!$A$3:$A$434,0),),'IRA-BIL_IRA-BIL - Mid_annual_st'!$W$1:$AR$1,$B53) -> 5170208 | K53: =SUMIFS(INDEX('IRA-BIL_IRA-BIL - Mid_annual_st'!$W$3:$AR$434,MATCH(K44,'IRA-BIL_IRA-BIL - Mid_annual_st'!$A$3:$A$434,0),),'IRA-BIL_IRA-BIL - Mid_annual_st'!$W$1:$AR$1,$B53) -> 8853169 | M53: =C53/SUM(C46:C57) -> 0 | N53: =D53/SUM(D46:D57) -> 0 | O53: =E53/SUM(E46:E57) -> 0 | P53: =F53/SUM(F46:F57) -> 0 | Q53: =G53/SUM(G46:G57) -> 0 | R53: =H53/SUM(H46:H57) -> 0 | S53: =I53/SUM(I46:I57) -> 0.012350451 | T53: =J53/SUM(J46:J57) -> 0.028541525 | U53: =K53/SUM(K46:K57) -> 0.043528828
A54: =A53 -> CA | B54: petroleum | C54: =SUMIFS(INDEX('IRA-BIL_IRA-BIL - Mid_annual_st'!$W$3:$AR$434,MATCH(C44,'IRA-BIL_IRA-BIL - Mid_annual_st'!$A$3:$A$434,0),),'IRA-BIL_IRA-BIL - Mid_annual_st'!$W$1:$AR$1,$B54) -> 2607764 | D54: =SUMIFS(INDEX('IRA-BIL_IRA-BIL - Mid_annual_st'!$W$3:$AR$434,MATCH(D44,'IRA-BIL_IRA-BIL - Mid_annual_st'!$A$3:$A$434,0),),'IRA-BIL_IRA-BIL - Mid_annual_st'!$W$1:$AR$1,$B54) -> 1447345 | E54: =SUMIFS(INDEX('IRA-BIL_IRA-BIL - Mid_annual_st'!$W$3:$AR$434,MATCH(E44,'IRA-BIL_IRA-BIL - Mid_annual_st'!$A$3:$A$434,0),),'IRA-BIL_IRA-BIL - Mid_annual_st'!$W$1:$AR$1,$B54) -> 522762 | F54: =SUMIFS(INDEX('IRA-BIL_IRA-BIL - Mid_annual_st'!$W$3:$AR$434,MATCH(F44,'IRA-BIL_IRA-BIL - Mid_annual_st'!$A$3:$A$434,0),),'IRA-BIL_IRA-BIL - Mid_annual_st'!$W$1:$AR$1,$B54) -> 522762 | G54: =SUMIFS(INDEX('IRA-BIL_IRA-BIL - Mid_annual_st'!$W$3:$AR$434,MATCH(G44,'IRA-BIL_IRA-BIL - Mid_annual_st'!$A$3:$A$434,0),),'IRA-BIL_IRA-BIL - Mid_annual_st'!$W$1:$AR$1,$B54) -> 521921 | H54: =SUMIFS(INDEX('IRA-BIL_IRA-BIL - Mid_annual_st'!$W$3:$AR$434,MATCH(H44,'IRA-BIL_IRA-BIL - Mid_annual_st'!$A$3:$A$434,0),),'IRA-BIL_IRA-BIL - Mid_annual_st'!$W$1:$AR$1,$B54) -> 521921 | I54: =SUMIFS(INDEX('IRA-BIL_IRA-BIL - Mid_annual_st'!$W$3:$AR$434,MATCH(I44,'IRA-BIL_IRA-BIL - Mid_annual_st'!$A$3:$A$434,0),),'IRA-BIL_IRA-BIL - Mid_annual_st'!$W$1:$AR$1,$B54) -> 464105 | J54: =SUMIFS(INDEX('IRA-BIL_IRA-BIL - Mid_annual_st'!$W$3:$AR$434,MATCH(J44,'IRA-BIL_IRA-BIL - Mid_annual_st'!$A$3:$A$434,0),),'IRA-BIL_IRA-BIL - Mid_annual_st'!$W$1:$AR$1,$B54) -> 464105 | K54: =SUMIFS(INDEX('IRA-BIL_IRA-BIL - Mid_annual_st'!$W$3:$AR$434,MATCH(K44,'IRA-BIL_IRA-BIL - Mid_annual_st'!$A$3:$A$434,0),),'IRA-BIL_IRA-BIL - Mid_annual_st'!$W$1:$AR$1,$B54) -> 311628 | M54: =C54/SUM(C46:C57) -> 0.012832532 | N54: =D54/SUM(D46:D57) -> 0.0074767263 | O54: =E54/SUM(E46:E57) -> 0.002545043 | P54: =F54/SUM(F46:F57) -> 0.0026390487 | Q54: =G54/SUM(G46:G57) -> 0.0026568477 | R54: =H54/SUM(H46:H57) -> 0.0025740141 | S54: =I54/SUM(I46:I57) -> 0.0024515231 | T54: =J54/SUM(J46:J57) -> 0.0025620371 | U54: =K54/SUM(K46:K57) -> 0.0015321973
A55: =A54 -> CA | B55: onshore wind | C55: =SUMIFS(INDEX('IRA-BIL_IRA-BIL - Mid_annual_st'!$W$3:$AR$434,MATCH(C44,'IRA-BIL_IRA-BIL - Mid_annual_st'!$A$3:$A$434,0),),'IRA-BIL_IRA-BIL - Mid_annual_st'!$W$1:$AR$1,$B55) -> 14121780 | D55: =SUMIFS(INDEX('IRA-BIL_IRA-BIL - Mid_annual_st'!$W$3:$AR$434,MATCH(D44,'IRA-BIL_IRA-BIL - Mid_annual_st'!$A$3:$A$434,0),),'IRA-BIL_IRA-BIL - Mid_annual_st'!$W$1:$AR$1,$B55) -> 13875629 | E55: =SUMIFS(INDEX('IRA-BIL_IRA-BIL - Mid_annual_st'!$W$3:$AR$434,MATCH(E44,'IRA-BIL_IRA-BIL - Mid_annual_st'!$A$3:$A$434,0),),'IRA-BIL_IRA-BIL - Mid_annual_st'!$W$1:$AR$1,$B55) -> 16167737 | F55: =SUMIFS(INDEX('IRA-BIL_IRA-BIL - Mid_annual_st'!$W$3:$AR$434,MATCH(F44,'IRA-BIL_IRA-BIL - Mid_annual_st'!$A$3:$A$434,0),),'IRA-BIL_IRA-BIL - Mid_annual_st'!$W$1:$AR$1,$B55) -> 16360910 | G55: =SUMIFS(INDEX('IRA-BIL_IRA-BIL - Mid_annual_st'!$W$3:$AR$434,MATCH(G44,'IRA-BIL_IRA-BIL - Mid_annual_st'!$A$3:$A$434,0),),'IRA-BIL_IRA-BIL - Mid_annual_st'!$W$1:$AR$1,$B55) -> 16430224 | H55: =SUMIFS(INDEX('IRA-BIL_IRA-BIL - Mid_annual_st'!$W$3:$AR$434,MATCH(H44,'IRA-BIL_IRA-BIL - Mid_annual_st'!$A$3:$A$434,0),),'IRA-BIL_IRA-BIL - Mid_annual_st'!$W$1:$AR$1,$B55) -> 16482159 | I55: =SUMIFS(INDEX('IRA-BIL_IRA-BIL - Mid_annual_st'!$W$3:$AR$434,MATCH(I44,'IRA-BIL_IRA-BIL - Mid_annual_st'!$A$3:$A$434,0),),'IRA-BIL_IRA-BIL - Mid_annual_st'!$W$1:$AR$1,$B55) -> 16394201 | J55: =SUMIFS(INDEX('IRA-BIL_IRA-BIL - Mid_annual_st'!$W$3:$AR$434,MATCH(J44,'IRA-BIL_IRA-BIL - Mid_annual_st'!$A$3:$A$434,0),),'IRA-BIL_IRA-BIL - Mid_annual_st'!$W$1:$AR$1,$B55) -> 15765636 | K55: =SUMIFS(INDEX('IRA-BIL_IRA-BIL - Mid_annual_st'!$W$3:$AR$434,MATCH(K44,'IRA-BIL_IRA-BIL - Mid_annual_st'!$A$3:$A$434,0),),'IRA-BIL_IRA-BIL - Mid_annual_st'!$W$1:$AR$1,$B55) -> 15925287 | M55: =C55/SUM(C46:C57) -> 0.069491791 | N55: =D55/SUM(D46:D57) -> 0.071679026 | O55: =E55/SUM(E46:E57) -> 0.078711891 | P55: =F55/SUM(F46:F57) -> 0.082594447 | Q55: =G55/SUM(G46:G57) -> 0.083638333 | R55: =H55/SUM(H46:H57) -> 0.081286842 | S55: =I55/SUM(I46:I57) -> 0.086598426 | T55: =J55/SUM(J46:J57) -> 0.087032339 | U55: =K55/SUM(K46:K57) -> 0.078300671
A56: =A55 -> CA | B56: pumped hydro | C56: 0 | D56: 0 | E56: 0 | F56: 0 | G56: 0 | H56: 0 | I56: 0 | J56: 0 | K56: 0 | M56: 0 | N56: 0 | O56: 0 | P56: 0 | Q56: 0 | R56: 0 | S56: 0 | T56: 0 | U56: 0
A57: =A56 -> CA | B57: solar pv | C57: =SUMIFS(INDEX('IRA-BIL_IRA-BIL - Mid_annual_st'!$W$3:$AR$434,MATCH(C44,'IRA-BIL_IRA-BIL - Mid_annual_st'!$A$3:$A$434,0),),'IRA-BIL_IRA-BIL - Mid_annual_st'!$W$1:$AR$1,$B57) -> 44640799 | D57: =SUMIFS(INDEX('IRA-BIL_IRA-BIL - Mid_annual_st'!$W$3:$AR$434,MATCH(D44,'IRA-BIL_IRA-BIL - Mid_annual_st'!$A$3:$A$434,0),),'IRA-BIL_IRA-BIL - Mid_annual_st'!$W$1:$AR$1,$B57) -> 45404601 | E57: =SUMIFS(INDEX('IRA-BIL_IRA-BIL - Mid_annual_st'!$W$3:$AR$434,MATCH(E44,'IRA-BIL_IRA-BIL - Mid_annual_st'!$A$3:$A$434,0),),'IRA-BIL_IRA-BIL - Mid_annual_st'!$W$1:$AR$1,$B57) -> 64107152 | F57: =SUMIFS(INDEX('IRA-BIL_IRA-BIL - Mid_annual_st'!$W$3:$AR$434,MATCH(F44,'IRA-BIL_IRA-BIL - Mid_annual_st'!$A$3:$A$434,0),),'IRA-BIL_IRA-BIL - Mid_annual_st'!$W$1:$AR$1,$B57) -> 63729300 | G57: =SUMIFS(INDEX('IRA-BIL_IRA-BIL - Mid_annual_st'!$W$3:$AR$434,MATCH(G44,'IRA-BIL_IRA-BIL - Mid_annual_st'!$A$3:$A$434,0),),'IRA-BIL_IRA-BIL - Mid_annual_st'!$W$1:$AR$1,$B57) -> 63780822 | H57: =SUMIFS(INDEX('IRA-BIL_IRA-BIL - Mid_annual_st'!$W$3:$AR$434,MATCH(H44,'IRA-BIL_IRA-BIL - Mid_annual_st'!$A$3:$A$434,0),),'IRA-BIL_IRA-BIL - Mid_annual_st'!$W$1:$AR$1,$B57) -> 69647268 | I57: =SUMIFS(INDEX('IRA-BIL_IRA-BIL - Mid_annual_st'!$W$3:$AR$434,MATCH(I44,'IRA-BIL_IRA-BIL - Mid_annual_st'!$A$3:$A$434,0),),'IRA-BIL_IRA-BIL - Mid_annual_st'!$W$1:$AR$1,$B57) -> 69177295 | J57: =SUMIFS(INDEX('IRA-BIL_IRA-BIL - Mid_annual_st'!$W$3:$AR$434,MATCH(J44,'IRA-BIL_IRA-BIL - Mid_annual_st'!$A$3:$A$434,0),),'IRA-BIL_IRA-BIL - Mid_annual_st'!$W$1:$AR$1,$B57) -> 70971560 | K57: =SUMIFS(INDEX('IRA-BIL_IRA-BIL - Mid_annual_st'!$W$3:$AR$434,MATCH(K44,'IRA-BIL_IRA-BIL - Mid_annual_st'!$A$3:$A$434,0),),'IRA-BIL_IRA-BIL - Mid_annual_st'!$W$1:$AR$1,$B57) -> 111195041 | M57: =C57/SUM(C46:C57) -> 0.21967267 | N57: =D57/SUM(D46:D57) -> 0.23455208 | O57: =E57/SUM(E46:E57) -> 0.31210275 | P57: =F57/SUM(F46:F57) -> 0.32172332 | Q57: =G57/SUM(G46:G57) -> 0.32467735 | R57: =H57/SUM(H46:H57) -> 0.34348695 | S57: =I57/SUM(I46:I57) -> 0.36541243 | T57: =J57/SUM(J46:J57) -> 0.39179015 | U57: =K57/SUM(K46:K57) -> 0.54671833
A58: CO | C58: =$A58&"_"&C59 -> CO_2022 | D58: =$A58&"_"&D59 -> CO_2023 | E58: =$A58&"_"&E59 -> CO_2024 | F58: =$A58&"_"&F59 -> CO_2025 | G58: =$A58&"_"&G59 -> CO_2026 | H58: =$A58&"_"&H59 -> CO_2027 | I58: =$A58&"_"&I59 -> CO_2028 | J58: =$A58&"_"&J59 -> CO_2029 | K58: =$A58&"_"&K59 -> CO_2030 | M58: =$A58&"_"&M59 -> CO_2022 | N58: =$A58&"_"&N59 -> CO_2023 | O58: =$A58&"_"&O59 -> CO_2024 | P58: =$A58&"_"&P59 -> CO_2025 | Q58: =$A58&"_"&Q59 -> CO_2026 | R58: =$A58&"_"&R59 -> CO_2027 | S58: =$A58&"_"&S59 -> CO_2028 | T58: =$A58&"_"&T59 -> CO_2029 | U58: =$A58&"_"&U59 -> CO_2030
C59: 2022 | D59: 2023 | E59: 2024 | F59: 2025 | G59: 2026 | H59: 2027 | I59: 2028 | J59: 2029 | K59: 2030 | M59: 2022 | N59: 2023 | O59: 2024 | P59: 2025 | Q59: 2026 | R59: 2027 | S59: 2028 | T59: 2029 | U59: 2030
A60: =A58 -> CO | B60: battery | C60: 0 | D60: 0 | E60: 0 | F60: 0 | G60: 0 | H60: 0 | I60: 0 | J60: 0 | K60: 0 | M60: 0 | N60: 0 | O60: 0 | P60: 0 | Q60: 0 | R60: 0 | S60: 0 | T60: 0 | U60: 0
A61: =A60 -> CO | B61: biomass | C61: =SUMIFS(INDEX('IRA-BIL_IRA-BIL - Mid_annual_st'!$W$3:$AR$434,MATCH(C58,'IRA-BIL_IRA-BIL - Mid_annual_st'!$A$3:$A$434,0),),'IRA-BIL_IRA-BIL - Mid_annual_st'!$W$1:$AR$1,$B61) -> 98986 | D61: =SUMIFS(INDEX('IRA-BIL_IRA-BIL - Mid_annual_st'!$W$3:$AR$434,MATCH(D58,'IRA-BIL_IRA-BIL - Mid_annual_st'!$A$3:$A$434,0),),'IRA-BIL_IRA-BIL - Mid_annual_st'!$W$1:$AR$1,$B61) -> 54806 | E61: =SUMIFS(INDEX('IRA-BIL_IRA-BIL - Mid_annual_st'!$W$3:$AR$434,MATCH(E58,'IRA-BIL_IRA-BIL - Mid_annual_st'!$A$3:$A$434,0),),'IRA-BIL_IRA-BIL - Mid_annual_st'!$W$1:$AR$1,$B61) -> 54806 | F61: =SUMIFS(INDEX('IRA-BIL_IRA-BIL - Mid_annual_st'!$W$3:$AR$434,MATCH(F58,'IRA-BIL_IRA-BIL - Mid_annual_st'!$A$3:$A$434,0),),'IRA-BIL_IRA-BIL - Mid_annual_st'!$W$1:$AR$1,$B61) -> 54443 | G61: =SUMIFS(INDEX('IRA-BIL_IRA-BIL - Mid_annual_st'!$W$3:$AR$434,MATCH(G58,'IRA-BIL_IRA-BIL - Mid_annual_st'!$A$3:$A$434,0),),'IRA-BIL_IRA-BIL - Mid_annual_st'!$W$1:$AR$1,$B61) -> 54806 | H61: =SUMIFS(INDEX('IRA-BIL_IRA-BIL - Mid_annual_st'!$W$3:$AR$434,MATCH(H58,'IRA-BIL_IRA-BIL - Mid_annual_st'!$A$3:$A$434,0),),'IRA-BIL_IRA-BIL - Mid_annual_st'!$W$1:$AR$1,$B61) -> 54806 | I61: =SUMIFS(INDEX('IRA-BIL_IRA-BIL - Mid_annual_st'!$W$3:$AR$434,MATCH(I58,'IRA-BIL_IRA-BIL - Mid_annual_st'!$A$3:$A$434,0),),'IRA-BIL_IRA-BIL - Mid_annual_st'!$W$1:$AR$1,$B61) -> 49295 | J61: =SUMIFS(INDEX('IRA-BIL_IRA-BIL - Mid_annual_st'!$W$3:$AR$434,MATCH(J58,'IRA-BIL_IRA-BIL - Mid_annual_st'!$A$3:$A$434,0),),'IRA-BIL_IRA-BIL - Mid_annual_st'!$W$1:$AR$1,$B61) -> 48856 | K61: =SUMIFS(INDEX('IRA-BIL_IRA-BIL - Mid_annual_st'!$W$3:$AR$434,MATCH(K58,'IRA-BIL_IRA-BIL - Mid_annual_st'!$A$3:$A$434,0),),'IRA-BIL_IRA-BIL - Mid_annual_st'!$W$1:$AR$1,$B61) -> 42088 | M61: =C61/SUM(C60:C71) -> 0.0019144532 | N61: =D61/SUM(D60:D71) -> 0.00065305554 | O61: =E61/SUM(E60:E71) -> 0.0006492891 | P61: =F61/SUM(F60:F71) -> 0.00060751185 | Q61: =G61/SUM(G60:G71) -> 0.0006203843 | R61: =H61/SUM(H60:H71) -> 0.0006420488 | S61: =I61/SUM(I60:I71) -> 0.0005755806 | T61: =J61/SUM(J60:J71) -> 0.00058788121 | U61: =K61/SUM(K60:K71) -> 0.00048058968
A62: =A61 -> CO | B62: hard coal | C62: =SUMIFS(INDEX('IRA-BIL_IRA-BIL - Mid_annual_st'!$W$3:$AR$434,MATCH(C58,'IRA-BIL_IRA-BIL - Mid_annual_st'!$A$3:$A$434,0),),'IRA-BIL_IRA-BIL - Mid_annual_st'!$W$1:$AR$1,$B62) -> 26975784 | D62: =SUMIFS(INDEX('IRA-BIL_IRA-BIL - Mid_annual_st'!$W$3:$AR$434,MATCH(D58,'IRA-BIL_IRA-BIL - Mid_annual_st'!$A$3:$A$434,0),),'IRA-BIL_IRA-BIL - Mid_annual_st'!$W$1:$AR$1,$B62) -> 21310306 | E62: =SUMIFS(INDEX('IRA-BIL_IRA-BIL - Mid_annual_st'!$W$3:$AR$434,MATCH(E58,'IRA-BIL_IRA-BIL - Mid_annual_st'!$A$3:$A$434,0),),'IRA-BIL_IRA-BIL - Mid_annual_st'!$W$1:$AR$1,$B62) -> 17320441 | F62: =SUMIFS(INDEX('IRA-BIL_IRA-BIL - Mid_annual_st'!$W$3:$AR$434,MATCH(F58,'IRA-BIL_IRA-BIL - Mid_annual_st'!$A$3:$A$434,0),),'IRA-BIL_IRA-BIL - Mid_annual_st'!$W$1:$AR$1,$B62) -> 11146197 | G62: =SUMIFS(INDEX('IRA-BIL_IRA-BIL - Mid_annual_st'!$W$3:$AR$434,MATCH(G58,'IRA-BIL_IRA-BIL - Mid_annual_st'!$A$3:$A$434,0),),'IRA-BIL_IRA-BIL - Mid_annual_st'!$W$1:$AR$1,$B62) -> 9816942 | H62: =SUMIFS(INDEX('IRA-BIL_IRA-BIL - Mid_annual_st'!$W$3:$AR$434,MATCH(H58,'IRA-BIL_IRA-BIL - Mid_annual_st'!$A$3:$A$434,0),),'IRA-BIL_IRA-BIL - Mid_annual_st'!$W$1:$AR$1,$B62) -> 8666901 | I62: =SUMIFS(INDEX('IRA-BIL_IRA-BIL - Mid_annual_st'!$W$3:$AR$434,MATCH(I58,'IRA-BIL_IRA-BIL - Mid_annual_st'!$A$3:$A$434,0),),'IRA-BIL_IRA-BIL - Mid_annual_st'!$W$1:$AR$1,$B62) -> 1100912 | J62: =SUMIFS(INDEX('IRA-BIL_IRA-BIL - Mid_annual_st'!$W$3:$AR$434,MATCH(J58,'IRA-BIL_IRA-BIL - Mid_annual_st'!$A$3:$A$434,0),),'IRA-BIL_IRA-BIL - Mid_annual_st'!$W$1:$AR$1,$B62) -> 176454 | K62: =SUMIFS(INDEX('IRA-BIL_IRA-BIL - Mid_annual_st'!$W$3:$AR$434,MATCH(K58,'IRA-BIL_IRA-BIL - Mid_annual_st'!$A$3:$A$434,0),),'IRA-BIL_IRA-BIL - Mid_annual_st'!$W$1:$AR$1,$B62) -> 0 | M62: =C62/SUM(C60:C71) -> 0.52172909 | N62: =D62/SUM(D60:D71) -> 0.25392865 | O62: =E62/SUM(E60:E71) -> 0.20519603 | P62: =F62/SUM(F60:F71) -> 0.12437681 | Q62: =G62/SUM(G60:G71) -> 0.11112427 | R62: =H62/SUM(H60:H71) -> 0.10153219 | S62: =I62/SUM(I60:I71) -> 0.01285452 | T62: =J62/SUM(J60:J71) -> 0.00212326 | U62: =K62/SUM(K60:K71) -> 0
A63: =A62 -> CO | B63: geothermal | C63: =SUMIFS(INDEX('IRA-BIL_IRA-BIL - Mid_annual_st'!$W$3:$AR$434,MATCH(C58,'IRA-BIL_IRA-BIL - Mid_annual_st'!$A$3:$A$434,0),),'IRA-BIL_IRA-BIL - Mid_annual_st'!$W$1:$AR$1,$B63) -> 0 | D63: =SUMIFS(INDEX('IRA-BIL_IRA-BIL - Mid_annual_st'!$W$3:$AR$434,MATCH(D58,'IRA-BIL_IRA-BIL - Mid_annual_st'!$A$3:$A$434,0),),'IRA-BIL_IRA-BIL - Mid_annual_st'!$W$1:$AR$1,$B63) -> 0 | E63: =SUMIFS(INDEX('IRA-BIL_IRA-BIL - Mid_annual_st'!$W$3:$AR$434,MATCH(E58,'IRA-BIL_IRA-BIL - Mid_annual_st'!$A$3:$A$434,0),),'IRA-BIL_IRA-BIL - Mid_annual_st'!$W$1:$AR$1,$B63) -> 0 | F63: =SUMIFS(INDEX('IRA-BIL_IRA-BIL - Mid_annual_st'!$W$3:$AR$434,MATCH(F58,'IRA-BIL_IRA-BIL - Mid_annual_st'!$A$3:$A$434,0),),'IRA-BIL_IRA-BIL - Mid_annual_st'!$W$1:$AR$1,$B63) -> 0 | G63: =SUMIFS(INDEX('IRA-BIL_IRA-BIL - Mid_annual_st'!$W$3:$AR$434,MATCH(G58,'IRA-BIL_IRA-BIL - Mid_annual_st'!$A$3:$A$434,0),),'IRA-BIL_IRA-BIL - Mid_annual_st'!$W$1:$AR$1,$B63) -> 0 | H63: =SUMIFS(INDEX('IRA-BIL_IRA-BIL - Mid_annual_st'!$W$3:$AR$434,MATCH(H58,'IRA-BIL_IRA-BIL - Mid_annual_st'!$A$3:$A$434,0),),'IRA-BIL_IRA-BIL - Mid_annual_st'!$W$1:$AR$1,$B63) -> 0 | I63: =SUMIFS(INDEX('IRA-BIL_IRA-BIL - Mid_annual_st'!$W$3:$AR$434,MATCH(I58,'IRA-BIL_IRA-BIL - Mid_annual_st'!$A$3:$A$434,0),),'IRA-BIL_IRA-BIL - Mid_annual_st'!$W$1:$AR$1,$B63) -> 0 | J63: =SUMIFS(INDEX('IRA-BIL_IRA-BIL - Mid_annual_st'!$W$3:$AR$434,MATCH(J58,'IRA-BIL_IRA-BIL - Mid_annual_st'!$A$3:$A$434,0),),'IRA-BIL_IRA-BIL - Mid_annual_st'!$W$1:$AR$1,$B63) -> 0 | K63: =SUMIFS(INDEX('IRA-BIL_IRA-BIL - Mid_annual_st'!$W$3:$AR$434,MATCH(K58,'IRA-BIL_IRA-BIL - Mid_annual_st'!$A$3:$A$434,0),),'IRA-BIL_IRA-BIL - Mid_annual_st'!$W$1:$AR$1,$B63) -> 0 | M63: =C63/SUM(C60:C71) -> 0 | N63: =D63/SUM(D60:D71) -> 0 | O63: =E63/SUM(E60:E71) -> 0 | P63: =F63/SUM(F60:F71) -> 0 | Q63: =G63/SUM(G60:G71) -> 0 | R63: =H63/SUM(H60:H71) -> 0 | S63: =I63/SUM(I60:I71) -> 0 | T63: =J63/SUM(J60:J71) -> 0 | U63: =K63/SUM(K60:K71) -> 0
A64: =A63 -> CO | B64: hydro | C64: =SUMIFS(INDEX('IRA-BIL_IRA-BIL - Mid_annual_st'!$W$3:$AR$434,MATCH(C58,'IRA-BIL_IRA-BIL - Mid_annual_st'!$A$3:$A$434,0),),'IRA-BIL_IRA-BIL - Mid_annual_st'!$W$1:$AR$1,$B64) -> 1841640 | D64: =SUMIFS(INDEX('IRA-BIL_IRA-BIL - Mid_annual_st'!$W$3:$AR$434,MATCH(D58,'IRA-BIL_IRA-BIL - Mid_annual_st'!$A$3:$A$434,0),),'IRA-BIL_IRA-BIL - Mid_annual_st'!$W$1:$AR$1,$B64) -> 1841640 | E64: =SUMIFS(INDEX('IRA-BIL_IRA-BIL - Mid_annual_st'!$W$3:$AR$434,MATCH(E58,'IRA-BIL_IRA-BIL - Mid_annual_st'!$A$3:$A$434,0),),'IRA-BIL_IRA-BIL - Mid_annual_st'!$W$1:$AR$1,$B64) -> 1841019 | F64: =SUMIFS(INDEX('IRA-BIL_IRA-BIL - Mid_annual_st'!$W$3:$AR$434,MATCH(F58,'IRA-BIL_IRA-BIL - Mid_annual_st'!$A$3:$A$434,0),),'IRA-BIL_IRA-BIL - Mid_annual_st'!$W$1:$AR$1,$B64) -> 1838935 | G64: =SUMIFS(INDEX('IRA-BIL_IRA-BIL - Mid_annual_st'!$W$3:$AR$434,MATCH(G58,'IRA-BIL_IRA-BIL - Mid_annual_st'!$A$3:$A$434,0),),'IRA-BIL_IRA-BIL - Mid_annual_st'!$W$1:$AR$1,$B64) -> 1842261 | H64: =SUMIFS(INDEX('IRA-BIL_IRA-BIL - Mid_annual_st'!$W$3:$AR$434,MATCH(H58,'IRA-BIL_IRA-BIL - Mid_annual_st'!$A$3:$A$434,0),),'IRA-BIL_IRA-BIL - Mid_annual_st'!$W$1:$AR$1,$B64) -> 1841507 | I64: =SUMIFS(INDEX('IRA-BIL_IRA-BIL - Mid_annual_st'!$W$3:$AR$434,MATCH(I58,'IRA-BIL_IRA-BIL - Mid_annual_st'!$A$3:$A$434,0),),'IRA-BIL_IRA-BIL - Mid_annual_st'!$W$1:$AR$1,$B64) -> 1828842 | J64: =SUMIFS(INDEX('IRA-BIL_IRA-BIL - Mid_annual_st'!$W$3:$AR$434,MATCH(J58,'IRA-BIL_IRA-BIL - Mid_annual_st'!$A$3:$A$434,0),),'IRA-BIL_IRA-BIL - Mid_annual_st'!$W$1:$AR$1,$B64) -> 1829509 | K64: =SUMIFS(INDEX('IRA-BIL_IRA-BIL - Mid_annual_st'!$W$3:$AR$434,MATCH(K58,'IRA-BIL_IRA-BIL - Mid_annual_st'!$A$3:$A$434,0),),'IRA-BIL_IRA-BIL - Mid_annual_st'!$W$1:$AR$1,$B64) -> 1834941 | M64: =C64/SUM(C60:C71) -> 0.035618507 | N64: =D64/SUM(D60:D71) -> 0.021944554 | O64: =E64/SUM(E60:E71) -> 0.021810633 | P64: =F64/SUM(F60:F71) -> 0.020520082 | Q64: =G64/SUM(G60:G71) -> 0.020853735 | R64: =H64/SUM(H60:H71) -> 0.021573137 | S64: =I64/SUM(I60:I71) -> 0.021354011 | T64: =J64/SUM(J60:J71) -> 0.022014368 | U64: =K64/SUM(K60:K71) -> 0.020952616
A65: =A64 -> CO | B65: natural gas steam turbine | C65: =SUMIFS(INDEX('IRA-BIL_IRA-BIL - Mid_annual_st'!$W$3:$AR$434,MATCH(C58,'IRA-BIL_IRA-BIL - Mid_annual_st'!$A$3:$A$434,0),),'IRA-BIL_IRA-BIL - Mid_annual_st'!$W$1:$AR$1,$B65) -> 6550637 | D65: =SUMIFS(INDEX('IRA-BIL_IRA-BIL - Mid_annual_st'!$W$3:$AR$434,MATCH(D58,'IRA-BIL_IRA-BIL - Mid_annual_st'!$A$3:$A$434,0),),'IRA-BIL_IRA-BIL - Mid_annual_st'!$W$1:$AR$1,$B65) -> 6205379 | E65: =SUMIFS(INDEX('IRA-BIL_IRA-BIL - Mid_annual_st'!$W$3:$AR$434,MATCH(E58,'IRA-BIL_IRA-BIL - Mid_annual_st'!$A$3:$A$434,0),),'IRA-BIL_IRA-BIL - Mid_annual_st'!$W$1:$AR$1,$B65) -> 3774828 | F65: =SUMIFS(INDEX('IRA-BIL_IRA-BIL - Mid_annual_st'!$W$3:$AR$434,MATCH(F58,'IRA-BIL_IRA-BIL - Mid_annual_st'!$A$3:$A$434,0),),'IRA-BIL_IRA-BIL - Mid_annual_st'!$W$1:$AR$1,$B65) -> 2281498 | G65: =SUMIFS(INDEX('IRA-BIL_IRA-BIL - Mid_annual_st'!$W$3:$AR$434,MATCH(G58,'IRA-BIL_IRA-BIL - Mid_annual_st'!$A$3:$A$434,0),),'IRA-BIL_IRA-BIL - Mid_annual_st'!$W$1:$AR$1,$B65) -> 3866958 | H65: =SUMIFS(INDEX('IRA-BIL_IRA-BIL - Mid_annual_st'!$W$3:$AR$434,MATCH(H58,'IRA-BIL_IRA-BIL - Mid_annual_st'!$A$3:$A$434,0),),'IRA-BIL_IRA-BIL - Mid_annual_st'!$W$1:$AR$1,$B65) -> 2607833 | I65: =SUMIFS(INDEX('IRA-BIL_IRA-BIL - Mid_annual_st'!$W$3:$AR$434,MATCH(I58,'IRA-BIL_IRA-BIL - Mid_annual_st'!$A$3:$A$434,0),),'IRA-BIL_IRA-BIL - Mid_annual_st'!$W$1:$AR$1,$B65) -> 940718 | J65: =SUMIFS(INDEX('IRA-BIL_IRA-BIL - Mid_annual_st'!$W$3:$AR$434,MATCH(J58,'IRA-BIL_IRA-BIL - Mid_annual_st'!$A$3:$A$434,0),),'IRA-BIL_IRA-BIL - Mid_annual_st'!$W$1:$AR$1,$B65) -> 922874 | K65: =SUMIFS(INDEX('IRA-BIL_IRA-BIL - Mid_annual_st'!$W$3:$AR$434,MATCH(K58,'IRA-BIL_IRA-BIL - Mid_annual_st'!$A$3:$A$434,0),),'IRA-BIL_IRA-BIL - Mid_annual_st'!$W$1:$AR$1,$B65) -> 535695 | M65: =C65/SUM(C60:C71) -> 0.12669355 | N65: =D65/SUM(D60:D71) -> 0.073941852 | O65: =E65/SUM(E60:E71) -> 0.044720554 | P65: =F65/SUM(F60:F71) -> 0.025458499 | Q65: =G65/SUM(G60:G71) -> 0.04377258 | R65: =H65/SUM(H60:H71) -> 0.030550597 | S65: =I65/SUM(I60:I71) -> 0.010984056 | T65: =J65/SUM(J60:J71) -> 0.011104885 | U65: =K65/SUM(K60:K71) -> 0.0061169333
A66: =A65 -> CO | B66: nuclear | C66: =SUMIFS(INDEX('IRA-BIL_IRA-BIL - Mid_annual_st'!$W$3:$AR$434,MATCH(C58,'IRA-BIL_IRA-BIL - Mid_annual_st'!$A$3:$A$434,0),),'IRA-BIL_IRA-BIL - Mid_annual_st'!$W$1:$AR$1,$B66) -> 0 | D66: =SUMIFS(INDEX('IRA-BIL_IRA-BIL - Mid_annual_st'!$W$3:$AR$434,MATCH(D58,'IRA-BIL_IRA-BIL - Mid_annual_st'!$A$3:$A$434,0),),'IRA-BIL_IRA-BIL - Mid_annual_st'!$W$1:$AR$1,$B66) -> 0 | E66: =SUMIFS(INDEX('IRA-BIL_IRA-BIL - Mid_annual_st'!$W$3:$AR$434,MATCH(E58,'IRA-BIL_IRA-BIL - Mid_annual_st'!$A$3:$A$434,0),),'IRA-BIL_IRA-BIL - Mid_annual_st'!$W$1:$AR$1,$B66) -> 0 | F66: =SUMIFS(INDEX('IRA-BIL_IRA-BIL - Mid_annual_st'!$W$3:$AR$434,MATCH(F58,'IRA-BIL_IRA-BIL - Mid_annual_st'!$A$3:$A$434,0),),'IRA-BIL_IRA-BIL - Mid_annual_st'!$W$1:$AR$1,$B66) -> 0 | G66: =SUMIFS(INDEX('IRA-BIL_IRA-BIL - Mid_annual_st'!$W$3:$AR$434,MATCH(G58,'IRA-BIL_IRA-BIL - Mid_annual_st'!$A$3:$A$434,0),),'IRA-BIL_IRA-BIL - Mid_annual_st'!$W$1:$AR$1,$B66) -> 0 | H66: =SUMIFS(INDEX('IRA-BIL_IRA-BIL - Mid_annual_st'!$W$3:$AR$434,MATCH(H58,'IRA-BIL_IRA-BIL - Mid_annual_st'!$A$3:$A$434,0),),'IRA-BIL_IRA-BIL - Mid_annual_st'!$W$1:$AR$1,$B66) -> 0 | I66: =SUMIFS(INDEX('IRA-BIL_IRA-BIL - Mid_annual_st'!$W$3:$AR$434,MATCH(I58,'IRA-BIL_IRA-BIL - Mid_annual_st'!$A$3:$A$434,0),),'IRA-BIL_IRA-BIL - Mid_annual_st'!$W$1:$AR$1,$B66) -> 0 | J66: =SUMIFS(INDEX('IRA-BIL_IRA-BIL - Mid_annual_st'!$W$3:$AR$434,MATCH(J58,'IRA-BIL_IRA-BIL - Mid_annual_st'!$A$3:$A$434,0),),'IRA-BIL_IRA-BIL - Mid_annual_st'!$W$1:$AR$1,$B66) -> 0 | K66: =SUMIFS(INDEX('IRA-BIL_IRA-BIL - Mid_annual_st'!$W$3:$AR$434,MATCH(K58,'IRA-BIL_IRA-BIL - Mid_annual_st'!$A$3:$A$434,0),),'IRA-BIL_IRA-BIL - Mid_annual_st'!$W$1:$AR$1,$B66) -> 0 | M66: =C66/SUM(C60:C71) -> 0 | N66: =D66/SUM(D60:D71) -> 0 | O66: =E66/SUM(E60:E71) -> 0 | P66: =F66/SUM(F60:F71) -> 0 | Q66: =G66/SUM(G60:G71) -> 0 | R66: =H66/SUM(H60:H71) -> 0 | S66: =I66/SUM(I60:I71) -> 0 | T66: =J66/SUM(J60:J71) -> 0 | U66: =K66/SUM(K60:K71) -> 0
A67: =A66 -> CO | B67: offshore wind | C67: =SUMIFS(INDEX('IRA-BIL_IRA-BIL - Mid_annual_st'!$W$3:$AR$434,MATCH(C58,'IRA-BIL_IRA-BIL - Mid_annual_st'!$A$3:$A$434,0),),'IRA-BIL_IRA-BIL - Mid_annual_st'!$W$1:$AR$1,$B67) -> 0 | D67: =SUMIFS(INDEX('IRA-BIL_IRA-BIL - Mid_annual_st'!$W$3:$AR$434,MATCH(D58,'IRA-BIL_IRA-BIL - Mid_annual_st'!$A$3:$A$434,0),),'IRA-BIL_IRA-BIL - Mid_annual_st'!$W$1:$AR$1,$B67) -> 0 | E67: =SUMIFS(INDEX('IRA-BIL_IRA-BIL - Mid_annual_st'!$W$3:$AR$434,MATCH(E58,'IRA-BIL_IRA-BIL - Mid_annual_st'!$A$3:$A$434,0),),'IRA-BIL_IRA-BIL - Mid_annual_st'!$W$1:$AR$1,$B67) -> 0 | F67: =SUMIFS(INDEX('IRA-BIL_IRA-BIL - Mid_annual_st'!$W$3:$AR$434,MATCH(F58,'IRA-BIL_IRA-BIL - Mid_annual_st'!$A$3:$A$434,0),),'IRA-BIL_IRA-BIL - Mid_annual_st'!$W$1:$AR$1,$B67) -> 0 | G67: =SUMIFS(INDEX('IRA-BIL_IRA-BIL - Mid_annual_st'!$W$3:$AR$434,MATCH(G58,'IRA-BIL_IRA-BIL - Mid_annual_st'!$A$3:$A$434,0),),'IRA-BIL_IRA-BIL - Mid_annual_st'!$W$1:$AR$1,$B67) -> 0 | H67: =SUMIFS(INDEX('IRA-BIL_IRA-BIL - Mid_annual_st'!$W$3:$AR$434,MATCH(H58,'IRA-BIL_IRA-BIL - Mid_annual_st'!$A$3:$A$434,0),),'IRA-BIL_IRA-BIL - Mid_annual_st'!$W$1:$AR$1,$B67) -> 0 | I67: =SUMIFS(INDEX('IRA-BIL_IRA-BIL - Mid_annual_st'!$W$3:$AR$434,MATCH(I58,'IRA-BIL_IRA-BIL - Mid_annual_st'!$A$3:$A$434,0),),'IRA-BIL_IRA-BIL - Mid_annual_st'!$W$1:$AR$1,$B67) -> 0 | J67: =SUMIFS(INDEX('IRA-BIL_IRA-BIL - Mid_annual_st'!$W$3:$AR$434,MATCH(J58,'IRA-BIL_IRA-BIL - Mid_annual_st'!$A$3:$A$434,0),),'IRA-BIL_IRA-BIL - Mid_annual_st'!$W$1:$AR$1,$B67) -> 0 | K67: =SUMIFS(INDEX('IRA-BIL_IRA-BIL - Mid_annual_st'!$W$3:$AR$434,MATCH(K58,'IRA-BIL_IRA-BIL - Mid_annual_st'!$A$3:$A$434,0),),'IRA-BIL_IRA-BIL - Mid_annual_st'!$W$1:$AR$1,$B67) -> 0 | M67: =C67/SUM(C60:C71) -> 0 | N67: =D67/SUM(D60:D71) -> 0 | O67: =E67/SUM(E60:E71) -> 0 | P67: =F67/SUM(F60:F71) -> 0 | Q67: =G67/SUM(G60:G71) -> 0 | R67: =H67/SUM(H60:H71) -> 0 | S67: =I67/SUM(I60:I71) -> 0 | T67: =J67/SUM(J60:J71) -> 0 | U67: =K67/SUM(K60:K71) -> 0
A68: =A67 -> CO | B68: petroleum | C68: =SUMIFS(INDEX('IRA-BIL_IRA-BIL - Mid_annual_st'!$W$3:$AR$434,MATCH(C58,'IRA-BIL_IRA-BIL - Mid_annual_st'!$A$3:$A$434,0),),'IRA-BIL_IRA-BIL - Mid_annual_st'!$W$1:$AR$1,$B68) -> 0 | D68: =SUMIFS(INDEX('IRA-BIL_IRA-BIL - Mid_annual_st'!$W$3:$AR$434,MATCH(D58,'IRA-BIL_IRA-BIL - Mid_annual_st'!$A$3:$A$434,0),),'IRA-BIL_IRA-BIL - Mid_annual_st'!$W$1:$AR$1,$B68) -> 0 | E68: =SUMIFS(INDEX('IRA-BIL_IRA-BIL - Mid_annual_st'!$W$3:$AR$434,MATCH(E58,'IRA-BIL_IRA-BIL - Mid_annual_st'!$A$3:$A$434,0),),'IRA-BIL_IRA-BIL - Mid_annual_st'!$W$1:$AR$1,$B68) -> 0 | F68: =SUMIFS(INDEX('IRA-BIL_IRA-BIL - Mid_annual_st'!$W$3:$AR$434,MATCH(F58,'IRA-BIL_IRA-BIL - Mid_annual_st'!$A$3:$A$434,0),),'IRA-BIL_IRA-BIL - Mid_annual_st'!$W$1:$AR$1,$B68) -> 0 | G68: =SUMIFS(INDEX('IRA-BIL_IRA-BIL - Mid_annual_st'!$W$3:$AR$434,MATCH(G58,'IRA-BIL_IRA-BIL - Mid_annual_st'!$A$3:$A$434,0),),'IRA-BIL_IRA-BIL - Mid_annual_st'!$W$1:$AR$1,$B68) -> 0 | H68: =SUMIFS(INDEX('IRA-BIL_IRA-BIL - Mid_annual_st'!$W$3:$AR$434,MATCH(H58,'IRA-BIL_IRA-BIL - Mid_annual_st'!$A$3:$A$434,0),),'IRA-BIL_IRA-BIL - Mid_annual_st'!$W$1:$AR$1,$B68) -> 0 | I68: =SUMIFS(INDEX('IRA-BIL_IRA-BIL - Mid_annual_st'!$W$3:$AR$434,MATCH(I58,'IRA-BIL_IRA-BIL - Mid_annual_st'!$A$3:$A$434,0),),'IRA-BIL_IRA-BIL - Mid_annual_st'!$W$1:$AR$1,$B68) -> 0 | J68: =SUMIFS(INDEX('IRA-BIL_IRA-BIL - Mid_annual_st'!$W$3:$AR$434,MATCH(J58,'IRA-BIL_IRA-BIL - Mid_annual_st'!$A$3:$A$434,0),),'IRA-BIL_IRA-BIL - Mid_annual_st'!$W$1:$AR$1,$B68) -> 0 | K68: =SUMIFS(INDEX('IRA-BIL_IRA-BIL - Mid_annual_st'!$W$3:$AR$434,MATCH(K58,'IRA-BIL_IRA-BIL - Mid_annual_st'!$A$3:$A$434,0),),'IRA-BIL_IRA-BIL - Mid_annual_st'!$W$1:$AR$1,$B68) -> 0 | M68: =C68/SUM(C60:C71) -> 0 | N68: =D68/SUM(D60:D71) -> 0 | O68: =E68/SUM(E60:E71) -> 0 | P68: =F68/SUM(F60:F71) -> 0 | Q68: =G68/SUM(G60:G71) -> 0 | R68: =H68/SUM(H60:H71) -> 0 | S68: =I68/SUM(I60:I71) -> 0 | T68: =J68/SUM(J60:J71) -> 0 | U68: =K68/SUM(K60:K71) -> 0
A69: =A68 -> CO | B69: onshore wind | C69: =SUMIFS(INDEX('IRA-BIL_IRA-BIL - Mid_annual_st'!$W$3:$AR$434,MATCH(C58,'IRA-BIL_IRA-BIL - Mid_annual_st'!$A$3:$A$434,0),),'IRA-BIL_IRA-BIL - Mid_annual_st'!$W$1:$AR$1,$B69) -> 13923172 | D69: =SUMIFS(INDEX('IRA-BIL_IRA-BIL - Mid_annual_st'!$W$3:$AR$434,MATCH(D58,'IRA-BIL_IRA-BIL - Mid_annual_st'!$A$3:$A$434,0),),'IRA-BIL_IRA-BIL - Mid_annual_st'!$W$1:$AR$1,$B69) -> 45070009 | E69: =SUMIFS(INDEX('IRA-BIL_IRA-BIL - Mid_annual_st'!$W$3:$AR$434,MATCH(E58,'IRA-BIL_IRA-BIL - Mid_annual_st'!$A$3:$A$434,0),),'IRA-BIL_IRA-BIL - Mid_annual_st'!$W$1:$AR$1,$B69) -> 51380850 | F69: =SUMIFS(INDEX('IRA-BIL_IRA-BIL - Mid_annual_st'!$W$3:$AR$434,MATCH(F58,'IRA-BIL_IRA-BIL - Mid_annual_st'!$A$3:$A$434,0),),'IRA-BIL_IRA-BIL - Mid_annual_st'!$W$1:$AR$1,$B69) -> 64295987 | G69: =SUMIFS(INDEX('IRA-BIL_IRA-BIL - Mid_annual_st'!$W$3:$AR$434,MATCH(G58,'IRA-BIL_IRA-BIL - Mid_annual_st'!$A$3:$A$434,0),),'IRA-BIL_IRA-BIL - Mid_annual_st'!$W$1:$AR$1,$B69) -> 63950853 | H69: =SUMIFS(INDEX('IRA-BIL_IRA-BIL - Mid_annual_st'!$W$3:$AR$434,MATCH(H58,'IRA-BIL_IRA-BIL - Mid_annual_st'!$A$3:$A$434,0),),'IRA-BIL_IRA-BIL - Mid_annual_st'!$W$1:$AR$1,$B69) -> 63662697 | I69: =SUMIFS(INDEX('IRA-BIL_IRA-BIL - Mid_annual_st'!$W$3:$AR$434,MATCH(I58,'IRA-BIL_IRA-BIL - Mid_annual_st'!$A$3:$A$434,0),),'IRA-BIL_IRA-BIL - Mid_annual_st'!$W$1:$AR$1,$B69) -> 71113375 | J69: =SUMIFS(INDEX('IRA-BIL_IRA-BIL - Mid_annual_st'!$W$3:$AR$434,MATCH(J58,'IRA-BIL_IRA-BIL - Mid_annual_st'!$A$3:$A$434,0),),'IRA-BIL_IRA-BIL - Mid_annual_st'!$W$1:$AR$1,$B69) -> 69474938 | K69: =SUMIFS(INDEX('IRA-BIL_IRA-BIL - Mid_annual_st'!$W$3:$AR$434,MATCH(K58,'IRA-BIL_IRA-BIL - Mid_annual_st'!$A$3:$A$434,0),),'IRA-BIL_IRA-BIL - Mid_annual_st'!$W$1:$AR$1,$B69) -> 72601452 | M69: =C69/SUM(C60:C71) -> 0.26928314 | N69: =D69/SUM(D60:D71) -> 0.53704374 | O69: =E69/SUM(E60:E71) -> 0.6087112 | P69: =F69/SUM(F60:F71) -> 0.71745815 | Q69: =G69/SUM(G60:G71) -> 0.72390076 | R69: =H69/SUM(H60:H71) -> 0.74580444 | S69: =I69/SUM(I60:I71) -> 0.83033733 | T69: =J69/SUM(J60:J71) -> 0.8359876 | U69: =K69/SUM(K60:K71) -> 0.82901323
A70: =A69 -> CO | B70: pumped hydro | C70: 0 | D70: 0 | E70: 0 | F70: 0 | G70: 0 | H70: 0 | I70: 0 | J70: 0 | K70: 0 | M70: 0 | N70: 0 | O70: 0 | P70: 0 | Q70: 0 | R70: 0 | S70: 0 | T70: 0 | U70: 0
A71: =A70 -> CO | B71: solar pv | C71: =SUMIFS(INDEX('IRA-BIL_IRA-BIL - Mid_annual_st'!$W$3:$AR$434,MATCH(C58,'IRA-BIL_IRA-BIL - Mid_annual_st'!$A$3:$A$434,0),),'IRA-BIL_IRA-BIL - Mid_annual_st'!$W$1:$AR$1,$B71) -> 2314362 | D71: =SUMIFS(INDEX('IRA-BIL_IRA-BIL - Mid_annual_st'!$W$3:$AR$434,MATCH(D58,'IRA-BIL_IRA-BIL - Mid_annual_st'!$A$3:$A$434,0),),'IRA-BIL_IRA-BIL - Mid_annual_st'!$W$1:$AR$1,$B71) -> 9440278 | E71: =SUMIFS(INDEX('IRA-BIL_IRA-BIL - Mid_annual_st'!$W$3:$AR$434,MATCH(E58,'IRA-BIL_IRA-BIL - Mid_annual_st'!$A$3:$A$434,0),),'IRA-BIL_IRA-BIL - Mid_annual_st'!$W$1:$AR$1,$B71) -> 10037297 | F71: =SUMIFS(INDEX('IRA-BIL_IRA-BIL - Mid_annual_st'!$W$3:$AR$434,MATCH(F58,'IRA-BIL_IRA-BIL - Mid_annual_st'!$A$3:$A$434,0),),'IRA-BIL_IRA-BIL - Mid_annual_st'!$W$1:$AR$1,$B71) -> 9999299 | G71: =SUMIFS(INDEX('IRA-BIL_IRA-BIL - Mid_annual_st'!$W$3:$AR$434,MATCH(G58,'IRA-BIL_IRA-BIL - Mid_annual_st'!$A$3:$A$434,0),),'IRA-BIL_IRA-BIL - Mid_annual_st'!$W$1:$AR$1,$B71) -> 8810197 | H71: =SUMIFS(INDEX('IRA-BIL_IRA-BIL - Mid_annual_st'!$W$3:$AR$434,MATCH(H58,'IRA-BIL_IRA-BIL - Mid_annual_st'!$A$3:$A$434,0),),'IRA-BIL_IRA-BIL - Mid_annual_st'!$W$1:$AR$1,$B71) -> 8527369 | I71: =SUMIFS(INDEX('IRA-BIL_IRA-BIL - Mid_annual_st'!$W$3:$AR$434,MATCH(I58,'IRA-BIL_IRA-BIL - Mid_annual_st'!$A$3:$A$434,0),),'IRA-BIL_IRA-BIL - Mid_annual_st'!$W$1:$AR$1,$B71) -> 10610815 | J71: =SUMIFS(INDEX('IRA-BIL_IRA-BIL - Mid_annual_st'!$W$3:$AR$434,MATCH(J58,'IRA-BIL_IRA-BIL - Mid_annual_st'!$A$3:$A$434,0),),'IRA-BIL_IRA-BIL - Mid_annual_st'!$W$1:$AR$1,$B71) -> 10652594 | K71: =SUMIFS(INDEX('IRA-BIL_IRA-BIL - Mid_annual_st'!$W$3:$AR$434,MATCH(K58,'IRA-BIL_IRA-BIL - Mid_annual_st'!$A$3:$A$434,0),),'IRA-BIL_IRA-BIL - Mid_annual_st'!$W$1:$AR$1,$B71) -> 12561570 | M71: =C71/SUM(C60:C71) -> 0.044761256 | N71: =D71/SUM(D60:D71) -> 0.11248816 | O71: =E71/SUM(E60:E71) -> 0.1189123 | P71: =F71/SUM(F60:F71) -> 0.11157895 | Q71: =G71/SUM(G60:G71) -> 0.099728275 | R71: =H71/SUM(H60:H71) -> 0.099897585 | S71: =I71/SUM(I60:I71) -> 0.1238945 | T71: =J71/SUM(J60:J71) -> 0.128182 | U71: =K71/SUM(K60:K71) -> 0.14343663
A72: CT | C72: =$A72&"_"&C73 -> CT_2022 | D72: =$A72&"_"&D73 -> CT_2023 | E72: =$A72&"_"&E73 -> CT_2024 | F72: =$A72&"_"&F73 -> CT_2025 | G72: =$A72&"_"&G73 -> CT_2026 | H72: =$A72&"_"&H73 -> CT_2027 | I72: =$A72&"_"&I73 -> CT_2028 | J72: =$A72&"_"&J73 -> CT_2029 | K72: =$A72&"_"&K73 -> CT_2030 | M72: =$A72&"_"&M73 -> CT_2022 | N72: =$A72&"_"&N73 -> CT_2023 | O72: =$A72&"_"&O73 -> CT_2024 | P72: =$A72&"_"&P73 -> CT_2025 | Q72: =$A72&"_"&Q73 -> CT_2026 | R72: =$A72&"_"&R73 -> CT_2027 | S72: =$A72&"_"&S73 -> CT_2028 | T72: =$A72&"_"&T73 -> CT_2029 | U72: =$A72&"_"&U73 -> CT_2030
C73: 2022 | D73: 2023 | E73: 2024 | F73: 2025 | G73: 2026 | H73: 2027 | I73: 2028 | J73: 2029 | K73: 2030 | M73: 2022 | N73: 2023 | O73: 2024 | P73: 2025 | Q73: 2026 | R73: 2027 | S73: 2028 | T73: 2029 | U73: 2030
A74: =A72 -> CT | B74: battery | C74: 0 | D74: 0 | E74: 0 | F74: 0 | G74: 0 | H74: 0 | I74: 0 | J74: 0 | K74: 0 | M74: 0 | N74: 0 | O74: 0 | P74: 0 | Q74: 0 | R74: 0 | S74: 0 | T74: 0 | U74: 0
A75: =A74 -> CT | B75: biomass | C75: =SUMIFS(INDEX('IRA-BIL_IRA-BIL - Mid_annual_st'!$W$3:$AR$434,MATCH(C72,'IRA-BIL_IRA-BIL - Mid_annual_st'!$A$3:$A$434,0),),'IRA-BIL_IRA-BIL - Mid_annual_st'!$W$1:$AR$1,$B75) -> 1021960 | D75: =SUMIFS(INDEX('IRA-BIL_IRA-BIL - Mid_annual_st'!$W$3:$AR$434,MATCH(D72,'IRA-BIL_IRA-BIL - Mid_annual_st'!$A$3:$A$434,0),),'IRA-BIL_IRA-BIL - Mid_annual_st'!$W$1:$AR$1,$B75) -> 1021960 | E75: =SUMIFS(INDEX('IRA-BIL_IRA-BIL - Mid_annual_st'!$W$3:$AR$434,MATCH(E72,'IRA-BIL_IRA-BIL - Mid_annual_st'!$A$3:$A$434,0),),'IRA-BIL_IRA-BIL - Mid_annual_st'!$W$1:$AR$1,$B75) -> 1021960 | F75: =SUMIFS(INDEX('IRA-BIL_IRA-BIL - Mid_annual_st'!$W$3:$AR$434,MATCH(F72,'IRA-BIL_IRA-BIL - Mid_annual_st'!$A$3:$A$434,0),),'IRA-BIL_IRA-BIL - Mid_annual_st'!$W$1:$AR$1,$B75) -> 807683 | G75: =SUMIFS(INDEX('IRA-BIL_IRA-BIL - Mid_annual_st'!$W$3:$AR$434,MATCH(G72,'IRA-BIL_IRA-BIL - Mid_annual_st'!$A$3:$A$434,0),),'IRA-BIL_IRA-BIL - Mid_annual_st'!$W$1:$AR$1,$B75) -> 807683 | H75: =SUMIFS(INDEX('IRA-BIL_IRA-BIL - Mid_annual_st'!$W$3:$AR$434,MATCH(H72,'IRA-BIL_IRA-BIL - Mid_annual_st'!$A$3:$A$434,0),),'IRA-BIL_IRA-BIL - Mid_annual_st'!$W$1:$AR$1,$B75) -> 828025 | I75: =SUMIFS(INDEX('IRA-BIL_IRA-BIL - Mid_annual_st'!$W$3:$AR$434,MATCH(I72,'IRA-BIL_IRA-BIL - Mid_annual_st'!$A$3:$A$434,0),),'IRA-BIL_IRA-BIL - Mid_annual_st'!$W$1:$AR$1,$B75) -> 913440 | J75: =SUMIFS(INDEX('IRA-BIL_IRA-BIL - Mid_annual_st'!$W$3:$AR$434,MATCH(J72,'IRA-BIL_IRA-BIL - Mid_annual_st'!$A$3:$A$434,0),),'IRA-BIL_IRA-BIL - Mid_annual_st'!$W$1:$AR$1,$B75) -> 949012 | K75: =SUMIFS(INDEX('IRA-BIL_IRA-BIL - Mid_annual_st'!$W$3:$AR$434,MATCH(K72,'IRA-BIL_IRA-BIL - Mid_annual_st'!$A$3:$A$434,0),),'IRA-BIL_IRA-BIL - Mid_annual_st'!$W$1:$AR$1,$B75) -> 932580 | M75: =C75/SUM(C74:C85) -> 0.022149253 | N75: =D75/SUM(D74:D85) -> 0.024875236 | O75: =E75/SUM(E74:E85) -> 0.023292941 | P75: =F75/SUM(F74:F85) -> 0.018920064 | Q75: =G75/SUM(G74:G85) -> 0.019393335 | R75: =H75/SUM(H74:H85) -> 0.020059064 | S75: =I75/SUM(I74:I85) -> 0.023266953 | T75: =J75/SUM(J74:J85) -> 0.024498202 | U75: =K75/SUM(K74:K85) -> 0.026829339
A76: =A75 -> CT | B76: hard coal | C76: =SUMIFS(INDEX('IRA-BIL_IRA-BIL - Mid_annual_st'!$W$3:$AR$434,MATCH(C72,'IRA-BIL_IRA-BIL - Mid_annual_st'!$A$3:$A$434,0),),'IRA-BIL_IRA-BIL - Mid_annual_st'!$W$1:$AR$1,$B76) -> 0 | D76: =SUMIFS(INDEX('IRA-BIL_IRA-BIL - Mid_annual_st'!$W$3:$AR$434,MATCH(D72,'IRA-BIL_IRA-BIL - Mid_annual_st'!$A$3:$A$434,0),),'IRA-BIL_IRA-BIL - Mid_annual_st'!$W$1:$AR$1,$B76) -> 0 | E76: =SUMIFS(INDEX('IRA-BIL_IRA-BIL - Mid_annual_st'!$W$3:$AR$434,MATCH(E72,'IRA-BIL_IRA-BIL - Mid_annual_st'!$A$3:$A$434,0),),'IRA-BIL_IRA-BIL - Mid_annual_st'!$W$1:$AR$1,$B76) -> 0 | F76: =SUMIFS(INDEX('IRA-BIL_IRA-BIL - Mid_annual_st'!$W$3:$AR$434,MATCH(F72,'IRA-BIL_IRA-BIL - Mid_annual_st'!$A$3:$A$434,0),),'IRA-BIL_IRA-BIL - Mid_annual_st'!$W$1:$AR$1,$B76) -> 10252 | G76: =SUMIFS(INDEX('IRA-BIL_IRA-BIL - Mid_annual_st'!$W$3:$AR$434,MATCH(G72,'IRA-BIL_IRA-BIL - Mid_annual_st'!$A$3:$A$434,0),),'IRA-BIL_IRA-BIL - Mid_annual_st'!$W$1:$AR$1,$B76) -> 20504 | H76: =SUMIFS(INDEX('IRA-BIL_IRA-BIL - Mid_annual_st'!$W$3:$AR$434,MATCH(H72,'IRA-BIL_IRA-BIL - Mid_annual_st'!$A$3:$A$434,0),),'IRA-BIL_IRA-BIL - Mid_annual_st'!$W$1:$AR$1,$B76) -> 30755 | I76: =SUMIFS(INDEX('IRA-BIL_IRA-BIL - Mid_annual_st'!$W$3:$AR$434,MATCH(I72,'IRA-BIL_IRA-BIL - Mid_annual_st'!$A$3:$A$434,0),),'IRA-BIL_IRA-BIL - Mid_annual_st'!$W$1:$AR$1,$B76) -> 0 | J76: =SUMIFS(INDEX('IRA-BIL_IRA-BIL - Mid_annual_st'!$W$3:$AR$434,MATCH(J72,'IRA-BIL_IRA-BIL - Mid_annual_st'!$A$3:$A$434,0),),'IRA-BIL_IRA-BIL - Mid_annual_st'!$W$1:$AR$1,$B76) -> 0 | K76: =SUMIFS(INDEX('IRA-BIL_IRA-BIL - Mid_annual_st'!$W$3:$AR$434,MATCH(K72,'IRA-BIL_IRA-BIL - Mid_annual_st'!$A$3:$A$434,0),),'IRA-BIL_IRA-BIL - Mid_annual_st'!$W$1:$AR$1,$B76) -> 0 | M76: =C76/SUM(C74:C85) -> 0 | N76: =D76/SUM(D74:D85) -> 0 | O76: =E76/SUM(E74:E85) -> 0 | P76: =F76/SUM(F74:F85) -> 0.00024015424 | Q76: =G76/SUM(G74:G85) -> 0.00049232304 | R76: =H76/SUM(H74:H85) -> 0.00074504575 | S76: =I76/SUM(I74:I85) -> 0 | T76: =J76/SUM(J74:J85) -> 0 | U76: =K76/SUM(K74:K85) -> 0
A77: =A76 -> CT | B77: geothermal | C77: =SUMIFS(INDEX('IRA-BIL_IRA-BIL - Mid_annual_st'!$W$3:$AR$434,MATCH(C72,'IRA-BIL_IRA-BIL - Mid_annual_st'!$A$3:$A$434,0),),'IRA-BIL_IRA-BIL - Mid_annual_st'!$W$1:$AR$1,$B77) -> 0 | D77: =SUMIFS(INDEX('IRA-BIL_IRA-BIL - Mid_annual_st'!$W$3:$AR$434,MATCH(D72,'IRA-BIL_IRA-BIL - Mid_annual_st'!$A$3:$A$434,0),),'IRA-BIL_IRA-BIL - Mid_annual_st'!$W$1:$AR$1,$B77) -> 0 | E77: =SUMIFS(INDEX('IRA-BIL_IRA-BIL - Mid_annual_st'!$W$3:$AR$434,MATCH(E72,'IRA-BIL_IRA-BIL - Mid_annual_st'!$A$3:$A$434,0),),'IRA-BIL_IRA-BIL - Mid_annual_st'!$W$1:$AR$1,$B77) -> 0 | F77: =SUMIFS(INDEX('IRA-BIL_IRA-BIL - Mid_annual_st'!$W$3:$AR$434,MATCH(F72,'IRA-BIL_IRA-BIL - Mid_annual_st'!$A$3:$A$434,0),),'IRA-BIL_IRA-BIL - Mid_annual_st'!$W$1:$AR$1,$B77) -> 0 | G77: =SUMIFS(INDEX('IRA-BIL_IRA-BIL - Mid_annual_st'!$W$3:$AR$434,MATCH(G72,'IRA-BIL_IRA-BIL - Mid_annual_st'!$A$3:$A$434,0),),'IRA-BIL_IRA-BIL - Mid_annual_st'!$W$1:$AR$1,$B77) -> 0 | H77: =SUMIFS(INDEX('IRA-BIL_IRA-BIL - Mid_annual_st'!$W$3:$AR$434,MATCH(H72,'IRA-BIL_IRA-BIL - Mid_annual_st'!$A$3:$A$434,0),),'IRA-BIL_IRA-BIL - Mid_annual_st'!$W$1:$AR$1,$B77) -> 0 | I77: =SUMIFS(INDEX('IRA-BIL_IRA-BIL - Mid_annual_st'!$W$3:$AR$434,MATCH(I72,'IRA-BIL_IRA-BIL - Mid_annual_st'!$A$3:$A$434,0),),'IRA-BIL_IRA-BIL - Mid_annual_st'!$W$1:$AR$1,$B77) -> 0 | J77: =SUMIFS(INDEX('IRA-BIL_IRA-BIL - Mid_annual_st'!$W$3:$AR$434,MATCH(J72,'IRA-BIL_IRA-BIL - Mid_annual_st'!$A$3:$A$434,0),),'IRA-BIL_IRA-BIL - Mid_annual_st'!$W$1:$AR$1,$B77) -> 0 | K77: =SUMIFS(INDEX('IRA-BIL_IRA-BIL - Mid_annual_st'!$W$3:$AR$434,MATCH(K72,'IRA-BIL_IRA-BIL - Mid_annual_st'!$A$3:$A$434,0),),'IRA-BIL_IRA-BIL - Mid_annual_st'!$W$1:$AR$1,$B77) -> 0 | M77: =C77/SUM(C74:C85) -> 0 | N77: =D77/SUM(D74:D85) -> 0 | O77: =E77/SUM(E74:E85) -> 0 | P77: =F77/SUM(F74:F85) -> 0 | Q77: =G77/SUM(G74:G85) -> 0 | R77: =H77/SUM(H74:H85) -> 0 | S77: =I77/SUM(I74:I85) -> 0 | T77: =J77/SUM(J74:J85) -> 0 | U77: =K77/SUM(K74:K85) -> 0
A78: =A77 -> CT | B78: hydro | C78: =SUMIFS(INDEX('IRA-BIL_IRA-BIL - Mid_annual_st'!$W$3:$AR$434,MATCH(C72,'IRA-BIL_IRA-BIL - Mid_annual_st'!$A$3:$A$434,0),),'IRA-BIL_IRA-BIL - Mid_annual_st'!$W$1:$AR$1,$B78) -> 410024 | D78: =SUMIFS(INDEX('IRA-BIL_IRA-BIL - Mid_annual_st'!$W$3:$AR$434,MATCH(D72,'IRA-BIL_IRA-BIL - Mid_annual_st'!$A$3:$A$434,0),),'IRA-BIL_IRA-BIL - Mid_annual_st'!$W$1:$AR$1,$B78) -> 410024 | E78: =SUMIFS(INDEX('IRA-BIL_IRA-BIL - Mid_annual_st'!$W$3:$AR$434,MATCH(E72,'IRA-BIL_IRA-BIL - Mid_annual_st'!$A$3:$A$434,0),),'IRA-BIL_IRA-BIL - Mid_annual_st'!$W$1:$AR$1,$B78) -> 410358 | F78: =SUMIFS(INDEX('IRA-BIL_IRA-BIL - Mid_annual_st'!$W$3:$AR$434,MATCH(F72,'IRA-BIL_IRA-BIL - Mid_annual_st'!$A$3:$A$434,0),),'IRA-BIL_IRA-BIL - Mid_annual_st'!$W$1:$AR$1,$B78) -> 410693 | G78: =SUMIFS(INDEX('IRA-BIL_IRA-BIL - Mid_annual_st'!$W$3:$AR$434,MATCH(G72,'IRA-BIL_IRA-BIL - Mid_annual_st'!$A$3:$A$434,0),),'IRA-BIL_IRA-BIL - Mid_annual_st'!$W$1:$AR$1,$B78) -> 411028 | H78: =SUMIFS(INDEX('IRA-BIL_IRA-BIL - Mid_annual_st'!$W$3:$AR$434,MATCH(H72,'IRA-BIL_IRA-BIL - Mid_annual_st'!$A$3:$A$434,0),),'IRA-BIL_IRA-BIL - Mid_annual_st'!$W$1:$AR$1,$B78) -> 411362 | I78: =SUMIFS(INDEX('IRA-BIL_IRA-BIL - Mid_annual_st'!$W$3:$AR$434,MATCH(I72,'IRA-BIL_IRA-BIL - Mid_annual_st'!$A$3:$A$434,0),),'IRA-BIL_IRA-BIL - Mid_annual_st'!$W$1:$AR$1,$B78) -> 411697 | J78: =SUMIFS(INDEX('IRA-BIL_IRA-BIL - Mid_annual_st'!$W$3:$AR$434,MATCH(J72,'IRA-BIL_IRA-BIL - Mid_annual_st'!$A$3:$A$434,0),),'IRA-BIL_IRA-BIL - Mid_annual_st'!$W$1:$AR$1,$B78) -> 412031 | K78: =SUMIFS(INDEX('IRA-BIL_IRA-BIL - Mid_annual_st'!$W$3:$AR$434,MATCH(K72,'IRA-BIL_IRA-BIL - Mid_annual_st'!$A$3:$A$434,0),),'IRA-BIL_IRA-BIL - Mid_annual_st'!$W$1:$AR$1,$B78) -> 412366 | M78: =C78/SUM(C74:C85) -> 0.0088865761 | N78: =D78/SUM(D74:D85) -> 0.0099802767 | O78: =E78/SUM(E74:E85) -> 0.0093530515 | P78: =F78/SUM(F74:F85) -> 0.0096205291 | Q78: =G78/SUM(G74:G85) -> 0.0098692232 | R78: =H78/SUM(H74:H85) -> 0.0099653231 | S78: =I78/SUM(I74:I85) -> 0.01048666 | T78: =J78/SUM(J74:J85) -> 0.010636344 | U78: =K78/SUM(K74:K85) -> 0.011863333
A79: =A78 -> CT | B79: natural gas steam turbine | C79: =SUMIFS(INDEX('IRA-BIL_IRA-BIL - Mid_annual_st'!$W$3:$AR$434,MATCH(C72,'IRA-BIL_IRA-BIL - Mid_annual_st'!$A$3:$A$434,0),),'IRA-BIL_IRA-BIL - Mid_annual_st'!$W$1:$AR$1,$B79) -> 26400211 | D79: =SUMIFS(INDEX('IRA-BIL_IRA-BIL - Mid_annual_st'!$W$3:$AR$434,MATCH(D72,'IRA-BIL_IRA-BIL - Mid_annual_st'!$A$3:$A$434,0),),'IRA-BIL_IRA-BIL - Mid_annual_st'!$W$1:$AR$1,$B79) -> 21854197 | E79: =SUMIFS(INDEX('IRA-BIL_IRA-BIL - Mid_annual_st'!$W$3:$AR$434,MATCH(E72,'IRA-BIL_IRA-BIL - Mid_annual_st'!$A$3:$A$434,0),),'IRA-BIL_IRA-BIL - Mid_annual_st'!$W$1:$AR$1,$B79) -> 23440867 | F79: =SUMIFS(INDEX('IRA-BIL_IRA-BIL - Mid_annual_st'!$W$3:$AR$434,MATCH(F72,'IRA-BIL_IRA-BIL - Mid_annual_st'!$A$3:$A$434,0),),'IRA-BIL_IRA-BIL - Mid_annual_st'!$W$1:$AR$1,$B79) -> 21982868 | G79: =SUMIFS(INDEX('IRA-BIL_IRA-BIL - Mid_annual_st'!$W$3:$AR$434,MATCH(G72,'IRA-BIL_IRA-BIL - Mid_annual_st'!$A$3:$A$434,0),),'IRA-BIL_IRA-BIL - Mid_annual_st'!$W$1:$AR$1,$B79) -> 20950437 | H79: =SUMIFS(INDEX('IRA-BIL_IRA-BIL - Mid_annual_st'!$W$3:$AR$434,MATCH(H72,'IRA-BIL_IRA-BIL - Mid_annual_st'!$A$3:$A$434,0),),'IRA-BIL_IRA-BIL - Mid_annual_st'!$W$1:$AR$1,$B79) -> 20583076 | I79: =SUMIFS(INDEX('IRA-BIL_IRA-BIL - Mid_annual_st'!$W$3:$AR$434,MATCH(I72,'IRA-BIL_IRA-BIL - Mid_annual_st'!$A$3:$A$434,0),),'IRA-BIL_IRA-BIL - Mid_annual_st'!$W$1:$AR$1,$B79) -> 18540740 | J79: =SUMIFS(INDEX('IRA-BIL_IRA-BIL - Mid_annual_st'!$W$3:$AR$434,MATCH(J72,'IRA-BIL_IRA-BIL - Mid_annual_st'!$A$3:$A$434,0),),'IRA-BIL_IRA-BIL - Mid_annual_st'!$W$1:$AR$1,$B79) -> 17891498 | K79: =SUMIFS(INDEX('IRA-BIL_IRA-BIL - Mid_annual_st'!$W$3:$AR$434,MATCH(K72,'IRA-BIL_IRA-BIL - Mid_annual_st'!$A$3:$A$434,0),),'IRA-BIL_IRA-BIL - Mid_annual_st'!$W$1:$AR$1,$B79) -> 13779844 | M79: =C79/SUM(C74:C85) -> 0.57217988 | N79: =D79/SUM(D74:D85) -> 0.53194675 | O79: =E79/SUM(E74:E85) -> 0.53427407 | P79: =F79/SUM(F74:F85) -> 0.51495112 | Q79: =G79/SUM(G74:G85) -> 0.50304247 | R79: =H79/SUM(H74:H85) -> 0.49862895 | S79: =I79/SUM(I74:I85) -> 0.47226586 | T79: =J79/SUM(J74:J85) -> 0.46185878 | U79: =K79/SUM(K74:K85) -> 0.39643151
A80: =A79 -> CT | B80: nuclear | C80: =SUMIFS(INDEX('IRA-BIL_IRA-BIL - Mid_annual_st'!$W$3:$AR$434,MATCH(C72,'IRA-BIL_IRA-BIL - Mid_annual_st'!$A$3:$A$434,0),),'IRA-BIL_IRA-BIL - Mid_annual_st'!$W$1:$AR$1,$B80) -> 16617388 | D80: =SUMIFS(INDEX('IRA-BIL_IRA-BIL - Mid_annual_st'!$W$3:$AR$434,MATCH(D72,'IRA-BIL_IRA-BIL - Mid_annual_st'!$A$3:$A$434,0),),'IRA-BIL_IRA-BIL - Mid_annual_st'!$W$1:$AR$1,$B80) -> 16617388 | E80: =SUMIFS(INDEX('IRA-BIL_IRA-BIL - Mid_annual_st'!$W$3:$AR$434,MATCH(E72,'IRA-BIL_IRA-BIL - Mid_annual_st'!$A$3:$A$434,0),),'IRA-BIL_IRA-BIL - Mid_annual_st'!$W$1:$AR$1,$B80) -> 16617388 | F80: =SUMIFS(INDEX('IRA-BIL_IRA-BIL - Mid_annual_st'!$W$3:$AR$434,MATCH(F72,'IRA-BIL_IRA-BIL - Mid_annual_st'!$A$3:$A$434,0),),'IRA-BIL_IRA-BIL - Mid_annual_st'!$W$1:$AR$1,$B80) -> 16617388 | G80: =SUMIFS(INDEX('IRA-BIL_IRA-BIL - Mid_annual_st'!$W$3:$AR$434,MATCH(G72,'IRA-BIL_IRA-BIL - Mid_annual_st'!$A$3:$A$434,0),),'IRA-BIL_IRA-BIL - Mid_annual_st'!$W$1:$AR$1,$B80) -> 16617388 | H80: =SUMIFS(INDEX('IRA-BIL_IRA-BIL - Mid_annual_st'!$W$3:$AR$434,MATCH(H72,'IRA-BIL_IRA-BIL - Mid_annual_st'!$A$3:$A$434,0),),'IRA-BIL_IRA-BIL - Mid_annual_st'!$W$1:$AR$1,$B80) -> 16617388 | I80: =SUMIFS(INDEX('IRA-BIL_IRA-BIL - Mid_annual_st'!$W$3:$AR$434,MATCH(I72,'IRA-BIL_IRA-BIL - Mid_annual_st'!$A$3:$A$434,0),),'IRA-BIL_IRA-BIL - Mid_annual_st'!$W$1:$AR$1,$B80) -> 16617388 | J80: =SUMIFS(INDEX('IRA-BIL_IRA-BIL - Mid_annual_st'!$W$3:$AR$434,MATCH(J72,'IRA-BIL_IRA-BIL - Mid_annual_st'!$A$3:$A$434,0),),'IRA-BIL_IRA-BIL - Mid_annual_st'!$W$1:$AR$1,$B80) -> 16617388 | K80: =SUMIFS(INDEX('IRA-BIL_IRA-BIL - Mid_annual_st'!$W$3:$AR$434,MATCH(K72,'IRA-BIL_IRA-BIL - Mid_annual_st'!$A$3:$A$434,0),),'IRA-BIL_IRA-BIL - Mid_annual_st'!$W$1:$AR$1,$B80) -> 16617388 | M80: =C80/SUM(C74:C85) -> 0.36015375 | N80: =D80/SUM(D74:D85) -> 0.40447908 | O80: =E80/SUM(E74:E85) -> 0.37875047 | P80: =F80/SUM(F74:F85) -> 0.38926416 | Q80: =G80/SUM(G74:G85) -> 0.39900131 | R80: =H80/SUM(H74:H85) -> 0.4025594 | S80: =I80/SUM(I74:I85) -> 0.42327464 | T80: =J80/SUM(J74:J85) -> 0.42896836 | U80: =K80/SUM(K74:K85) -> 0.47806465
A81: =A80 -> CT | B81: offshore wind | C81: =SUMIFS(INDEX('IRA-BIL_IRA-BIL - Mid_annual_st'!$W$3:$AR$434,MATCH(C72,'IRA-BIL_IRA-BIL - Mid_annual_st'!$A$3:$A$434,0),),'IRA-BIL_IRA-BIL - Mid_annual_st'!$W$1:$AR$1,$B81) -> 0 | D81: =SUMIFS(INDEX('IRA-BIL_IRA-BIL - Mid_annual_st'!$W$3:$AR$434,MATCH(D72,'IRA-BIL_IRA-BIL - Mid_annual_st'!$A$3:$A$434,0),),'IRA-BIL_IRA-BIL - Mid_annual_st'!$W$1:$AR$1,$B81) -> 0 | E81: =SUMIFS(INDEX('IRA-BIL_IRA-BIL - Mid_annual_st'!$W$3:$AR$434,MATCH(E72,'IRA-BIL_IRA-BIL - Mid_annual_st'!$A$3:$A$434,0),),'IRA-BIL_IRA-BIL - Mid_annual_st'!$W$1:$AR$1,$B81) -> 0 | F81: =SUMIFS(INDEX('IRA-BIL_IRA-BIL - Mid_annual_st'!$W$3:$AR$434,MATCH(F72,'IRA-BIL_IRA-BIL - Mid_annual_st'!$A$3:$A$434,0),),'IRA-BIL_IRA-BIL - Mid_annual_st'!$W$1:$AR$1,$B81) -> 0 | G81: =SUMIFS(INDEX('IRA-BIL_IRA-BIL - Mid_annual_st'!$W$3:$AR$434,MATCH(G72,'IRA-BIL_IRA-BIL - Mid_annual_st'!$A$3:$A$434,0),),'IRA-BIL_IRA-BIL - Mid_annual_st'!$W$1:$AR$1,$B81) -> 0 | H81: =SUMIFS(INDEX('IRA-BIL_IRA-BIL - Mid_annual_st'!$W$3:$AR$434,MATCH(H72,'IRA-BIL_IRA-BIL - Mid_annual_st'!$A$3:$A$434,0),),'IRA-BIL_IRA-BIL - Mid_annual_st'!$W$1:$AR$1,$B81) -> 0 | I81: =SUMIFS(INDEX('IRA-BIL_IRA-BIL - Mid_annual_st'!$W$3:$AR$434,MATCH(I72,'IRA-BIL_IRA-BIL - Mid_annual_st'!$A$3:$A$434,0),),'IRA-BIL_IRA-BIL - Mid_annual_st'!$W$1:$AR$1,$B81) -> 0 | J81: =SUMIFS(INDEX('IRA-BIL_IRA-BIL - Mid_annual_st'!$W$3:$AR$434,MATCH(J72,'IRA-BIL_IRA-BIL - Mid_annual_st'!$A$3:$A$434,0),),'IRA-BIL_IRA-BIL - Mid_annual_st'!$W$1:$AR$1,$B81) -> 0 | K81: =SUMIFS(INDEX('IRA-BIL_IRA-BIL - Mid_annual_st'!$W$3:$AR$434,MATCH(K72,'IRA-BIL_IRA-BIL - Mid_annual_st'!$A$3:$A$434,0),),'IRA-BIL_IRA-BIL - Mid_annual_st'!$W$1:$AR$1,$B81) -> 0 | M81: =C81/SUM(C74:C85) -> 0 | N81: =D81/SUM(D74:D85) -> 0 | O81: =E81/SUM(E74:E85) -> 0 | P81: =F81/SUM(F74:F85) -> 0 | Q81: =G81/SUM(G74:G85) -> 0 | R81: =H81/SUM(H74:H85) -> 0 | S81: =I81/SUM(I74:I85) -> 0 | T81: =J81/SUM(J74:J85) -> 0 | U81: =K81/SUM(K74:K85) -> 0
A82: =A81 -> CT | B82: petroleum | C82: =SUMIFS(INDEX('IRA-BIL_IRA-BIL - Mid_annual_st'!$W$3:$AR$434,MATCH(C72,'IRA-BIL_IRA-BIL - Mid_annual_st'!$A$3:$A$434,0),),'IRA-BIL_IRA-BIL - Mid_annual_st'!$W$1:$AR$1,$B82) -> 1212182 | D82: =SUMIFS(INDEX('IRA-BIL_IRA-BIL - Mid_annual_st'!$W$3:$AR$434,MATCH(D72,'IRA-BIL_IRA-BIL - Mid_annual_st'!$A$3:$A$434,0),),'IRA-BIL_IRA-BIL - Mid_annual_st'!$W$1:$AR$1,$B82) -> 673485 | E82: =SUMIFS(INDEX('IRA-BIL_IRA-BIL - Mid_annual_st'!$W$3:$AR$434,MATCH(E72,'IRA-BIL_IRA-BIL - Mid_annual_st'!$A$3:$A$434,0),),'IRA-BIL_IRA-BIL - Mid_annual_st'!$W$1:$AR$1,$B82) -> 25414 | F82: =SUMIFS(INDEX('IRA-BIL_IRA-BIL - Mid_annual_st'!$W$3:$AR$434,MATCH(F72,'IRA-BIL_IRA-BIL - Mid_annual_st'!$A$3:$A$434,0),),'IRA-BIL_IRA-BIL - Mid_annual_st'!$W$1:$AR$1,$B82) -> 25414 | G82: =SUMIFS(INDEX('IRA-BIL_IRA-BIL - Mid_annual_st'!$W$3:$AR$434,MATCH(G72,'IRA-BIL_IRA-BIL - Mid_annual_st'!$A$3:$A$434,0),),'IRA-BIL_IRA-BIL - Mid_annual_st'!$W$1:$AR$1,$B82) -> 25414 | H82: =SUMIFS(INDEX('IRA-BIL_IRA-BIL - Mid_annual_st'!$W$3:$AR$434,MATCH(H72,'IRA-BIL_IRA-BIL - Mid_annual_st'!$A$3:$A$434,0),),'IRA-BIL_IRA-BIL - Mid_annual_st'!$W$1:$AR$1,$B82) -> 25414 | I82: =SUMIFS(INDEX('IRA-BIL_IRA-BIL - Mid_annual_st'!$W$3:$AR$434,MATCH(I72,'IRA-BIL_IRA-BIL - Mid_annual_st'!$A$3:$A$434,0),),'IRA-BIL_IRA-BIL - Mid_annual_st'!$W$1:$AR$1,$B82) -> 0 | J82: =SUMIFS(INDEX('IRA-BIL_IRA-BIL - Mid_annual_st'!$W$3:$AR$434,MATCH(J72,'IRA-BIL_IRA-BIL - Mid_annual_st'!$A$3:$A$434,0),),'IRA-BIL_IRA-BIL - Mid_annual_st'!$W$1:$AR$1,$B82) -> 0 | K82: =SUMIFS(INDEX('IRA-BIL_IRA-BIL - Mid_annual_st'!$W$3:$AR$434,MATCH(K72,'IRA-BIL_IRA-BIL - Mid_annual_st'!$A$3:$A$434,0),),'IRA-BIL_IRA-BIL - Mid_annual_st'!$W$1:$AR$1,$B82) -> 0 | M82: =C82/SUM(C74:C85) -> 0.026271993 | N82: =D82/SUM(D74:D85) -> 0.016393105 | O82: =E82/SUM(E74:E85) -> 0.00057924654 | P82: =F82/SUM(F74:F85) -> 0.00059532577 | Q82: =G82/SUM(G74:G85) -> 0.0006102174 | R82: =H82/SUM(H74:H85) -> 0.00061565901 | S82: =I82/SUM(I74:I85) -> 0 | T82: =J82/SUM(J74:J85) -> 0 | U82: =K82/SUM(K74:K85) -> 0
A83: =A82 -> CT | B83: onshore wind | C83: =SUMIFS(INDEX('IRA-BIL_IRA-BIL - Mid_annual_st'!$W$3:$AR$434,MATCH(C72,'IRA-BIL_IRA-BIL - Mid_annual_st'!$A$3:$A$434,0),),'IRA-BIL_IRA-BIL - Mid_annual_st'!$W$1:$AR$1,$B83) -> 3005 | D83: =SUMIFS(INDEX('IRA-BIL_IRA-BIL - Mid_annual_st'!$W$3:$AR$434,MATCH(D72,'IRA-BIL_IRA-BIL - Mid_annual_st'!$A$3:$A$434,0),),'IRA-BIL_IRA-BIL - Mid_annual_st'!$W$1:$AR$1,$B83) -> 2997 | E83: =SUMIFS(INDEX('IRA-BIL_IRA-BIL - Mid_annual_st'!$W$3:$AR$434,MATCH(E72,'IRA-BIL_IRA-BIL - Mid_annual_st'!$A$3:$A$434,0),),'IRA-BIL_IRA-BIL - Mid_annual_st'!$W$1:$AR$1,$B83) -> 2989 | F83: =SUMIFS(INDEX('IRA-BIL_IRA-BIL - Mid_annual_st'!$W$3:$AR$434,MATCH(F72,'IRA-BIL_IRA-BIL - Mid_annual_st'!$A$3:$A$434,0),),'IRA-BIL_IRA-BIL - Mid_annual_st'!$W$1:$AR$1,$B83) -> 2981 | G83: =SUMIFS(INDEX('IRA-BIL_IRA-BIL - Mid_annual_st'!$W$3:$AR$434,MATCH(G72,'IRA-BIL_IRA-BIL - Mid_annual_st'!$A$3:$A$434,0),),'IRA-BIL_IRA-BIL - Mid_annual_st'!$W$1:$AR$1,$B83) -> 2973 | H83: =SUMIFS(INDEX('IRA-BIL_IRA-BIL - Mid_annual_st'!$W$3:$AR$434,MATCH(H72,'IRA-BIL_IRA-BIL - Mid_annual_st'!$A$3:$A$434,0),),'IRA-BIL_IRA-BIL - Mid_annual_st'!$W$1:$AR$1,$B83) -> 2965 | I83: =SUMIFS(INDEX('IRA-BIL_IRA-BIL - Mid_annual_st'!$W$3:$AR$434,MATCH(I72,'IRA-BIL_IRA-BIL - Mid_annual_st'!$A$3:$A$434,0),),'IRA-BIL_IRA-BIL - Mid_annual_st'!$W$1:$AR$1,$B83) -> 2932 | J83: =SUMIFS(INDEX('IRA-BIL_IRA-BIL - Mid_annual_st'!$W$3:$AR$434,MATCH(J72,'IRA-BIL_IRA-BIL - Mid_annual_st'!$A$3:$A$434,0),),'IRA-BIL_IRA-BIL - Mid_annual_st'!$W$1:$AR$1,$B83) -> 2566 | K83: =SUMIFS(INDEX('IRA-BIL_IRA-BIL - Mid_annual_st'!$W$3:$AR$434,MATCH(K72,'IRA-BIL_IRA-BIL - Mid_annual_st'!$A$3:$A$434,0),),'IRA-BIL_IRA-BIL - Mid_annual_st'!$W$1:$AR$1,$B83) -> 2749 | M83: =C83/SUM(C74:C85) -> 6.5128288e-05 | N83: =D83/SUM(D74:D85) -> 7.2949118e-05 | O83: =E83/SUM(E74:E85) -> 6.8126541e-05 | P83: =F83/SUM(F74:F85) -> 6.9830256e-05 | Q83: =G83/SUM(G74:G85) -> 7.1384919e-05 | R83: =H83/SUM(H74:H85) -> 7.1827692e-05 | S83: =I83/SUM(I74:I85) -> 7.4683291e-05 | T83: =J83/SUM(J74:J85) -> 6.6239822e-05 | U83: =K83/SUM(K74:K85) -> 7.9085817e-05
A84: =A83 -> CT | B84: pumped hydro | C84: 0 | D84: 0 | E84: 0 | F84: 0 | G84: 0 | H84: 0 | I84: 0 | J84: 0 | K84: 0 | M84: 0 | N84: 0 | O84: 0 | P84: 0 | Q84: 0 | R84: 0 | S84: 0 | T84: 0 | U84: 0
A85: =A84 -> CT | B85: solar pv | C85: =SUMIFS(INDEX('IRA-BIL_IRA-BIL - Mid_annual_st'!$W$3:$AR$434,MATCH(C72,'IRA-BIL_IRA-BIL - Mid_annual_st'!$A$3:$A$434,0),),'IRA-BIL_IRA-BIL - Mid_annual_st'!$W$1:$AR$1,$B85) -> 474935 | D85: =SUMIFS(INDEX('IRA-BIL_IRA-BIL - Mid_annual_st'!$W$3:$AR$434,MATCH(D72,'IRA-BIL_IRA-BIL - Mid_annual_st'!$A$3:$A$434,0),),'IRA-BIL_IRA-BIL - Mid_annual_st'!$W$1:$AR$1,$B85) -> 503379 | E85: =SUMIFS(INDEX('IRA-BIL_IRA-BIL - Mid_annual_st'!$W$3:$AR$434,MATCH(E72,'IRA-BIL_IRA-BIL - Mid_annual_st'!$A$3:$A$434,0),),'IRA-BIL_IRA-BIL - Mid_annual_st'!$W$1:$AR$1,$B85) -> 2355261 | F85: =SUMIFS(INDEX('IRA-BIL_IRA-BIL - Mid_annual_st'!$W$3:$AR$434,MATCH(F72,'IRA-BIL_IRA-BIL - Mid_annual_st'!$A$3:$A$434,0),),'IRA-BIL_IRA-BIL - Mid_annual_st'!$W$1:$AR$1,$B85) -> 2831953 | G85: =SUMIFS(INDEX('IRA-BIL_IRA-BIL - Mid_annual_st'!$W$3:$AR$434,MATCH(G72,'IRA-BIL_IRA-BIL - Mid_annual_st'!$A$3:$A$434,0),),'IRA-BIL_IRA-BIL - Mid_annual_st'!$W$1:$AR$1,$B85) -> 2812025 | H85: =SUMIFS(INDEX('IRA-BIL_IRA-BIL - Mid_annual_st'!$W$3:$AR$434,MATCH(H72,'IRA-BIL_IRA-BIL - Mid_annual_st'!$A$3:$A$434,0),),'IRA-BIL_IRA-BIL - Mid_annual_st'!$W$1:$AR$1,$B85) -> 2780359 | I85: =SUMIFS(INDEX('IRA-BIL_IRA-BIL - Mid_annual_st'!$W$3:$AR$434,MATCH(I72,'IRA-BIL_IRA-BIL - Mid_annual_st'!$A$3:$A$434,0),),'IRA-BIL_IRA-BIL - Mid_annual_st'!$W$1:$AR$1,$B85) -> 2772919 | J85: =SUMIFS(INDEX('IRA-BIL_IRA-BIL - Mid_annual_st'!$W$3:$AR$434,MATCH(J72,'IRA-BIL_IRA-BIL - Mid_annual_st'!$A$3:$A$434,0),),'IRA-BIL_IRA-BIL - Mid_annual_st'!$W$1:$AR$1,$B85) -> 2865532 | K85: =SUMIFS(INDEX('IRA-BIL_IRA-BIL - Mid_annual_st'!$W$3:$AR$434,MATCH(K72,'IRA-BIL_IRA-BIL - Mid_annual_st'!$A$3:$A$434,0),),'IRA-BIL_IRA-BIL - Mid_annual_st'!$W$1:$AR$1,$B85) -> 3014782 | M85: =C85/SUM(C74:C85) -> 0.010293412 | N85: =D85/SUM(D74:D85) -> 0.012252604 | O85: =E85/SUM(E74:E85) -> 0.053682096 | P85: =F85/SUM(F74:F85) -> 0.066338813 | Q85: =G85/SUM(G74:G85) -> 0.067519737 | R85: =H85/SUM(H74:H85) -> 0.067354728 | S85: =I85/SUM(I74:I85) -> 0.070631213 | T85: =J85/SUM(J74:J85) -> 0.073972069 | U85: =K85/SUM(K74:K85) -> 0.086732084
A86: DE | C86: =$A86&"_"&C87 -> DE_2022 | D86: =$A86&"_"&D87 -> DE_2023 | E86: =$A86&"_"&E87 -> DE_2024 | F86: =$A86&"_"&F87 -> DE_2025 | G86: =$A86&"_"&G87 -> DE_2026 | H86: =$A86&"_"&H87 -> DE_2027 | I86: =$A86&"_"&I87 -> DE_2028 | J86: =$A86&"_"&J87 -> DE_2029 | K86: =$A86&"_"&K87 -> DE_2030 | M86: =$A86&"_"&M87 -> DE_2022 | N86: =$A86&"_"&N87 -> DE_2023 | O86: =$A86&"_"&O87 -> DE_2024 | P86: =$A86&"_"&P87 -> DE_2025 | Q86: =$A86&"_"&Q87 -> DE_2026 | R86: =$A86&"_"&R87 -> DE_2027 | S86: =$A86&"_"&S87 -> DE_2028 | T86: =$A86&"_"&T87 -> DE_2029 | U86: =$A86&"_"&U87 -> DE_2030
C87: 2022 | D87: 2023 | E87: 2024 | F87: 2025 | G87: 2026 | H87: 2027 | I87: 2028 | J87: 2029 | K87: 2030 | M87: 2022 | N87: 2023 | O87: 2024 | P87: 2025 | Q87: 2026 | R87: 2027 | S87: 2028 | T87: 2029 | U87: 2030
A88: =A86 -> DE | B88: battery | C88: 0 | D88: 0 | E88: 0 | F88: 0 | G88: 0 | H88: 0 | I88: 0 | J88: 0 | K88: 0 | M88: 0 | N88: 0 | O88: 0 | P88: 0 | Q88: 0 | R88: 0 | S88: 0 | T88: 0 | U88: 0
A89: =A88 -> DE | B89: biomass | C89: =SUMIFS(INDEX('IRA-BIL_IRA-BIL - Mid_annual_st'!$W$3:$AR$434,MATCH(C86,'IRA-BIL_IRA-BIL - Mid_annual_st'!$A$3:$A$434,0),),'IRA-BIL_IRA-BIL - Mid_annual_st'!$W$1:$AR$1,$B89) -> 45827 | D89: =SUMIFS(INDEX('IRA-BIL_IRA-BIL - Mid_annual_st'!$W$3:$AR$434,MATCH(D86,'IRA-BIL_IRA-BIL - Mid_annual_st'!$A$3:$A$434,0),),'IRA-BIL_IRA-BIL - Mid_annual_st'!$W$1:$AR$1,$B89) -> 45827 | E89: =SUMIFS(INDEX('IRA-BIL_IRA-BIL - Mid_annual_st'!$W$3:$AR$434,MATCH(E86,'IRA-BIL_IRA-BIL - Mid_annual_st'!$A$3:$A$434,0),),'IRA-BIL_IRA-BIL - Mid_annual_st'!$W$1:$AR$1,$B89) -> 45827 | F89: =SUMIFS(INDEX('IRA-BIL_IRA-BIL - Mid_annual_st'!$W$3:$AR$434,MATCH(F86,'IRA-BIL_IRA-BIL - Mid_annual_st'!$A$3:$A$434,0),),'IRA-BIL_IRA-BIL - Mid_annual_st'!$W$1:$AR$1,$B89) -> 45827 | G89: =SUMIFS(INDEX('IRA-BIL_IRA-BIL - Mid_annual_st'!$W$3:$AR$434,MATCH(G86,'IRA-BIL_IRA-BIL - Mid_annual_st'!$A$3:$A$434,0),),'IRA-BIL_IRA-BIL - Mid_annual_st'!$W$1:$AR$1,$B89) -> 45827 | H89: =SUMIFS(INDEX('IRA-BIL_IRA-BIL - Mid_annual_st'!$W$3:$AR$434,MATCH(H86,'IRA-BIL_IRA-BIL - Mid_annual_st'!$A$3:$A$434,0),),'IRA-BIL_IRA-BIL - Mid_annual_st'!$W$1:$AR$1,$B89) -> 45827 | I89: =SUMIFS(INDEX('IRA-BIL_IRA-BIL - Mid_annual_st'!$W$3:$AR$434,MATCH(I86,'IRA-BIL_IRA-BIL - Mid_annual_st'!$A$3:$A$434,0),),'IRA-BIL_IRA-BIL - Mid_annual_st'!$W$1:$AR$1,$B89) -> 45827 | J89: =SUMIFS(INDEX('IRA-BIL_IRA-BIL - Mid_annual_st'!$W$3:$AR$434,MATCH(J86,'IRA-BIL_IRA-BIL - Mid_annual_st'!$A$3:$A$434,0),),'IRA-BIL_IRA-BIL - Mid_annual_st'!$W$1:$AR$1,$B89) -> 45827 | K89: =SUMIFS(INDEX('IRA-BIL_IRA-BIL - Mid_annual_st'!$W$3:$AR$434,MATCH(K86,'IRA-BIL_IRA-BIL - Mid_annual_st'!$A$3:$A$434,0),),'IRA-BIL_IRA-BIL - Mid_annual_st'!$W$1:$AR$1,$B89) -> 45827 | M89: =C89/SUM(C88:C99) -> 0.0084571664 | N89: =D89/SUM(D88:D99) -> 0.0088011537 | O89: =E89/SUM(E88:E99) -> 0.0090289616 | P89: =F89/SUM(F88:F99) -> 0.0094721029 | Q89: =G89/SUM(G88:G99) -> 0.010155908 | R89: =H89/SUM(H88:H99) -> 0.012491805 | S89: =I89/SUM(I88:I99) -> 0.015133168 | T89: =J89/SUM(J88:J99) -> 0.016405321 | U89: =K89/SUM(K88:K99) -> 0.017854423
A90: =A89 -> DE | B90: hard coal | C90: =SUMIFS(INDEX('IRA-BIL_IRA-BIL - Mid_annual_st'!$W$3:$AR$434,MATCH(C86,'IRA-BIL_IRA-BIL - Mid_annual_st'!$A$3:$A$434,0),),'IRA-BIL_IRA-BIL - Mid_annual_st'!$W$1:$AR$1,$B90) -> 0 | D90: =SUMIFS(INDEX('IRA-BIL_IRA-BIL - Mid_annual_st'!$W$3:$AR$434,MATCH(D86,'IRA-BIL_IRA-BIL - Mid_annual_st'!$A$3:$A$434,0),),'IRA-BIL_IRA-BIL - Mid_annual_st'!$W$1:$AR$1,$B90) -> 0 | E90: =SUMIFS(INDEX('IRA-BIL_IRA-BIL - Mid_annual_st'!$W$3:$AR$434,MATCH(E86,'IRA-BIL_IRA-BIL - Mid_annual_st'!$A$3:$A$434,0),),'IRA-BIL_IRA-BIL - Mid_annual_st'!$W$1:$AR$1,$B90) -> 0 | F90: =SUMIFS(INDEX('IRA-BIL_IRA-BIL - Mid_annual_st'!$W$3:$AR$434,MATCH(F86,'IRA-BIL_IRA-BIL - Mid_annual_st'!$A$3:$A$434,0),),'IRA-BIL_IRA-BIL - Mid_annual_st'!$W$1:$AR$1,$B90) -> 10252 | G90: =SUMIFS(INDEX('IRA-BIL_IRA-BIL - Mid_annual_st'!$W$3:$AR$434,MATCH(G86,'IRA-BIL_IRA-BIL - Mid_annual_st'!$A$3:$A$434,0),),'IRA-BIL_IRA-BIL - Mid_annual_st'!$W$1:$AR$1,$B90) -> 20504 | H90: =SUMIFS(INDEX('IRA-BIL_IRA-BIL - Mid_annual_st'!$W$3:$AR$434,MATCH(H86,'IRA-BIL_IRA-BIL - Mid_annual_st'!$A$3:$A$434,0),),'IRA-BIL_IRA-BIL - Mid_annual_st'!$W$1:$AR$1,$B90) -> 30755 | I90: =SUMIFS(INDEX('IRA-BIL_IRA-BIL - Mid_annual_st'!$W$3:$AR$434,MATCH(I86,'IRA-BIL_IRA-BIL - Mid_annual_st'!$A$3:$A$434,0),),'IRA-BIL_IRA-BIL - Mid_annual_st'!$W$1:$AR$1,$B90) -> 0 | J90: =SUMIFS(INDEX('IRA-BIL_IRA-BIL - Mid_annual_st'!$W$3:$AR$434,MATCH(J86,'IRA-BIL_IRA-BIL - Mid_annual_st'!$A$3:$A$434,0),),'IRA-BIL_IRA-BIL - Mid_annual_st'!$W$1:$AR$1,$B90) -> 0 | K90: =SUMIFS(INDEX('IRA-BIL_IRA-BIL - Mid_annual_st'!$W$3:$AR$434,MATCH(K86,'IRA-BIL_IRA-BIL - Mid_annual_st'!$A$3:$A$434,0),),'IRA-BIL_IRA-BIL - Mid_annual_st'!$W$1:$AR$1,$B90) -> 0 | M90: =C90/SUM(C88:C99) -> 0 | N90: =D90/SUM(D88:D99) -> 0 | O90: =E90/SUM(E88:E99) -> 0 | P90: =F90/SUM(F88:F99) -> 0.0021190128 | Q90: =G90/SUM(G88:G99) -> 0.0045439748 | R90: =H90/SUM(H88:H99) -> 0.008383387 | S90: =I90/SUM(I88:I99) -> 0 | T90: =J90/SUM(J88:J99) -> 0 | U90: =K90/SUM(K88:K99) -> 0
A91: =A90 -> DE | B91: geothermal | C91: =SUMIFS(INDEX('IRA-BIL_IRA-BIL - Mid_annual_st'!$W$3:$AR$434,MATCH(C86,'IRA-BIL_IRA-BIL - Mid_annual_st'!$A$3:$A$434,0),),'IRA-BIL_IRA-BIL - Mid_annual_st'!$W$1:$AR$1,$B91) -> 0 | D91: =SUMIFS(INDEX('IRA-BIL_IRA-BIL - Mid_annual_st'!$W$3:$AR$434,MATCH(D86,'IRA-BIL_IRA-BIL - Mid_annual_st'!$A$3:$A$434,0),),'IRA-BIL_IRA-BIL - Mid_annual_st'!$W$1:$AR$1,$B91) -> 0 | E91: =SUMIFS(INDEX('IRA-BIL_IRA-BIL - Mid_annual_st'!$W$3:$AR$434,MATCH(E86,'IRA-BIL_IRA-BIL - Mid_annual_st'!$A$3:$A$434,0),),'IRA-BIL_IRA-BIL - Mid_annual_st'!$W$1:$AR$1,$B91) -> 0 | F91: =SUMIFS(INDEX('IRA-BIL_IRA-BIL - Mid_annual_st'!$W$3:$AR$434,MATCH(F86,'IRA-BIL_IRA-BIL - Mid_annual_st'!$A$3:$A$434,0),),'IRA-BIL_IRA-BIL - Mid_annual_st'!$W$1:$AR$1,$B91) -> 0 | G91: =SUMIFS(INDEX('IRA-BIL_IRA-BIL - Mid_annual_st'!$W$3:$AR$434,MATCH(G86,'IRA-BIL_IRA-BIL - Mid_annual_st'!$A$3:$A$434,0),),'IRA-BIL_IRA-BIL - Mid_annual_st'!$W$1:$AR$1,$B91) -> 0 | H91: =SUMIFS(INDEX('IRA-BIL_IRA-BIL - Mid_annual_st'!$W$3:$AR$434,MATCH(H86,'IRA-BIL_IRA-BIL - Mid_annual_st'!$A$3:$A$434,0),),'IRA-BIL_IRA-BIL - Mid_annual_st'!$W$1:$AR$1,$B91) -> 0 | I91: =SUMIFS(INDEX('IRA-BIL_IRA-BIL - Mid_annual_st'!$W$3:$AR$434,MATCH(I86,'IRA-BIL_IRA-BIL - Mid_annual_st'!$A$3:$A$434,0),),'IRA-BIL_IRA-BIL - Mid_annual_st'!$W$1:$AR$1,$B91) -> 0 | J91: =SUMIFS(INDEX('IRA-BIL_IRA-BIL - Mid_annual_st'!$W$3:$AR$434,MATCH(J86,'IRA-BIL_IRA-BIL - Mid_annual_st'!$A$3:$A$434,0),),'IRA-BIL_IRA-BIL - Mid_annual_st'!$W$1:$AR$1,$B91) -> 0 | K91: =SUMIFS(INDEX('IRA-BIL_IRA-BIL - Mid_annual_st'!$W$3:$AR$434,MATCH(K86,'IRA-BIL_IRA-BIL - Mid_annual_st'!$A$3:$A$434,0),),'IRA-BIL_IRA-BIL - Mid_annual_st'!$W$1:$AR$1,$B91) -> 0 | M91: =C91/SUM(C88:C99) -> 0 | N91: =D91/SUM(D88:D99) -> 0 | O91: =E91/SUM(E88:E99) -> 0 | P91: =F91/SUM(F88:F99) -> 0 | Q91: =G91/SUM(G88:G99) -> 0 | R91: =H91/SUM(H88:H99) -> 0 | S91: =I91/SUM(I88:I99) -> 0 | T91: =J91/SUM(J88:J99) -> 0 | U91: =K91/SUM(K88:K99) -> 0
A92: =A91 -> DE | B92: hydro | C92: =SUMIFS(INDEX('IRA-BIL_IRA-BIL - Mid_annual_st'!$W$3:$AR$434,MATCH(C86,'IRA-BIL_IRA-BIL - Mid_annual_st'!$A$3:$A$434,0),),'IRA-BIL_IRA-BIL - Mid_annual_st'!$W$1:$AR$1,$B92) -> 0 | D92: =SUMIFS(INDEX('IRA-BIL_IRA-BIL - Mid_annual_st'!$W$3:$AR$434,MATCH(D86,'IRA-BIL_IRA-BIL - Mid_annual_st'!$A$3:$A$434,0),),'IRA-BIL_IRA-BIL - Mid_annual_st'!$W$1:$AR$1,$B92) -> 0 | E92: =SUMIFS(INDEX('IRA-BIL_IRA-BIL - Mid_annual_st'!$W$3:$AR$434,MATCH(E86,'IRA-BIL_IRA-BIL - Mid_annual_st'!$A$3:$A$434,0),),'IRA-BIL_IRA-BIL - Mid_annual_st'!$W$1:$AR$1,$B92) -> 0 | F92: =SUMIFS(INDEX('IRA-BIL_IRA-BIL - Mid_annual_st'!$W$3:$AR$434,MATCH(F86,'IRA-BIL_IRA-BIL - Mid_annual_st'!$A$3:$A$434,0),),'IRA-BIL_IRA-BIL - Mid_annual_st'!$W$1:$AR$1,$B92) -> 0 | G92: =SUMIFS(INDEX('IRA-BIL_IRA-BIL - Mid_annual_st'!$W$3:$AR$434,MATCH(G86,'IRA-BIL_IRA-BIL - Mid_annual_st'!$A$3:$A$434,0),),'IRA-BIL_IRA-BIL - Mid_annual_st'!$W$1:$AR$1,$B92) -> 0 | H92: =SUMIFS(INDEX('IRA-BIL_IRA-BIL - Mid_annual_st'!$W$3:$AR$434,MATCH(H86,'IRA-BIL_IRA-BIL - Mid_annual_st'!$A$3:$A$434,0),),'IRA-BIL_IRA-BIL - Mid_annual_st'!$W$1:$AR$1,$B92) -> 0 | I92: =SUMIFS(INDEX('IRA-BIL_IRA-BIL - Mid_annual_st'!$W$3:$AR$434,MATCH(I86,'IRA-BIL_IRA-BIL - Mid_annual_st'!$A$3:$A$434,0),),'IRA-BIL_IRA-BIL - Mid_annual_st'!$W$1:$AR$1,$B92) -> 0 | J92: =SUMIFS(INDEX('IRA-BIL_IRA-BIL - Mid_annual_st'!$W$3:$AR$434,MATCH(J86,'IRA-BIL_IRA-BIL - Mid_annual_st'!$A$3:$A$434,0),),'IRA-BIL_IRA-BIL - Mid_annual_st'!$W$1:$AR$1,$B92) -> 0 | K92: =SUMIFS(INDEX('IRA-BIL_IRA-BIL - Mid_annual_st'!$W$3:$AR$434,MATCH(K86,'IRA-BIL_IRA-BIL - Mid_annual_st'!$A$3:$A$434,0),),'IRA-BIL_IRA-BIL - Mid_annual_st'!$W$1:$AR$1,$B92) -> 0 | M92: =C92/SUM(C88:C99) -> 0 | N92: =D92/SUM(D88:D99) -> 0 | O92: =E92/SUM(E88:E99) -> 0 | P92: =F92/SUM(F88:F99) -> 0 | Q92: =G92/SUM(G88:G99) -> 0 | R92: =H92/SUM(H88:H99) -> 0 | S92: =I92/SUM(I88:I99) -> 0 | T92: =J92/SUM(J88:J99) -> 0 | U92: =K92/SUM(K88:K99) -> 0
A93: =A92 -> DE | B93: natural gas steam turbine | C93: =SUMIFS(INDEX('IRA-BIL_IRA-BIL - Mid_annual_st'!$W$3:$AR$434,MATCH(C86,'IRA-BIL_IRA-BIL - Mid_annual_st'!$A$3:$A$434,0),),'IRA-BIL_IRA-BIL - Mid_annual_st'!$W$1:$AR$1,$B93) -> 4018241 | D93: =SUMIFS(INDEX('IRA-BIL_IRA-BIL - Mid_annual_st'!$W$3:$AR$434,MATCH(D86,'IRA-BIL_IRA-BIL - Mid_annual_st'!$A$3:$A$434,0),),'IRA-BIL_IRA-BIL - Mid_annual_st'!$W$1:$AR$1,$B93) -> 3684535 | E93: =SUMIFS(INDEX('IRA-BIL_IRA-BIL - Mid_annual_st'!$W$3:$AR$434,MATCH(E86,'IRA-BIL_IRA-BIL - Mid_annual_st'!$A$3:$A$434,0),),'IRA-BIL_IRA-BIL - Mid_annual_st'!$W$1:$AR$1,$B93) -> 3646706 | F93: =SUMIFS(INDEX('IRA-BIL_IRA-BIL - Mid_annual_st'!$W$3:$AR$434,MATCH(F86,'IRA-BIL_IRA-BIL - Mid_annual_st'!$A$3:$A$434,0),),'IRA-BIL_IRA-BIL - Mid_annual_st'!$W$1:$AR$1,$B93) -> 3469361 | G93: =SUMIFS(INDEX('IRA-BIL_IRA-BIL - Mid_annual_st'!$W$3:$AR$434,MATCH(G86,'IRA-BIL_IRA-BIL - Mid_annual_st'!$A$3:$A$434,0),),'IRA-BIL_IRA-BIL - Mid_annual_st'!$W$1:$AR$1,$B93) -> 3382586 | H93: =SUMIFS(INDEX('IRA-BIL_IRA-BIL - Mid_annual_st'!$W$3:$AR$434,MATCH(H86,'IRA-BIL_IRA-BIL - Mid_annual_st'!$A$3:$A$434,0),),'IRA-BIL_IRA-BIL - Mid_annual_st'!$W$1:$AR$1,$B93) -> 2524140 | I93: =SUMIFS(INDEX('IRA-BIL_IRA-BIL - Mid_annual_st'!$W$3:$AR$434,MATCH(I86,'IRA-BIL_IRA-BIL - Mid_annual_st'!$A$3:$A$434,0),),'IRA-BIL_IRA-BIL - Mid_annual_st'!$W$1:$AR$1,$B93) -> 1920298 | J93: =SUMIFS(INDEX('IRA-BIL_IRA-BIL - Mid_annual_st'!$W$3:$AR$434,MATCH(J86,'IRA-BIL_IRA-BIL - Mid_annual_st'!$A$3:$A$434,0),),'IRA-BIL_IRA-BIL - Mid_annual_st'!$W$1:$AR$1,$B93) -> 1692877 | K93: =SUMIFS(INDEX('IRA-BIL_IRA-BIL - Mid_annual_st'!$W$3:$AR$434,MATCH(K86,'IRA-BIL_IRA-BIL - Mid_annual_st'!$A$3:$A$434,0),),'IRA-BIL_IRA-BIL - Mid_annual_st'!$W$1:$AR$1,$B93) -> 1413546 | M93: =C93/SUM(C88:C99) -> 0.74154828 | N93: =D93/SUM(D88:D99) -> 0.70762125 | O93: =E93/SUM(E88:E99) -> 0.71848404 | P93: =F93/SUM(F88:F99) -> 0.71709133 | Q93: =G93/SUM(G88:G99) -> 0.74962863 | R93: =H93/SUM(H88:H99) -> 0.6880456 | S93: =I93/SUM(I88:I99) -> 0.63412817 | T93: =J93/SUM(J88:J99) -> 0.60602243 | U93: =K93/SUM(K88:K99) -> 0.55072441
A94: =A93 -> DE | B94: nuclear | C94: =SUMIFS(INDEX('IRA-BIL_IRA-BIL - Mid_annual_st'!$W$3:$AR$434,MATCH(C86,'IRA-BIL_IRA-BIL - Mid_annual_st'!$A$3:$A$434,0),),'IRA-BIL_IRA-BIL - Mid_annual_st'!$W$1:$AR$1,$B94) -> 0 | D94: =SUMIFS(INDEX('IRA-BIL_IRA-BIL - Mid_annual_st'!$W$3:$AR$434,MATCH(D86,'IRA-BIL_IRA-BIL - Mid_annual_st'!$A$3:$A$434,0),),'IRA-BIL_IRA-BIL - Mid_annual_st'!$W$1:$AR$1,$B94) -> 0 | E94: =SUMIFS(INDEX('IRA-BIL_IRA-BIL - Mid_annual_st'!$W$3:$AR$434,MATCH(E86,'IRA-BIL_IRA-BIL - Mid_annual_st'!$A$3:$A$434,0),),'IRA-BIL_IRA-BIL - Mid_annual_st'!$W$1:$AR$1,$B94) -> 0 | F94: =SUMIFS(INDEX('IRA-BIL_IRA-BIL - Mid_annual_st'!$W$3:$AR$434,MATCH(F86,'IRA-BIL_IRA-BIL - Mid_annual_st'!$A$3:$A$434,0),),'IRA-BIL_IRA-BIL - Mid_annual_st'!$W$1:$AR$1,$B94) -> 0 | G94: =SUMIFS(INDEX('IRA-BIL_IRA-BIL - Mid_annual_st'!$W$3:$AR$434,MATCH(G86,'IRA-BIL_IRA-BIL - Mid_annual_st'!$A$3:$A$434,0),),'IRA-BIL_IRA-BIL - Mid_annual_st'!$W$1:$AR$1,$B94) -> 0 | H94: =SUMIFS(INDEX('IRA-BIL_IRA-BIL - Mid_annual_st'!$W$3:$AR$434,MATCH(H86,'IRA-BIL_IRA-BIL - Mid_annual_st'!$A$3:$A$434,0),),'IRA-BIL_IRA-BIL - Mid_annual_st'!$W$1:$AR$1,$B94) -> 0 | I94: =SUMIFS(INDEX('IRA-BIL_IRA-BIL - Mid_annual_st'!$W$3:$AR$434,MATCH(I86,'IRA-BIL_IRA-BIL - Mid_annual_st'!$A$3:$A$434,0),),'IRA-BIL_IRA-BIL - Mid_annual_st'!$W$1:$AR$1,$B94) -> 0 | J94: =SUMIFS(INDEX('IRA-BIL_IRA-BIL - Mid_annual_st'!$W$3:$AR$434,MATCH(J86,'IRA-BIL_IRA-BIL - Mid_annual_st'!$A$3:$A$434,0),),'IRA-BIL_IRA-BIL - Mid_annual_st'!$W$1:$AR$1,$B94) -> 0 | K94: =SUMIFS(INDEX('IRA-BIL_IRA-BIL - Mid_annual_st'!$W$3:$AR$434,MATCH(K86,'IRA-BIL_IRA-BIL - Mid_annual_st'!$A$3:$A$434,0),),'IRA-BIL_IRA-BIL - Mid_annual_st'!$W$1:$AR$1,$B94) -> 0 | M94: =C94/SUM(C88:C99) -> 0 | N94: =D94/SUM(D88:D99) -> 0 | O94: =E94/SUM(E88:E99) -> 0 | P94: =F94/SUM(F88:F99) -> 0 | Q94: =G94/SUM(G88:G99) -> 0 | R94: =H94/SUM(H88:H99) -> 0 | S94: =I94/SUM(I88:I99) -> 0 | T94: =J94/SUM(J88:J99) -> 0 | U94: =K94/SUM(K88:K99) -> 0
A95: =A94 -> DE | B95: offshore wind | C95: =SUMIFS(INDEX('IRA-BIL_IRA-BIL - Mid_annual_st'!$W$3:$AR$434,MATCH(C86,'IRA-BIL_IRA-BIL - Mid_annual_st'!$A$3:$A$434,0),),'IRA-BIL_IRA-BIL - Mid_annual_st'!$W$1:$AR$1,$B95) -> 0 | D95: =SUMIFS(INDEX('IRA-BIL_IRA-BIL - Mid_annual_st'!$W$3:$AR$434,MATCH(D86,'IRA-BIL_IRA-BIL - Mid_annual_st'!$A$3:$A$434,0),),'IRA-BIL_IRA-BIL - Mid_annual_st'!$W$1:$AR$1,$B95) -> 0 | E95: =SUMIFS(INDEX('IRA-BIL_IRA-BIL - Mid_annual_st'!$W$3:$AR$434,MATCH(E86,'IRA-BIL_IRA-BIL - Mid_annual_st'!$A$3:$A$434,0),),'IRA-BIL_IRA-BIL - Mid_annual_st'!$W$1:$AR$1,$B95) -> 0 | F95: =SUMIFS(INDEX('IRA-BIL_IRA-BIL - Mid_annual_st'!$W$3:$AR$434,MATCH(F86,'IRA-BIL_IRA-BIL - Mid_annual_st'!$A$3:$A$434,0),),'IRA-BIL_IRA-BIL - Mid_annual_st'!$W$1:$AR$1,$B95) -> 0 | G95: =SUMIFS(INDEX('IRA-BIL_IRA-BIL - Mid_annual_st'!$W$3:$AR$434,MATCH(G86,'IRA-BIL_IRA-BIL - Mid_annual_st'!$A$3:$A$434,0),),'IRA-BIL_IRA-BIL - Mid_annual_st'!$W$1:$AR$1,$B95) -> 0 | H95: =SUMIFS(INDEX('IRA-BIL_IRA-BIL - Mid_annual_st'!$W$3:$AR$434,MATCH(H86,'IRA-BIL_IRA-BIL - Mid_annual_st'!$A$3:$A$434,0),),'IRA-BIL_IRA-BIL - Mid_annual_st'!$W$1:$AR$1,$B95) -> 0 | I95: =SUMIFS(INDEX('IRA-BIL_IRA-BIL - Mid_annual_st'!$W$3:$AR$434,MATCH(I86,'IRA-BIL_IRA-BIL - Mid_annual_st'!$A$3:$A$434,0),),'IRA-BIL_IRA-BIL - Mid_annual_st'!$W$1:$AR$1,$B95) -> 0 | J95: =SUMIFS(INDEX('IRA-BIL_IRA-BIL - Mid_annual_st'!$W$3:$AR$434,MATCH(J86,'IRA-BIL_IRA-BIL - Mid_annual_st'!$A$3:$A$434,0),),'IRA-BIL_IRA-BIL - Mid_annual_st'!$W$1:$AR$1,$B95) -> 0 | K95: =SUMIFS(INDEX('IRA-BIL_IRA-BIL - Mid_annual_st'!$W$3:$AR$434,MATCH(K86,'IRA-BIL_IRA-BIL - Mid_annual_st'!$A$3:$A$434,0),),'IRA-BIL_IRA-BIL - Mid_annual_st'!$W$1:$AR$1,$B95) -> 0 | M95: =C95/SUM(C88:C99) -> 0 | N95: =D95/SUM(D88:D99) -> 0 | O95: =E95/SUM(E88:E99) -> 0 | P95: =F95/SUM(F88:F99) -> 0 | Q95: =G95/SUM(G88:G99) -> 0 | R95: =H95/SUM(H88:H99) -> 0 | S95: =I95/SUM(I88:I99) -> 0 | T95: =J95/SUM(J88:J99) -> 0 | U95: =K95/SUM(K88:K99) -> 0
A96: =A95 -> DE | B96: petroleum | C96: =SUMIFS(INDEX('IRA-BIL_IRA-BIL - Mid_annual_st'!$W$3:$AR$434,MATCH(C86,'IRA-BIL_IRA-BIL - Mid_annual_st'!$A$3:$A$434,0),),'IRA-BIL_IRA-BIL - Mid_annual_st'!$W$1:$AR$1,$B96) -> 788997 | D96: =SUMIFS(INDEX('IRA-BIL_IRA-BIL - Mid_annual_st'!$W$3:$AR$434,MATCH(D86,'IRA-BIL_IRA-BIL - Mid_annual_st'!$A$3:$A$434,0),),'IRA-BIL_IRA-BIL - Mid_annual_st'!$W$1:$AR$1,$B96) -> 403075 | E96: =SUMIFS(INDEX('IRA-BIL_IRA-BIL - Mid_annual_st'!$W$3:$AR$434,MATCH(E86,'IRA-BIL_IRA-BIL - Mid_annual_st'!$A$3:$A$434,0),),'IRA-BIL_IRA-BIL - Mid_annual_st'!$W$1:$AR$1,$B96) -> 318546 | F96: =SUMIFS(INDEX('IRA-BIL_IRA-BIL - Mid_annual_st'!$W$3:$AR$434,MATCH(F86,'IRA-BIL_IRA-BIL - Mid_annual_st'!$A$3:$A$434,0),),'IRA-BIL_IRA-BIL - Mid_annual_st'!$W$1:$AR$1,$B96) -> 228796 | G96: =SUMIFS(INDEX('IRA-BIL_IRA-BIL - Mid_annual_st'!$W$3:$AR$434,MATCH(G86,'IRA-BIL_IRA-BIL - Mid_annual_st'!$A$3:$A$434,0),),'IRA-BIL_IRA-BIL - Mid_annual_st'!$W$1:$AR$1,$B96) -> 0 | H96: =SUMIFS(INDEX('IRA-BIL_IRA-BIL - Mid_annual_st'!$W$3:$AR$434,MATCH(H86,'IRA-BIL_IRA-BIL - Mid_annual_st'!$A$3:$A$434,0),),'IRA-BIL_IRA-BIL - Mid_annual_st'!$W$1:$AR$1,$B96) -> 0 | I96: =SUMIFS(INDEX('IRA-BIL_IRA-BIL - Mid_annual_st'!$W$3:$AR$434,MATCH(I86,'IRA-BIL_IRA-BIL - Mid_annual_st'!$A$3:$A$434,0),),'IRA-BIL_IRA-BIL - Mid_annual_st'!$W$1:$AR$1,$B96) -> 0 | J96: =SUMIFS(INDEX('IRA-BIL_IRA-BIL - Mid_annual_st'!$W$3:$AR$434,MATCH(J86,'IRA-BIL_IRA-BIL - Mid_annual_st'!$A$3:$A$434,0),),'IRA-BIL_IRA-BIL - Mid_annual_st'!$W$1:$AR$1,$B96) -> 0 | K96: =SUMIFS(INDEX('IRA-BIL_IRA-BIL - Mid_annual_st'!$W$3:$AR$434,MATCH(K86,'IRA-BIL_IRA-BIL - Mid_annual_st'!$A$3:$A$434,0),),'IRA-BIL_IRA-BIL - Mid_annual_st'!$W$1:$AR$1,$B96) -> 0 | M96: =C96/SUM(C88:C99) -> 0.14560584 | N96: =D96/SUM(D88:D99) -> 0.077411243 | O96: =E96/SUM(E88:E99) -> 0.062760809 | P96: =F96/SUM(F88:F99) -> 0.047290446 | Q96: =G96/SUM(G88:G99) -> 0 | R96: =H96/SUM(H88:H99) -> 0 | S96: =I96/SUM(I88:I99) -> 0 | T96: =J96/SUM(J88:J99) -> 0 | U96: =K96/SUM(K88:K99) -> 0
A97: =A96 -> DE | B97: onshore wind | C97: =SUMIFS(INDEX('IRA-BIL_IRA-BIL - Mid_annual_st'!$W$3:$AR$434,MATCH(C86,'IRA-BIL_IRA-BIL - Mid_annual_st'!$A$3:$A$434,0),),'IRA-BIL_IRA-BIL - Mid_annual_st'!$W$1:$AR$1,$B97) -> 0 | D97: =SUMIFS(INDEX('IRA-BIL_IRA-BIL - Mid_annual_st'!$W$3:$AR$434,MATCH(D86,'IRA-BIL_IRA-BIL - Mid_annual_st'!$A$3:$A$434,0),),'IRA-BIL_IRA-BIL - Mid_annual_st'!$W$1:$AR$1,$B97) -> 0 | E97: =SUMIFS(INDEX('IRA-BIL_IRA-BIL - Mid_annual_st'!$W$3:$AR$434,MATCH(E86,'IRA-BIL_IRA-BIL - Mid_annual_st'!$A$3:$A$434,0),),'IRA-BIL_IRA-BIL - Mid_annual_st'!$W$1:$AR$1,$B97) -> 0 | F97: =SUMIFS(INDEX('IRA-BIL_IRA-BIL - Mid_annual_st'!$W$3:$AR$434,MATCH(F86,'IRA-BIL_IRA-BIL - Mid_annual_st'!$A$3:$A$434,0),),'IRA-BIL_IRA-BIL - Mid_annual_st'!$W$1:$AR$1,$B97) -> 0 | G97: =SUMIFS(INDEX('IRA-BIL_IRA-BIL - Mid_annual_st'!$W$3:$AR$434,MATCH(G86,'IRA-BIL_IRA-BIL - Mid_annual_st'!$A$3:$A$434,0),),'IRA-BIL_IRA-BIL - Mid_annual_st'!$W$1:$AR$1,$B97) -> 0 | H97: =SUMIFS(INDEX('IRA-BIL_IRA-BIL - Mid_annual_st'!$W$3:$AR$434,MATCH(H86,'IRA-BIL_IRA-BIL - Mid_annual_st'!$A$3:$A$434,0),),'IRA-BIL_IRA-BIL - Mid_annual_st'!$W$1:$AR$1,$B97) -> 0 | I97: =SUMIFS(INDEX('IRA-BIL_IRA-BIL - Mid_annual_st'!$W$3:$AR$434,MATCH(I86,'IRA-BIL_IRA-BIL - Mid_annual_st'!$A$3:$A$434,0),),'IRA-BIL_IRA-BIL - Mid_annual_st'!$W$1:$AR$1,$B97) -> 0 | J97: =SUMIFS(INDEX('IRA-BIL_IRA-BIL - Mid_annual_st'!$W$3:$AR$434,MATCH(J86,'IRA-BIL_IRA-BIL - Mid_annual_st'!$A$3:$A$434,0),),'IRA-BIL_IRA-BIL - Mid_annual_st'!$W$1:$AR$1,$B97) -> 0 | K97: =SUMIFS(INDEX('IRA-BIL_IRA-BIL - Mid_annual_st'!$W$3:$AR$434,MATCH(K86,'IRA-BIL_IRA-BIL - Mid_annual_st'!$A$3:$A$434,0),),'IRA-BIL_IRA-BIL - Mid_annual_st'!$W$1:$AR$1,$B97) -> 0 | M97: =C97/SUM(C88:C99) -> 0 | N97: =D97/SUM(D88:D99) -> 0 | O97: =E97/SUM(E88:E99) -> 0 | P97: =F97/SUM(F88:F99) -> 0 | Q97: =G97/SUM(G88:G99) -> 0 | R97: =H97/SUM(H88:H99) -> 0 | S97: =I97/SUM(I88:I99) -> 0 | T97: =J97/SUM(J88:J99) -> 0 | U97: =K97/SUM(K88:K99) -> 0
A98: =A97 -> DE | B98: pumped hydro | C98: 0 | D98: 0 | E98: 0 | F98: 0 | G98: 0 | H98: 0 | I98: 0 | J98: 0 | K98: 0 | M98: 0 | N98: 0 | O98: 0 | P98: 0 | Q98: 0 | R98: 0 | S98: 0 | T98: 0 | U98: 0
A99: =A98 -> DE | B99: solar pv | C99: =SUMIFS(INDEX('IRA-BIL_IRA-BIL - Mid_annual_st'!$W$3:$AR$434,MATCH(C86,'IRA-BIL_IRA-BIL - Mid_annual_st'!$A$3:$A$434,0),),'IRA-BIL_IRA-BIL - Mid_annual_st'!$W$1:$AR$1,$B99) -> 565653 | D99: =SUMIFS(INDEX('IRA-BIL_IRA-BIL - Mid_annual_st'!$W$3:$AR$434,MATCH(D86,'IRA-BIL_IRA-BIL - Mid_annual_st'!$A$3:$A$434,0),),'IRA-BIL_IRA-BIL - Mid_annual_st'!$W$1:$AR$1,$B99) -> 1073494 | E99: =SUMIFS(INDEX('IRA-BIL_IRA-BIL - Mid_annual_st'!$W$3:$AR$434,MATCH(E86,'IRA-BIL_IRA-BIL - Mid_annual_st'!$A$3:$A$434,0),),'IRA-BIL_IRA-BIL - Mid_annual_st'!$W$1:$AR$1,$B99) -> 1064477 | F99: =SUMIFS(INDEX('IRA-BIL_IRA-BIL - Mid_annual_st'!$W$3:$AR$434,MATCH(F86,'IRA-BIL_IRA-BIL - Mid_annual_st'!$A$3:$A$434,0),),'IRA-BIL_IRA-BIL - Mid_annual_st'!$W$1:$AR$1,$B99) -> 1083866 | G99: =SUMIFS(INDEX('IRA-BIL_IRA-BIL - Mid_annual_st'!$W$3:$AR$434,MATCH(G86,'IRA-BIL_IRA-BIL - Mid_annual_st'!$A$3:$A$434,0),),'IRA-BIL_IRA-BIL - Mid_annual_st'!$W$1:$AR$1,$B99) -> 1063432 | H99: =SUMIFS(INDEX('IRA-BIL_IRA-BIL - Mid_annual_st'!$W$3:$AR$434,MATCH(H86,'IRA-BIL_IRA-BIL - Mid_annual_st'!$A$3:$A$434,0),),'IRA-BIL_IRA-BIL - Mid_annual_st'!$W$1:$AR$1,$B99) -> 1067843 | I99: =SUMIFS(INDEX('IRA-BIL_IRA-BIL - Mid_annual_st'!$W$3:$AR$434,MATCH(I86,'IRA-BIL_IRA-BIL - Mid_annual_st'!$A$3:$A$434,0),),'IRA-BIL_IRA-BIL - Mid_annual_st'!$W$1:$AR$1,$B99) -> 1062124 | J99: =SUMIFS(INDEX('IRA-BIL_IRA-BIL - Mid_annual_st'!$W$3:$AR$434,MATCH(J86,'IRA-BIL_IRA-BIL - Mid_annual_st'!$A$3:$A$434,0),),'IRA-BIL_IRA-BIL - Mid_annual_st'!$W$1:$AR$1,$B99) -> 1054719 | K99: =SUMIFS(INDEX('IRA-BIL_IRA-BIL - Mid_annual_st'!$W$3:$AR$434,MATCH(K86,'IRA-BIL_IRA-BIL - Mid_annual_st'!$A$3:$A$434,0),),'IRA-BIL_IRA-BIL - Mid_annual_st'!$W$1:$AR$1,$B99) -> 1107330 | M99: =C99/SUM(C88:C99) -> 0.10438871 | N99: =D99/SUM(D88:D99) -> 0.20616636 | O99: =E99/SUM(E88:E99) -> 0.20972619 | P99: =F99/SUM(F88:F99) -> 0.22402711 | Q99: =G99/SUM(G88:G99) -> 0.23567149 | R99: =H99/SUM(H88:H99) -> 0.29107921 | S99: =I99/SUM(I88:I99) -> 0.35073866 | T99: =J99/SUM(J88:J99) -> 0.37757225 | U99: =K99/SUM(K88:K99) -> 0.43142117
A100: FL | C100: =$A100&"_"&C101 -> FL_2022 | D100: =$A100&"_"&D101 -> FL_2023 | E100: =$A100&"_"&E101 -> FL_2024 | F100: =$A100&"_"&F101 -> FL_2025 | G100: =$A100&"_"&G101 -> FL_2026 | H100: =$A100&"_"&H101 -> FL_2027 | I100: =$A100&"_"&I101 -> FL_2028 | J100: =$A100&"_"&J101 -> FL_2029 | K100: =$A100&"_"&K101 -> FL_2030 | M100: =$A100&"_"&M101 -> FL_2022 | N100: =$A100&"_"&N101 -> FL_2023 | O100: =$A100&"_"&O101 -> FL_2024 | P100: =$A100&"_"&P101 -> FL_2025 | Q100: =$A100&"_"&Q101 -> FL_2026 | R100: =$A100&"_"&R101 -> FL_2027 | S100: =$A100&"_"&S101 -> FL_2028 | T100: =$A100&"_"&T101 -> FL_2029 | U100: =$A100&"_"&U101 -> FL_2030
...

Sheet Cross border connections
A1: r | B1: rr | C1: AC | D1: DC | E1: DC Converted to AC | F1: Notes | G1: rnum | H1: rrnum | I1: State1 | J1: State2 | K1: In-state vs out-of-state | N1: State | O1: =About!B2 -> ND
A2: p1 | B2: p2 | C2: 9000 | D2: 0 | E2: 9000 | G2: 1 | H2: 2 | I2: WA | J2: WA | K2: Same | L2: =IF(AND(K2="Different",OR(I2 = $O$1,J2=$O$1)),E2,"") | M2: =IF(L2<>"",IF(I2=$O$1,J2,I2),"")
A3: p1 | B3: p4 | C3: 9804 | D3: 0 | E3: 9804 | G3: 1 | H3: 4 | I3: WA | J3: WA | K3: Same | L3: =IF(AND(K3="Different",OR(I3 = $O$1,J3=$O$1)),E3,"") | M3: =IF(L3<>"",IF(I3=$O$1,J3,I3),"") | Q3: Total capacity between state and surrounding states | R3: Fraction of total
A4: p2 | B4: p3 | C4: 1942 | D4: 0 | E4: 1942 | G4: 2 | H4: 3 | I4: WA | J4: WA | K4: Same | L4: =IF(AND(K4="Different",OR(I4 = $O$1,J4=$O$1)),E4,"") | M4: =IF(L4<>"",IF(I4=$O$1,J4,I4),"") | P4: AL | Q4: =SUMIFS($L$2:$L$312,$M$2:$M$312,P4) -> 0 | R4: =Q4/$Q$54 -> 0
A5: p2 | B5: p4 | C5: 4252 | D5: 0 | E5: 4252 | G5: 2 | H5: 4 | I5: WA | J5: WA | K5: Same | L5: =IF(AND(K5="Different",OR(I5 = $O$1,J5=$O$1)),E5,"") | M5: =IF(L5<>"",IF(I5=$O$1,J5,I5),"") | P5: AK | Q5: =SUMIFS($L$2:$L$312,$M$2:$M$312,P5) -> 0 | R5: =Q5/$Q$54 -> 0
A6: p2 | B6: p5 | C6: 15397 | D6: 0 | E6: 15397 | G6: 2 | H6: 5 | I6: WA | J6: OR | K6: Different | L6: =IF(AND(K6="Different",OR(I6 = $O$1,J6=$O$1)),E6,"") | M6: =IF(L6<>"",IF(I6=$O$1,J6,I6),"") | P6: AZ | Q6: =SUMIFS($L$2:$L$312,$M$2:$M$312,P6) -> 0 | R6: =Q6/$Q$54 -> 0
A7: p2 | B7: p14 | C7: 5207 | D7: 0 | E7: 5207 | G7: 2 | H7: 14 | I7: WA | J7: ID | K7: Different | L7: =IF(AND(K7="Different",OR(I7 = $O$1,J7=$O$1)),E7,"") | M7: =IF(L7<>"",IF(I7=$O$1,J7,I7),"") | P7: AR | Q7: =SUMIFS($L$2:$L$312,$M$2:$M$312,P7) -> 0 | R7: =Q7/$Q$54 -> 0
A8: p3 | B8: p4 | C8: 9721 | D8: 0 | E8: 9721 | G8: 3 | H8: 4 | I8: WA | J8: WA | K8: Same | L8: =IF(AND(K8="Different",OR(I8 = $O$1,J8=$O$1)),E8,"") | M8: =IF(L8<>"",IF(I8=$O$1,J8,I8),"") | P8: CA | Q8: =SUMIFS($L$2:$L$312,$M$2:$M$312,P8) -> 0 | R8: =Q8/$Q$54 -> 0
A9: p3 | B9: p5 | C9: 762 | D9: 0 | E9: 762 | G9: 3 | H9: 5 | I9: WA | J9: OR | K9: Different | L9: =IF(AND(K9="Different",OR(I9 = $O$1,J9=$O$1)),E9,"") | M9: =IF(L9<>"",IF(I9=$O$1,J9,I9),"") | P9: CO | Q9: =SUMIFS($L$2:$L$312,$M$2:$M$312,P9) -> 0 | R9: =Q9/$Q$54 -> 0
A10: p3 | B10: p14 | C10: 8360 | D10: 0 | E10: 8360 | G10: 3 | H10: 14 | I10: WA | J10: ID | K10: Different | L10: =IF(AND(K10="Different",OR(I10 = $O$1,J10=$O$1)),E10,"") | M10: =IF(L10<>"",IF(I10=$O$1,J10,I10),"") | P10: CT | Q10: =SUMIFS($L$2:$L$312,$M$2:$M$312,P10) -> 0 | R10: =Q10/$Q$54 -> 0
A11: p3 | B11: p17 | C11: 2843 | D11: 0 | E11: 2843 | G11: 3 | H11: 17 | I11: WA | J11: MT | K11: Different | L11: =IF(AND(K11="Different",OR(I11 = $O$1,J11=$O$1)),E11,"") | M11: =IF(L11<>"",IF(I11=$O$1,J11,I11),"") | P11: DE | Q11: =SUMIFS($L$2:$L$312,$M$2:$M$312,P11) -> 0 | R11: =Q11/$Q$54 -> 0
A12: p5 | B12: p6 | C12: 3809 | D12: 0 | E12: 3809 | G12: 5 | H12: 6 | I12: OR | J12: OR | K12: Same | L12: =IF(AND(K12="Different",OR(I12 = $O$1,J12=$O$1)),E12,"") | M12: =IF(L12<>"",IF(I12=$O$1,J12,I12),"") | P12: FL | Q12: =SUMIFS($L$2:$L$312,$M$2:$M$312,P12) -> 0 | R12: =Q12/$Q$54 -> 0
A13: p5 | B13: p7 | C13: 1778 | D13: 0 | E13: 1778 | G13: 5 | H13: 7 | I13: OR | J13: OR | K13: Same | L13: =IF(AND(K13="Different",OR(I13 = $O$1,J13=$O$1)),E13,"") | M13: =IF(L13<>"",IF(I13=$O$1,J13,I13),"") | P13: GA | Q13: =SUMIFS($L$2:$L$312,$M$2:$M$312,P13) -> 0 | R13: =Q13/$Q$54 -> 0
A14: p5 | B14: p10 | C14: 0 | D14: 2780 | E14: 4370.994 | G14: 5 | H14: 10 | I14: OR | J14: CA | K14: Different | L14: =IF(AND(K14="Different",OR(I14 = $O$1,J14=$O$1)),E14,"") | M14: =IF(L14<>"",IF(I14=$O$1,J14,I14),"") | P14: HI | Q14: =SUMIFS($L$2:$L$312,$M$2:$M$312,P14) -> 0 | R14: =Q14/$Q$54 -> 0
A15: p5 | B15: p14 | C15: 352 | D15: 0 | E15: 352 | G15: 5 | H15: 14 | I15: OR | J15: ID | K15: Different | L15: =IF(AND(K15="Different",OR(I15 = $O$1,J15=$O$1)),E15,"") | M15: =IF(L15<>"",IF(I15=$O$1,J15,I15),"") | P15: ID | Q15: =SUMIFS($L$2:$L$312,$M$2:$M$312,P15) -> 0 | R15: =Q15/$Q$54 -> 0
... A53: p18 | B53: p19 | C53: 262 | D53: 0 | E53: 262 | G53: 18 | H53: 19 | I53: MT | J53: MT | K53: Same | L53: =IF(AND(K53="Different",OR(I53 = $O$1,J53=$O$1)),E53,"") | M53: =IF(L53<>"",IF(I53=$O$1,J53,I53),"") | P53: WY | Q53: =SUMIFS($L$2:$L$312,$M$2:$M$312,P53) -> 0 | R53: =Q53/$Q$54 -> 0
A54: p18 | B54: p20 | C54: 2321 | D54: 0 | E54: 2321 | G54: 18 | H54: 20 | I54: MT | J54: MT | K54: Same | L54: =IF(AND(K54="Different",OR(I54 = $O$1,J54=$O$1)),E54,"") | M54: =IF(L54<>"",IF(I54=$O$1,J54,I54),"") | Q54: =SUM(Q4:Q53) -> 5875.6035 | R54: =SUM(R3:R53) -> 1
A55: p18 | B55: p21 | C55: 1361 | D55: 0 | E55: 1361 | G55: 18 | H55: 21 | I55: MT | J55: WY | K55: Different | L55: =IF(AND(K55="Different",OR(I55 = $O$1,J55=$O$1)),E55,"") | M55: =IF(L55<>"",IF(I55=$O$1,J55,I55),"")
A56: p18 | B56: p22 | C56: 94.559271 | D56: 0 | E56: 94.559271 | G56: 18 | H56: 22 | I56: MT | J56: WY | K56: Different | L56: =IF(AND(K56="Different",OR(I56 = $O$1,J56=$O$1)),E56,"") | M56: =IF(L56<>"",IF(I56=$O$1,J56,I56),"")
A57: p20 | B57: p35 | C57: 0 | D57: 200 | E57: 314.46 | G57: 20 | H57: 35 | I57: MT | J57: MT | K57: Same | L57: =IF(AND(K57="Different",OR(I57 = $O$1,J57=$O$1)),E57,"") | M57: =IF(L57<>"",IF(I57=$O$1,J57,I57),"")
A58: p21 | B58: p24 | C58: 295.82067 | D58: 0 | E58: 295.82067 | G58: 21 | H58: 24 | I58: WY | J58: WY | K58: Same | L58: =IF(AND(K58="Different",OR(I58 = $O$1,J58=$O$1)),E58,"") | M58: =IF(L58<>"",IF(I58=$O$1,J58,I58),"")
A59: p21 | B59: p25 | C59: 1282 | D59: 0 | E59: 1282 | G59: 21 | H59: 25 | I59: WY | J59: UT | K59: Different | L59: =IF(AND(K59="Different",OR(I59 = $O$1,J59=$O$1)),E59,"") | M59: =IF(L59<>"",IF(I59=$O$1,J59,I59),"")
A60: p21 | B60: p26 | C60: 628 | D60: 0 | E60: 628 | G60: 21 | H60: 26 | I60: WY | J60: UT | K60: Different | L60: =IF(AND(K60="Different",OR(I60 = $O$1,J60=$O$1)),E60,"") | M60: =IF(L60<>"",IF(I60=$O$1,J60,I60),"")
A61: p22 | B61: p23 | C61: 1010 | D61: 0 | E61: 1010 | G61: 22 | H61: 23 | I61: WY | J61: WY | K61: Same | L61: =IF(AND(K61="Different",OR(I61 = $O$1,J61=$O$1)),E61,"") | M61: =IF(L61<>"",IF(I61=$O$1,J61,I61),"")
A62: p22 | B62: p24 | C62: 518 | D62: 0 | E62: 518 | G62: 22 | H62: 24 | I62: WY | J62: WY | K62: Same | L62: =IF(AND(K62="Different",OR(I62 = $O$1,J62=$O$1)),E62,"") | M62: =IF(L62<>"",IF(I62=$O$1,J62,I62),"")
A63: p23 | B63: p24 | C63: 868 | D63: 0 | E63: 868 | G63: 23 | H63: 24 | I63: WY | J63: WY | K63: Same | L63: =IF(AND(K63="Different",OR(I63 = $O$1,J63=$O$1)),E63,"") | M63: =IF(L63<>"",IF(I63=$O$1,J63,I63),"")
A64: p23 | B64: p32 | C64: 2063 | D64: 0 | E64: 2063 | G64: 23 | H64: 32 | I64: WY | J64: SD | K64: Different | L64: =IF(AND(K64="Different",OR(I64 = $O$1,J64=$O$1)),E64,"") | M64: =IF(L64<>"",IF(I64=$O$1,J64,I64),"")
A65: p24 | B65: p32 | C65: 422 | D65: 0 | E65: 422 | G65: 24 | H65: 32 | I65: WY | J65: SD | K65: Different | L65: =IF(AND(K65="Different",OR(I65 = $O$1,J65=$O$1)),E65,"") | M65: =IF(L65<>"",IF(I65=$O$1,J65,I65),"")
A66: p24 | B66: p33 | C66: 3320 | D66: 0 | E66: 3320 | G66: 24 | H66: 33 | I66: WY | J66: CO | K66: Different | L66: =IF(AND(K66="Different",OR(I66 = $O$1,J66=$O$1)),E66,"") | M66: =IF(L66<>"",IF(I66=$O$1,J66,I66),"")
A67: p24 | B67: p39 | C67: 0 | D67: 310 | E67: 487.413 | F67: changed to 310 MW (200 VS; 110 Segall) | G67: 24 | H67: 39 | I67: WY | J67: NE | K67: Different | L67: =IF(AND(K67="Different",OR(I67 = $O$1,J67=$O$1)),E67,"") | M67: =IF(L67<>"",IF(I67=$O$1,J67,I67),"")
A68: p25 | B68: p26 | C68: 1237 | D68: 0 | E68: 1237 | G68: 25 | H68: 26 | I68: UT | J68: UT | K68: Same | L68: =IF(AND(K68="Different",OR(I68 = $O$1,J68=$O$1)),E68,"") | M68: =IF(L68<>"",IF(I68=$O$1,J68,I68),"")
A69: p25 | B69: p28 | C69: 142.27245 | D69: 0 | E69: 142.27245 | G69: 25 | H69: 28 | I69: UT | J69: AZ | K69: Different | L69: =IF(AND(K69="Different",OR(I69 = $O$1,J69=$O$1)),E69,"") | M69: =IF(L69<>"",IF(I69=$O$1,J69,I69),"")
A70: p25 | B70: p31 | C70: 299.08369 | D70: 0 | E70: 299.08369 | G70: 25 | H70: 31 | I70: UT | J70: NM | K70: Different | L70: =IF(AND(K70="Different",OR(I70 = $O$1,J70=$O$1)),E70,"") | M70: =IF(L70<>"",IF(I70=$O$1,J70,I70),"")
A71: p26 | B71: p33 | C71: 239.24012 | D71: 0 | E71: 239.24012 | G71: 26 | H71: 33 | I71: UT | J71: CO | K71: Different | L71: =IF(AND(K71="Different",OR(I71 = $O$1,J71=$O$1)),E71,"") | M71: =IF(L71<>"",IF(I71=$O$1,J71,I71),"")
A72: p27 | B72: p28 | C72: 799 | D72: 0 | E72: 799 | G72: 27 | H72: 28 | I72: AZ | J72: AZ | K72: Same | L72: =IF(AND(K72="Different",OR(I72 = $O$1,J72=$O$1)),E72,"") | M72: =IF(L72<>"",IF(I72=$O$1,J72,I72),"")
A73: p28 | B73: p29 | C73: 5047 | D73: 0 | E73: 5047 | G73: 28 | H73: 29 | I73: AZ | J73: AZ | K73: Same | L73: =IF(AND(K73="Different",OR(I73 = $O$1,J73=$O$1)),E73,"") | M73: =IF(L73<>"",IF(I73=$O$1,J73,I73),"")
A74: p28 | B74: p30 | C74: 4209 | D74: 0 | E74: 4209 | G74: 28 | H74: 30 | I74: AZ | J74: AZ | K74: Same | L74: =IF(AND(K74="Different",OR(I74 = $O$1,J74=$O$1)),E74,"") | M74: =IF(L74<>"",IF(I74=$O$1,J74,I74),"")
A75: p28 | B75: p31 | C75: 3357 | D75: 0 | E75: 3357 | G75: 28 | H75: 31 | I75: AZ | J75: NM | K75: Different | L75: =IF(AND(K75="Different",OR(I75 = $O$1,J75=$O$1)),E75,"") | M75: =IF(L75<>"",IF(I75=$O$1,J75,I75),"")
A76: p29 | B76: p30 | C76: 639 | D76: 0 | E76: 639 | G76: 29 | H76: 30 | I76: AZ | J76: AZ | K76: Same | L76: =IF(AND(K76="Different",OR(I76 = $O$1,J76=$O$1)),E76,"") | M76: =IF(L76<>"",IF(I76=$O$1,J76,I76),"")
A77: p29 | B77: p31 | C77: 3602 | D77: 0 | E77: 3602 | G77: 29 | H77: 31 | I77: AZ | J77: NM | K77: Different | L77: =IF(AND(K77="Different",OR(I77 = $O$1,J77=$O$1)),E77,"") | M77: =IF(L77<>"",IF(I77=$O$1,J77,I77),"")
A78: p31 | B78: p34 | C78: 690 | D78: 0 | E78: 690 | G78: 31 | H78: 34 | I78: NM | J78: CO | K78: Different | L78: =IF(AND(K78="Different",OR(I78 = $O$1,J78=$O$1)),E78,"") | M78: =IF(L78<>"",IF(I78=$O$1,J78,I78),"")
A79: p31 | B79: p47 | C79: 0 | D79: 200 | E79: 314.46 | F79: changed to 200 MW | G79: 31 | H79: 47 | I79: NM | J79: NM | K79: Same | L79: =IF(AND(K79="Different",OR(I79 = $O$1,J79=$O$1)),E79,"") | M79: =IF(L79<>"",IF(I79=$O$1,J79,I79),"")
A80: p31 | B80: p48 | C80: 0 | D80: 200 | E80: 314.46 | F80: changed to 200 MW | G80: 31 | H80: 48 | I80: NM | J80: TX | K80: Different | L80: =IF(AND(K80="Different",OR(I80 = $O$1,J80=$O$1)),E80,"") | M80: =IF(L80<>"",IF(I80=$O$1,J80,I80),"")
A81: p31 | B81: p59 | C81: 2859 | D81: 0 | E81: 2859 | G81: 31 | H81: 59 | I81: NM | J81: TX | K81: Different | L81: =IF(AND(K81="Different",OR(I81 = $O$1,J81=$O$1)),E81,"") | M81: =IF(L81<>"",IF(I81=$O$1,J81,I81),"")
A82: p32 | B82: p38 | C82: 0 | D82: 200 | E82: 314.46 | G82: 32 | H82: 38 | I82: SD | J82: SD | K82: Same | L82: =IF(AND(K82="Different",OR(I82 = $O$1,J82=$O$1)),E82,"") | M82: =IF(L82<>"",IF(I82=$O$1,J82,I82),"")
A83: p33 | B83: p34 | C83: 2735 | D83: 0 | E83: 2735 | G83: 33 | H83: 34 | I83: CO | J83: CO | K83: Same | L83: =IF(AND(K83="Different",OR(I83 = $O$1,J83=$O$1)),E83,"") | M83: =IF(L83<>"",IF(I83=$O$1,J83,I83),"")
A84: p34 | B84: p52 | C84: 0 | D84: 210 | E84: 330.183 | G84: 34 | H84: 52 | I84: CO | J84: KS | K84: Different | L84: =IF(AND(K84="Different",OR(I84 = $O$1,J84=$O$1)),E84,"") | M84: =IF(L84<>"",IF(I84=$O$1,J84,I84),"")
A85: p35 | B85: p36 | C85: 609.5499 | D85: 0 | E85: 609.5499 | G85: 35 | H85: 36 | I85: MT | J85: ND | K85: Different | L85: =IF(AND(K85="Different",OR(I85 = $O$1,J85=$O$1)),E85,"") -> 609.5499 | M85: =IF(L85<>"",IF(I85=$O$1,J85,I85),"") -> MT
A86: p36 | B86: p37 | C86: 1127.729 | D86: 0 | E86: 1127.729 | G86: 36 | H86: 37 | I86: ND | J86: ND | K86: Same | L86: =IF(AND(K86="Different",OR(I86 = $O$1,J86=$O$1)),E86,"") | M86: =IF(L86<>"",IF(I86=$O$1,J86,I86),"")
A87: p36 | B87: p38 | C87: 2054.032 | D87: 0 | E87: 2054.032 | G87: 36 | H87: 38 | I87: ND | J87: SD | K87: Different | L87: =IF(AND(K87="Different",OR(I87 = $O$1,J87=$O$1)),E87,"") -> 2054.032 | M87: =IF(L87<>"",IF(I87=$O$1,J87,I87),"") -> SD
A88: p37 | B88: p38 | C88: 206.3271 | D88: 0 | E88: 206.3271 | G88: 37 | H88: 38 | I88: ND | J88: SD | K88: Different | L88: =IF(AND(K88="Different",OR(I88 = $O$1,J88=$O$1)),E88,"") -> 206.3271 | M88: =IF(L88<>"",IF(I88=$O$1,J88,I88),"") -> SD
A89: p37 | B89: p42 | C89: 647.2445 | D89: 0 | E89: 647.2445 | G89: 37 | H89: 42 | I89: ND | J89: MN | K89: Different | L89: =IF(AND(K89="Different",OR(I89 = $O$1,J89=$O$1)),E89,"") -> 647.2445 | M89: =IF(L89<>"",IF(I89=$O$1,J89,I89),"") -> MN
A90: p37 | B90: p43 | C90: 1678.682 | D90: 1500 | E90: 2358.45 | F90: the DC projects were missing | G90: 37 | H90: 43 | I90: ND | J90: MN | K90: Different | L90: =IF(AND(K90="Different",OR(I90 = $O$1,J90=$O$1)),E90,"") -> 2358.45 | M90: =IF(L90<>"",IF(I90=$O$1,J90,I90),"") -> MN
A91: p38 | B91: p39 | C91: 314.5868 | D91: 0 | E91: 314.5868 | G91: 38 | H91: 39 | I91: SD | J91: NE | K91: Different | L91: =IF(AND(K91="Different",OR(I91 = $O$1,J91=$O$1)),E91,"") | M91: =IF(L91<>"",IF(I91=$O$1,J91,I91),"")
A92: p38 | B92: p40 | C92: 733.8224 | D92: 0 | E92: 733.8224 | G92: 38 | H92: 40 | I92: SD | J92: NE | K92: Different | L92: =IF(AND(K92="Different",OR(I92 = $O$1,J92=$O$1)),E92,"") | M92: =IF(L92<>"",IF(I92=$O$1,J92,I92),"")
A93: p38 | B93: p43 | C93: 84.39539 | D93: 0 | E93: 84.39539 | G93: 38 | H93: 43 | I93: SD | J93: MN | K93: Different | L93: =IF(AND(K93="Different",OR(I93 = $O$1,J93=$O$1)),E93,"") | M93: =IF(L93<>"",IF(I93=$O$1,J93,I93),"")
A94: p38 | B94: p44 | C94: 1147.3 | D94: 0 | E94: 1147.3 | G94: 38 | H94: 44 | I94: SD | J94: MN | K94: Different | L94: =IF(AND(K94="Different",OR(I94 = $O$1,J94=$O$1)),E94,"") | M94: =IF(L94<>"",IF(I94=$O$1,J94,I94),"")
A95: p38 | B95: p45 | C95: 1494.105 | D95: 0 | E95: 1494.105 | G95: 38 | H95: 45 | I95: SD | J95: IA | K95: Different | L95: =IF(AND(K95="Different",OR(I95 = $O$1,J95=$O$1)),E95,"") | M95: =IF(L95<>"",IF(I95=$O$1,J95,I95),"")
A96: p39 | B96: p40 | C96: 2750.307 | D96: 0 | E96: 2750.307 | G96: 39 | H96: 40 | I96: NE | J96: NE | K96: Same | L96: =IF(AND(K96="Different",OR(I96 = $O$1,J96=$O$1)),E96,"") | M96: =IF(L96<>"",IF(I96=$O$1,J96,I96),"")
A97: p40 | B97: p41 | C97: 1733.566 | D97: 0 | E97: 1733.566 | G97: 40 | H97: 41 | I97: NE | J97: NE | K97: Same | L97: =IF(AND(K97="Different",OR(I97 = $O$1,J97=$O$1)),E97,"") | M97: =IF(L97<>"",IF(I97=$O$1,J97,I97),"")
A98: p40 | B98: p45 | C98: 781.058 | D98: 0 | E98: 781.058 | G98: 40 | H98: 45 | I98: NE | J98: IA | K98: Different | L98: =IF(AND(K98="Different",OR(I98 = $O$1,J98=$O$1)),E98,"") | M98: =IF(L98<>"",IF(I98=$O$1,J98,I98),"")
A99: p40 | B99: p52 | C99: 622.12389 | D99: 0 | E99: 622.12389 | G99: 40 | H99: 52 | I99: NE | J99: KS | K99: Different | L99: =IF(AND(K99="Different",OR(I99 = $O$1,J99=$O$1)),E99,"") | M99: =IF(L99<>"",IF(I99=$O$1,J99,I99),"")
A100: p41 | B100: p45 | C100: 2798.112 | D100: 0 | E100: 2798.112 | G100: 41 | H100: 45 | I100: NE | J100: IA | K100: Different | L100: =IF(AND(K100="Different",OR(I100 = $O$1,J100=$O$1)),E100,"") | M100: =IF(L100<>"",IF(I100=$O$1,J100,I100),"")
A101: p41 | B101: p53 | C101: 332.74336 | D101: 0 | E101: 332.74336 | G101: 41 | H101: 53 | I101: NE | J101: KS | K101: Different | L101: =IF(AND(K101="Different",OR(I101 = $O$1,J101=$O$1)),E101,"") | M101: =IF(L101<>"",IF(I101=$O$1,J101,I101),"")
A102: p41 | B102: p54 | C102: 1923.0088 | D102: 0 | E102: 1923.0088 | G102: 41 | H102: 54 | I102: NE | J102: MO | K102: Different | L102: =IF(AND(K102="Different",OR(I102 = $O$1,J102=$O$1)),E102,"") | M102: =IF(L102<>"",IF(I102=$O$1,J102,I102),"")
... A128: p50 | B128: p57 | C128: 952.1273 | D128: 0 | E128: 952.1273 | G128: 50 | H128: 57 | I128: OK | J128: TX | K128: Different | L128: =IF(AND(K128="Different",OR(I128 = $O$1,J128=$O$1)),E128,"") | M128: =IF(L128<>"",IF(I128=$O$1,J128,I128),"")
A129: p50 | B129: p60 | C129: 0 | D129: 220 | E129: 345.906 | F129: changed to 220 MW | G129: 50 | H129: 60 | I129: OK | J129: TX | K129: Different | L129: =IF(AND(K129="Different",OR(I129 = $O$1,J129=$O$1)),E129,"") | M129: =IF(L129<>"",IF(I129=$O$1,J129,I129),"")
A130: p50 | B130: p63 | C130: 0 | D130: 0 | E130: 0 | F130: removed; not a real line | G130: 50 | H130: 63 | I130: OK | J130: TX | K130: Different | L130: =IF(AND(K130="Different",OR(I130 = $O$1,J130=$O$1)),E130,"") | M130: =IF(L130<>"",IF(I130=$O$1,J130,I130),"")
A131: p50 | B131: p85 | C131: 225.68021 | D131: 0 | E131: 225.68021 | G131: 50 | H131: 85 | I131: OK | J131: AR | K131: Different | L131: =IF(AND(K131="Different",OR(I131 = $O$1,J131=$O$1)),E131,"") | M131: =IF(L131<>"",IF(I131=$O$1,J131,I131),"")
A132: p51 | B132: p53 | C132: 112.7907 | D132: 0 | E132: 112.7907 | G132: 51 | H132: 53 | I132: OK | J132: KS | K132: Different | L132: =IF(AND(K132="Different",OR(I132 = $O$1,J132=$O$1)),E132,"") | M132: =IF(L132<>"",IF(I132=$O$1,J132,I132),"")
A133: p51 | B133: p55 | C133: 35.362517 | D133: 0 | E133: 35.362517 | G133: 51 | H133: 55 | I133: OK | J133: MO | K133: Different | L133: =IF(AND(K133="Different",OR(I133 = $O$1,J133=$O$1)),E133,"") | M133: =IF(L133<>"",IF(I133=$O$1,J133,I133),"")
A134: p51 | B134: p56 | C134: 3107.563 | D134: 0 | E134: 3107.563 | G134: 51 | H134: 56 | I134: OK | J134: AR | K134: Different | L134: =IF(AND(K134="Different",OR(I134 = $O$1,J134=$O$1)),E134,"") | M134: =IF(L134<>"",IF(I134=$O$1,J134,I134),"")
A135: p52 | B135: p53 | C135: 610.6625 | D135: 0 | E135: 610.6625 | G135: 52 | H135: 53 | I135: KS | J135: KS | K135: Same | L135: =IF(AND(K135="Different",OR(I135 = $O$1,J135=$O$1)),E135,"") | M135: =IF(L135<>"",IF(I135=$O$1,J135,I135),"")
A136: p53 | B136: p54 | C136: 1406.588 | D136: 0 | E136: 1406.588 | G136: 53 | H136: 54 | I136: KS | J136: MO | K136: Different | L136: =IF(AND(K136="Different",OR(I136 = $O$1,J136=$O$1)),E136,"") | M136: =IF(L136<>"",IF(I136=$O$1,J136,I136),"")
A137: p53 | B137: p55 | C137: 1085.692 | D137: 0 | E137: 1085.692 | G137: 53 | H137: 55 | I137: KS | J137: MO | K137: Different | L137: =IF(AND(K137="Different",OR(I137 = $O$1,J137=$O$1)),E137,"") | M137: =IF(L137<>"",IF(I137=$O$1,J137,I137),"")
A138: p54 | B138: p55 | C138: 1037.173 | D138: 0 | E138: 1037.173 | G138: 54 | H138: 55 | I138: MO | J138: MO | K138: Same | L138: =IF(AND(K138="Different",OR(I138 = $O$1,J138=$O$1)),E138,"") | M138: =IF(L138<>"",IF(I138=$O$1,J138,I138),"")
A139: p54 | B139: p70 | C139: 192.92035 | D139: 0 | E139: 192.92035 | G139: 54 | H139: 70 | I139: MO | J139: IA | K139: Different | L139: =IF(AND(K139="Different",OR(I139 = $O$1,J139=$O$1)),E139,"") | M139: =IF(L139<>"",IF(I139=$O$1,J139,I139),"")
A140: p54 | B140: p71 | C140: 158.47227 | D140: 0 | E140: 158.47227 | G140: 54 | H140: 71 | I140: MO | J140: MO | K140: Same | L140: =IF(AND(K140="Different",OR(I140 = $O$1,J140=$O$1)),E140,"") | M140: =IF(L140<>"",IF(I140=$O$1,J140,I140),"")
A141: p54 | B141: p72 | C141: 1183.9882 | D141: 0 | E141: 1183.9882 | G141: 54 | H141: 72 | I141: MO | J141: MO | K141: Same | L141: =IF(AND(K141="Different",OR(I141 = $O$1,J141=$O$1)),E141,"") | M141: =IF(L141<>"",IF(I141=$O$1,J141,I141),"")
A142: p55 | B142: p56 | C142: 206.63475 | D142: 0 | E142: 206.63475 | G142: 55 | H142: 56 | I142: MO | J142: AR | K142: Different | L142: =IF(AND(K142="Different",OR(I142 = $O$1,J142=$O$1)),E142,"") | M142: =IF(L142<>"",IF(I142=$O$1,J142,I142),"")
... A312: p132 | B312: p133 | C312: 1038.325 | D312: 0 | E312: 1038.325 | G312: 132 | H312: 133 | I312: CT | J312: RI | K312: Different | L312: =IF(AND(K312="Different",OR(I312 = $O$1,J312=$O$1)),E312,"") | M312: =IF(L312<>"",IF(I312=$O$1,J312,I312),"")
E313: 539028.3 | L313: =SUM(L2:L312) -> 5875.6035 | M313: =IF(L313<>"",IF(I313=$O$1,J313,I313),"") -> 0

Sheet EIA_State Elec Profiles
B1: Table 10. Supply and disposition of electricity, 1990 through 2024
A2: Alabama | B2: Alabama
A3: Alabama | B3: megawatthours
A4: Alabama | B4: Category | C4: Year 2024 | D4: Year 2023 | E4: Year 2022 | F4: Year 2021 | G4: Year 2020 | H4: Year 2019 | I4: Year 2018 | J4: Year 2017 | K4: Year 2016 | L4: Year 2015 | M4: Year 2014 | N4: Year 2013 | O4: Year 2012 | P4: Year 2011 | Q4: Year 2010 | R4: Year 2009 | S4: Year 2008 | T4: Year 2007 | U4: Year 2006 | V4: Year 2005 | W4: Year 2004 | X4: Year 2003 | Y4: Year 2002 | Z4: Year 2001 | AA4: Year 2000 | AB4: Year 1999 | AC4: Year 1998 | AD4: Year 1997 | AE4: Year 1996 | AF4: Year 1995 | AG4: Year 1994 | AH4: Year 1993 | AI4: Year 1992 | AJ4: Year 1991 | AK4: Year 1990
A5: Alabama | B5: Supply
A6: Alabama | B6: Generation
A7: Alabama | B7: ..Electric utilities | C7: 104914796 | D7: 97500930 | E7: 103494925 | F7: 106804340 | G7: 102357230 | H7: 102180494 | I7: 102665414 | J7: 101709381 | K7: 97991203 | L7: 107868476 | M7: 112340555 | N7: 115027021 | O7: 108425247 | P7: 118834736 | Q7: 122766490 | R7: 118781555 | S7: 128054895 | T7: 124273167 | U7: 124365180 | V7: 126303893 | W7: 124554606 | X7: 126845720 | Y7: 123739223 | Z7: 118744284 | AA7: 118037076 | AB7: 113908581 | AC7: 113393840 | AD7: 113683627 | AE7: 115093211 | AF7: 99589284 | AG7: 95171057 | AH7: 94123557 | AI7: 90792233 | AJ7: 85050801 | AK7: 76231696
A8: Alabama | B8: ..Independent power producers | C8: 32981091 | D8: 31787099 | E8: 31750036 | F8: 26941613 | G8: 27553362 | H8: 32439211 | I8: 32906202 | J8: 29571872 | K8: 35632171 | L8: 35059831 | M8: 29036222 | N8: 27383743 | O8: 35812766 | P8: 29424158 | Q8: 20923024 | R8: 15302426 | S8: 10683147 | T8: 9201656 | U8: 7103396 | V8: 4821000 | W8: 6127041 | X8: 4064709 | Y8: 2357413 | Z8: 44733 | AA8: 42291 | AB8: 48901 | AC8: 4410 | AD8: 4852 | AE8: 5847 | AF8: 7278 | AG8: 15314 | AH8: 10989 | AI8: 25233 | AJ8: 25233 | AK8: 27936
A9: Alabama | B9: ..Combined heat and power, electric | C9: 0 | D9: 5422456 | E9: 5032840 | F9: 4031284 | G9: 2848326 | H9: 3157136 | I9: 4864301 | J9: 4245625 | K9: 4506703 | L9: 5332204 | M9: 4125833 | N9: 4014623 | O9: 4393369 | P9: 3773959 | Q9: 4243149 | R9: 4605863 | S9: 2569428 | T9: 5705071 | U9: 4683179 | V9: 2173642 | W9: 1445678 | X9: 1310750 | Y9: 1458857 | Z9: 698013 | AA9: 549830 | AB9: 746941 | AC9: 842095 | AD9: 683325 | AE9: 670529 | AF9: 647195 | AG9: 692589 | AH9: 787844 | AI9: 778496 | AJ9: 786954 | AK9: 665814
A10: Alabama | B10: Electric power sector generation subtotal | C10: 137895887 | D10: 134710486 | E10: 140277801 | F10: 137777237 | G10: 132758918 | H10: 137776841 | I10: 140435917 | J10: 135526878 | K10: 138130077 | L10: 148260511 | M10: 145502610 | N10: 146425387 | O10: 148631382 | P10: 152032853 | Q10: 147932663 | R10: 138689844 | S10: 141307470 | T10: 139179894 | U10: 136151755 | V10: 133298535 | W10: 132127325 | X10: 132221179 | Y10: 127555493 | Z10: 119487030 | AA10: 118629197 | AB10: 114704423 | AC10: 114240345 | AD10: 114371803 | AE10: 115769588 | AF10: 100243757 | AG10: 95878960 | AH10: 94922390 | AI10: 91595962 | AJ10: 85862988 | AK10: 76925446
A11: Alabama | B11: ..Combined heat and power, commercial | C11: 0 | D11: 0 | E11: 0 | F11: 0 | G11: 0 | H11: 0 | I11: 0 | J11: 0 | K11: 0 | L11: 0 | M11: 0 | N11: 0 | O11: 0 | P11: 0 | Q11: 0 | R11: 0 | S11: 0 | T11: 0 | U11: 0 | V11: 0 | W11: 0 | X11: 0 | Y11: 0 | Z11: 0 | AA11: 0 | AB11: 0 | AC11: 0 | AD11: 0 | AE11: 0 | AF11: 0 | AG11: 0 | AH11: 0 | AI11: 0 | AJ11: 0 | AK11: 0
A12: Alabama | B12: ..Combined heat and power, industrial | C12: 5025329 | D12: 4724524 | E12: 4511092 | F12: 4956093 | G12: 4788458 | H12: 4902592 | I12: 4622077 | J12: 4437372 | K12: 4255021 | L12: 4216916 | M12: 3837837 | N12: 4147537 | O12: 4247306 | P12: 4306357 | Q12: 4217849 | R12: 4565712 | S12: 4562425 | T12: 4646377 | U12: 4743686 | V12: 4650046 | W12: 5227446 | X12: 5266043 | Y12: 5365177 | Z12: 5858092 | AA12: 5776146 | AB12: 5953085 | AC12: 5621779 | AD12: 5170528 | AE12: 5703321 | AF12: 4945610 | AG12: 4885299 | AH12: 4414607 | AI12: 3638459 | AJ12: 2923624 | AK12: 2726687
A13: Alabama | B13: Industrial and commercial generation subtotal | C13: 5025329 | D13: 4724524 | E13: 4511092 | F13: 4956093 | G13: 4788458 | H13: 4902592 | I13: 4622077 | J13: 4437372 | K13: 4255021 | L13: 4216916 | M13: 3837837 | N13: 4147537 | O13: 4247306 | P13: 4306357 | Q13: 4217849 | R13: 4565712 | S13: 4562425 | T13: 4646377 | U13: 4743686 | V13: 4650046 | W13: 5227446 | X13: 5266043 | Y13: 5365177 | Z13: 5858092 | AA13: 5776146 | AB13: 5953085 | AC13: 5621779 | AD13: 5170528 | AE13: 5703321 | AF13: 4945610 | AG13: 4885299 | AH13: 4414607 | AI13: 3638459 | AJ13: 2923624 | AK13: 2726687
A14: Alabama | B14: Total net generation | C14: 142921216 | D14: 139435010 | E14: 144788893 | F14: 142733330 | G14: 137547377 | H14: 142679433 | I14: 145057994 | J14: 139964250 | K14: 142385098 | L14: 152477427 | M14: 149340447 | N14: 150572924 | O14: 152878688 | P14: 156339210 | Q14: 152150512 | R14: 143255556 | S14: 145869895 | T14: 143826271 | U14: 140895441 | V14: 137948581 | W14: 137354771 | X14: 137487222 | Y14: 132920670 | Z14: 125345122 | AA14: 124405343 | AB14: 120657508 | AC14: 119862125 | AD14: 119542331 | AE14: 121472909 | AF14: 105189368 | AG14: 100764259 | AH14: 99336997 | AI14: 95234421 | AJ14: 88786611 | AK14: 79652133
A15: Alabama | B15: Total international imports | C15: 0 | D15: 0 | E15: 0 | F15: 0 | G15: 0 | H15: 0 | I15: 0 | J15: 0 | K15: 0 | L15: 0 | M15: 0 | N15: 0 | O15: 0 | P15: 0 | Q15: 0 | R15: 0 | S15: 0 | T15: 0 | U15: 0 | V15: 0 | W15: 0 | X15: 0 | Y15: 0 | Z15: 0 | AA15: 0 | AB15: 0 | AC15: 0 | AD15: 0 | AE15: 0 | AF15: 0 | AG15: 0 | AH15: 0 | AI15: 0 | AJ15: 0 | AK15: 0
