Workbook

Sheet About
A1: BRZSPbS BAU Required ZEV Sales Percentage by Subregion | B1: North Dakota | C1: 46223 | F1: Alabama | G1: AL
B2: =_xlfn.XLOOKUP(B1,F:F,G:G) -> ND | F2: Alaska | G2: AK
A3: Sources: | B3: State Passenger LDVs | F3: Arizona | G3: AZ
B4: California Air Resources Board | F4: Arkansas | G4: AR
B5: 2022 | F5: California | G5: CA
B6: Final Regulation Order, Section 1962.4, Title 13, California Code of Regulations | F6: Colorado | G6: CO
B7: https://ww2.arb.ca.gov/sites/default/files/barcu/regact/2022/accii/acciifro1962.4.pdf | F7: Connecticut | G7: CT
B8: Page 4 | F8: Delaware | G8: DE
F9: Florida | G9: FL
B10: State Freight LDVs and HDVs | F10: Georgia | G10: GA
B11: California Air Resources Board | F11: Hawaii | G11: HI
B12: 2022 | F12: Idaho | G12: ID
B13: Final Regulation Order: Advanced Clean Trucks Regulation | F13: Illinois | G13: IL
B14: https://ww2.arb.ca.gov/sites/default/files/barcu/regact/2019/act2019/fro2.pdf | F14: Indiana | G14: IN
B15: Page 5, Table A-1 | F15: Iowa | G15: IA
F16: Kansas | G16: KS
B17: Which States Follow ACC I Standards? | F17: Kentucky | G17: KY
B18: California Air Resources Board + state regs | F18: Louisiana | G18: LA
B19: 2019-2022 | F19: Maine | G19: ME
B20: 177 States | F20: Maryland | G20: MD
B21: https://ww2.arb.ca.gov/sites/default/files/2019-03/177-states.pdf | F21: Massachusetts | G21: MA
B22: https://ecology.wa.gov/Regulations-Permits/Laws-rules-rulemaking/Rulemaking/WAC-173-423-400 | F22: Michigan | G22: MI
B23: https://ndep.nv.gov/uploads/air-ccn-docs/clean_cars_nv_reg.pdf | F23: Minnesota | G23: MN
B24: https://cloud.env.nm.gov/air/resources/_translator.php/NoP4Wd1EyorPC~sl~BWz~sl~H2+PXdCQEKefUZ7Ou8Vgq~sl~x2ZYzqa1zexRjaNVbxGMCgU8AVirLkjjLdev8vysjOadSflGgbBfGQtLEpGCtN+kDVh1YPy2q5u9L4gGZ4Ls+vKK.pdf | F24: Mississippi | G24: MS
B25: https://lis.virginia.gov/cgi-bin/legp604.exe?212+ful+HB1965ER | F25: Missouri | G25: MO
F26: Montana | G26: MT
B27: Which States Follow ACC II and Advanced Clean Truck Standards? | F27: Nebraska | G27: NE
B28: Sierra Club | F28: Nevada | G28: NV
B29: 2023 | F29: New Hampshire | G29: NH
B30: Clean Vehicle Programs: State Tracker | F30: New Jersey | G30: NJ
B31: https://www.sierraclub.org/transportation/clean-vehicle-programs-state-tracker | F31: New Mexico | G31: NM
B32: Last Accessed January 9, 2024 | F32: New York | G32: NY
F33: North Carolina | G33: NC
B34: Transportation Data | F34: North Dakota | G34: ND
B35: Oak Ridge National Laboratory | F35: Ohio | G35: OH
B36: 2022 | F36: Oklahoma | G36: OK
B37: Transportation Energy Data Book: Edition 40 | F37: Oregon | G37: OR
B38: https://tedb.ornl.gov/data/ | F38: Pennsylvania | G38: PA
F39: Rhode Island | G39: RI
B40: Bus Registration Data | F40: South Carolina | G40: SC
B41: U.S. DOT Federal Highway Administration | F41: South Dakota | G41: SD
B42: 2022 | F42: Tennessee | G42: TN
B43: Highway Statistics 2020 - Table MV-10 | F43: Texas | G43: TX
B44: https://www.fhwa.dot.gov/policyinformation/statistics/2020/mv10.cfm | F44: Utah | G44: UT
F45: Vermont | G45: VT
B46: Medium-Duty Truck Data | F46: Virginia | G46: VA
B47: Oak Ridge National Laboratory | F47: Washington | G47: WA
B48: 2017 | F48: West Virginia | G48: WV
B49: Transportation Electrification Beyond Light Duty: Technology and Market Assessment | F49: Wisconsin | G49: WI
B50: https://info.ornl.gov/sites/publications/Files/Pub72938.pdf | F50: Wyoming | G50: WY
A52: Notes
A53: This variable expresses the percentage of vehicles sold in each subregion that must be
A54: ZEVs in each year (i.e., due to a mandate or binding target implemented in legislation).
A55: It should not cover any requirements outside the subregional geography (for the whole model region).
A56: I.e. the US national model should not cover federal requirements here, only state requirements.
A57: The model will allow more ZEVs than this to be sold if economic factors would favor
A58: a higher level of ZEV deployment. This variable should only contain the legislative
A59: required ZEV shares, not projected or expected ZEV shares based on economics,
A60: ZEV subsidies, or other such factors.
A62: Although manufacturers often begin selling new models before the calendar year begins, the
A63: EPS can't impose a ZEV standard for part of a year. Therefore, we assume sales year = model year.
A65: U.S. Data
... A79: Only leave in place Advanced Clean Cars 1 and estimate as 8% of ZEV sales held constant.

Sheet EPS Vehicle Class Mapping
A1: The ZEV sales standards imposed by a region or subregion may have schedules that
A2: do not overlap with EPS classifications. In this sheet, the California Air Resource Board (CARB)
A3: Advanced Clean Cars I/II (ACC I/II) and Advanced Clean Trucks (ACT) schedules are mapped
A4: onto EPS vehicle classes using U.S. vehicle registration & sales data.
A6: EPS Vehicle Classes | C6: Description
A7: passenger LDVs | B7: Cars | C7: most light-duty road vehicles (such as cars and SUVs)
A8: passenger HDVs | B8: Buses | C8: buses (including school, transit, and intercity buses)
A9: passenger motorbikes | C9: registered motorcycles
A10: freight LDVs | B10: Class 2b-6 | C10: light commercial trucks
A11: freight HDVs | B11: Class 7-8 | C11: all other heavy road vehicles (mostly freight trucks)
A12: freight motorbikes | C12: registered motorcycles
A14: CARB Schedules
A15: Year | B15: 2020 | C15: 2021 | D15: 2022 | E15: 2023 | F15: 2024 | G15: 2025 | H15: 2026 | I15: 2027 | J15: 2028 | K15: 2029 | L15: 2030 | M15: 2031 | N15: 2032 | O15: 2033 | P15: 2034 | Q15: 2035 | R15: 2036 | S15: 2037 | T15: 2038 | U15: 2039 | V15: 2040 | W15: 2041 | X15: 2042 | Y15: 2043 | Z15: 2044 | AA15: 2045 | AB15: 2046 | AC15: 2047 | AD15: 2048 | AE15: 2049 | AF15: 2050
A16: ACC I passenger cars | B16: 0 | C16: 0 | D16: 0 | E16: 0 | F16: 0.08 | G16: 0.08 | H16: =G16 -> 0.08 | I16: =H16 -> 0.08 | J16: =I16 -> 0.08 | K16: =J16 -> 0.08 | L16: =K16 -> 0.08 | M16: =L16 -> 0.08 | N16: =M16 -> 0.08 | O16: =N16 -> 0.08 | ... AF16: =AE16 -> 0.08
A17: ACC II passenger cars | B17: =B16 -> 0 | C17: =C16 -> 0 | D17: =D16 -> 0 | E17: =E16 -> 0 | F17: =F16 -> 0.08 | G17: =G16 -> 0.08 | H17: 0.35 | I17: 0.43 | J17: 0.51 | K17: 0.59 | L17: 0.68 | M17: 0.76 | N17: 0.82 | O17: 0.88 | P17: 0.94 | Q17: 1 | R17: =Q17 -> 1 | S17: =R17 -> 1 | T17: =S17 -> 1 | U17: =T17 -> 1 | V17: =U17 -> 1 | W17: =V17 -> 1 | X17: =W17 -> 1 | Y17: =X17 -> 1 | ... AF17: =AE17 -> 1
A18: ACT Class 2b-3 pickup trucks and vans | B18: 0 | C18: 0 | D18: 0 | E18: 0 | F18: 0.05 | G18: 0.07 | H18: 0.1 | I18: 0.15 | J18: 0.2 | K18: 0.25 | L18: 0.3 | M18: 0.35 | N18: 0.4 | O18: 0.45 | P18: 0.5 | Q18: 0.55 | R18: =Q18 -> 0.55 | S18: =R18 -> 0.55 | T18: =S18 -> 0.55 | U18: =T18 -> 0.55 | V18: =U18 -> 0.55 | W18: =V18 -> 0.55 | X18: =W18 -> 0.55 | Y18: =X18 -> 0.55 | ... AF18: =AE18 -> 0.55
A19: ACT Class 4-8 rigid (i.e., non-tractor) trucks | B19: 0 | C19: 0 | D19: 0 | E19: 0 | F19: 0.09 | G19: 0.11 | H19: 0.13 | I19: 0.2 | J19: 0.3 | K19: 0.4 | L19: 0.5 | M19: 0.55 | N19: 0.6 | O19: 0.65 | P19: 0.7 | Q19: 0.75 | R19: =Q19 -> 0.75 | S19: =R19 -> 0.75 | T19: =S19 -> 0.75 | U19: =T19 -> 0.75 | V19: =U19 -> 0.75 | W19: =V19 -> 0.75 | X19: =W19 -> 0.75 | Y19: =X19 -> 0.75 | ... AF19: =AE19 -> 0.75
A20: ACT Class 7-8 tractor trucks | B20: 0 | C20: 0 | D20: 0 | E20: 0 | F20: 0.05 | G20: 0.07 | H20: 0.1 | I20: 0.15 | J20: 0.2 | K20: 0.25 | L20: 0.3 | M20: 0.35 | N20: 0.4 | O20: 0.4 | P20: 0.4 | Q20: 0.4 | R20: =Q20 -> 0.4 | S20: =R20 -> 0.4 | T20: =S20 -> 0.4 | U20: =T20 -> 0.4 | V20: =U20 -> 0.4 | W20: =V20 -> 0.4 | X20: =W20 -> 0.4 | Y20: =X20 -> 0.4 | ... AF20: =AE20 -> 0.4
A22: Class 2b-3 VMT | C22: =SUM('AEO by Class'!B3:B4) -> 162858256786 | D22: =SUM('AEO by Class'!C3:C4) -> 171035865319 | E22: =SUM('AEO by Class'!D3:D4) -> 173544893263 | F22: =SUM('AEO by Class'!E3:E4) -> 175151360297 | G22: =SUM('AEO by Class'!F3:F4) -> 176642088958 | H22: =SUM('AEO by Class'!G3:G4) -> 179046425003 | I22: =SUM('AEO by Class'!H3:H4) -> 181640723246 | J22: =SUM('AEO by Class'!I3:I4) -> 184184673851 | ... AF22: =SUM('AEO by Class'!AE3:AE4) -> 253966556134
A23: Class 4-8 rigid truck VMT | C23: =SUM('AEO by Class'!B5:B8) -> 60343802126 | D23: =SUM('AEO by Class'!C5:C8) -> 61265916527 | E23: =SUM('AEO by Class'!D5:D8) -> 60770468811 | F23: =SUM('AEO by Class'!E5:E8) -> 60621853767 | G23: =SUM('AEO by Class'!F5:F8) -> 60956381365 | H23: =SUM('AEO by Class'!G5:G8) -> 61694583706 | I23: =SUM('AEO by Class'!H5:H8) -> 62460976106 | J23: =SUM('AEO by Class'!I5:I8) -> 63287516270 | ... AF23: =SUM('AEO by Class'!AE5:AE8) -> 86169767894
A24: Class 7-8 tractor truck VMT | C24: =SUM('AEO by Class'!B9:B10) -> 181451501319 | D24: =SUM('AEO by Class'!C9:C10) -> 185622287850 | E24: =SUM('AEO by Class'!D9:D10) -> 185197254875 | F24: =SUM('AEO by Class'!E9:E10) -> 185421480578 | G24: =SUM('AEO by Class'!F9:F10) -> 186898742848 | H24: =SUM('AEO by Class'!G9:G10) -> 189159842657 | I24: =SUM('AEO by Class'!H9:H10) -> 191006166106 | J24: =SUM('AEO by Class'!I9:I10) -> 192510372713 | ... AF24: =SUM('AEO by Class'!AE9:AE10) -> 203649410349
A26: Percent of Class 4-8 truck VMT in freight LDV EPS category | C26: =SUM('AEO by Class'!B5:B7)/SUM('AEO by Class'!B5:B8) -> 0.97399343 | D26: =SUM('AEO by Class'!C5:C7)/SUM('AEO by Class'!C5:C8) -> 0.97438178 | E26: =SUM('AEO by Class'!D5:D7)/SUM('AEO by Class'!D5:D8) -> 0.97470042 | F26: =SUM('AEO by Class'!E5:E7)/SUM('AEO by Class'!E5:E8) -> 0.97497706 | G26: =SUM('AEO by Class'!F5:F7)/SUM('AEO by Class'!F5:F8) -> 0.97520525 | H26: =SUM('AEO by Class'!G5:G7)/SUM('AEO by Class'!G5:G8) -> 0.97543856 | I26: =SUM('AEO by Class'!H5:H7)/SUM('AEO by Class'!H5:H8) -> 0.97570205 | J26: =SUM('AEO by Class'!I5:I7)/SUM('AEO by Class'!I5:I8) -> 0.97600379 | ... AF26: =SUM('AEO by Class'!AE5:AE7)/SUM('AEO by Class'!AE5:AE8) -> 0.98228881
A27: Percent of Class 4-8 truck VMT in freight HDV EPS category | C27: =1-C26 -> 0.02600657 | D27: =1-D26 -> 0.025618221 | E27: =1-E26 -> 0.025299582 | F27: =1-F26 -> 0.025022939 | G27: =1-G26 -> 0.024794745 | H27: =1-H26 -> 0.024561445 | I27: =1-I26 -> 0.024297953 | J27: =1-J26 -> 0.023996212 | ... AF27: =1-AF26 -> 0.01771119
A29: Class 2b-3 percent of freight LDV VMT | C29: =C22/SUM(C22,C23*C26) -> 0.73481142 | D29: =D22/SUM(D22,D23*D26) -> 0.74127418 | E29: =E22/SUM(E22,E23*E26) -> 0.74553855 | F29: =F22/SUM(F22,F23*F26) -> 0.74769121 | G29: =G22/SUM(G22,G23*G26) -> 0.74820738 | H29: =H22/SUM(H22,H23*H26) -> 0.74844143 | I29: =I22/SUM(I22,I23*I26) -> 0.74877446 | J29: =J22/SUM(J22,J23*J26) -> 0.74885965 | ... AF29: =AF22/SUM(AF22,AF23*AF26) -> 0.7500264
A30: Class 4-8 rigid truck percent of freight LDV VMT | C30: =1-C29 -> 0.26518858 | D30: =1-D29 -> 0.25872582 | E30: =1-E29 -> 0.25446145 | F30: =1-F29 -> 0.25230879 | G30: =1-G29 -> 0.25179262 | H30: =1-H29 -> 0.25155857 | I30: =1-I29 -> 0.25122554 | J30: =1-J29 -> 0.25114035 | ... AF30: =1-AF29 -> 0.2499736
A31: Class 4-8 rigid truck percent of freight HDV VMT | C31: =(C23*C27)/SUM(C23*C27,C24) -> 0.0085746266 | D31: =(D23*D27)/SUM(D23*D27,D24) -> 0.0083845752 | E31: =(E23*E27)/SUM(E23*E27,E24) -> 0.0082334311 | F31: =(F23*F27)/SUM(F23*F27,F24) -> 0.0081146347 | G31: =(G23*G27)/SUM(G23*G27,G24) -> 0.0080218503 | H31: =(H23*H27)/SUM(H23*H27,H24) -> 0.0079470666 | I31: =(I23*I27)/SUM(I23*I27,I24) -> 0.0078830439 | J31: =(J23*J27)/SUM(J23*J27,J24) -> 0.0078269763 | ... AF31: =(AF23*AF27)/SUM(AF23*AF27,AF24) -> 0.0074383567
A32: Class 7-8 tractor truck percent of freight HDV VMT | C32: =1-C31 -> 0.99142537 | D32: =1-D31 -> 0.99161542 | E32: =1-E31 -> 0.99176657 | F32: =1-F31 -> 0.99188537 | G32: =1-G31 -> 0.99197815 | H32: =1-H31 -> 0.99205293 | I32: =1-I31 -> 0.99211696 | J32: =1-J31 -> 0.99217302 | ... AF32: =1-AF31 -> 0.99256164
A35: U.S. DOT Federal Highway Administration, Highway Statistics Table MV-10 - 2020
A36: Bus Registrations
A37: TOTAL BUSES
A39: TOTAL | B39: TOTAL
A40: SCHOOL | B40: NON-SCHOOL | C40: GRAND
B41: AND FEDERAL | C41: TOTAL
A43: 441729.58 | B43: 420505.55 | C43: 967456.95
A45: EPS Schedules
A46: Year | B46: 2020 | C46: 2021 | D46: 2022 | E46: 2023 | F46: 2024 | G46: 2025 | H46: 2026 | I46: 2027 | J46: 2028 | K46: 2029 | L46: 2030 | M46: 2031 | N46: 2032 | O46: 2033 | P46: 2034 | Q46: 2035 | R46: 2036 | S46: 2037 | T46: 2038 | U46: 2039 | V46: 2040 | W46: 2041 | X46: 2042 | Y46: 2043 | Z46: 2044 | AA46: 2045 | AB46: 2046 | AC46: 2047 | AD46: 2048 | AE46: 2049 | AF46: 2050
A47: passenger LDVs ACC I | B47: =B16 -> 0 | C47: =C16 -> 0 | D47: =D16 -> 0 | E47: =E16 -> 0 | F47: =F16 -> 0.08 | G47: =G16 -> 0.08 | H47: =H16 -> 0.08 | I47: =I16 -> 0.08 | ... AF47: =AF16 -> 0.08
A48: passenger LDVs ACC II | B48: =B17 -> 0 | C48: =C17 -> 0 | D48: =D17 -> 0 | E48: =E17 -> 0 | F48: =F17 -> 0.08 | G48: =G17 -> 0.08 | H48: =H17 -> 0.35 | I48: =I17 -> 0.43 | ... AF48: =AF17 -> 1
A49: passenger HDVs | B49: 0 | C49: 0 | D49: 0 | E49: 0 | F49: =($A$43*0+$B$43*F19)/($C$43) -> 0.039118536 | G49: =($A$43*0+$B$43*G19)/($C$43) -> 0.047811544 | H49: =($A$43*0+$B$43*H19)/($C$43) -> 0.056504552 | I49: =($A$43*0+$B$43*I19)/($C$43) -> 0.086930079 | J49: =($A$43*0+$B$43*J19)/($C$43) -> 0.13039512 | K49: =($A$43*0+$B$43*K19)/($C$43) -> 0.17386016 | L49: =($A$43*0+$B$43*L19)/($C$43) -> 0.2173252 | M49: =($A$43*0+$B$43*M19)/($C$43) -> 0.23905772 | ... AF49: =($A$43*0+$B$43*AF19)/($C$43) -> 0.3259878
A50: passenger motorbikes | B50: 0 | C50: 0 | D50: 0 | E50: 0 | F50: 0 | G50: 0 | H50: 0 | I50: 0 | J50: 0 | K50: 0 | L50: 0 | M50: 0 | N50: 0 | O50: 0 | P50: 0 | Q50: 0 | R50: 0 | S50: 0 | T50: 0 | U50: 0 | V50: 0 | W50: 0 | X50: 0 | Y50: 0 | Z50: 0 | AA50: 0 | AB50: 0 | AC50: 0 | AD50: 0 | AE50: 0 | AF50: 0
A51: freight LDVs | B51: 0 | C51: 0 | D51: 0 | E51: 0 | F51: =F18*F29+F19*F30 -> 0.060092351 | G51: =G18*G29+G19*G30 -> 0.080071705 | H51: =H18*H29+H19*H30 -> 0.10754676 | I51: =I18*I29+I19*I30 -> 0.16256128 | J51: =J18*J29+J19*J30 -> 0.22511404 | K51: =K18*K29+K19*K30 -> 0.28764856 | L51: =L18*L29+L19*L30 -> 0.35012393 | M51: =M18*M29+M19*M30 -> 0.40009158 | ... AF51: =AF18*AF29+AF19*AF30 -> 0.59999472
A52: freight HDVs | B52: 0 | C52: 0 | D52: 0 | E52: 0 | F52: =F19*F31+F20*F32 -> 0.050324585 | G52: =G19*G31+G20*G32 -> 0.070320874 | H52: =H19*H31+H20*H32 -> 0.10023841 | I52: =I19*I31+I20*I32 -> 0.15039415 | J52: =J19*J31+J20*J32 -> 0.2007827 | K52: =K19*K31+K20*K32 -> 0.25116641 | L52: =L19*L31+L20*L32 -> 0.30154674 | M52: =M19*M31+M20*M32 -> 0.35154017 | ... AF52: =AF19*AF31+AF20*AF32 -> 0.40260342
A53: freight motorbikes | B53: 0 | C53: 0 | D53: 0 | E53: 0 | F53: 0 | G53: 0 | H53: 0 | I53: 0 | J53: 0 | K53: 0 | L53: 0 | M53: 0 | N53: 0 | O53: 0 | P53: 0 | Q53: 0 | R53: 0 | S53: 0 | T53: 0 | U53: 0 | V53: 0 | W53: 0 | X53: 0 | Y53: 0 | Z53: 0 | AA53: 0 | AB53: 0 | AC53: 0 | AD53: 0 | AE53: 0 | AF53: 0

Sheet CA Standards and Followers
B1: 2020 | C1: 2021 | D1: 2022 | E1: 2023 | F1: 2024 | G1: 2025 | H1: 2026 | I1: 2027 | J1: 2028 | K1: 2029 | L1: 2030 | M1: 2031 | N1: 2032 | O1: 2033 | P1: 2034 | Q1: 2035 | R1: 2036 | S1: 2037 | T1: 2038 | U1: 2039 | V1: 2040 | W1: 2041 | X1: 2042 | Y1: 2043 | Z1: 2044 | AA1: 2045 | AB1: 2046 | AC1: 2047 | AD1: 2048 | AE1: 2049 | AF1: 2050
A2: passenger LDVs ACC I | B2: ='EPS Vehicle Class Mapping'!B47 -> 0 | C2: ='EPS Vehicle Class Mapping'!C47 -> 0 | D2: ='EPS Vehicle Class Mapping'!D47 -> 0 | E2: ='EPS Vehicle Class Mapping'!E47 -> 0 | F2: ='EPS Vehicle Class Mapping'!F47 -> 0.08 | G2: ='EPS Vehicle Class Mapping'!G47 -> 0.08 | H2: ='EPS Vehicle Class Mapping'!H47 -> 0.08 | I2: ='EPS Vehicle Class Mapping'!I47 -> 0.08 | ... AF2: ='EPS Vehicle Class Mapping'!AF47 -> 0.08
A3: passenger LDVs ACC II | B3: ='EPS Vehicle Class Mapping'!B48 -> 0 | C3: ='EPS Vehicle Class Mapping'!C48 -> 0 | D3: ='EPS Vehicle Class Mapping'!D48 -> 0 | E3: ='EPS Vehicle Class Mapping'!E48 -> 0 | F3: ='EPS Vehicle Class Mapping'!F48 -> 0.08 | G3: ='EPS Vehicle Class Mapping'!G48 -> 0.08 | H3: ='EPS Vehicle Class Mapping'!H48 -> 0.35 | I3: ='EPS Vehicle Class Mapping'!I48 -> 0.43 | ... AF3: ='EPS Vehicle Class Mapping'!AF48 -> 1
A4: passenger LDVs ACC II - CO | B4: =B3 -> 0 | C4: =C3 -> 0 | D4: =D3 -> 0 | E4: =E3 -> 0 | F4: =F3 -> 0.08 | G4: =G3 -> 0.08 | H4: =H3 -> 0.35 | I4: =I3 -> 0.43 | ... N4: =N3 -> 0.82 | O4: =$N$4 -> 0.82 | P4: =$N$4 -> 0.82 | Q4: =$N$4 -> 0.82 | R4: =$N$4 -> 0.82 | S4: =$N$4 -> 0.82 | T4: =$N$4 -> 0.82 | U4: =$N$4 -> 0.82 | V4: =$N$4 -> 0.82 | ... AF4: =$N$4 -> 0.82
A5: passenger HDVs | B5: ='EPS Vehicle Class Mapping'!B49 -> 0 | C5: ='EPS Vehicle Class Mapping'!C49 -> 0 | D5: ='EPS Vehicle Class Mapping'!D49 -> 0 | E5: ='EPS Vehicle Class Mapping'!E49 -> 0 | F5: ='EPS Vehicle Class Mapping'!F49 -> 0.039118536 | G5: ='EPS Vehicle Class Mapping'!G49 -> 0.047811544 | H5: ='EPS Vehicle Class Mapping'!H49 -> 0.056504552 | I5: ='EPS Vehicle Class Mapping'!I49 -> 0.086930079 | ... AF5: ='EPS Vehicle Class Mapping'!AF49 -> 0.3259878
A6: passenger motorbikes | B6: ='EPS Vehicle Class Mapping'!B50 -> 0 | C6: ='EPS Vehicle Class Mapping'!C50 -> 0 | D6: ='EPS Vehicle Class Mapping'!D50 -> 0 | E6: ='EPS Vehicle Class Mapping'!E50 -> 0 | F6: ='EPS Vehicle Class Mapping'!F50 -> 0 | G6: ='EPS Vehicle Class Mapping'!G50 -> 0 | H6: ='EPS Vehicle Class Mapping'!H50 -> 0 | I6: ='EPS Vehicle Class Mapping'!I50 -> 0 | ... AF6: ='EPS Vehicle Class Mapping'!AF50 -> 0
A7: freight LDVs | B7: ='EPS Vehicle Class Mapping'!B51 -> 0 | C7: ='EPS Vehicle Class Mapping'!C51 -> 0 | D7: ='EPS Vehicle Class Mapping'!D51 -> 0 | E7: ='EPS Vehicle Class Mapping'!E51 -> 0 | F7: ='EPS Vehicle Class Mapping'!F51 -> 0.060092351 | G7: ='EPS Vehicle Class Mapping'!G51 -> 0.080071705 | H7: ='EPS Vehicle Class Mapping'!H51 -> 0.10754676 | I7: ='EPS Vehicle Class Mapping'!I51 -> 0.16256128 | ... AF7: ='EPS Vehicle Class Mapping'!AF51 -> 0.59999472
A8: freight HDVs | B8: ='EPS Vehicle Class Mapping'!B52 -> 0 | C8: ='EPS Vehicle Class Mapping'!C52 -> 0 | D8: ='EPS Vehicle Class Mapping'!D52 -> 0 | E8: ='EPS Vehicle Class Mapping'!E52 -> 0 | F8: ='EPS Vehicle Class Mapping'!F52 -> 0.050324585 | G8: ='EPS Vehicle Class Mapping'!G52 -> 0.070320874 | H8: ='EPS Vehicle Class Mapping'!H52 -> 0.10023841 | I8: ='EPS Vehicle Class Mapping'!I52 -> 0.15039415 | ... AF8: ='EPS Vehicle Class Mapping'!AF52 -> 0.40260342
A9: freight motorbikes | B9: ='EPS Vehicle Class Mapping'!B53 -> 0 | C9: ='EPS Vehicle Class Mapping'!C53 -> 0 | D9: ='EPS Vehicle Class Mapping'!D53 -> 0 | E9: ='EPS Vehicle Class Mapping'!E53 -> 0 | F9: ='EPS Vehicle Class Mapping'!F53 -> 0 | G9: ='EPS Vehicle Class Mapping'!G53 -> 0 | H9: ='EPS Vehicle Class Mapping'!H53 -> 0 | I9: ='EPS Vehicle Class Mapping'!I53 -> 0 | ... AF9: ='EPS Vehicle Class Mapping'!AF53 -> 0
A12: use '1' to indicate that the state follows the rule | B12: Calibration Values for EPA LDV Stds Applied? | C12: Calibration Values for EPA HDV Stds Applied? | D12: Does this state follow: | G12: What model year does this state begin regulating:
D13: ACC I | E13: ACC II | F13: ACT | G13: ACC I Cars | H13: ACC II Cars | I13: Trucks
A14: Alabama | B14: =IF(E14>0,0,1) -> 1 | C14: =IF(F14=0,1) -> 1 | D14: 0 | E14: 0 | F14: 0
A15: Alaska | B15: =IF(E15>0,0,1) -> 1 | C15: =IF(F15=0,1) -> 1 | D15: 0 | E15: 0 | F15: 0
A16: Arizona | B16: =IF(E16>0,0,1) -> 1 | C16: =IF(F16=0,1) -> 1 | D16: 0 | E16: 0 | F16: 0
A17: Arkansas | B17: =IF(E17>0,0,1) -> 1 | C17: =IF(F17=0,1) -> 1 | D17: 0 | E17: 0 | F17: 0
A18: California | B18: =IF(E18>0,0,1) -> 1 | C18: =IF(F18=0,1) -> FALSE | D18: 1 | E18: 0 | F18: 1 | G18: 1990 | H18: 2026 | I18: 2024
A19: Colorado | B19: =IF(E19>0,0,1) -> 1 | C19: =IF(F19=0,1) -> FALSE | D19: 1 | E19: 0 | F19: 1 | G19: 2023 | H19: 2026 | I19: 2027
A20: Connecticut | B20: =IF(E20>0,0,1) -> 1 | C20: =IF(F20=0,1) -> 1 | D20: 1 | E20: 0 | F20: 0 | G20: 2008
A21: Delaware | B21: =IF(E21>0,0,1) -> 1 | C21: =IF(F21=0,1) -> 1 | D21: 0 | E21: 0 | F21: 0 | H21: 2026
A22: District of Columbia | B22: =IF(E22>0,0,1) -> 1 | C22: =IF(F22=0,1) -> 1 | D22: 0 | E22: 0 | F22: 0 | H22: 2026
A23: Florida | B23: =IF(E23>0,0,1) -> 1 | C23: =IF(F23=0,1) -> 1 | D23: 0 | E23: 0 | F23: 0
A24: Georgia | B24: =IF(E24>0,0,1) -> 1 | C24: =IF(F24=0,1) -> 1 | D24: 0 | E24: 0 | F24: 0
A25: Hawaii | B25: =IF(E25>0,0,1) -> 1 | C25: =IF(F25=0,1) -> 1 | D25: 0 | E25: 0 | F25: 0
A26: Idaho | B26: =IF(E26>0,0,1) -> 1 | C26: =IF(F26=0,1) -> 1 | D26: 0 | E26: 0 | F26: 0
A27: Illinois | B27: =IF(E27>0,0,1) -> 1 | C27: =IF(F27=0,1) -> 1 | D27: 0 | E27: 0 | F27: 0
A28: Indiana | B28: =IF(E28>0,0,1) -> 1 | C28: =IF(F28=0,1) -> 1 | D28: 0 | E28: 0 | F28: 0
A29: Iowa | B29: =IF(E29>0,0,1) -> 1 | C29: =IF(F29=0,1) -> 1 | D29: 0 | E29: 0 | F29: 0
A30: Kansas | B30: =IF(E30>0,0,1) -> 1 | C30: =IF(F30=0,1) -> 1 | D30: 0 | E30: 0 | F30: 0
A31: Kentucky | B31: =IF(E31>0,0,1) -> 1 | C31: =IF(F31=0,1) -> 1 | D31: 0 | E31: 0 | F31: 0
A32: Louisiana | B32: =IF(E32>0,0,1) -> 1 | C32: =IF(F32=0,1) -> 1 | D32: 0 | E32: 0 | F32: 0
A33: Maine | B33: =IF(E33>0,0,1) -> 1 | C33: =IF(F33=0,1) -> 1 | D33: 1 | E33: 0 | F33: 0 | G33: 2001
A34: Maryland | B34: =IF(E34>0,0,1) -> 1 | C34: =IF(F34=0,1) -> FALSE | D34: 1 | E34: 0 | F34: 1 | G34: 2011 | H34: 2026 | I34: 2027
A35: Massachusetts | B35: =IF(E35>0,0,1) -> 1 | C35: =IF(F35=0,1) -> FALSE | D35: 1 | E35: 0 | F35: 1 | G35: 1995 | H35: 2026 | I35: 2025
A36: Michigan | B36: =IF(E36>0,0,1) -> 1 | C36: =IF(F36=0,1) -> 1 | D36: 0 | E36: 0 | F36: 0
A37: Minnesota | B37: =IF(E37>0,0,1) -> 1 | C37: =IF(F37=0,1) -> 1 | D37: 1 | E37: 0 | F37: 0 | G37: 2025
A38: Mississippi | B38: =IF(E38>0,0,1) -> 1 | C38: =IF(F38=0,1) -> 1 | D38: 0 | E38: 0 | F38: 0
A39: Missouri | B39: =IF(E39>0,0,1) -> 1 | C39: =IF(F39=0,1) -> 1 | D39: 0 | E39: 0 | F39: 0
A40: Montana | B40: =IF(E40>0,0,1) -> 1 | C40: =IF(F40=0,1) -> 1 | D40: 0 | E40: 0 | F40: 0
A41: Nebraska | B41: =IF(E41>0,0,1) -> 1 | C41: =IF(F41=0,1) -> 1 | D41: 0 | E41: 0 | F41: 0
A42: Nevada | B42: =IF(E42>0,0,1) -> 1 | C42: =IF(F42=0,1) -> 1 | D42: 1 | E42: 0 | F42: 0 | G42: 2025
A43: New Hampshire | B43: =IF(E43>0,0,1) -> 1 | C43: =IF(F43=0,1) -> 1 | D43: 0 | E43: 0 | F43: 0
A44: New Jersey | B44: =IF(E44>0,0,1) -> 1 | C44: =IF(F44=0,1) -> FALSE | D44: 1 | E44: 0 | F44: 1 | G44: 2009 | H44: 2026 | I44: 2025
A45: New Mexico | B45: =IF(E45>0,0,1) -> 1 | C45: =IF(F45=0,1) -> FALSE | D45: 1 | E45: 0 | F45: 1 | G45: 2026 | H45: 2026 | I45: 2027
A46: New York | B46: =IF(E46>0,0,1) -> 1 | C46: =IF(F46=0,1) -> FALSE | D46: 1 | E46: 0 | F46: 1 | G46: 1993 | H46: 2026 | I46: 2025
A47: North Carolina | B47: =IF(E47>0,0,1) -> 1 | C47: =IF(F47=0,1) -> 1 | D47: 0 | E47: 0 | F47: 0
A48: North Dakota | B48: =IF(E48>0,0,1) -> 1 | C48: =IF(F48=0,1) -> 1 | D48: 0 | E48: 0 | F48: 0
A49: Ohio | B49: =IF(E49>0,0,1) -> 1 | C49: =IF(F49=0,1) -> 1 | D49: 0 | E49: 0 | F49: 0
A50: Oklahoma | B50: =IF(E50>0,0,1) -> 1 | C50: =IF(F50=0,1) -> 1 | D50: 0 | E50: 0 | F50: 0
A51: Oregon | B51: =IF(E51>0,0,1) -> 1 | C51: =IF(F51=0,1) -> FALSE | D51: 1 | E51: 0 | F51: 1 | G51: 2009 | H51: 2026 | I51: 2024
A52: Pennsylvania | B52: =IF(E52>0,0,1) -> 1 | C52: =IF(F52=0,1) -> 1 | D52: 0 | E52: 0 | F52: 0
A53: Rhode Island | B53: =IF(E53>0,0,1) -> 1 | C53: =IF(F53=0,1) -> FALSE | D53: 1 | E53: 0 | F53: 1 | G53: 2008 | H53: 2026 | I53: 2027
A54: South Carolina | B54: =IF(E54>0,0,1) -> 1 | C54: =IF(F54=0,1) -> 1 | D54: 0 | E54: 0 | F54: 0
A55: South Dakota | B55: =IF(E55>0,0,1) -> 1 | C55: =IF(F55=0,1) -> 1 | D55: 0 | E55: 0 | F55: 0
A56: Tennessee | B56: =IF(E56>0,0,1) -> 1 | C56: =IF(F56=0,1) -> 1 | D56: 0 | E56: 0 | F56: 0
A57: Texas | B57: =IF(E57>0,0,1) -> 1 | C57: =IF(F57=0,1) -> 1 | D57: 0 | E57: 0 | F57: 0
A58: Utah | B58: =IF(E58>0,0,1) -> 1 | C58: =IF(F58=0,1) -> 1 | D58: 0 | E58: 0 | F58: 0
A59: Vermont | B59: =IF(E59>0,0,1) -> 1 | C59: =IF(F59=0,1) -> FALSE | D59: 1 | E59: 0 | F59: 1 | G59: 2000 | H59: 2026 | I59: 2025
A60: Virginia | B60: =IF(E60>0,0,1) -> 1 | C60: =IF(F60=0,1) -> 1 | D60: 1 | E60: 0 | F60: 0 | G60: 2025 | H60: 2026
A61: Washington | B61: =IF(E61>0,0,1) -> 1 | C61: =IF(F61=0,1) -> FALSE | D61: 1 | E61: 0 | F61: 1 | G61: 2025 | H61: 2026 | I61: 2025
A62: West Virginia | B62: =IF(E62>0,0,1) -> 1 | C62: =IF(F62=0,1) -> 1 | D62: 0 | E62: 0 | F62: 0
A63: Wisconsin | B63: =IF(E63>0,0,1) -> 1 | C63: =IF(F63=0,1) -> 1 | D63: 0 | E63: 0 | F63: 0
A64: Wyoming | B64: =IF(E64>0,0,1) -> 1 | C64: =IF(F64=0,1) -> 1 | D64: 0 | E64: 0 | F64: 0
A65: subregion52 | B65: =IF(E65>0,0,1) -> 1 | C65: =IF(F65=0,1) -> 1 | D65: 0 | E65: 0 | F65: 0
A66: subregion53 | B66: =IF(E66>0,0,1) -> 1 | C66: =IF(F66=0,1) -> 1 | D66: 0 | E66: 0 | F66: 0
A67: subregion54 | B67: =IF(E67>0,0,1) -> 1 | C67: =IF(F67=0,1) -> 1 | D67: 0 | E67: 0 | F67: 0
A68: subregion55 | B68: =IF(E68>0,0,1) -> 1 | C68: =IF(F68=0,1) -> 1 | D68: 0 | E68: 0 | F68: 0
A69: subregion56 | B69: =IF(E69>0,0,1) -> 1 | C69: =IF(F69=0,1) -> 1 | D69: 0 | E69: 0 | F69: 0
A70: subregion57 | B70: =IF(E70>0,0,1) -> 1 | C70: =IF(F70=0,1) -> 1 | D70: 0 | E70: 0 | F70: 0
A71: subregion58 | B71: =IF(E71>0,0,1) -> 1 | C71: =IF(F71=0,1) -> 1 | D71: 0 | E71: 0 | F71: 0
A72: subregion59 | B72: =IF(E72>0,0,1) -> 1 | C72: =IF(F72=0,1) -> 1 | D72: 0 | E72: 0 | F72: 0
A73: subregion60 | B73: =IF(E73>0,0,1) -> 1 | C73: =IF(F73=0,1) -> 1 | D73: 0 | E73: 0 | F73: 0

Sheet AEO Table 7
B1: ref2023.d020623a | C1: 2022 | D1: 2023 | E1: 2024 | F1: 2025 | G1: 2026 | H1: 2027 | I1: 2028 | J1: 2029 | K1: 2030 | L1: 2031 | M1: 2032 | N1: 2033 | O1: 2034 | P1: 2035 | Q1: 2036 | R1: 2037 | S1: 2038 | T1: 2039 | U1: 2040 | V1: 2041 | W1: 2042 | X1: 2043 | Y1: 2044 | Z1: 2045 | AA1: 2046 | AB1: 2047 | AC1: 2048 | AD1: 2049 | AE1: 2050
C3: Report | D3: Annual Energy Outlook 2023
C4: Scenario | D4: ref2023 | G4: Reference
C5: Datekey | D5: d020623a
C6: Release Date | E6: March 2023
A10: TKI000 | B10: 7. Transportation Sector Key Indicators and Delivered Energy Consumption | AF10: Average
AF11: Annual
AF12: Change
B13: Key Indicators and Consumption | C13: 2022 | D13: 2023 | E13: 2024 | F13: 2025 | G13: 2026 | H13: 2027 | I13: 2028 | J13: 2029 | K13: 2030 | L13: 2031 | M13: 2032 | N13: 2033 | O13: 2034 | P13: 2035 | Q13: 2036 | R13: 2037 | S13: 2038 | T13: 2039 | U13: 2040 | V13: 2041 | W13: 2042 | X13: 2043 | Y13: 2044 | Z13: 2045 | AA13: 2046 | AB13: 2047 | AC13: 2048 | AD13: 2049 | AE13: 2050 | AF13: 2022–2050
B15: Key Indicators
B16: Travel Indicators
B17: (billion vehicle miles traveled)
A18: TKI000:ba_Light-DutyVeh | B18: Light-Duty Vehicles less than 8,501 pounds | C18: 2843.2981 | D18: 2901.3589 | E18: 2922.5066 | F18: 2933.3601 | G18: 2954.238 | H18: 2981.9343 | I18: 3007.5581 | J18: 3027.573 | K18: 3042.8433 | L18: 3055.7747 | M18: 3066.6516 | N18: 3082.3594 | O18: 3102.4182 | P18: 3120.7375 | Q18: 3135.6208 | R18: 3152.9177 | S18: 3172.4355 | T18: 3192.1006 | U18: 3214.563 | V18: 3237.5806 | W18: 3261.5847 | X18: 3284.8975 | Y18: 3309.0391 | Z18: 3334.7034 | AA18: 3364.5225 | AB18: 3396.5352 | AC18: 3429.5627 | AD18: 3463.0249 | AE18: 3499.543 | AF18: 0.007444
A19: TKI000:ba_CommercialLig | B19: Commercial Light Trucks 1/ | C19: 102.21495 | D19: 103.34346 | E19: 103.55378 | F19: 104.36999 | G19: 105.65627 | H19: 107.00255 | I19: 108.20406 | J19: 109.32984 | K19: 110.21457 | L19: 111.0637 | M19: 112.17591 | N19: 113.26731 | O19: 114.36133 | P19: 115.53986 | Q19: 116.6934 | R19: 117.93478 | S19: 119.26325 | T19: 120.51714 | U19: 121.9657 | V19: 123.54321 | W19: 125.05544 | X19: 126.4902 | Y19: 127.8319 | Z19: 129.14803 | AA19: 130.64792 | AB19: 132.25534 | AC19: 133.71924 | AD19: 135.16911 | AE19: 137.06503 | AF19: 0.010533
A20: TKI000:ba_FreightTrucks | B20: Freight Trucks greater than 10,000 pounds | C20: 321.95499 | D20: 320.72061 | E20: 321.15665 | F20: 324.03918 | G20: 328.45148 | H20: 332.31928 | I20: 335.87875 | J20: 338.621 | K20: 341.15326 | L20: 344.16229 | M20: 348.16583 | N20: 351.54123 | O20: 354.83011 | P20: 358.3447 | Q20: 361.39355 | R20: 364.92679 | S20: 368.38065 | T20: 371.81143 | U20: 375.58807 | V20: 379.58752 | W20: 383.51465 | X20: 387.20883 | Y20: 390.63339 | Z20: 393.83795 | AA20: 397.54263 | AB20: 401.35467 | AC20: 404.65982 | AD20: 408.22446 | AE20: 413.08252 | AF20: 0.008941
B21: (billion passenger miles traveled)
A22: TKI000:buspassmiles | B22: Bus Transportation | C22: 175.47365 | D22: 186.88329 | E22: 193.3692 | F22: 197.39229 | G22: 200.32752 | H22: 202.52968 | I22: 204.21141 | J22: 205.46838 | K22: 206.39357 | L22: 207.0294 | M22: 207.54085 | N22: 207.99565 | O22: 208.43976 | P22: 208.79684 | Q22: 209.10339 | R22: 209.37013 | S22: 209.49379 | T22: 209.54416 | U22: 209.54358 | V22: 209.49118 | W22: 209.41185 | X22: 209.25844 | Y22: 209.10913 | Z22: 208.93102 | AA22: 208.81189 | AB22: 208.60612 | AC22: 208.41769 | AD22: 208.19235 | AE22: 207.99593 | AF22: 0.006091
A23: TKI000:railpassmiles | B23: Passenger Rail | C23: 30.144947 | D23: 32.030231 | E23: 33.06411 | F23: 33.706196 | G23: 34.620327 | H23: 35.443916 | I23: 36.137474 | J23: 36.650322 | K23: 37.00806 | L23: 37.264553 | M23: 37.633518 | N23: 38.06789 | O23: 38.564194 | P23: 38.985653 | Q23: 39.398945 | R23: 39.809189 | S23: 40.237045 | T23: 40.652229 | U23: 41.127975 | V23: 41.567631 | W23: 42.019573 | X23: 42.40731 | Y23: 42.842342 | Z23: 43.266335 | AA23: 43.867863 | AB23: 44.361511 | AC23: 44.905075 | AD23: 45.395485 | AE23: 46.002594 | AF23: 0.01521
B24: (billion seat miles available)
A25: TKI000:ba_Air | B25: Air | C25: 1173.0347 | D25: 1318.6946 | E25: 1361.6111 | F25: 1371.6552 | G25: 1402.928 | H25: 1433.8398 | I25: 1461.4722 | J25: 1484.8291 | K25: 1504.2688 | L25: 1524.7269 | M25: 1552.2568 | N25: 1583.9248 | O25: 1615.3802 | P25: 1647.3462 | Q25: 1682.5896 | R25: 1721.0469 | S25: 1761.139 | T25: 1801.941 | U25: 1848.072 | V25: 1894.2041 | W25: 1941.463 | X25: 1990.3643 | Y25: 2038.4374 | Z25: 2085.6875 | AA25: 2134.0049 | AB25: 2185.897 | AC25: 2238.8362 | AD25: 2292.3555 | AE25: 2350.269 | AF25: 0.02513
B26: (billion ton miles traveled)
A27: TKI000:ba_Rail | B27: Rail | C27: 1620.4949 | D27: 1600.1008 | E27: 1666.9198 | F27: 1628.4084 | G27: 1561.4207 | H27: 1509.6494 | I27: 1489.7312 | J27: 1507.5151 | K27: 1500.1649 | L27: 1506.9524 | M27: 1522.1982 | N27: 1534.7394 | O27: 1543.2374 | P27: 1554.5907 | Q27: 1557.5254 | R27: 1562.4816 | S27: 1568.9661 | T27: 1568.3395 | U27: 1571.7775 | V27: 1585.6112 | W27: 1597.307 | X27: 1600.1909 | Y27: 1601.8328 | Z27: 1602.9988 | AA27: 1608.1294 | AB27: 1618.0824 | AC27: 1630.808 | AD27: 1636.8905 | AE27: 1649.4695 | AF27: 0.000633
A28: TKI000:ba_DomesticShipp | B28: Domestic Shipping | C28: 444.89887 | D28: 450.42761 | E28: 448.61005 | F28: 446.74628 | G28: 445.22772 | H28: 442.84778 | I28: 440.43005 | J28: 437.0246 | K28: 434.03641 | L28: 431.39212 | M28: 429.99737 | N28: 428.16068 | O28: 426.27862 | P28: 424.17816 | Q28: 421.71698 | R28: 419.81464 | S28: 417.56705 | T28: 415.80768 | U28: 414.04514 | V28: 412.52209 | W28: 411.24774 | X28: 409.97736 | Y28: 408.52225 | Z28: 406.63034 | AA28: 405.35852 | AB28: 403.86591 | AC28: 401.97906 | AD28: 400.55664 | AE28: 400.09833 | AF28: -0.003783
B30: Energy Efficiency Indicators
B31: (miles per gallon)
A32: TKI000:ca_AvgCAFEStand | B32: New Light-Duty Vehicle CAFE Standard 2/ | C32: 35.855949 | D32: 36.277985 | E32: 39.337013 | F32: 42.578201 | G32: 47.262627 | H32: 47.227249 | I32: 47.18121 | J32: 47.168774 | K32: 47.163849 | L32: 47.152081 | M32: 47.159279 | N32: 47.152672 | O32: 47.146118 | P32: 47.131687 | Q32: 47.138325 | R32: 47.119869 | S32: 47.100937 | T32: 47.084251 | U32: 47.059879 | V32: 47.032314 | W32: 47.004074 | X32: 46.960155 | Y32: 46.939564 | Z32: 46.91069 | AA32: 46.948238 | AB32: 46.913113 | AC32: 46.90683 | AD32: 46.880138 | AE32: 46.870857 | AF32: 0.009613
A33: TKI000:ca_CarCAFEStand | B33: New Car 2/ | C33: 45.004654 | D33: 45.471119 | E33: 49.460312 | F33: 53.789036 | G33: 59.791531 | H33: 59.80352 | I33: 59.817413 | J33: 59.819332 | K33: 59.821598 | L33: 59.822445 | M33: 59.827473 | N33: 59.828793 | O33: 59.83078 | P33: 59.83112 | Q33: 59.842136 | R33: 59.842136 | S33: 59.842136 | T33: 59.843197 | U33: 59.843197 | V33: 59.843231 | W33: 59.845177 | X33: 59.845177 | Y33: 59.848228 | Z33: 59.848228 | AA33: 59.867775 | AB33: 59.867775 | AC33: 59.867775 | AD33: 59.867775 | AE33: 59.867775 | AF33: 0.010244
A34: TKI000:ca_TwukCAFEStand | B34: New Light Truck 2/ | C34: 32.047302 | D34: 32.608868 | E34: 35.403008 | F34: 38.46349 | G34: 42.755749 | H34: 42.75658 | I34: 42.76173 | J34: 42.76173 | K34: 42.761841 | L34: 42.762085 | M34: 42.762169 | N34: 42.76236 | O34: 42.76239 | P34: 42.76252 | Q34: 42.762554 | R34: 42.762699 | S34: 42.762756 | T34: 42.762825 | U34: 42.762897 | V34: 42.762962 | W34: 42.763016 | X34: 42.763103 | Y34: 42.763103 | Z34: 42.763184 | AA34: 42.763184 | AB34: 42.763294 | AC34: 42.763294 | AD34: 42.763393 | AE34: 42.763393 | AF34: 0.010356
A35: TKI000:ca_NewVehCred | B35: Compliance New Light-Duty Vehicle 3/ | C35: 41.802036 | D35: 43.2672 | E35: 44.448151 | F35: 47.052715 | G35: 48.571758 | H35: 49.79253 | I35: 52.281479 | J35: 53.248959 | K35: 53.962006 | L35: 54.332035 | M35: 54.872646 | N35: 55.329353 | O35: 55.771633 | P35: 56.242725 | Q35: 56.632603 | R35: 56.856194 | S35: 57.030457 | T35: 57.310715 | U35: 57.240421 | V35: 57.306023 | W35: 57.371868 | X35: 57.326744 | Y35: 57.237999 | Z35: 57.125122 | AA35: 57.475964 | AB35: 57.327747 | AC35: 57.273457 | AD35: 57.524818 | AE35: 57.479156 | AF35: 0.011439
A36: TKI000:ca_NewCarCred | B36: New Car 3/ | C36: 56.582645 | D36: 58.322227 | E36: 59.783314 | F36: 64.222374 | G36: 65.997482 | H36: 68.148636 | I36: 72.759445 | J36: 74.876167 | K36: 76.446304 | L36: 77.157303 | M36: 78.145363 | N36: 78.735664 | O36: 79.269257 | P36: 79.864815 | Q36: 80.311752 | R36: 80.510567 | S36: 80.643074 | T36: 81.042244 | U36: 80.790894 | V36: 80.999863 | W36: 81.213394 | X36: 81.251564 | Y36: 81.126785 | Z36: 80.963654 | AA36: 81.962257 | AB36: 81.685669 | AC36: 81.57402 | AD36: 82.338425 | AE36: 82.243484 | AF36: 0.013446
A37: TKI000:ca_NewTwukCred | B37: New Light Truck 3/ | C37: 36.263931 | D37: 37.832123 | E37: 39.014805 | F37: 41.375153 | G37: 42.876762 | H37: 43.911583 | I37: 45.953789 | J37: 46.678478 | K37: 47.207012 | L37: 47.518375 | M37: 47.939487 | N37: 48.362621 | O37: 48.779861 | P37: 49.233047 | Q37: 49.585567 | R37: 49.838345 | S37: 50.048077 | T37: 50.325745 | U37: 50.338009 | V37: 50.426777 | W37: 50.517311 | X37: 50.542614 | Y37: 50.50412 | Z37: 50.459385 | AA37: 50.61805 | AB37: 50.565735 | AC37: 50.535652 | AD37: 50.739391 | AE37: 50.721836 | AF37: 0.012055
A38: TKI000:ca_TestedNewVeh | B38: Tested New Light-Duty Vehicle 4/ | C38: 37.621078 | D38: 38.382416 | E38: 39.075672 | F38: 40.794502 | G38: 41.684994 | H38: 42.387779 | I38: 43.992405 | J38: 44.482399 | K38: 44.828846 | L38: 45.012852 | M38: 45.295109 | N38: 45.54966 | O38: 45.800465 | P38: 46.072914 | Q38: 46.308186 | R38: 46.454895 | S38: 46.573441 | T38: 46.763412 | U38: 46.743324 | V38: 46.781216 | W38: 46.812752 | X38: 46.781078 | Y38: 46.720787 | Z38: 46.649311 | AA38: 46.812588 | AB38: 46.721981 | AC38: 46.686661 | AD38: 46.844208 | AE38: 46.809135 | AF38: 0.007835
A39: TKI000:ca_TestedNewCar | B39: New Car 4/ | C39: 49.658657 | D39: 50.63982 | E39: 51.418789 | F39: 54.041267 | G39: 54.808311 | H39: 55.812794 | I39: 58.414131 | J39: 59.295654 | K39: 59.885937 | L39: 60.128426 | M39: 60.482559 | N39: 60.696911 | O39: 60.896141 | P39: 61.139969 | Q39: 61.34211 | R39: 61.456459 | S39: 61.54549 | T39: 61.791069 | U39: 61.720493 | V39: 61.820892 | W39: 61.909645 | X39: 61.923454 | Y39: 61.848679 | Z39: 61.762375 | AA39: 62.120819 | AB39: 61.989952 | AC39: 61.932671 | AD39: 62.331699 | AE39: 62.272804 | AF39: 0.008117
A40: TKI000:ca_TestedNewTwuk | B40: New Light Truck 4/ | C40: 32.951321 | D40: 33.82571 | E40: 34.570251 | F40: 36.235542 | G40: 37.203815 | H40: 37.859802 | I40: 39.251301 | J40: 39.65464 | K40: 39.942871 | L40: 40.123779 | M40: 40.372108 | N40: 40.635685 | O40: 40.898228 | P40: 41.187042 | Q40: 41.415565 | R40: 41.589336 | S40: 41.735809 | T40: 41.930031 | U40: 41.954327 | V40: 42.014381 | W40: 42.070942 | X40: 42.089371 | Y40: 42.062252 | Z40: 42.034523 | AA40: 42.106945 | AB40: 42.074627 | AC40: 42.053329 | AD40: 42.192116 | AE40: 42.17543 | AF40: 0.008853
A41: TKI000:ca_OnRoadNewVeh | B41: On-Road New Light-Duty Vehicle 5/ | C41: 30.687853 | D41: 31.308468 | E41: 31.873775 | F41: 33.275242 | G41: 34.001518 | H41: 34.574638 | I41: 35.883228 | J41: 36.28281 | K41: 36.56535 | L41: 36.715401 | M41: 36.945652 | N41: 37.153278 | O41: 37.357868 | P41: 37.580082 | Q41: 37.772026 | R41: 37.891651 | S41: 37.988308 | T41: 38.143211 | U41: 38.126759 | V41: 38.157574 | W41: 38.183201 | X41: 38.157219 | Y41: 38.107975 | Z41: 38.049587 | AA41: 38.182838 | AB41: 38.108822 | AC41: 38.080002 | AD41: 38.208389 | AE41: 38.179749 | AF41: 0.007832
A42: TKI000:ca_OnRoadNewCar | B42: New Car 5/ | C42: 40.552002 | D42: 41.353237 | E42: 41.989353 | F42: 44.130909 | G42: 44.75729 | H42: 45.577564 | I42: 47.701855 | J42: 48.421719 | K42: 48.903755 | L42: 49.101772 | M42: 49.390965 | N42: 49.566006 | O42: 49.728703 | P42: 49.927814 | Q42: 50.092888 | R42: 50.186264 | S42: 50.258968 | T42: 50.459515 | U42: 50.401878 | V42: 50.483868 | W42: 50.556343 | X42: 50.567619 | Y42: 50.506557 | Z42: 50.436081 | AA42: 50.72879 | AB42: 50.621925 | AC42: 50.575146 | AD42: 50.901001 | AE42: 50.852905 | AF42: 0.008117
A43: TKI000:ca_OnRoadNewTwuk | B43: New Light Truck 5/ | C43: 26.867123 | D43: 27.580063 | E43: 28.18713 | F43: 29.544939 | G43: 30.334429 | H43: 30.869291 | I43: 32.00386 | J43: 32.332729 | K43: 32.567738 | L43: 32.715244 | M43: 32.917721 | N43: 33.132629 | O43: 33.346695 | P43: 33.582184 | Q43: 33.768513 | R43: 33.910198 | S43: 34.029625 | T43: 34.187984 | U43: 34.207794 | V43: 34.25676 | W43: 34.302879 | X43: 34.317905 | Y43: 34.295792 | Z43: 34.273186 | AA43: 34.332233 | AB43: 34.305882 | AC43: 34.288517 | AD43: 34.40168 | AE43: 34.388073 | AF43: 0.008853
... A47: TKI000:ca_FreightTruck | B47: Freight Truck | C47: 7.472406 | D47: 7.578529 | E47: 7.705323 | F47: 7.84859 | G47: 8.002383 | H47: 8.163677 | I47: 8.321285 | J47: 8.479755 | K47: 8.638294 | L47: 8.79593 | M47: 8.948549 | N47: 9.090997 | O47: 9.222516 | P47: 9.343068 | Q47: 9.453315 | R47: 9.553063 | S47: 9.643444 | T47: 9.72671 | U47: 9.804593 | V47: 9.877275 | W47: 9.942431 | X47: 10.001567 | Y47: 10.055841 | Z47: 10.108454 | AA47: 10.161228 | AB47: 10.213311 | AC47: 10.263764 | AD47: 10.314513 | AE47: 10.365861 | AF47: 0.011758
B48: (seat miles per gallon)
A49: TKI000:ca_Aircraft | B49: Aircraft | C49: 72.717087 | D49: 73.091972 | E49: 73.492531 | F49: 74.018456 | G49: 74.683121 | H49: 75.131767 | I49: 75.59214 | J49: 76.024017 | K49: 76.492363 | L49: 77.014214 | M49: 77.60096 | N49: 78.266678 | O49: 78.981506 | P49: 79.730591 | Q49: 80.48922 | R49: 81.260979 | S49: 82.048454 | T49: 82.814575 | U49: 83.594772 | V49: 84.382309 | W49: 85.171204 | X49: 85.974022 | Y49: 86.764038 | Z49: 87.549927 | AA49: 88.321091 | AB49: 89.091156 | AC49: 89.849762 | AD49: 90.593376 | AE49: 91.328148 | AF49: 0.008172
B50: (ton miles/thousand Btu)
A51: TKI000:ca_Rail | B51: Rail | C51: 3.36634 | D51: 3.369893 | E51: 3.37345 | F51: 3.37701 | G51: 3.380574 | H51: 3.384142 | I51: 3.387713 | J51: 3.391289 | K51: 3.394868 | L51: 3.398451 | M51: 3.402037 | N51: 3.405628 | O51: 3.409222 | P51: 3.41282 | Q51: 3.416422 | R51: 3.420027 | S51: 3.423637 | T51: 3.42725 | U51: 3.430867 | V51: 3.434488 | W51: 3.438113 | X51: 3.441741 | Y51: 3.445373 | Z51: 3.44901 | AA51: 3.452649 | AB51: 3.456293 | AC51: 3.459941 | AD51: 3.463593 | AE51: 3.467248 | AF51: 0.001055
A52: TKI000:ca_DomesticShipp | B52: Domestic Shipping | C52: 4.820226 | D52: 4.838966 | E52: 4.857779 | F52: 4.876665 | G52: 4.895624 | H52: 4.914657 | I52: 4.933764 | J52: 4.952945 | K52: 4.9722 | L52: 4.991531 | M52: 5.010937 | N52: 5.030418 | O52: 5.049975 | P52: 5.069608 | Q52: 5.089317 | R52: 5.109103 | S52: 5.128966 | T52: 5.148906 | U52: 5.168923 | V52: 5.189019 | W52: 5.209192 | X52: 5.229445 | Y52: 5.249775 | Z52: 5.270185 | AA52: 5.290674 | AB52: 5.311243 | AC52: 5.331892 | AD52: 5.352621 | AE52: 5.37343 | AF52: 0.003888
B54: Energy Use by Mode
B55: (quadrillion Btu)
A56: TKI000:da_Light-DutyVeh | B56: Light-Duty Vehicles | C56: 14.541973 | D56: 14.586114 | E56: 14.429692 | F56: 14.201925 | G56: 14.016909 | H56: 13.860763 | I56: 13.679087 | J56: 13.473832 | K56: 13.253083 | L56: 13.044086 | M56: 12.836978 | N56: 12.674039 | O56: 12.534656 | P56: 12.394664 | Q56: 12.251548 | R56: 12.130822 | S56: 12.028416 | T56: 11.933923 | U56: 11.864001 | V56: 11.805396 | W56: 11.762742 | X56: 11.733644 | Y56: 11.725387 | Z56: 11.735775 | AA56: 11.770763 | AB56: 11.824349 | AC56: 11.889715 | AD56: 11.96291 | AE56: 12.054455 | AF56: -0.006678
A57: TKI000:da_CommercialLig | B57: Commercial Light Trucks 1/ | C57: 0.951503 | D57: 0.942558 | E57: 0.92534 | F57: 0.912452 | G57: 0.903111 | H57: 0.894807 | I57: 0.888385 | J57: 0.882995 | K57: 0.877033 | L57: 0.872791 | M57: 0.871791 | N57: 0.871868 | O57: 0.873034 | P57: 0.875074 | Q57: 0.8775 | R57: 0.881023 | S57: 0.885541 | T57: 0.889796 | U57: 0.896146 | V57: 0.903924 | W57: 0.911921 | X57: 0.918675 | Y57: 0.924721 | Z57: 0.93183 | AA57: 0.93994 | AB57: 0.94995 | AC57: 0.95832 | AD57: 0.96721 | AE57: 0.978898 | AF57: 0.001014
A58: TKI000:da_BusTransporta | B58: Bus Transportation | C58: 0.212163 | D58: 0.222312 | E58: 0.226957 | F58: 0.228013 | G58: 0.228798 | H58: 0.229238 | I58: 0.229403 | J58: 0.229156 | K58: 0.228548 | L58: 0.227556 | M58: 0.22653 | N58: 0.226005 | O58: 0.225336 | P58: 0.224473 | Q58: 0.223496 | R58: 0.22194 | S58: 0.220576 | T58: 0.219099 | U58: 0.2175 | V58: 0.215784 | W58: 0.214032 | X58: 0.212017 | Y58: 0.210154 | Z58: 0.208215 | AA58: 0.206535 | AB58: 0.204463 | AC58: 0.20246 | AD58: 0.200282 | AE58: 0.198183 | AF58: -0.002432
A59: TKI000:da_FreightTrucks | B59: Freight Trucks | C59: 5.921126 | D59: 5.815005 | E59: 5.726179 | F59: 5.670887 | G59: 5.636415 | H59: 5.588956 | I59: 5.540693 | J59: 5.48039 | K59: 5.418849 | L59: 5.367491 | M59: 5.336062 | N59: 5.302126 | O59: 5.274123 | P59: 5.25631 | Q59: 5.237802 | R59: 5.232226 | S59: 5.230621 | T59: 5.23229 | U59: 5.241601 | V59: 5.256566 | W59: 5.274461 | X59: 5.292318 | Y59: 5.309026 | Z59: 5.323563 | AA59: 5.344643 | AB59: 5.367305 | AC59: 5.383854 | AD59: 5.403469 | AE59: 5.43954 | AF59: -0.003025
A60: TKI000:da_Rail,Passenge | B60: Rail, Passenger | C60: 0.043913 | D60: 0.045564 | E60: 0.046541 | F60: 0.047205 | G60: 0.0479 | H60: 0.048571 | I60: 0.049133 | J60: 0.049707 | K60: 0.05015 | L60: 0.050599 | M60: 0.05114 | N60: 0.051727 | O60: 0.052369 | P60: 0.052924 | Q60: 0.053457 | R60: 0.053973 | S60: 0.05451 | T60: 0.055034 | U60: 0.055627 | V60: 0.056181 | W60: 0.056754 | X60: 0.057258 | Y60: 0.057816 | Z60: 0.058367 | AA60: 0.059116 | AB60: 0.059751 | AC60: 0.060445 | AD60: 0.061081 | AE60: 0.061848 | AF60: 0.012306
A61: TKI000:da_Rail,Freight | B61: Rail, Freight | C61: 0.481382 | D61: 0.474822 | E61: 0.494129 | F61: 0.482204 | G61: 0.46188 | H61: 0.446095 | I61: 0.439745 | J61: 0.444526 | K61: 0.441892 | L61: 0.443423 | M61: 0.447437 | N61: 0.450648 | O61: 0.452666 | P61: 0.455515 | Q61: 0.455894 | R61: 0.456862 | S61: 0.458275 | T61: 0.457609 | U61: 0.458128 | V61: 0.461673 | W61: 0.464588 | X61: 0.464937 | Y61: 0.464923 | Z61: 0.464771 | AA61: 0.465767 | AB61: 0.468155 | AC61: 0.47134 | AD61: 0.472599 | AE61: 0.475729 | AF61: -0.000422
A62: TKI000:da_Shipping,Dome | B62: Shipping, Domestic | C62: 0.098239 | D62: 0.098921 | E62: 0.098115 | F62: 0.097346 | G62: 0.096686 | H62: 0.095823 | I62: 0.094965 | J62: 0.093891 | K62: 0.092919 | L62: 0.09203 | M62: 0.091401 | N62: 0.090674 | O62: 0.089934 | P62: 0.089169 | Q62: 0.088333 | R62: 0.087615 | S62: 0.086833 | T62: 0.086157 | U62: 0.085474 | V62: 0.084846 | W62: 0.084274 | X62: 0.083705 | Y62: 0.083103 | Z62: 0.082418 | AA62: 0.081856 | AB62: 0.081249 | AC62: 0.080573 | AD62: 0.07999 | AE62: 0.079593 | AF62: -0.007489
A63: TKI000:da_Shipping,Inte | B63: Shipping, International | C63: 0.935028 | D63: 0.88183 | E63: 0.877727 | F63: 0.878604 | G63: 0.87125 | H63: 0.868449 | I63: 0.862689 | J63: 0.859142 | K63: 0.856634 | L63: 0.857136 | M63: 0.857437 | N63: 0.858 | O63: 0.85776 | P63: 0.858218 | Q63: 0.857547 | R63: 0.857614 | S63: 0.857635 | T63: 0.85735 | U63: 0.857245 | V63: 0.857301 | W63: 0.85783 | X63: 0.85782 | Y63: 0.858048 | Z63: 0.858068 | AA63: 0.860633 | AB63: 0.860924 | AC63: 0.859834 | AD63: 0.859122 | AE63: 0.858095 | AF63: -0.003062
A64: TKI000:da_RecreationalB | B64: Recreational Boats | C64: 0.202837 | D64: 0.199163 | E64: 0.195805 | F64: 0.193737 | G64: 0.192813 | H64: 0.191897 | I64: 0.190734 | J64: 0.18921 | K64: 0.187404 | L64: 0.185677 | M64: 0.184467 | N64: 0.18361 | O64: 0.182778 | P64: 0.181998 | Q64: 0.18145 | R64: 0.181106 | S64: 0.180746 | T64: 0.180383 | U64: 0.180295 | V64: 0.180161 | W64: 0.179988 | X64: 0.179814 | Y64: 0.179557 | Z64: 0.179244 | AA64: 0.17895 | AB64: 0.178728 | AC64: 0.178491 | AD64: 0.178228 | AE64: 0.178156 | AF64: -0.004623
A65: TKI000:da_Air | B65: Air | C65: 2.802808 | D65: 3.008168 | E65: 3.051203 | F65: 3.057111 | G65: 3.095898 | H65: 3.134227 | I65: 3.164552 | J65: 3.187108 | K65: 3.202938 | L65: 3.218783 | M65: 3.243937 | N65: 3.270448 | O65: 3.294403 | P65: 3.322924 | Q65: 3.359825 | R65: 3.403895 | S65: 3.450172 | T65: 3.498488 | U65: 3.554644 | V65: 3.608403 | W65: 3.663098 | X65: 3.718625 | Y65: 3.77401 | Z65: 3.827919 | AA65: 3.880434 | AB65: 3.936738 | AC65: 3.993604 | AD65: 4.049651 | AE65: 4.112158 | AF65: 0.013784
A66: TKI000:da_MilitaryUse | B66: Military Use | C66: 0.430832 | D66: 0.433131 | E66: 0.433968 | F66: 0.434628 | G66: 0.435162 | H66: 0.435947 | I66: 0.436506 | J66: 0.436951 | K66: 0.437332 | L66: 0.437576 | M66: 0.437744 | N66: 0.437827 | O66: 0.437858 | P66: 0.437879 | Q66: 0.438004 | R66: 0.438203 | S66: 0.438412 | T66: 0.438631 | U66: 0.438858 | V66: 0.439093 | W66: 0.439335 | X66: 0.439584 | Y66: 0.439839 | Z66: 0.440099 | AA66: 0.440364 | AB66: 0.440633 | AC66: 0.440907 | AD66: 0.441184 | AE66: 0.441465 | AF66: 0.000871
A67: TKI000:da_Lubricants | B67: Lubricants | C67: 0.125945 | D67: 0.125925 | E67: 0.126012 | F67: 0.12605 | G67: 0.126114 | H67: 0.125984 | I67: 0.125853 | J67: 0.125755 | K67: 0.125652 | L67: 0.125546 | M67: 0.125439 | N67: 0.12533 | O67: 0.12525 | P67: 0.125225 | Q67: 0.125255 | R67: 0.125318 | S67: 0.125412 | T67: 0.125527 | U67: 0.125667 | V67: 0.125797 | W67: 0.125925 | X67: 0.126046 | Y67: 0.126166 | Z67: 0.12632 | AA67: 0.126492 | AB67: 0.126661 | AC67: 0.126811 | AD67: 0.126974 | AE67: 0.127159 | AF67: 0.000342
... A70: TKI000:da_Total | B70: Total | C70: 27.986006 | D70: 28.032028 | E70: 27.776655 | F70: 27.4657 | G70: 27.255045 | H70: 27.051918 | I70: 26.819283 | J70: 26.59227 | K70: 26.360722 | L70: 26.162958 | M70: 26.008129 | N70: 25.897749 | O70: 25.802094 | P70: 25.704212 | Q70: 25.598515 | R70: 25.533525 | S70: 25.493338 | T70: 25.449312 | U70: 25.46059 | V70: 25.485914 | W70: 25.531475 | X70: 25.583796 | Y70: 25.657438 | Z70: 25.744152 | AA70: 25.868387 | AB70: 26.019403 | AC70: 26.175444 | AD70: 26.332941 | AE70: 26.540415 | AF70: -0.001892
B72: (million barrels per day oil equivalent)
A73: TKI000:ea_Light-DutyVeh | B73: Light-Duty Vehicles | C73: 7.887402 | D73: 7.912227 | E73: 7.827434 | F73: 7.704175 | G73: 7.603646 | H73: 7.518498 | I73: 7.419035 | J73: 7.306525 | K73: 7.185357 | L73: 7.070691 | M73: 6.957016 | N73: 6.86728 | O73: 6.790267 | P73: 6.712955 | Q73: 6.633772 | R73: 6.566808 | S73: 6.509881 | T73: 6.457382 | U73: 6.418384 | V73: 6.385576 | W73: 6.361585 | X73: 6.345073 | Y73: 6.340106 | Z73: 6.345462 | AA73: 6.36419 | AB73: 6.393152 | AC73: 6.428598 | AD73: 6.468379 | AE73: 6.518199 | AF73: -0.006786
A74: TKI000:ea_CommercialLig | B74: Commercial Light Trucks 1/ | C74: 0.496809 | D74: 0.492193 | E74: 0.483314 | F74: 0.476842 | G74: 0.472221 | H74: 0.467932 | I74: 0.464712 | J74: 0.462053 | K74: 0.459111 | L74: 0.457084 | M74: 0.456754 | N74: 0.456989 | O74: 0.457814 | P74: 0.459091 | Q74: 0.460564 | R74: 0.462619 | S74: 0.465189 | T74: 0.467623 | U74: 0.471176 | V74: 0.475436 | W74: 0.479853 | X74: 0.483793 | Y74: 0.487354 | Z74: 0.491353 | AA74: 0.496003 | AB74: 0.501565 | AC74: 0.506491 | AD74: 0.511462 | AE74: 0.517981 | AF74: 0.001492
A75: TKI000:ea_BusTransporta | B75: Bus Transportation | C75: 0.105213 | D75: 0.110296 | E75: 0.11259 | F75: 0.113083 | G75: 0.113492 | H75: 0.113737 | I75: 0.113843 | J75: 0.113729 | K75: 0.113434 | L75: 0.112917 | M75: 0.112403 | N75: 0.112129 | O75: 0.111806 | P75: 0.111381 | Q75: 0.110915 | R75: 0.110151 | S75: 0.109477 | T75: 0.108762 | U75: 0.107969 | V75: 0.107129 | W75: 0.106288 | X75: 0.105307 | Y75: 0.104391 | Z75: 0.103434 | AA75: 0.102605 | AB75: 0.101578 | AC75: 0.100586 | AD75: 0.099507 | AE75: 0.09846 | AF75: -0.002366
A76: TKI000:ea_FreightTrucks | B76: Freight Trucks | C76: 2.850965 | D76: 2.800434 | E76: 2.758164 | F76: 2.732194 | G76: 2.716136 | H76: 2.693672 | I76: 2.671257 | J76: 2.642962 | K76: 2.614177 | L76: 2.590174 | M76: 2.575932 | N76: 2.560368 | O76: 2.547745 | P76: 2.539845 | Q76: 2.531643 | R76: 2.529634 | S76: 2.5295 | T76: 2.530971 | U76: 2.536117 | V76: 2.544034 | W76: 2.553331 | X76: 2.562598 | Y76: 2.571348 | Z76: 2.579022 | AA76: 2.589984 | AB76: 2.601707 | AC76: 2.610389 | AD76: 2.620612 | AE76: 2.638885 | AF76: -0.002757
A77: TKI000:ea_Rail,Passenge | B77: Rail, Passenger | C77: 0.020781 | D77: 0.021563 | E77: 0.022025 | F77: 0.02234 | G77: 0.022668 | H77: 0.022984 | I77: 0.023251 | J77: 0.023523 | K77: 0.023733 | L77: 0.023945 | M77: 0.024201 | N77: 0.024479 | O77: 0.024783 | P77: 0.025045 | Q77: 0.025298 | R77: 0.025542 | S77: 0.025796 | T77: 0.026044 | U77: 0.026325 | V77: 0.026587 | W77: 0.026858 | X77: 0.027097 | Y77: 0.027361 | Z77: 0.027622 | AA77: 0.027977 | AB77: 0.028278 | AC77: 0.028605 | AD77: 0.028906 | AE77: 0.02927 | AF77: 0.012308
A78: TKI000:ea_Rail,Freight | B78: Rail, Freight | C78: 0.228347 | D78: 0.225234 | E78: 0.234373 | F78: 0.228717 | G78: 0.21906 | H78: 0.211545 | I78: 0.208541 | J78: 0.210806 | K78: 0.209559 | L78: 0.210276 | M78: 0.212178 | N78: 0.213692 | O78: 0.21465 | P78: 0.215989 | Q78: 0.216165 | R78: 0.216616 | S78: 0.21728 | T78: 0.216956 | U78: 0.217194 | V78: 0.218865 | W78: 0.220234 | X78: 0.220387 | Y78: 0.22037 | Z78: 0.220283 | AA78: 0.220747 | AB78: 0.221866 | AC78: 0.223355 | AD78: 0.223935 | AE78: 0.225407 | AF78: -0.000463
A79: TKI000:ea_Shipping,Dome | B79: Shipping, Domestic | C79: 0.046527 | D79: 0.046853 | E79: 0.04647 | F79: 0.04611 | G79: 0.045796 | H79: 0.045385 | I79: 0.044983 | J79: 0.044476 | K79: 0.04402 | L79: 0.0436 | M79: 0.043306 | N79: 0.042963 | O79: 0.042617 | P79: 0.042256 | Q79: 0.041863 | R79: 0.041525 | S79: 0.041158 | T79: 0.04084 | U79: 0.040519 | V79: 0.040222 | W79: 0.03995 | X79: 0.039681 | Y79: 0.039395 | Z79: 0.03907 | AA79: 0.038805 | AB79: 0.038517 | AC79: 0.038196 | AD79: 0.037919 | AE79: 0.037732 | AF79: -0.007455
A80: TKI000:ea_Shipping,Inte | B80: Shipping, International | C80: 0.417032 | D80: 0.39771 | E80: 0.396229 | F80: 0.396613 | G80: 0.393975 | H80: 0.392997 | I80: 0.390956 | J80: 0.389709 | K80: 0.388847 | L80: 0.389075 | M80: 0.389247 | N80: 0.389507 | O80: 0.389481 | P80: 0.389698 | Q80: 0.389505 | R80: 0.389575 | S80: 0.389634 | T80: 0.389581 | U80: 0.389597 | V80: 0.38967 | W80: 0.389917 | X80: 0.389969 | Y80: 0.390113 | Z80: 0.390178 | AA80: 0.391183 | AB80: 0.391349 | AC80: 0.391006 | AD80: 0.3908 | AE80: 0.390489 | AF80: -0.002346
A81: TKI000:ea_RecreationalB | B81: Recreational Boats | C81: 0.110006 | D81: 0.108038 | E81: 0.106242 | F81: 0.105144 | G81: 0.104667 | H81: 0.104195 | I81: 0.103587 | J81: 0.102784 | K81: 0.101827 | L81: 0.100913 | M81: 0.100279 | N81: 0.099838 | O81: 0.099409 | P81: 0.099009 | Q81: 0.098731 | R81: 0.098564 | S81: 0.098387 | T81: 0.098209 | U81: 0.098181 | V81: 0.098125 | W81: 0.098049 | X81: 0.097971 | Y81: 0.097849 | Z81: 0.097695 | AA81: 0.097552 | AB81: 0.097448 | AC81: 0.097337 | AD81: 0.097211 | AE81: 0.097188 | AF81: -0.004415
A82: TKI000:ea_Air | B82: Air | C82: 1.355634 | D82: 1.454865 | E82: 1.475662 | F82: 1.478519 | G82: 1.497263 | H82: 1.515786 | I82: 1.530442 | J82: 1.541344 | K82: 1.548995 | L82: 1.556654 | M82: 1.568811 | N82: 1.581624 | O82: 1.593202 | P82: 1.606986 | Q82: 1.624819 | R82: 1.646116 | S82: 1.668479 | T82: 1.691828 | U82: 1.718965 | V82: 1.744943 | W82: 1.771373 | X82: 1.798206 | Y82: 1.82497 | Z82: 1.851021 | AA82: 1.876398 | AB82: 1.903606 | AC82: 1.931086 | AD82: 1.95817 | AE82: 1.988375 | AF82: 0.013774
A83: TKI000:ea_MilitaryUse | B83: Military Use | C83: 0.207325 | D83: 0.208431 | E83: 0.20883 | F83: 0.209148 | G83: 0.209402 | H83: 0.209774 | I83: 0.210045 | J83: 0.210259 | K83: 0.210443 | L83: 0.21056 | M83: 0.210641 | N83: 0.21068 | O83: 0.210697 | P83: 0.210706 | Q83: 0.210766 | R83: 0.210862 | S83: 0.210964 | T83: 0.211069 | U83: 0.211179 | V83: 0.211292 | W83: 0.211409 | X83: 0.211529 | Y83: 0.211652 | Z83: 0.211777 | AA83: 0.211906 | AB83: 0.212036 | AC83: 0.212167 | AD83: 0.2123 | AE83: 0.212437 | AF83: 0.00087
A84: TKI000:ea_Lubricants | B84: Lubricants | C84: 0.059492 | D84: 0.059483 | E84: 0.059524 | F84: 0.059542 | G84: 0.059572 | H84: 0.059511 | I84: 0.059449 | J84: 0.059403 | K84: 0.059354 | L84: 0.059304 | M84: 0.059253 | N84: 0.059202 | O84: 0.059164 | P84: 0.059152 | Q84: 0.059166 | R84: 0.059196 | S84: 0.05924 | T84: 0.059295 | U84: 0.059361 | V84: 0.059422 | W84: 0.059483 | X84: 0.05954 | Y84: 0.059597 | Z84: 0.059669 | AA84: 0.059751 | AB84: 0.05983 | AC84: 0.059901 | AD84: 0.059978 | AE84: 0.060066 | AF84: 0.000342
... A87: TKI000:ea_Total | B87: Total | C87: 14.370443 | D87: 14.403465 | E87: 14.271711 | F87: 14.108815 | G87: 13.997396 | H87: 13.890337 | I87: 13.767988 | J87: 13.645885 | K87: 13.520164 | L87: 13.411051 | M87: 13.323045 | N87: 13.25902 | O87: 13.203858 | P87: 13.147519 | Q87: 13.087383 | R87: 13.048246 | S87: 13.022289 | T87: 12.995312 | U87: 12.996621 | V87: 13.0055 | W87: 13.025239 | X87: 13.049395 | Y87: 13.085273 | Z87: 13.128707 | AA87: 13.19174 | AB87: 13.269163 | AC87: 13.350009 | AD87: 13.432016 | AE87: 13.539635 | AF87: -0.002125
B89: 1/ Commercial trucks have a 8,501 to 10,000 pound gross vehicle weight rating.
B90: 2/ CAFE standard based on projected new vehicle sales.
B91: 3/ Includes CAFE credits for alternative fueled vehicle sales and credit banking.
B92: 4/ U.S. Environmental Protection Agency rated miles per gallon.
B93: 5/ Tested new vehicle efficiency revised for on-road performance.
B94: 6/ Combined "on-the-road" estimate for all cars and light trucks.
B95: 7/ Fuel used in facilities that liquefy natural gas for export.
B96: CAFE = Corporate average fuel economy.
B97: Btu = British thermal unit.
B98: Note: Totals may not equal sum of components due to independent rounding.
B99: Data source: 2022: U.S. Energy Information Administration (EIA), Short-Term Energy Outlook, November 2022 and EIA, AEO2023
B100: AEO2023 National Energy Modeling System run ref2023.d020623a. Projections: EIA, AEO2023 National Energy Modeling System run ref2023.d020623a.

Sheet AEO Table 44
B1: ref2023.d020623a | C1: 2022 | D1: 2023 | E1: 2024 | F1: 2025 | G1: 2026 | H1: 2027 | I1: 2028 | J1: 2029 | K1: 2030 | L1: 2031 | M1: 2032 | N1: 2033 | O1: 2034 | P1: 2035 | Q1: 2036 | R1: 2037 | S1: 2038 | T1: 2039 | U1: 2040 | V1: 2041 | W1: 2042 | X1: 2043 | Y1: 2044 | Z1: 2045 | AA1: 2046 | AB1: 2047 | AC1: 2048 | AD1: 2049 | AE1: 2050
C3: Report | D3: Annual Energy Outlook 2023
C4: Scenario | D4: ref2023 | G4: Reference
C5: Datekey | D5: d020623a
C6: Release Date | E6: March 2023
A10: TFS000 | B10: 44. Transportation Fleet Car and Truck Sales by Type and Technology | AF10: Annual
B11: (thousands) | AF11: Change
AF12: 2022–2050
B13: Technology Type | C13: 2022 | D13: 2023 | E13: 2024 | F13: 2025 | G13: 2026 | H13: 2027 | I13: 2028 | J13: 2029 | K13: 2030 | L13: 2031 | M13: 2032 | N13: 2033 | O13: 2034 | P13: 2035 | Q13: 2036 | R13: 2037 | S13: 2038 | T13: 2039 | U13: 2040 | V13: 2041 | W13: 2042 | X13: 2043 | Y13: 2044 | Z13: 2045 | AA13: 2046 | AB13: 2047 | AC13: 2048 | AD13: 2049 | AE13: 2050 | AF13: 2050
B15: New Car Sales 1/
B16: Conventional Cars
A17: TFS000:ba_GasolineICEVe | B17: Gasoline ICE Vehicles | C17: 745.48859 | D17: 752.84778 | E17: 752.35828 | F17: 735.73346 | G17: 714.39777 | H17: 699.98785 | I17: 685.04047 | J17: 673.87494 | K17: 663.85052 | L17: 653.93219 | M17: 646.67609 | N17: 638 | O17: 632.65363 | P17: 629.94421 | Q17: 630.54657 | R17: 627.93366 | S17: 625.11896 | T17: 622.16144 | U17: 618.44098 | V17: 611.17291 | W17: 603.78058 | X17: 594.08051 | Y17: 586.63452 | Z17: 582.1673 | AA17: 581.98822 | AB17: 575.44702 | AC17: 569.67371 | AD17: 564.75281 | AE17: 561.18835 | AF17: -0.010091
A18: TFS000:ba_TDIDieselICE | B18: TDI Diesel ICE | C18: 0 | D18: 0 | E18: 0 | F18: 0 | G18: 0 | H18: 0 | I18: 0 | J18: 0 | K18: 0 | L18: 0 | M18: 0 | N18: 0 | O18: 0 | P18: 0 | Q18: 0 | R18: 0 | S18: 0 | T18: 0 | U18: 0 | V18: 0 | W18: 0 | X18: 0 | Y18: 0 | Z18: 0 | AA18: 0 | AB18: 0 | AC18: 0 | AD18: 0 | AE18: 0 | AF18: --
A19: TFS000:ba_TotalConventi | B19: Total Conventional Cars | C19: 745.48859 | D19: 752.84778 | E19: 752.35828 | F19: 735.73346 | G19: 714.39777 | H19: 699.98785 | I19: 685.04047 | J19: 673.87494 | K19: 663.85052 | L19: 653.93219 | M19: 646.67609 | N19: 638 | O19: 632.65363 | P19: 629.94421 | Q19: 630.54657 | R19: 627.93366 | S19: 625.11896 | T19: 622.16144 | U19: 618.44098 | V19: 611.17291 | W19: 603.78058 | X19: 594.08051 | Y19: 586.63452 | Z19: 582.1673 | AA19: 581.98822 | AB19: 575.44702 | AC19: 569.67371 | AD19: 564.75281 | AE19: 561.18835 | AF19: -0.010091
B21: Alternative-Fuel Cars
A22: TFS000:ca_Ethanol-FlexF | B22: Ethanol-Flex Fuel ICE | C22: 27.701494 | D22: 28.161213 | E22: 28.336246 | F22: 27.930389 | G22: 27.360483 | H22: 27.062561 | I22: 26.745171 | J22: 26.574789 | K22: 26.450092 | L22: 26.327152 | M22: 26.309853 | N22: 26.236437 | O22: 26.300083 | P22: 26.476437 | Q22: 26.802656 | R22: 26.993179 | S22: 27.175011 | T22: 27.3564 | U22: 27.506229 | V22: 27.497744 | W22: 27.48558 | X22: 27.36544 | Y22: 27.347322 | Z22: 27.466482 | AA22: 27.77367 | AB22: 27.796991 | AC22: 27.862095 | AD22: 27.968414 | AE22: 27.940855 | AF22: 0.000307
A23: TFS000:ca_100mileEV | B23: 100-Mile Electric Vehicle | C23: 1.733732 | D23: 2.015718 | E23: 2.282101 | F23: 2.494302 | G23: 2.678695 | H23: 2.879138 | I23: 3.07065 | J23: 3.273858 | K23: 3.479208 | L23: 3.682477 | M23: 3.899189 | N23: 4.106014 | O23: 4.333928 | P23: 4.58201 | Q23: 4.858603 | R23: 5.115785 | S23: 5.375243 | T23: 5.636921 | U23: 5.89505 | V23: 6.120733 | W23: 6.344616 | X23: 6.542595 | Y23: 6.763642 | Z23: 7.019996 | AA23: 7.332982 | AB23: 7.569391 | AC23: 7.816744 | AD23: 8.077607 | AE23: 8.358113 | AF23: 0.057785
A24: TFS000:ca_ElectricVehic | B24: 200-Mile Electric Vehicle | C24: 2.34727 | D24: 4.423422 | E24: 6.51033 | F24: 8.447515 | G24: 10.260118 | H24: 12.106405 | I24: 13.894964 | J24: 15.720405 | K24: 17.546631 | L24: 19.353251 | M24: 21.224617 | N24: 23.038656 | O24: 24.968584 | P24: 27.018316 | Q24: 29.246431 | R24: 31.364456 | S24: 33.500416 | T24: 35.655449 | U24: 37.791504 | V24: 39.719631 | W24: 41.633911 | X24: 43.373734 | Y24: 45.262123 | Z24: 47.386185 | AA24: 49.898258 | AB24: 51.892063 | AC24: 53.95982 | AD24: 56.121365 | AE24: 58.420788 | AF24: 0.12165
A25: TFS000:ea_FuelCellGasol | B25: 300-Mile Electric Vehicle | C25: 16.660831 | D25: 19.503101 | E25: 22.200615 | F25: 24.367395 | G25: 26.25774 | H25: 28.301954 | I25: 30.256197 | J25: 32.324257 | K25: 34.412506 | L25: 36.479725 | M25: 38.679714 | N25: 40.781128 | O25: 43.091831 | P25: 45.603497 | Q25: 48.399467 | R25: 51.002945 | S25: 53.629681 | T25: 56.278992 | U25: 58.893322 | V25: 61.18375 | W25: 63.455978 | X25: 65.468964 | Y25: 67.712502 | Z25: 70.309715 | AA25: 73.47554 | AB25: 75.873489 | AC25: 78.380974 | AD25: 81.024094 | AE25: 83.864441 | AF25: 0.059418
A26: TFS000:ca_Plug-inGasoli | B26: Plug-in 20 Gasoline Hybrid | C26: 2.416381 | D26: 2.779324 | E26: 3.120898 | F26: 3.388887 | G26: 3.61952 | H26: 3.871928 | I26: 4.112279 | J26: 4.368149 | K26: 4.626535 | L26: 4.881974 | M26: 5.155017 | N26: 5.414467 | O26: 5.701344 | P26: 6.014175 | Q26: 6.363098 | R26: 6.686507 | S26: 7.012915 | T26: 7.341406 | U26: 7.665002 | V26: 7.946321 | W26: 8.224556 | X26: 8.469109 | Y26: 8.743222 | Z26: 9.063097 | AA26: 9.459611 | AB26: 9.753787 | AC26: 10.060923 | AD26: 10.385608 | AE26: 10.734817 | AF26: 0.054702
A27: TFS000:ca_Plug-in40Hybd | B27: Plug-in 50 Gasoline Hybrid | C27: 0.85057 | D27: 1.23013 | E27: 1.607591 | F27: 1.947863 | G27: 2.261849 | H27: 2.585001 | I27: 2.896867 | J27: 3.217093 | K27: 3.53761 | L27: 3.854425 | M27: 4.184191 | N27: 4.502318 | O27: 4.842849 | P27: 5.205986 | Q27: 5.601945 | R27: 5.976532 | S27: 6.354444 | T27: 6.735092 | U27: 7.111816 | V27: 7.449342 | W27: 7.783675 | X27: 8.085442 | Y27: 8.414771 | Z27: 8.788048 | AA27: 9.236242 | AB27: 9.585274 | AC27: 9.946996 | AD27: 10.326148 | AE27: 10.729992 | AF27: 0.094756
A28: TFS000:ca_Electric-Dies | B28: Electric-Diesel Hybrid | C28: 0 | D28: 0 | E28: 0 | F28: 0 | G28: 0 | H28: 0 | I28: 0 | J28: 0 | K28: 0 | L28: 0 | M28: 0 | N28: 0 | O28: 0 | P28: 0 | Q28: 0 | R28: 0 | S28: 0 | T28: 0 | U28: 0 | V28: 0 | W28: 0 | X28: 0 | Y28: 0 | Z28: 0 | AA28: 0 | AB28: 0 | AC28: 0 | AD28: 0 | AE28: 0 | AF28: --
A29: TFS000:ca_Electric-Gaso | B29: Electric-Gasoline Hybrid | C29: 32.527454 | D29: 34.683559 | E29: 36.517467 | F29: 37.527821 | G29: 38.211796 | H29: 39.194439 | I29: 40.098598 | J29: 41.186401 | K29: 42.318878 | L29: 43.439339 | M29: 44.725349 | N29: 45.902386 | O29: 47.315739 | P29: 48.939678 | Q29: 50.848152 | R29: 52.535007 | S29: 54.232723 | T29: 55.940033 | U29: 57.601685 | V29: 58.942471 | W29: 60.265564 | X29: 61.346802 | Y29: 62.647991 | Z29: 64.274544 | AA29: 66.418465 | AB29: 67.85157 | AC29: 69.378136 | AD29: 71.021629 | AE29: 72.830383 | AF29: 0.029206
A30: TFS000:ca_CompressedNat | B30: Natural Gas ICE | C30: 0 | D30: 0 | E30: 0 | F30: 0 | G30: 0 | H30: 0 | I30: 0 | J30: 0 | K30: 0 | L30: 0 | M30: 0 | N30: 0 | O30: 0 | P30: 0 | Q30: 0 | R30: 0 | S30: 0 | T30: 0 | U30: 0 | V30: 0 | W30: 0 | X30: 0 | Y30: 0 | Z30: 0 | AA30: 0 | AB30: 0 | AC30: 0 | AD30: 0 | AE30: 0 | AF30: --
A31: TFS000:da_CompressedNat | B31: Natural Gas Bi-fuel | C31: 0 | D31: 0 | E31: 0 | F31: 0 | G31: 0 | H31: 0 | I31: 0 | J31: 0 | K31: 0 | L31: 0 | M31: 0 | N31: 0 | O31: 0 | P31: 0 | Q31: 0 | R31: 0 | S31: 0 | T31: 0 | U31: 0 | V31: 0 | W31: 0 | X31: 0 | Y31: 0 | Z31: 0 | AA31: 0 | AB31: 0 | AC31: 0 | AD31: 0 | AE31: 0 | AF31: --
A32: TFS000:da_LiquefiedPetr | B32: Propane ICE | C32: 0 | D32: 0 | E32: 0 | F32: 0 | G32: 0 | H32: 0 | I32: 0 | J32: 0 | K32: 0 | L32: 0 | M32: 0 | N32: 0 | O32: 0 | P32: 0 | Q32: 0 | R32: 0 | S32: 0 | T32: 0 | U32: 0 | V32: 0 | W32: 0 | X32: 0 | Y32: 0 | Z32: 0 | AA32: 0 | AB32: 0 | AC32: 0 | AD32: 0 | AE32: 0 | AF32: --
A33: TFS000:ea_LiquefiedPetr | B33: Propane Bi-fuel | C33: 0 | D33: 0 | E33: 0 | F33: 0 | G33: 0 | H33: 0 | I33: 0 | J33: 0 | K33: 0 | L33: 0 | M33: 0 | N33: 0 | O33: 0 | P33: 0 | Q33: 0 | R33: 0 | S33: 0 | T33: 0 | U33: 0 | V33: 0 | W33: 0 | X33: 0 | Y33: 0 | Z33: 0 | AA33: 0 | AB33: 0 | AC33: 0 | AD33: 0 | AE33: 0 | AF33: --
A34: TFS000:ea_FuelCellMetha | B34: Fuel Cell Methanol | C34: 0 | D34: 0 | E34: 0 | F34: 0 | G34: 0 | H34: 0 | I34: 0 | J34: 0 | K34: 0 | L34: 0 | M34: 0 | N34: 0 | O34: 0 | P34: 0 | Q34: 0 | R34: 0 | S34: 0 | T34: 0 | U34: 0 | V34: 0 | W34: 0 | X34: 0 | Y34: 0 | Z34: 0 | AA34: 0 | AB34: 0 | AC34: 0 | AD34: 0 | AE34: 0 | AF34: --
A35: TFS000:ea_FuelCellHydro | B35: Fuel Cell Hydrogen | C35: 0.048113 | D35: 0.092384 | E35: 0.137451 | F35: 0.179425 | G35: 0.218551 | H35: 0.258121 | I35: 0.29623 | J35: 0.334905 | K35: 0.373342 | L35: 0.411207 | M35: 0.450298 | N35: 0.487883 | O35: 0.527722 | P35: 0.569856 | Q35: 0.615191 | R35: 0.65825 | S35: 0.701748 | T35: 0.745306 | U35: 0.78838 | V35: 0.827084 | W35: 0.865125 | X35: 0.89946 | Y35: 0.936702 | Z35: 0.978884 | AA35: 1.03084 | AB35: 1.070397 | AC35: 1.110929 | AD35: 1.153482 | AE35: 1.19854 | AF35: 0.121686
A36: TFS000:ea_TotalAlternat | B36: Total Alternative Cars | C36: 84.285843 | D36: 92.888847 | E36: 100.7127 | F36: 106.28359 | G36: 110.86876 | H36: 116.25954 | I36: 121.37095 | J36: 126.99986 | K36: 132.7448 | L36: 138.42955 | M36: 144.62823 | N36: 150.46928 | O36: 157.08208 | P36: 164.40996 | Q36: 172.73555 | R36: 180.33266 | S36: 187.98219 | T36: 195.68961 | U36: 203.25299 | V36: 209.68707 | W36: 216.05902 | X36: 221.55154 | Y36: 227.82828 | Z36: 235.28696 | AA36: 244.62561 | AB36: 251.39296 | AC36: 258.51663 | AD36: 266.07834 | AE36: 274.07794 | AF36: 0.043014
A38: TFS000:fa_PercentAltern | B38: Percent Alternative Car Sales | C38: 10.157681 | D38: 10.983189 | E38: 11.8059 | F38: 12.622499 | G38: 13.434297 | H38: 14.243176 | I38: 15.050748 | J38: 15.857643 | K38: 16.664019 | L38: 17.470499 | M38: 18.277195 | N38: 19.083721 | O38: 19.890461 | P38: 20.697311 | Q38: 21.503721 | R38: 22.311045 | S38: 23.119165 | T38: 23.92729 | U38: 24.735849 | V38: 25.544804 | W38: 26.353815 | X38: 27.163172 | Y38: 27.97283 | Z38: 28.782892 | AA38: 29.5937 | AB38: 30.404064 | AC38: 31.214642 | AD38: 32.025562 | AE38: 32.813244 | AF38: 0.042768
A39: TFS000:fa_TotalNewCarSa | B39: Total New Car Sales | C39: 829.77441 | D39: 845.73663 | E39: 853.07098 | F39: 842.01703 | G39: 825.26654 | H39: 816.24738 | I39: 806.41144 | J39: 800.87482 | K39: 796.59534 | L39: 792.36176 | M39: 791.30432 | N39: 788.4693 | O39: 789.73572 | P39: 794.35419 | Q39: 803.2821 | R39: 808.2663 | S39: 813.10113 | T39: 817.85107 | U39: 821.69397 | V39: 820.85999 | W39: 819.8396 | X39: 815.63208 | Y39: 814.46277 | Z39: 817.45422 | AA39: 826.61383 | AB39: 826.83997 | AC39: 828.19031 | AD39: 830.83118 | AE39: 835.2663 | AF39: 0.000236
B41: New Light Truck Sales 1/
B42: Conventional Light Trucks
A43: TFS000:ga_GasolineICEVe | B43: Gasoline ICE Vehicles | C43: 1139.8827 | D43: 1177.5922 | E43: 1225.1962 | F43: 1266.6293 | G43: 1280.5264 | H43: 1273.6564 | I43: 1266.3192 | J43: 1266.3704 | K43: 1255.4795 | L43: 1247.1234 | M43: 1238.2233 | N43: 1229.917 | O43: 1228.6764 | P43: 1234.7007 | Q43: 1240.9656 | R43: 1247.8655 | S43: 1256.8419 | T43: 1264.0477 | U43: 1273.665 | V43: 1276.9398 | W43: 1280.7981 | X43: 1284.9028 | Y43: 1287.0942 | Z43: 1296.9729 | AA43: 1299.4546 | AB43: 1304.3114 | AC43: 1303.999 | AD43: 1310.5312 | AE43: 1318.3575 | AF43: 0.005209
A44: TFS000:ga_TDIDieselICE | B44: TDI Diesel ICE | C44: 0.042834 | D44: 0.0448 | E44: 0.047137 | F44: 0.049205 | G44: 0.050164 | H44: 0.05028 | I44: 0.050354 | J44: 0.050707 | K44: 0.050606 | L44: 0.050601 | M44: 0.050573 | N44: 0.05056 | O44: 0.050837 | P44: 0.051416 | Q44: 0.051999 | R44: 0.052623 | S44: 0.053332 | T44: 0.053966 | U44: 0.054716 | V44: 0.055203 | W44: 0.05572 | X44: 0.056254 | Y44: 0.056709 | Z44: 0.057515 | AA44: 0.058032 | AB44: 0.058632 | AC44: 0.058999 | AD44: 0.059676 | AE44: 0.06041 | AF44: 0.012355
A45: TFS000:ga_TotalConventi | B45: Total Conventional Light Trucks | C45: 1139.9255 | D45: 1177.637 | E45: 1225.2433 | F45: 1266.6785 | G45: 1280.5765 | H45: 1273.7067 | I45: 1266.3696 | J45: 1266.421 | K45: 1255.5302 | L45: 1247.1741 | M45: 1238.2738 | N45: 1229.9675 | O45: 1228.7272 | P45: 1234.7521 | Q45: 1241.0176 | R45: 1247.9181 | S45: 1256.8953 | T45: 1264.1017 | U45: 1273.7197 | V45: 1276.995 | W45: 1280.8538 | X45: 1284.9591 | Y45: 1287.151 | Z45: 1297.0304 | AA45: 1299.5126 | AB45: 1304.37 | AC45: 1304.058 | AD45: 1310.5909 | AE45: 1318.418 | AF45: 0.005209
B47: Alternative-Fuel Light Trucks
A48: TFS000:ha_Ethanol-FlexF | B48: Ethanol-Flex Fuel ICE | C48: 97.975632 | D48: 102.39687 | E48: 107.67007 | F48: 112.33575 | G48: 114.48013 | H48: 114.70761 | I48: 114.84385 | J48: 115.61748 | K48: 115.36041 | L48: 115.32437 | M48: 115.23352 | N48: 115.18002 | O48: 115.78656 | P48: 117.08218 | Q48: 118.38756 | R48: 119.78483 | S48: 121.37783 | T48: 122.8025 | U48: 124.48741 | V48: 125.57402 | W48: 126.72716 | X48: 127.91966 | Y48: 128.93149 | Z48: 130.74116 | AA48: 131.88454 | AB48: 133.22308 | AC48: 134.03351 | AD48: 135.54968 | AE48: 137.19547 | AF48: 0.012097
A49: TFS000:ha_100mileEV | B49: 100-Mile Electric Vehicle | C49: 0.077187 | D49: 0.076893 | E49: 0.07708 | F49: 0.076725 | G49: 0.074614 | H49: 0.071291 | I49: 0.067977 | J49: 0.065073 | K49: 0.061625 | L49: 0.058332 | M49: 0.055036 | N49: 0.051793 | O49: 0.048852 | P49: 0.046172 | Q49: 0.043459 | R49: 0.040714 | S49: 0.037982 | T49: 0.035139 | U49: 0.0323 | V49: 0.029246 | W49: 0.026166 | X49: 0.02305 | Y49: 0.019861 | Z49: 0.016736 | AA49: 0.013458 | AB49: 0.010167 | AC49: 0.006801 | AD49: 0.00343 | AE49: 0 | AF49: --
A50: TFS000:ha_ElectricVehic | B50: 200-Mile Electric Vehicle | C50: 3.626619 | D50: 7.114282 | E50: 10.936429 | F50: 14.991846 | G50: 18.91403 | H50: 22.581854 | I50: 26.231239 | J50: 30.04413 | K50: 33.597034 | L50: 37.19194 | M50: 40.750645 | N50: 44.308708 | O50: 48.125023 | P50: 52.274918 | Q50: 56.508244 | R50: 60.848198 | S50: 65.376472 | T50: 69.901756 | U50: 74.653328 | V50: 79.114174 | W50: 83.673813 | X50: 88.316002 | Y50: 92.888107 | Z50: 98.097862 | AA50: 102.83463 | AB50: 107.82616 | AC50: 112.44904 | AD50: 117.72791 | AE50: 123.21871 | AF50: 0.134187
A51: TFS000:ja_FuelCellGasol | B51: 300-Mile Electric Vehicle | C51: 1.540752 | D51: 2.054901 | E51: 2.625191 | F51: 3.223209 | G51: 3.778698 | H51: 4.280706 | I51: 4.780124 | J51: 5.309176 | K51: 5.792547 | L51: 6.284184 | M51: 6.770445 | N51: 7.25732 | O51: 7.786545 | P51: 8.368753 | Q51: 8.962948 | R51: 9.572627 | S51: 10.210526 | T51: 10.846562 | U51: 11.516315 | V51: 12.140107 | W51: 12.778309 | X51: 13.428332 | Y51: 14.067024 | Z51: 14.801416 | AA51: 15.463592 | AB51: 16.163538 | AC51: 16.80772 | AD51: 17.549417 | AE51: 18.321917 | AF51: 0.09245
A52: TFS000:ha_Plug-inGasoli | B52: Plug-in 20 Gasoline Hybrid | C52: 4.744301 | D52: 5.045507 | E52: 5.402499 | F52: 5.747861 | G52: 5.979481 | H52: 6.117843 | I52: 6.254298 | J52: 6.428265 | K52: 6.547184 | L52: 6.678004 | M52: 6.80469 | N52: 6.933836 | O52: 7.102757 | P52: 7.315749 | Q52: 7.534082 | R52: 7.758972 | S52: 8.001135 | T52: 8.236279 | U52: 8.490767 | V52: 8.706131 | W52: 8.928126 | X52: 9.154455 | Y52: 9.369674 | Z52: 9.643818 | AA52: 9.863976 | AB52: 10.107215 | AC52: 10.313154 | AD52: 10.576284 | AE52: 10.854796 | AF52: 0.030001
A53: TFS000:ha_Plug-in40Hybd | B53: Plug-in 50 Gasoline Hybrid | C53: 0.346853 | D53: 0.685489 | E53: 1.054651 | F53: 1.445064 | G53: 1.821794 | H53: 2.173277 | I53: 2.522332 | J53: 2.886506 | K53: 3.225218 | L53: 3.567282 | M53: 3.905131 | N53: 4.242438 | O53: 4.603806 | P53: 4.996414 | Q53: 5.396834 | R53: 5.806306 | S53: 6.233519 | T53: 6.660077 | U53: 7.107193 | V53: 7.525671 | W53: 7.952894 | X53: 8.387099 | Y53: 8.813905 | Z53: 9.299941 | AA53: 9.737713 | AB53: 10.201078 | AC53: 10.629158 | AD53: 11.11884 | AE53: 11.628694 | AF53: 0.133648
A54: TFS000:ha_Electric-Dies | B54: Electric-Diesel Hybrid | C54: 0 | D54: 0 | E54: 0 | F54: 0 | G54: 0 | H54: 0 | I54: 0 | J54: 0 | K54: 0 | L54: 0 | M54: 0 | N54: 0 | O54: 0 | P54: 0 | Q54: 0 | R54: 0 | S54: 0 | T54: 0 | U54: 0 | V54: 0 | W54: 0 | X54: 0 | Y54: 0 | Z54: 0 | AA54: 0 | AB54: 0 | AC54: 0 | AD54: 0 | AE54: 0 | AF54: --
A55: TFS000:ha_Electric-Gaso | B55: Electric-Gasoline Hybrid | C55: 37.296288 | D55: 39.102524 | E55: 41.305428 | F55: 43.376812 | G55: 44.561203 | H55: 45.045021 | I55: 45.519054 | J55: 46.267311 | K55: 46.621571 | L55: 47.067921 | M55: 47.492344 | N55: 47.939545 | O55: 48.665665 | P55: 49.692074 | Q55: 50.747635 | R55: 51.84573 | S55: 53.052174 | T55: 54.205021 | U55: 55.481575 | V55: 56.500191 | W55: 57.560112 | X55: 58.646866 | Y55: 59.661129 | Z55: 61.050877 | AA55: 62.110481 | AB55: 63.303482 | AC55: 64.26046 | AD55: 65.571259 | AE55: 66.969986 | AF55: 0.021125
A56: TFS000:ha_CompressedNat | B56: Natural Gas ICE | C56: 0 | D56: 0 | E56: 0 | F56: 0 | G56: 0 | H56: 0 | I56: 0 | J56: 0 | K56: 0 | L56: 0 | M56: 0 | N56: 0 | O56: 0 | P56: 0 | Q56: 0 | R56: 0 | S56: 0 | T56: 0 | U56: 0 | V56: 0 | W56: 0 | X56: 0 | Y56: 0 | Z56: 0 | AA56: 0 | AB56: 0 | AC56: 0 | AD56: 0 | AE56: 0 | AF56: --
A57: TFS000:ia_CompressedNat | B57: Natural Gas Bi-fuel | C57: 0 | D57: 0 | E57: 0 | F57: 0 | G57: 0 | H57: 0 | I57: 0 | J57: 0 | K57: 0 | L57: 0 | M57: 0 | N57: 0 | O57: 0 | P57: 0 | Q57: 0 | R57: 0 | S57: 0 | T57: 0 | U57: 0 | V57: 0 | W57: 0 | X57: 0 | Y57: 0 | Z57: 0 | AA57: 0 | AB57: 0 | AC57: 0 | AD57: 0 | AE57: 0 | AF57: --
A58: TFS000:ia_LiquefiedPetr | B58: Propane ICE | C58: 0 | D58: 0 | E58: 0 | F58: 0 | G58: 0 | H58: 0 | I58: 0 | J58: 0 | K58: 0 | L58: 0 | M58: 0 | N58: 0 | O58: 0 | P58: 0 | Q58: 0 | R58: 0 | S58: 0 | T58: 0 | U58: 0 | V58: 0 | W58: 0 | X58: 0 | Y58: 0 | Z58: 0 | AA58: 0 | AB58: 0 | AC58: 0 | AD58: 0 | AE58: 0 | AF58: --
A59: TFS000:ja_LiquefiedPetr | B59: Propane Bi-fuel | C59: 0 | D59: 0 | E59: 0 | F59: 0 | G59: 0 | H59: 0 | I59: 0 | J59: 0 | K59: 0 | L59: 0 | M59: 0 | N59: 0 | O59: 0 | P59: 0 | Q59: 0 | R59: 0 | S59: 0 | T59: 0 | U59: 0 | V59: 0 | W59: 0 | X59: 0 | Y59: 0 | Z59: 0 | AA59: 0 | AB59: 0 | AC59: 0 | AD59: 0 | AE59: 0 | AF59: --
A60: TFS000:ja_FuelCellMetha | B60: Fuel Cell Methanol | C60: 0 | D60: 0 | E60: 0 | F60: 0 | G60: 0 | H60: 0 | I60: 0 | J60: 0 | K60: 0 | L60: 0 | M60: 0 | N60: 0 | O60: 0 | P60: 0 | Q60: 0 | R60: 0 | S60: 0 | T60: 0 | U60: 0 | V60: 0 | W60: 0 | X60: 0 | Y60: 0 | Z60: 0 | AA60: 0 | AB60: 0 | AC60: 0 | AD60: 0 | AE60: 0 | AF60: --
A61: TFS000:ja_FuelCellHydro | B61: Fuel Cell Hydrogen | C61: 0.002034 | D61: 0.004225 | E61: 0.006628 | F61: 0.00918 | G61: 0.011653 | H61: 0.013968 | I61: 0.016271 | J61: 0.018672 | K61: 0.020911 | L61: 0.023173 | M61: 0.025411 | N61: 0.027647 | O61: 0.030044 | P61: 0.032647 | Q61: 0.035303 | R61: 0.038024 | S61: 0.040864 | T61: 0.043703 | U61: 0.046681 | V61: 0.049475 | W61: 0.052331 | X61: 0.055236 | Y61: 0.058096 | Z61: 0.061352 | AA61: 0.064302 | AB61: 0.067422 | AC61: 0.070311 | AD61: 0.073611 | AE61: 0.077048 | AF61: 0.138607
A62: TFS000:ja_TotalAlternat | B62: Total Alternative Light Trucks | C62: 145.60967 | D62: 156.48068 | E62: 169.07797 | F62: 181.20645 | G62: 189.62161 | H62: 194.99156 | I62: 200.23515 | J62: 206.63663 | K62: 211.22647 | L62: 216.19522 | M62: 221.03722 | N62: 225.94132 | O62: 232.14925 | P62: 239.80893 | Q62: 247.61607 | R62: 255.6954 | S62: 264.33047 | T62: 272.73105 | U62: 281.81561 | V62: 289.63901 | W62: 297.69894 | X62: 305.93072 | Y62: 313.8093 | Z62: 323.71317 | AA62: 331.97269 | AB62: 340.90216 | AC62: 348.57013 | AD62: 358.17044 | AE62: 368.26666 | AF62: 0.033694
A64: TFS000:ka_PercentAltern | B64: Percent Alternative Light Truck Sales | C64: 11.326775 | D64: 11.729152 | E64: 12.126184 | F64: 12.515253 | G64: 12.897691 | H64: 13.276489 | I64: 13.652973 | J64: 14.027736 | K64: 14.400922 | L64: 14.773798 | M64: 15.146683 | N64: 15.518919 | O64: 15.891093 | P64: 16.263073 | Q64: 16.633781 | R64: 17.005394 | S64: 17.37615 | T64: 17.746307 | U64: 18.116953 | V64: 18.487982 | W64: 18.85898 | X64: 19.230164 | Y64: 19.601316 | Z64: 19.973127 | AA64: 20.347881 | AB64: 20.720106 | AC64: 21.091866 | AD64: 21.463251 | AE64: 21.833759 | AF64: 0.023716
A65: TFS000:ka_TotalNewTruck | B65: Total New Light Truck Sales | C65: 1285.5352 | D65: 1334.1177 | E65: 1394.3213 | F65: 1447.8849 | G65: 1470.1981 | H65: 1468.6982 | I65: 1466.6047 | J65: 1473.0576 | K65: 1466.7566 | L65: 1463.3693 | M65: 1459.311 | N65: 1455.9088 | O65: 1460.8765 | P65: 1474.561 | Q65: 1488.6337 | R65: 1503.6135 | S65: 1521.2257 | T65: 1536.8328 | U65: 1555.5354 | V65: 1566.634 | W65: 1578.5527 | X65: 1590.8899 | Y65: 1600.9603 | Z65: 1620.7435 | AA65: 1631.4852 | AB65: 1645.2722 | AC65: 1652.6282 | AD65: 1668.7614 | AE65: 1686.6846 | AF65: 0.009747
A67: TFS000:la_TotalFleetVeh | B67: Total Fleet Vehicles | C67: 2115.3096 | D67: 2179.8542 | E67: 2247.3923 | F67: 2289.9019 | G67: 2295.4646 | H67: 2284.9456 | I67: 2273.0161 | J67: 2273.9324 | K67: 2263.3521 | L67: 2255.731 | M67: 2250.6152 | N67: 2244.3782 | O67: 2250.6123 | P67: 2268.9153 | Q67: 2291.9158 | R67: 2311.8799 | S67: 2334.3269 | T67: 2354.6838 | U67: 2377.2295 | V67: 2387.4941 | W67: 2398.3923 | X67: 2406.522 | Y67: 2415.4231 | Z67: 2438.1978 | AA67: 2458.0991 | AB67: 2472.1123 | AC67: 2480.8184 | AD67: 2499.5925 | AE67: 2521.9509 | AF67: 0.006299
B69: Commercial Light Truck Sales 2/
A70: TFS000:clt_MotorGasICE | B70: Motor Gasoline | C70: 410.29077 | D70: 411.8602 | E70: 422.08719 | F70: 427.93866 | G70: 425.80893 | H70: 420.11331 | I70: 414.63776 | J70: 410.57367 | K70: 405.62149 | L70: 400.92529 | M70: 396.54636 | N70: 391.28879 | O70: 387.86078 | P70: 386.62799 | Q70: 386.7623 | R70: 386.57773 | S70: 387.32144 | T70: 387.70996 | U70: 388.84601 | V70: 388.04797 | W70: 387.54559 | X70: 386.55063 | Y70: 386.34116 | Z70: 388.39728 | AA70: 390.78958 | AB70: 393.30301 | AC70: 393.95352 | AD70: 395.85947 | AE70: 398.83917 | AF70: -0.00101
A71: TFS000:clt_DieselTDI | B71: Diesel | C71: 201.5527 | D71: 203.64354 | E71: 209.87985 | F71: 213.99391 | G71: 214.05772 | H71: 212.22472 | I71: 210.50501 | J71: 209.42543 | K71: 207.82423 | L71: 206.28252 | M71: 205.66522 | N71: 205.2451 | O71: 205.64667 | P71: 207.12898 | Q71: 209.04892 | R71: 210.68805 | S71: 212.59926 | T71: 214.24075 | U71: 216.09015 | V71: 216.77892 | W71: 217.4895 | X71: 217.91325 | Y71: 218.44653 | Z71: 220.21542 | AA71: 221.82936 | AB71: 223.04495 | AC71: 223.58778 | AD71: 225.01088 | AE71: 226.82165 | AF71: 0.004227
A72: TFS000:clt_propane | B72: Propane | C72: 0 | D72: 0.426189 | E72: 0.443802 | F72: 0.452902 | G72: 0.472858 | H72: 0.495123 | I72: 0.522636 | J72: 0.559383 | K72: 0.606095 | L72: 0.666157 | M72: 0.739718 | N72: 0.82662 | O72: 0.930666 | P72: 1.058675 | Q72: 1.215913 | R72: 1.400357 | S72: 1.611812 | T72: 1.853485 | U72: 2.121979 | V72: 2.4104 | W72: 2.716785 | X72: 3.048225 | Y72: 3.396039 | Z72: 3.774491 | AA72: 4.156269 | AB72: 4.525984 | AC72: 4.863328 | AD72: 5.19646 | AE72: 5.514914 | AF72: --
A73: TFS000:clt_cng_lng | B73: Compressed/Liquefied Natural Gas | C73: 0 | D73: 0 | E73: 0 | F73: 0 | G73: 0 | H73: 0 | I73: 0 | J73: 0 | K73: 0 | L73: 0 | M73: 0 | N73: 0 | O73: 0 | P73: 0 | Q73: 0 | R73: 0 | S73: 0 | T73: 0 | U73: 0 | V73: 0 | W73: 0 | X73: 0 | Y73: 0 | Z73: 0 | AA73: 0 | AB73: 0 | AC73: 0 | AD73: 0 | AE73: 0 | AF73: --
A74: TFS000:clt_eth_flex | B74: Ethanol-Flex Fuel | C74: 30.450521 | D74: 34.585701 | E74: 41.047306 | F74: 45.537777 | G74: 49.499519 | H74: 53.91124 | I74: 56.826736 | J74: 60.335323 | K74: 64.028458 | L74: 68.345497 | M74: 72.455597 | N74: 76.482697 | O74: 80.193878 | P74: 84.221336 | Q74: 87.631432 | R74: 90.807678 | S74: 93.597557 | T74: 96.278252 | U74: 98.649979 | V74: 100.45418 | W74: 102.04842 | X74: 103.66414 | Y74: 104.52655 | Z74: 105.99032 | AA74: 106.50535 | AB74: 105.59877 | AC74: 105.57081 | AD74: 106.51856 | AE74: 107.08038 | AF74: 0.045934
A75: TFS000:clt_electric | B75: Electric | C75: 0 | D75: 0 | E75: 0 | F75: 0 | G75: 0 | H75: 0 | I75: 0 | J75: 0 | K75: 0 | L75: 0 | M75: 0 | N75: 0 | O75: 0 | P75: 0 | Q75: 0 | R75: 0 | S75: 0 | T75: 0 | U75: 0 | V75: 0 | W75: 0 | X75: 0 | Y75: 0 | Z75: 0 | AA75: 0 | AB75: 0 | AC75: 0 | AD75: 0 | AE75: 0 | AF75: --
A76: TFS000:clt_plug_gas | B76: Plug-in Gasoline Hybrid | C76: 0 | D76: 0.787767 | E76: 0.800162 | F76: 0.80873 | G76: 0.811863 | H76: 0.818902 | I76: 0.83272 | J76: 0.857921 | K76: 0.888965 | L76: 0.926874 | M76: 0.975346 | N76: 1.032321 | O76: 1.10005 | P76: 1.182309 | Q76: 1.282668 | R76: 1.396122 | S76: 1.526245 | T76: 1.669053 | U76: 1.825708 | V76: 1.981003 | W76: 2.139786 | X76: 2.294503 | Y76: 2.443944 | Z76: 2.598308 | AA76: 2.739717 | AB76: 2.862724 | AC76: 2.963504 | AD76: 3.063527 | AE76: 3.154913 | AF76: --
A77: TFS000:clt_plug_diesel | B77: Plug-in Diesel Hybrid | C77: 0 | D77: 0.855433 | E77: 0.878329 | F77: 0.872768 | G77: 0.866021 | H77: 0.860978 | I77: 0.859267 | J77: 0.870182 | K77: 0.892912 | L77: 0.931418 | M77: 0.984099 | N77: 1.050674 | O77: 1.131704 | P77: 1.236498 | Q77: 1.359498 | R77: 1.501473 | S77: 1.662221 | T77: 1.841707 | U77: 2.037043 | V77: 2.23404 | W77: 2.435504 | X77: 2.635596 | Y77: 2.821458 | Z77: 3.013784 | AA77: 3.179278 | AB77: 3.327742 | AC77: 3.442774 | AD77: 3.561341 | AE77: 3.662281 | AF77: --
A78: TFS000:clr_fuel_cell | B78: Fuel Cell | C78: 0 | D78: 0 | E78: 0 | F78: 0 | G78: 0 | H78: 0 | I78: 0 | J78: 0 | K78: 0 | L78: 0 | M78: 0 | N78: 0 | O78: 0 | P78: 0 | Q78: 0 | R78: 0 | S78: 0 | T78: 0 | U78: 0 | V78: 0 | W78: 0 | X78: 0 | Y78: 0 | Z78: 0 | AA78: 0 | AB78: 0 | AC78: 0 | AD78: 0 | AE78: 0 | AF78: --
A79: TFS000:ma_CommercialLig | B79: Total Commercial Light Truck Sales | C79: 642.29395 | D79: 652.15881 | E79: 675.13666 | F79: 689.60468 | G79: 691.51691 | H79: 688.42426 | I79: 684.18414 | J79: 682.62189 | K79: 679.86218 | L79: 678.07776 | M79: 677.36639 | N79: 675.92621 | O79: 676.86371 | P79: 681.45581 | Q79: 687.30078 | R79: 692.37146 | S79: 698.3186 | T79: 703.5932 | U79: 709.57092 | V79: 711.90656 | W79: 714.37567 | X79: 716.10638 | Y79: 717.97565 | Z79: 723.98962 | AA79: 729.19946 | AB79: 732.66321 | AC79: 734.38165 | AD79: 739.21014 | AE79: 745.07336 | AF79: 0.005315
B81: 1/ Includes all fleets of 10 or more.
B82: 2/ Commercial trucks from 8,501 to 10,000 pounds.
B83: ICE = Internal combustion engine.
B84: TDI = Turbocharged direct injection
B85: - - = Not Applicable.
B86: Note: Totals may not equal sum of components due to independent rounding.
B87: Data source: U.S. Energy Information Administration, AEO2023 National Energy Modeling System run ref2023.d020623a.
AF109: Average

Sheet AEO Table 45
B1: ref2023.d020623a | C1: 2022 | D1: 2023 | E1: 2024 | F1: 2025 | G1: 2026 | H1: 2027 | I1: 2028 | J1: 2029 | K1: 2030 | L1: 2031 | M1: 2032 | N1: 2033 | O1: 2034 | P1: 2035 | Q1: 2036 | R1: 2037 | S1: 2038 | T1: 2039 | U1: 2040 | V1: 2041 | W1: 2042 | X1: 2043 | Y1: 2044 | Z1: 2045 | AA1: 2046 | AB1: 2047 | AC1: 2048 | AD1: 2049 | AE1: 2050
C3: Report | D3: Annual Energy Outlook 2023
C4: Scenario | D4: ref2023 | G4: Reference
C5: Datekey | D5: d020623a
C6: Release Date | E6: March 2023
A10: TFL000 | B10: 45. Transportation Fleet Car and Truck Stock by Type and Technology | AF10: Annual
B11: (thousands) | AF11: Change
AF12: 2022–2050
B13: Technology Type | C13: 2022 | D13: 2023 | E13: 2024 | F13: 2025 | G13: 2026 | H13: 2027 | I13: 2028 | J13: 2029 | K13: 2030 | L13: 2031 | M13: 2032 | N13: 2033 | O13: 2034 | P13: 2035 | Q13: 2036 | R13: 2037 | S13: 2038 | T13: 2039 | U13: 2040 | V13: 2041 | W13: 2042 | X13: 2043 | Y13: 2044 | Z13: 2045 | AA13: 2046 | AB13: 2047 | AC13: 2048 | AD13: 2049 | AE13: 2050 | AF13: 2050
B15: Car Stock 1/
B16: Conventional Cars
A17: TFL000:ba_GasolineICEVe | B17: Gasoline ICE Vehicles | C17: 5006.5488 | D17: 4623.4966 | E17: 4322.0991 | F17: 4050.3804 | G17: 3798.4448 | H17: 3573.9875 | I17: 3375.2903 | J17: 3201.9536 | K17: 3049.9338 | L17: 2915.8713 | M17: 2799.1982 | N17: 2695.3247 | O17: 2605.9509 | P17: 2531.2725 | Q17: 2471.8772 | R17: 2420.7988 | S17: 2375.9214 | T17: 2335.8723 | U17: 2299.6143 | V17: 2263.064 | W17: 2226.7246 | X17: 2188.9048 | Y17: 2153.0828 | Z17: 2121.8831 | AA17: 2098.4036 | AB17: 2073.5654 | AC17: 2048.2012 | AD17: 2023.4009 | AE17: 2001.2681 | AF17: -0.032218
A18: TFL000:ba_TDIDieselICE | B18: TDI Diesel ICE | C18: 16.267254 | D18: 14.041601 | E18: 12.078984 | F18: 10.34063 | G18: 8.810128 | H18: 7.452874 | I18: 6.247537 | J18: 5.194445 | K18: 4.291502 | L18: 3.527866 | M18: 2.892869 | N18: 2.376716 | O18: 1.965617 | P18: 1.6438 | Q18: 1.393396 | R18: 1.198524 | S18: 1.047394 | T18: 0.928337 | U18: 0.828804 | V18: 0.742408 | W18: 0.667005 | X18: 0.600459 | Y18: 0.541114 | Z18: 0.488003 | AA18: 0.440443 | AB18: 0.39783 | AC18: 0.359624 | AD18: 0.325348 | AE18: 0.294577 | AF18: -0.133474
A19: TFL000:ba_TotalConventi | B19: Total Conventional Cars | C19: 5022.8159 | D19: 4637.5381 | E19: 4334.1782 | F19: 4060.7209 | G19: 3807.2549 | H19: 3581.4404 | I19: 3381.5378 | J19: 3207.1479 | K19: 3054.2253 | L19: 2919.3992 | M19: 2802.0911 | N19: 2697.7014 | O19: 2607.9165 | P19: 2532.9163 | Q19: 2473.2705 | R19: 2421.9973 | S19: 2376.9688 | T19: 2336.8005 | U19: 2300.4431 | V19: 2263.8064 | W19: 2227.3916 | X19: 2189.5051 | Y19: 2153.6238 | Z19: 2122.3711 | AA19: 2098.844 | AB19: 2073.9634 | AC19: 2048.5608 | AD19: 2023.7262 | AE19: 2001.5626 | AF19: -0.032325
B21: Alternative-Fuel Cars
A22: TFL000:ca_Ethanol-FlexF | B22: Ethanol-Flex Fuel ICE | C22: 260.40921 | D22: 233.98811 | E22: 209.63817 | F22: 186.64131 | G22: 165.97789 | H22: 147.82109 | I22: 132.07271 | J22: 118.78522 | K22: 107.73377 | L22: 98.722214 | M22: 91.63073 | N22: 86.220879 | O22: 82.223007 | P22: 79.438202 | Q22: 77.735916 | R22: 76.54174 | S22: 75.666542 | T22: 75.034683 | U22: 74.555443 | V22: 74.032272 | W22: 73.489876 | X22: 72.862831 | Y22: 72.320984 | Z22: 71.990898 | AA22: 72.008469 | AB22: 71.941269 | AC22: 71.822685 | AD22: 71.715027 | AE22: 71.534599 | AF22: -0.045097
A23: TFL000:ca_100mileEV | B23: 100-Mile Electric Vehicle | C23: 11.328024 | D23: 11.751799 | E23: 12.242356 | F23: 12.619924 | G23: 12.897101 | H23: 13.181957 | I23: 13.471307 | J23: 13.783559 | K23: 14.123207 | L23: 14.488546 | M23: 14.888898 | N23: 15.317131 | O23: 15.79207 | P23: 16.327549 | Q23: 16.936695 | R23: 17.57663 | S23: 18.235157 | T23: 18.903063 | U23: 19.57601 | V23: 20.217279 | W23: 20.833857 | X23: 21.407917 | Y23: 21.97821 | Z23: 22.581919 | AA23: 23.266811 | AB23: 23.926888 | AC23: 24.574036 | AD23: 25.223347 | AE23: 25.902096 | AF23: 0.029978
A24: TFL000:ca_ElectricVehic | B24: 200-Mile Electric Vehicle | C24: 17.462101 | D24: 18.744711 | E24: 21.541321 | F24: 25.222059 | G24: 29.118896 | H24: 33.20546 | I24: 37.426132 | J24: 41.846264 | K24: 46.466694 | L24: 51.259415 | M24: 56.27491 | N24: 61.416988 | O24: 66.797653 | P24: 72.494194 | Q24: 78.615685 | R24: 84.929886 | S24: 91.387436 | T24: 97.968834 | U24: 104.64284 | V24: 111.18373 | W24: 117.62488 | X24: 123.84116 | Y24: 130.07907 | Z24: 136.56813 | AA24: 143.62234 | AB24: 150.50897 | AC24: 157.30911 | AD24: 164.12808 | AE24: 171.15567 | AF24: 0.084934
A25: TFL000:ea_FuelCellGasol | B25: 300-Mile Electric Vehicle | C25: 55.467815 | D25: 63.862431 | E25: 72.749718 | F25: 81.883339 | G25: 90.405708 | H25: 98.471451 | I25: 106.06701 | J25: 113.40288 | K25: 120.48434 | L25: 127.29469 | M25: 133.98381 | N25: 140.44589 | O25: 146.91003 | P25: 153.54129 | Q25: 160.5623 | R25: 167.61523 | S25: 174.68607 | T25: 181.77106 | U25: 188.8676 | V25: 195.65595 | W25: 202.22496 | X25: 208.40951 | Y25: 214.59907 | Z25: 221.16119 | AA25: 228.55313 | AB25: 235.69231 | AC25: 242.69841 | AD25: 249.72317 | AE25: 257.04065 | AF25: 0.056293
A26: TFL000:ca_Plug-inGasoli | B26: Plug-in 20 Gasoline Hybrid | C26: 18.620897 | D26: 18.742386 | E26: 19.225786 | F26: 19.769812 | G26: 20.255058 | H26: 20.684639 | I26: 21.07461 | J26: 21.458031 | K26: 21.848562 | L26: 22.249832 | M26: 22.686924 | N26: 23.151102 | O26: 23.674931 | P26: 24.288008 | Q26: 25.015554 | R26: 25.810991 | S26: 26.663719 | T26: 27.561453 | U26: 28.491934 | V26: 29.406263 | W26: 30.308496 | X26: 31.167662 | Y26: 32.028728 | Z26: 32.935436 | AA26: 33.948967 | AB26: 34.930641 | AC26: 35.897713 | AD26: 36.868179 | AE26: 37.873577 | AF26: 0.02568
A27: TFL000:ca_Plug-in40Hybd | B27: Plug-in 50 Gasoline Hybrid | C27: 9.18985 | D27: 9.232191 | E27: 9.513065 | F27: 9.890547 | G27: 10.297814 | H27: 10.742392 | I27: 11.226655 | J27: 11.782159 | K27: 12.41293 | L27: 13.113447 | M27: 13.8957 | N27: 14.741248 | O27: 15.667826 | P27: 16.685068 | Q27: 17.809175 | R27: 18.991947 | S27: 20.221149 | T27: 21.486172 | U27: 22.775742 | V27: 24.045906 | W27: 25.302801 | X27: 26.519762 | Y27: 27.738804 | Z27: 29.00321 | AA27: 30.374689 | AB27: 31.715918 | AC27: 33.043564 | AD27: 34.375633 | AE27: 35.743801 | AF27: 0.049706
A28: TFL000:ca_Electric-Dies | B28: Electric-Diesel Hybrid | C28: 0 | D28: 0 | E28: 0 | F28: 0 | G28: 0 | H28: 0 | I28: 0 | J28: 0 | K28: 0 | L28: 0 | M28: 0 | N28: 0 | O28: 0 | P28: 0 | Q28: 0 | R28: 0 | S28: 0 | T28: 0 | U28: 0 | V28: 0 | W28: 0 | X28: 0 | Y28: 0 | Z28: 0 | AA28: 0 | AB28: 0 | AC28: 0 | AD28: 0 | AE28: 0 | AF28: --
A29: TFL000:ca_Electric-Gaso | B29: Electric-Gasoline Hybrid | C29: 223.61549 | D29: 216.07962 | E29: 210.16901 | F29: 203.94279 | G29: 198.138 | H29: 193.12856 | I29: 188.94823 | J29: 185.78183 | K29: 183.58957 | L29: 182.24689 | M29: 181.81209 | N29: 182.02373 | O29: 183.03459 | P29: 184.91509 | Q29: 187.75081 | R29: 191.07138 | S29: 194.74928 | T29: 198.696 | U29: 202.83295 | V29: 206.79274 | W29: 210.62627 | X29: 214.1521 | Y29: 217.71721 | Z29: 221.63664 | AA29: 226.31955 | AB29: 230.77928 | AC29: 235.12669 | AD29: 239.49492 | AE29: 244.11679 | AF29: 0.003138
A30: TFL000:ca_CompressedNat | B30: Natural Gas ICE | C30: 11.524047 | D30: 10.680966 | E30: 9.790733 | F30: 8.885427 | G30: 7.990345 | H30: 7.103336 | I30: 6.237593 | J30: 5.428048 | K30: 4.758622 | L30: 4.129239 | M30: 3.577585 | N30: 3.107362 | O30: 2.721086 | P30: 2.399466 | Q30: 2.138429 | R30: 1.966115 | S30: 1.819323 | T30: 1.697581 | U30: 1.589439 | V30: 1.488186 | W30: 1.393384 | X30: 1.30462 | Y30: 1.221511 | Z30: 1.143696 | AA30: 1.070839 | AB30: 1.002622 | AC30: 0.938752 | AD30: 0.87895 | AE30: 0.822958 | AF30: -0.089954
A31: TFL000:da_CompressedNat | B31: Natural Gas Bi-fuel | C31: 0.307861 | D31: 0.264919 | E31: 0.239802 | F31: 0.224525 | G31: 0.210222 | H31: 0.19683 | I31: 0.184292 | J31: 0.172551 | K31: 0.161559 | L31: 0.151267 | M31: 0.141631 | N31: 0.132609 | O31: 0.124161 | P31: 0.116252 | Q31: 0.108846 | R31: 0.101912 | S31: 0.09542 | T31: 0.089341 | U31: 0.08365 | V31: 0.078321 | W31: 0.073332 | X31: 0.06866 | Y31: 0.064286 | Z31: 0.060191 | AA31: 0.056357 | AB31: 0.052767 | AC31: 0.049405 | AD31: 0.046258 | AE31: 0.043311 | AF31: -0.067647
A32: TFL000:da_LiquefiedPetr | B32: Propane ICE | C32: 2.087991 | D32: 1.784609 | E32: 1.535312 | F32: 1.333347 | G32: 1.206512 | H32: 1.127065 | I32: 1.055267 | J32: 0.988043 | K32: 0.925101 | L32: 0.866168 | M32: 0.810991 | N32: 0.759328 | O32: 0.710956 | P32: 0.665665 | Q32: 0.62326 | R32: 0.583556 | S32: 0.546381 | T32: 0.511575 | U32: 0.478986 | V32: 0.448473 | W32: 0.419903 | X32: 0.393154 | Y32: 0.368109 | Z32: 0.344659 | AA32: 0.322703 | AB32: 0.302145 | AC32: 0.282898 | AD32: 0.264876 | AE32: 0.248003 | AF32: -0.073267
A33: TFL000:ea_LiquefiedPetr | B33: Propane Bi-fuel | C33: 4.082679 | D33: 3.480398 | E33: 2.97779 | F33: 2.565041 | G33: 2.283806 | H33: 2.108607 | I33: 1.959856 | J33: 1.835006 | K33: 1.718109 | L33: 1.60866 | M33: 1.506182 | N33: 1.410233 | O33: 1.320396 | P33: 1.236282 | Q33: 1.157526 | R33: 1.083788 | S33: 1.014747 | T33: 0.950104 | U33: 0.889579 | V33: 0.832909 | W33: 0.77985 | X33: 0.730171 | Y33: 0.683656 | Z33: 0.640105 | AA33: 0.599328 | AB33: 0.561149 | AC33: 0.525401 | AD33: 0.491931 | AE33: 0.460594 | AF33: -0.074969
A34: TFL000:ea_FuelCellMetha | B34: Fuel Cell Methanol | C34: 0 | D34: 0 | E34: 0 | F34: 0 | G34: 0 | H34: 0 | I34: 0 | J34: 0 | K34: 0 | L34: 0 | M34: 0 | N34: 0 | O34: 0 | P34: 0 | Q34: 0 | R34: 0 | S34: 0 | T34: 0 | U34: 0 | V34: 0 | W34: 0 | X34: 0 | Y34: 0 | Z34: 0 | AA34: 0 | AB34: 0 | AC34: 0 | AD34: 0 | AE34: 0 | AF34: --
A35: TFL000:ea_FuelCellHydro | B35: Fuel Cell Hydrogen | C35: 0.695658 | D35: 0.693525 | E35: 0.730931 | F35: 0.79699 | G35: 0.88554 | H35: 0.9894 | I35: 1.10531 | J35: 1.234237 | K35: 1.374475 | L35: 1.524476 | M35: 1.685228 | N35: 1.854181 | O35: 2.033293 | P35: 2.223712 | Q35: 2.427094 | R35: 2.639039 | S35: 2.858608 | T35: 3.08428 | U35: 3.314411 | V35: 3.544198 | W35: 3.773129 | X35: 3.997288 | Y35: 4.220754 | Z35: 4.448301 | AA35: 4.688444 | AB35: 4.925473 | AC35: 5.161976 | AD35: 5.399414 | AE35: 5.639956 | AF35: 0.077606
A36: TFL000:ea_TotalAlternat | B36: Total Alternative Cars | C36: 614.79175 | D36: 589.30566 | E36: 570.354 | F36: 553.77508 | G36: 539.66693 | H36: 528.7608 | I36: 520.82898 | J36: 516.4978 | K36: 515.59692 | L36: 517.65485 | M36: 522.89471 | N36: 530.58075 | O36: 541.01001 | P36: 554.33075 | Q36: 570.88135 | R36: 588.91223 | S36: 607.94379 | T36: 627.75415 | U36: 648.09857 | V36: 667.7262 | W36: 686.85071 | X36: 704.85486 | Y36: 723.02039 | Z36: 742.51434 | AA36: 764.8316 | AB36: 786.33948 | AC36: 807.43066 | AD36: 828.60986 | AE36: 850.58197 | AF36: 0.011662
A38: TFL000:fa_TotalNewCarSa | B38: Total Car Stock | C38: 5637.6074 | D38: 5226.8438 | E38: 4904.5322 | F38: 4614.4961 | G38: 4346.9219 | H38: 4110.2012 | I38: 3902.3667 | J38: 3723.6458 | K38: 3569.8223 | L38: 3437.054 | M38: 3324.9858 | N38: 3228.2822 | O38: 3148.9265 | P38: 3087.2471 | Q38: 3044.1519 | R38: 3010.9097 | S38: 2984.9126 | T38: 2964.5547 | U38: 2948.5417 | V38: 2931.5327 | W38: 2914.2422 | X38: 2894.3599 | Y38: 2876.644 | Z38: 2864.8855 | AA38: 2863.6755 | AB38: 2860.3027 | AC38: 2855.9915 | AD38: 2852.3359 | AE38: 2852.1445 | AF38: -0.024042
B40: Light Truck Stock 1/
B41: Conventional Light Trucks
A42: TFL000:ga_GasolineICEVe | B42: Gasoline ICE Vehicles | C42: 7639.083 | D42: 7655.0962 | E42: 7760.314 | F42: 7895.3628 | G42: 8023.1143 | H42: 8127.6328 | I42: 8212.9814 | J42: 8290.5889 | K42: 8349.9736 | L42: 8394.4512 | M42: 8423.9824 | N42: 8440.4258 | O42: 8451.6865 | P42: 8465.3477 | Q42: 8480.6543 | R42: 8497.1035 | S42: 8516.1016 | T42: 8536.0273 | U42: 8559.6494 | V42: 8580.2031 | W42: 8599.4805 | X42: 8618.3643 | Y42: 8635.5254 | Z42: 8659.0557 | AA42: 8680.4678 | AB42: 8702.9229 | AC42: 8720.7891 | AD42: 8742.2803 | AE42: 8768.0771 | AF42: 0.004935
A43: TFL000:ga_TDIDieselICE | B43: TDI Diesel ICE | C43: 60.55452 | D43: 54.813412 | E43: 48.998947 | F43: 43.883667 | G43: 39.715416 | H43: 35.790714 | I43: 32.023296 | J43: 28.420086 | K43: 24.994423 | L43: 21.770369 | M43: 18.758324 | N43: 15.995414 | O43: 13.487585 | P43: 11.270679 | Q43: 9.33564 | R43: 7.682456 | S43: 6.313601 | T43: 5.195662 | U43: 4.315732 | V43: 3.636456 | W43: 3.103021 | X43: 2.68296 | Y43: 2.347914 | Z43: 2.093235 | AA43: 1.89311 | AB43: 1.714415 | AC43: 1.55453 | AD43: 1.411821 | AE43: 1.284441 | AF43: -0.128566
A44: TFL000:ga_TotalConventi | B44: Total Conventional Light Trucks | C44: 7699.6377 | D44: 7709.9097 | E44: 7809.313 | F44: 7939.2466 | G44: 8062.8296 | H44: 8163.4233 | I44: 8245.0049 | J44: 8319.0088 | K44: 8374.9678 | L44: 8416.2217 | M44: 8442.7412 | N44: 8456.4209 | O44: 8465.1738 | P44: 8476.6182 | Q44: 8489.9902 | R44: 8504.7861 | S44: 8522.415 | T44: 8541.2227 | U44: 8563.9648 | V44: 8583.8398 | W44: 8602.583 | X44: 8621.0469 | Y44: 8637.873 | Z44: 8661.1484 | AA44: 8682.3613 | AB44: 8704.6377 | AC44: 8722.3438 | AD44: 8743.6924 | AE44: 8769.3613 | AF44: 0.004657
B46: Alternative-Fuel Light Trucks
A47: TFL000:ha_Ethanol-FlexF | B47: Ethanol-Flex Fuel ICE | C47: 1218.5098 | D47: 1120.8608 | E47: 1037.9226 | F47: 953.25147 | G47: 874.38513 | H47: 799.1477 | I47: 728.95618 | J47: 665.63318 | K47: 608.78552 | L47: 558.96545 | M47: 515.91949 | N47: 479.58041 | O47: 449.99478 | P47: 427.03122 | Q47: 409.60956 | R47: 396.73981 | S47: 387.82333 | T47: 381.65939 | U47: 377.57605 | V47: 374.55402 | W47: 372.48346 | X47: 371.24045 | Y47: 370.60294 | Z47: 371.13873 | AA47: 371.85049 | AB47: 372.85184 | AC47: 373.50031 | AD47: 374.77466 | AE47: 376.6777 | AF47: -0.041062
A48: TFL000:ha_100mileEV | B48: 100-Mile Electric Vehicle | C48: 0.402784 | D48: 0.424502 | E48: 0.4509 | F48: 0.475507 | G48: 0.495525 | H48: 0.511744 | I48: 0.524131 | J48: 0.533375 | K48: 0.539227 | L48: 0.542153 | M48: 0.542259 | N48: 0.539481 | O48: 0.534017 | P48: 0.526224 | Q48: 0.516212 | R48: 0.50371 | S48: 0.488581 | T48: 0.471082 | U48: 0.451541 | V48: 0.430114 | W48: 0.407183 | X48: 0.383066 | Y48: 0.357975 | Z48: 0.33221 | AA48: 0.305866 | AB48: 0.279164 | AC48: 0.252075 | AD48: 0.224646 | AE48: 0.196857 | AF48: -0.025244
A49: TFL000:ha_ElectricVehic | B49: 200-Mile Electric Vehicle | C49: 7.412667 | D49: 13.531482 | E49: 22.335041 | F49: 33.406113 | G49: 46.353321 | H49: 60.676521 | I49: 76.242645 | J49: 93.138985 | K49: 110.99479 | L49: 129.77493 | M49: 149.34218 | N49: 169.6248 | O49: 190.79437 | P49: 213.05165 | Q49: 236.29544 | R49: 260.44391 | S49: 285.51135 | T49: 311.33316 | U49: 338.00738 | V49: 365.09576 | W49: 392.64249 | X49: 420.65604 | Y49: 449.01431 | Z49: 478.30362 | AA49: 507.88632 | AB49: 537.97443 | AC49: 568.08893 | AD49: 598.92822 | AE49: 630.58472 | AF49: 0.17198
A50: TFL000:ja_FuelCellGasol | B50: 300-Mile Electric Vehicle | C50: 4.682086 | D50: 6.222938 | E50: 8.134543 | F50: 10.340325 | G50: 12.714148 | H50: 15.219875 | I50: 17.849283 | J50: 20.622627 | K50: 23.482182 | L50: 26.428581 | M50: 29.444866 | N50: 32.522842 | O50: 35.698284 | P50: 39.007183 | Q50: 42.437012 | R50: 45.980495 | S50: 49.641651 | T50: 53.398613 | U50: 57.268452 | V50: 61.18808 | W50: 65.168549 | X50: 69.211052 | Y50: 73.297386 | Z50: 77.51741 | AA50: 81.776482 | AB50: 86.10894 | AC50: 90.443428 | AD50: 94.884018 | AE50: 99.444466 | AF50: 0.115316
A51: TFL000:ha_Plug-inGasoli | B51: Plug-in 20 Gasoline Hybrid | C51: 19.925865 | D51: 21.544413 | E51: 23.247982 | F51: 26.570223 | G51: 29.872574 | H51: 33.027237 | I51: 36.027607 | J51: 38.916355 | K51: 41.642071 | L51: 44.229752 | M51: 46.675167 | N51: 48.98344 | O51: 51.200951 | P51: 53.372917 | Q51: 55.503918 | R51: 57.604095 | S51: 59.697903 | T51: 61.78006 | U51: 63.879299 | V51: 65.963066 | W51: 68.048286 | X51: 70.14286 | Y51: 72.239494 | Z51: 74.405258 | AA51: 76.580681 | AB51: 78.79007 | AC51: 80.991341 | AD51: 83.242905 | AE51: 85.554489 | AF51: 0.053418
A52: TFL000:ha_Plug-in40Hybd | B52: Plug-in 50 Gasoline Hybrid | C52: 1.216323 | D52: 1.800487 | E52: 2.66213 | F52: 3.815796 | G52: 5.275611 | H52: 6.958508 | I52: 8.842771 | J52: 10.92844 | K52: 13.17403 | L52: 15.571791 | M52: 18.100981 | N52: 20.747391 | O52: 23.521433 | P52: 26.438812 | Q52: 29.488754 | R52: 32.663853 | S52: 35.966309 | T52: 39.37788 | U52: 42.906147 | V52: 46.508396 | W52: 50.184578 | X52: 53.931499 | Y52: 57.733253 | Z52: 61.64463 | AA52: 65.605125 | AB52: 69.635689 | AC52: 73.692322 | AD52: 77.833954 | AE52: 82.071625 | AF52: 0.162322
A53: TFL000:ha_Electric-Dies | B53: Electric-Diesel Hybrid | C53: 0 | D53: 0 | E53: 0 | F53: 0 | G53: 0 | H53: 0 | I53: 0 | J53: 0 | K53: 0 | L53: 0 | M53: 0 | N53: 0 | O53: 0 | P53: 0 | Q53: 0 | R53: 0 | S53: 0 | T53: 0 | U53: 0 | V53: 0 | W53: 0 | X53: 0 | Y53: 0 | Z53: 0 | AA53: 0 | AB53: 0 | AC53: 0 | AD53: 0 | AE53: 0 | AF53: --
A54: TFL000:ha_Electric-Gaso | B54: Electric-Gasoline Hybrid | C54: 135.86803 | D54: 160.33597 | E54: 184.47356 | F54: 209.81908 | G54: 234.51753 | H54: 257.46469 | I54: 278.54953 | J54: 298.11563 | K54: 315.83499 | L54: 331.87372 | M54: 346.20721 | N54: 358.90128 | O54: 370.3175 | P54: 380.79077 | Q54: 390.40115 | R54: 399.24509 | S54: 407.54202 | T54: 415.3074 | U54: 422.79144 | V54: 429.82556 | W54: 436.56516 | X54: 443.10947 | Y54: 449.46088 | Z54: 456.09204 | AA54: 462.64462 | AB54: 469.25632 | AC54: 475.66361 | AD54: 482.26096 | AE54: 489.10043 | AF54: 0.046808
A55: TFL000:ha_CompressedNat | B55: Natural Gas ICE | C55: 2.839469 | D55: 2.640239 | E55: 2.471421 | F55: 2.307671 | G55: 2.148902 | H55: 1.994446 | I55: 1.851924 | J55: 1.735058 | K55: 1.626692 | L55: 1.521126 | M55: 1.420394 | N55: 1.324712 | O55: 1.23502 | P55: 1.150507 | Q55: 1.071948 | R55: 1.010057 | S55: 0.950586 | T55: 0.898791 | U55: 0.849829 | V55: 0.803543 | W55: 0.759786 | X55: 0.718421 | Y55: 0.679315 | Z55: 0.642346 | AA55: 0.607395 | AB55: 0.574352 | AC55: 0.543113 | AD55: 0.513579 | AE55: 0.485657 | AF55: -0.061119
A56: TFL000:ia_CompressedNat | B56: Natural Gas Bi-fuel | C56: 2.185251 | D56: 2.015078 | E56: 1.904845 | F56: 1.800663 | G56: 1.702199 | H56: 1.609138 | I56: 1.521183 | J56: 1.438052 | K56: 1.35948 | L56: 1.285217 | M56: 1.215024 | N56: 1.148678 | O56: 1.085968 | P56: 1.026693 | Q56: 0.970665 | R56: 0.917705 | S56: 0.867645 | T56: 0.820325 | U56: 0.775595 | V56: 0.733312 | W56: 0.693342 | X56: 0.655559 | Y56: 0.619842 | Z56: 0.586077 | AA56: 0.554158 | AB56: 0.523983 | AC56: 0.495457 | AD56: 0.468489 | AE56: 0.442995 | AF56: -0.055404
A57: TFL000:ia_LiquefiedPetr | B57: Propane ICE | C57: 5.754653 | D57: 5.170995 | E57: 4.633657 | F57: 4.204803 | G57: 3.890476 | H57: 3.661827 | I57: 3.461627 | J57: 3.272411 | K57: 3.093574 | L57: 2.924544 | M57: 2.764783 | N57: 2.61378 | O57: 2.471052 | P57: 2.336146 | Q57: 2.208631 | R57: 2.0881 | S57: 1.97417 | T57: 1.866478 | U57: 1.764681 | V57: 1.668455 | W57: 1.577494 | X57: 1.49151 | Y57: 1.410229 | Z57: 1.333392 | AA57: 1.260757 | AB57: 1.192091 | AC57: 1.127179 | AD57: 1.065813 | AE57: 1.0078 | AF57: -0.060327
A58: TFL000:ja_LiquefiedPetr | B58: Propane Bi-fuel | C58: 5.126245 | D58: 4.726759 | E58: 4.468183 | F58: 4.223802 | G58: 3.992835 | H58: 3.774542 | I58: 3.568225 | J58: 3.373224 | K58: 3.188919 | L58: 3.014719 | M58: 2.850067 | N58: 2.69444 | O58: 2.547341 | P58: 2.4083 | Q58: 2.276875 | R58: 2.152647 | S58: 2.035221 | T58: 1.924223 | U58: 1.819299 | V58: 1.720117 | W58: 1.62636 | X58: 1.537732 | Y58: 1.45395 | Z58: 1.374748 | AA58: 1.299876 | AB58: 1.229095 | AC58: 1.162182 | AD58: 1.098925 | AE58: 1.039122 | AF58: -0.055406
A59: TFL000:ja_FuelCellMetha | B59: Fuel Cell Methanol | C59: 0 | D59: 0 | E59: 0 | F59: 0 | G59: 0 | H59: 0 | I59: 0 | J59: 0 | K59: 0 | L59: 0 | M59: 0 | N59: 0 | O59: 0 | P59: 0 | Q59: 0 | R59: 0 | S59: 0 | T59: 0 | U59: 0 | V59: 0 | W59: 0 | X59: 0 | Y59: 0 | Z59: 0 | AA59: 0 | AB59: 0 | AC59: 0 | AD59: 0 | AE59: 0 | AF59: --
A60: TFL000:ja_FuelCellHydro | B60: Fuel Cell Hydrogen | C60: 0.002034 | D60: 0.006205 | E60: 0.012722 | F60: 0.0217 | G60: 0.033009 | H60: 0.046429 | I60: 0.061843 | J60: 0.079235 | K60: 0.098309 | L60: 0.118946 | M60: 0.140962 | N60: 0.164185 | O60: 0.188612 | P60: 0.214285 | Q60: 0.241124 | R60: 0.269074 | S60: 0.298147 | T60: 0.328241 | U60: 0.359404 | V60: 0.391358 | W60: 0.424089 | X60: 0.45757 | Y60: 0.491682 | Z60: 0.526757 | AA60: 0.562411 | AB60: 0.598777 | AC60: 0.635567 | AD60: 0.67315 | AE60: 0.711608 | AF60: 0.232694
A61: TFL000:ja_TotalAlternat | B61: Total Alternative Light Trucks | C61: 1403.9254 | D61: 1339.2802 | E61: 1292.7174 | F61: 1250.2372 | G61: 1215.3812 | H61: 1184.0927 | I61: 1157.457 | J61: 1137.7867 | K61: 1123.8199 | L61: 1116.2509 | M61: 1114.6233 | N61: 1118.8455 | O61: 1129.5892 | P61: 1147.3549 | Q61: 1171.0212 | R61: 1199.6185 | S61: 1232.7968 | T61: 1269.1655 | U61: 1308.4491 | V61: 1348.8818 | W61: 1390.5808 | X61: 1433.535 | Y61: 1477.3615 | Z61: 1523.8972 | AA61: 1570.9343 | AB61: 1619.0146 | AC61: 1666.5957 | AD61: 1715.9692 | AE61: 1767.3174 | AF61: 0.008255
A63: TFL000:ka_TotalNewTruck | B63: Total Light Truck Stock | C63: 9103.5635 | D63: 9049.1895 | E63: 9102.0303 | F63: 9189.4834 | G63: 9278.2109 | H63: 9347.5156 | I63: 9402.4619 | J63: 9456.7959 | K63: 9498.7881 | L63: 9532.4727 | M63: 9557.3643 | N63: 9575.2666 | O63: 9594.7627 | P63: 9623.9727 | Q63: 9661.0117 | R63: 9704.4043 | S63: 9755.2119 | T63: 9810.3887 | U63: 9872.4141 | V63: 9932.7217 | W63: 9993.1641 | X63: 10054.582 | Y63: 10115.234 | Z63: 10185.046 | AA63: 10253.296 | AB63: 10323.652 | AC63: 10388.939 | AD63: 10459.662 | AE63: 10536.679 | AF63: 0.005235
A65: TFL000:la_TotalFleetVeh | B65: Total Fleet Vehicles | C65: 14741.171 | D65: 14276.033 | E65: 14006.562 | F65: 13803.979 | G65: 13625.133 | H65: 13457.717 | I65: 13304.828 | J65: 13180.441 | K65: 13068.61 | L65: 12969.526 | M65: 12882.35 | N65: 12803.549 | O65: 12743.689 | P65: 12711.22 | Q65: 12705.164 | R65: 12715.314 | S65: 12740.125 | T65: 12774.943 | U65: 12820.956 | V65: 12864.254 | W65: 12907.406 | X65: 12948.941 | Y65: 12991.879 | Z65: 13049.932 | AA65: 13116.972 | AB65: 13183.955 | AC65: 13244.931 | AD65: 13311.998 | AE65: 13388.823 | AF65: -0.003431
B67: Commercial Light Truck Stock 2/
A68: TFL000:clt_MotorGasICE | B68: Motor Gasoline | C68: 8031.3188 | D68: 7940.3721 | E68: 7903.7354 | F68: 7909.8018 | G68: 7940.8301 | H68: 7987.8506 | I68: 8042.6831 | J68: 8101.8809 | K68: 8168.1221 | L68: 8235.2178 | M68: 8306.8525 | N68: 8373.7109 | O68: 8435.4941 | P68: 8494.0547 | Q68: 8552.7588 | R68: 8606.1826 | S68: 8658.1016 | T68: 8711.0576 | U68: 8762.5674 | V68: 8814.5947 | W68: 8864.6865 | X68: 8916.5879 | Y68: 8972.7021 | Z68: 9027.6074 | AA68: 9080.1377 | AB68: 9132.8711 | AC68: 9182.998 | AD68: 9228.2012 | AE68: 9269.6211 | AF68: 0.005134
A69: TFL000:clt_DieselTDI | B69: Diesel | C69: 5201.8086 | D69: 5250.897 | E69: 5302.2627 | F69: 5353.2271 | G69: 5399.2612 | H69: 5437.2954 | I69: 5468.6099 | J69: 5492.0894 | K69: 5507.6777 | L69: 5512.2534 | M69: 5521.1802 | N69: 5519.0474 | O69: 5513.2485 | P69: 5500.6274 | Q69: 5486.0024 | R69: 5469.0234 | S69: 5449.0186 | T69: 5431.8198 | U69: 5414.2065 | V69: 5406.397 | W69: 5405.3071 | X69: 5420.1104 | Y69: 5445.6807 | Z69: 5472.603 | AA69: 5500.2749 | AB69: 5530.6382 | AC69: 5561.6924 | AD69: 5585.7549 | AE69: 5608.0508 | AF69: 0.002689
A70: TFL000:clt_propane | B70: Propane | C70: 0.0272 | D70: 0.446405 | E70: 0.885205 | F70: 1.334503 | G70: 1.804604 | H70: 2.297728 | I70: 2.818901 | J70: 3.37659 | K70: 3.979535 | L70: 4.63974 | M70: 5.36918 | N70: 6.179323 | O70: 7.085126 | P70: 8.108479 | Q70: 9.276356 | R70: 10.613518 | S70: 12.144465 | T70: 13.896809 | U70: 15.894682 | V70: 18.155231 | W70: 20.693428 | X70: 23.531113 | Y70: 26.681091 | Z70: 30.170033 | AA70: 33.996666 | AB70: 38.143761 | AC70: 42.573021 | AD70: 47.273495 | AE70: 52.222855 | AF70: 0.309968
A71: TFL000:clt_cng_lng | B71: Compressed/Liquefied Natural Gas | C71: 12.657215 | D71: 12.253946 | E71: 11.837053 | F71: 11.405747 | G71: 10.958616 | H71: 10.497103 | I71: 10.004997 | J71: 9.502007 | K71: 8.96981 | L71: 8.417904 | M71: 7.827207 | N71: 7.176929 | O71: 6.57033 | P71: 6.001122 | Q71: 5.468161 | R71: 4.972802 | S71: 4.512303 | T71: 4.093148 | U71: 3.71057 | V71: 3.361499 | W71: 3.043814 | X71: 2.755612 | Y71: 2.494757 | Z71: 2.250751 | AA71: 1.967801 | AB71: 1.629623 | AC71: 1.333248 | AD71: 1.052214 | AE71: 0.836617 | AF71: -0.092464
A72: TFL000:clt_e85_or_not | B72: Ethanol-Flex Fuel | C72: 1568.9006 | D72: 1592.0657 | E72: 1617.6141 | F72: 1642.8894 | G72: 1666.8478 | H72: 1689.6023 | I72: 1709.5068 | J72: 1727.177 | K72: 1742.9712 | L72: 1757.8314 | M72: 1771.9937 | N72: 1785.913 | O72: 1799.8901 | P72: 1814.8966 | Q72: 1830.9843 | R72: 1848.5692 | S72: 1867.8733 | T72: 1889.3264 | U72: 1913.0802 | V72: 1938.9139 | W72: 1966.855 | X72: 1997.0092 | Y72: 2025.7972 | Z72: 2053.8918 | AA72: 2081.9648 | AB72: 2106.8191 | AC72: 2130.8447 | AD72: 2151.365 | AE72: 2171.7822 | AF72: 0.011681
A73: TFL000:clt_electric | B73: Electric | C73: 0 | D73: 0 | E73: 0 | F73: 0 | G73: 0 | H73: 0 | I73: 0 | J73: 0 | K73: 0 | L73: 0 | M73: 0 | N73: 0 | O73: 0 | P73: 0 | Q73: 0 | R73: 0 | S73: 0 | T73: 0 | U73: 0 | V73: 0 | W73: 0 | X73: 0 | Y73: 0 | Z73: 0 | AA73: 0 | AB73: 0 | AC73: 0 | AD73: 0 | AE73: 0 | AF73: --
A74: TFL000:clt_plgin_gas | B74: Plug-in Gasoline Hybrid | C74: 0 | D74: 0.787767 | E74: 1.587929 | F74: 2.39666 | G74: 3.208523 | H74: 4.027426 | I74: 4.860145 | J74: 5.716928 | K74: 6.601765 | L74: 7.519146 | M74: 8.476849 | N74: 9.480237 | O74: 10.536694 | P74: 11.657214 | Q74: 12.856302 | R74: 14.143478 | S74: 15.531952 | T74: 17.031109 | U74: 18.651724 | V74: 20.389593 | W74: 22.245596 | X74: 24.213247 | Y74: 26.284992 | Z74: 28.463531 | AA74: 30.733688 | AB74: 33.074711 | AC74: 35.461926 | AD74: 37.891819 | AE74: 40.35284 | AF74: --
A75: TFL000:clt_plugin_dies | B75: Plug-in Diesel Hybrid | C75: 0 | D75: 0.855433 | E75: 1.733762 | F75: 2.60653 | G75: 3.472551 | H75: 4.333529 | I75: 5.192794 | J75: 6.061743 | K75: 6.950156 | L75: 7.87124 | M75: 8.836157 | N75: 9.855454 | O75: 10.940022 | P75: 12.10994 | Q75: 13.379708 | R75: 14.764685 | S75: 16.280159 | T75: 17.941574 | U75: 19.761744 | V75: 21.739498 | W75: 23.87665 | X75: 26.169352 | Y75: 28.600906 | Z75: 31.175287 | AA75: 33.863022 | AB75: 36.644165 | AC75: 39.482059 | AD75: 42.376591 | AE75: 45.30611 | AF75: --
A76: TFL000:clr_fuel_sells | B76: Fuel Cell | C76: 0 | D76: 0 | E76: 0 | F76: 0 | G76: 0 | H76: 0 | I76: 0 | J76: 0 | K76: 0 | L76: 0 | M76: 0 | N76: 0 | O76: 0 | P76: 0 | Q76: 0 | R76: 0 | S76: 0 | T76: 0 | U76: 0 | V76: 0 | W76: 0 | X76: 0 | Y76: 0 | Z76: 0 | AA76: 0 | AB76: 0 | AC76: 0 | AD76: 0 | AE76: 0 | AF76: --
A77: TFL000:ma_CommercialLig | B77: Total Commercial Light Truck Stock | C77: 14814.712 | D77: 14797.679 | E77: 14839.655 | F77: 14923.662 | G77: 15026.385 | H77: 15135.905 | I77: 15243.677 | J77: 15345.805 | K77: 15445.272 | L77: 15533.75 | M77: 15630.535 | N77: 15711.363 | O77: 15783.765 | P77: 15847.455 | Q77: 15910.727 | R77: 15968.27 | S77: 16023.463 | T77: 16085.165 | U77: 16147.872 | V77: 16223.552 | W77: 16306.708 | X77: 16410.377 | Y77: 16528.242 | Z77: 16646.162 | AA77: 16762.939 | AB77: 16879.82 | AC77: 16994.387 | AD77: 17093.916 | AE77: 17188.174 | AF77: 0.005321
B79: 1/ Includes all fleets of 10 or more.
B80: 2/ Commercial trucks from 8,501 to 10,000 pounds.
B81: ICE = Internal combustion engine.
B82: TDI = Turbocharged direct injection
B83: - - = Not applicable.
B84: Note: Totals may not equal sum of components due to independent rounding.
B85: Data source: U.S. Energy Information Administration, AEO2023 National Energy Modeling System run ref2023.d020623a.
AF109: Average

Sheet AEO Table 49
B1: ref2023.d020623a | C1: 2022 | D1: 2023 | E1: 2024 | F1: 2025 | G1: 2026 | H1: 2027 | I1: 2028 | J1: 2029 | K1: 2030 | L1: 2031 | M1: 2032 | N1: 2033 | O1: 2034 | P1: 2035 | Q1: 2036 | R1: 2037 | S1: 2038 | T1: 2039 | U1: 2040 | V1: 2041 | W1: 2042 | X1: 2043 | Y1: 2044 | Z1: 2045 | AA1: 2046 | AB1: 2047 | AC1: 2048 | AD1: 2049 | AE1: 2050
C3: Report | D3: Annual Energy Outlook 2023
C4: Scenario | D4: ref2023 | G4: Reference
C5: Datekey | D5: d020623a
C6: Release Date | E6: March 2023
A10: FTE000 | B10: 49. Freight Transportation Energy Use | AF10: Annual
AF11: Change
AF12: 2022–2050
B13: Technology and Fuel Type | C13: 2022 | D13: 2023 | E13: 2024 | F13: 2025 | G13: 2026 | H13: 2027 | I13: 2028 | J13: 2029 | K13: 2030 | L13: 2031 | M13: 2032 | N13: 2033 | O13: 2034 | P13: 2035 | Q13: 2036 | R13: 2037 | S13: 2038 | T13: 2039 | U13: 2040 | V13: 2041 | W13: 2042 | X13: 2043 | Y13: 2044 | Z13: 2045 | AA13: 2046 | AB13: 2047 | AC13: 2048 | AD13: 2049 | AE13: 2050 | AF13: 2050
B15: Freight Truck Stock by Size Class 1/
B17: Vehicle Miles Traveled (billion miles)
B18: Light Medium
A19: FTE000:lm_vmt_stk_Dies | B19: Diesel | C19: 54.392624 | D19: 53.187412 | E19: 52.529724 | F19: 52.479733 | G19: 52.720959 | H19: 52.851051 | I19: 52.993168 | J19: 53.175175 | K19: 53.566818 | L19: 54.220245 | M19: 55.079853 | N19: 55.840675 | O19: 56.638935 | P19: 57.504395 | Q19: 58.304447 | R19: 59.176174 | S19: 60.063702 | T19: 61.000946 | U19: 62.044392 | V19: 63.120777 | W19: 64.186768 | X19: 65.249405 | Y19: 66.318535 | Z19: 67.468948 | AA19: 68.816582 | AB19: 70.243614 | AC19: 71.603302 | AD19: 73.056641 | AE19: 74.77961 | AF19: 0.011433
A20: FTE000:lm_vmt_stk_Gas | B20: Motor Gasoline | C20: 16.846205 | D20: 17.761892 | E20: 18.76346 | F20: 19.899122 | G20: 21.083855 | H20: 22.151054 | I20: 23.138805 | J20: 24.075592 | K20: 25.031351 | L20: 26.026825 | M20: 27.096857 | N20: 28.109198 | O20: 29.09211 | P20: 30.063576 | Q20: 30.988947 | R20: 31.943773 | S20: 32.87841 | T20: 33.782879 | U20: 34.707161 | V20: 35.65567 | W20: 36.558773 | X20: 37.368587 | Y20: 38.121651 | Z20: 38.871418 | AA20: 39.695541 | AB20: 40.532322 | AC20: 41.299179 | AD20: 42.100204 | AE20: 43.049957 | AF20: 0.034076
A21: FTE000:lm_vmt_stk_Liq | B21: Propane | C21: 0.000585 | D21: 0.007631 | E21: 0.014685 | F21: 0.021224 | G21: 0.027498 | H21: 0.033387 | I21: 0.038968 | J21: 0.044345 | K21: 0.049704 | L21: 0.055248 | M21: 0.061056 | N21: 0.066844 | O21: 0.072697 | P21: 0.078774 | Q21: 0.085074 | R21: 0.091911 | S21: 0.099268 | T21: 0.107287 | U21: 0.116186 | V21: 0.125999 | W21: 0.136618 | X21: 0.148055 | Y21: 0.160189 | Z21: 0.173373 | AA21: 0.188008 | AB21: 0.203789 | AC21: 0.220242 | AD21: 0.237737 | AE21: 0.256857 | AF21: 0.242756
A22: FTE000:lm_vmt_stk_NGas | B22: Compressed/Liquefied Natural Gas | C22: 0.015418 | D22: 0.013986 | E22: 0.012747 | F22: 0.011705 | G22: 0.010794 | H22: 0.00993 | I22: 0.00913 | J22: 0.008393 | K22: 0.007732 | L22: 0.007146 | M22: 0.006624 | N22: 0.006093 | O22: 0.005543 | P22: 0.004963 | Q22: 0.004369 | R22: 0.003744 | S22: 0.003165 | T22: 0.002637 | U22: 0.002105 | V22: 0.001683 | W22: 0.001373 | X22: 0.001147 | Y22: 0.001 | Z22: 0.000899 | AA22: 0.00082 | AB22: 0.000769 | AC22: 0.000703 | AD22: 0.000625 | AE22: 0.000529 | AF22: -0.113488
A23: FTE000:lm_vmt_stk_eff | B23: Ethanol-Flex Fuel | C23: 3.793104 | D23: 3.733989 | E23: 3.701197 | F23: 3.694834 | G23: 3.705554 | H23: 3.713322 | I23: 3.722355 | J23: 3.737602 | K23: 3.763645 | L23: 3.807043 | M23: 3.864232 | N23: 3.914667 | O23: 3.947316 | P23: 3.968468 | Q23: 3.971855 | R23: 3.975454 | S23: 3.964083 | T23: 3.953435 | U23: 3.955495 | V23: 3.973439 | W23: 4.000788 | X23: 4.04146 | Y23: 4.095368 | Z23: 4.15557 | AA23: 4.225757 | AB23: 4.299688 | AC23: 4.36784 | AD23: 4.436968 | AE23: 4.51719 | AF23: 0.006259
A24: FTE000:lm_vmt_stk_elec | B24: Electric | C24: 0.000803 | D24: 0.000726 | E24: 0.000665 | F24: 0.000618 | G24: 0.000584 | H24: 0.000557 | I24: 0.000536 | J24: 0.000504 | K24: 0.000463 | L24: 0.000425 | M24: 0.000392 | N24: 0.00033 | O24: 0.00026 | P24: 0.000205 | Q24: 0.000161 | R24: 0.000126 | S24: 9.9e-05 | T24: 7.7e-05 | U24: 6.9e-05 | V24: 6.7e-05 | W24: 6.6e-05 | X24: 6.4e-05 | Y24: 5.2e-05 | Z24: 3.6e-05 | AA24: 2.6e-05 | AB24: 1.8e-05 | AC24: 1.3e-05 | AD24: 9e-06 | AE24: 6e-06 | AF24: -0.159098
A25: FTE000:lm_vmt_stk_pidh | B25: Plug-in Diesel Hybrid | C25: 0 | D25: 0.005791 | E25: 0.011641 | F25: 0.017745 | G25: 0.024024 | H25: 0.030277 | I25: 0.036508 | J25: 0.042765 | K25: 0.049185 | L25: 0.055924 | M25: 0.063112 | N25: 0.070484 | O25: 0.078226 | P25: 0.086534 | Q25: 0.095422 | R25: 0.105274 | S25: 0.116181 | T25: 0.128332 | U25: 0.142063 | V25: 0.157389 | W25: 0.174051 | X25: 0.191836 | Y25: 0.210715 | Z25: 0.230889 | AA25: 0.252466 | AB25: 0.274962 | AC25: 0.297693 | AD25: 0.321199 | AE25: 0.346224 | AF25: --
A26: FTE000:lm_vmt_stk_pigh | B26: Plug-in Gasoline Hybrid | C26: 0 | D26: 0.006025 | E26: 0.012129 | F26: 0.018395 | G26: 0.024749 | H26: 0.030966 | I26: 0.037011 | J26: 0.042946 | K26: 0.048956 | L26: 0.055274 | M26: 0.06205 | N26: 0.069098 | O26: 0.076634 | P26: 0.084903 | Q26: 0.093932 | R26: 0.104143 | S26: 0.115635 | T26: 0.12865 | U26: 0.143532 | V26: 0.160333 | W26: 0.178793 | X26: 0.198736 | Y26: 0.21998 | Z26: 0.242805 | AA26: 0.267198 | AB26: 0.292703 | AC26: 0.318521 | AD26: 0.345285 | AE26: 0.373702 | AF26: --
A27: FTE000:lm_vmt_stk_cell | B27: Fuel Cell | C27: 0 | D27: 0 | E27: 2e-06 | F27: 4e-06 | G27: 6e-06 | H27: 8e-06 | I27: 1e-05 | J27: 1.1e-05 | K27: 1.3e-05 | L27: 1.5e-05 | M27: 1.7e-05 | N27: 1.8e-05 | O27: 2e-05 | P27: 2.1e-05 | Q27: 2.2e-05 | R27: 2.3e-05 | S27: 2.4e-05 | T27: 2.5e-05 | U27: 2.6e-05 | V27: 2.7e-05 | W27: 2.8e-05 | X27: 2.8e-05 | Y27: 2.8e-05 | Z27: 2.9e-05 | AA27: 2.9e-05 | AB27: 2.8e-05 | AC27: 2.8e-05 | AD27: 2.7e-05 | AE27: 2.7e-05 | AF27: --
A28: FTE000:lm_vmt_stk_total | B28: Light Medium Subtotal | C28: 75.048714 | D28: 74.717514 | E28: 75.046082 | F28: 76.143509 | G28: 77.598 | H28: 78.820419 | I28: 79.976402 | J28: 81.127167 | K28: 82.517715 | L28: 84.228111 | M28: 86.234123 | N28: 88.07753 | O28: 89.911659 | P28: 91.791748 | Q28: 93.544197 | R28: 95.400566 | S28: 97.240463 | T28: 99.104271 | U28: 101.111 | V28: 103.19528 | W28: 105.2371 | X28: 107.19923 | Y28: 109.12768 | Z28: 111.1437 | AA28: 113.44614 | AB28: 115.84798 | AC28: 118.10761 | AD28: 120.49865 | AE28: 123.32388 | AF28: 0.017897
B29: Medium
A30: FTE000:ca_Diesel | B30: Diesel | C30: 39.558544 | D30: 39.337627 | E30: 39.299656 | F30: 39.581608 | G30: 40.110664 | H30: 40.671707 | I30: 41.263809 | J30: 41.765324 | K30: 42.233723 | L30: 42.75589 | M30: 43.429985 | N30: 44.019016 | O30: 44.583286 | P30: 45.18047 | Q30: 45.736732 | R30: 46.355183 | S30: 46.957836 | T30: 47.563808 | U30: 48.222565 | V30: 48.907677 | W30: 49.5737 | X30: 50.240974 | Y30: 50.887699 | Z30: 51.487984 | AA30: 52.142113 | AB30: 52.823296 | AC30: 53.454895 | AD30: 54.11842 | AE30: 54.955475 | AF30: 0.01181
A31: FTE000:ca_Gasoline | B31: Motor Gasoline | C31: 19.487116 | D31: 19.215473 | E31: 19.072891 | F31: 19.059853 | G31: 19.182478 | H31: 19.313581 | I31: 19.47892 | J31: 19.629051 | K31: 19.775127 | L31: 19.949099 | M31: 20.21559 | N31: 20.442692 | O31: 20.670752 | P31: 20.9112 | Q31: 21.112675 | R31: 21.367302 | S31: 21.576696 | T31: 21.845287 | U31: 22.11479 | V31: 22.415617 | W31: 22.714939 | X31: 23.016796 | Y31: 23.311953 | Z31: 23.583118 | AA31: 23.878855 | AB31: 24.179132 | AC31: 24.450663 | AD31: 24.739687 | AE31: 25.09705 | AF31: 0.009077
A32: FTE000:ca_LiquefiedPetr | B32: Propane | C32: 0.035519 | D32: 0.036849 | E32: 0.0383 | F32: 0.039928 | G32: 0.041891 | H32: 0.043984 | I32: 0.046242 | J32: 0.048501 | K32: 0.050945 | L32: 0.053743 | M32: 0.057158 | N32: 0.061107 | O32: 0.065479 | P32: 0.069911 | Q32: 0.074638 | R32: 0.079953 | S32: 0.085782 | T32: 0.092219 | U32: 0.099416 | V32: 0.107424 | W32: 0.115934 | X32: 0.124888 | Y32: 0.134116 | Z32: 0.143486 | AA32: 0.153252 | AB32: 0.163224 | AC32: 0.173081 | AD32: 0.182492 | AE32: 0.192533 | AF32: 0.062223
A33: FTE000:ca_CompressedNat | B33: Compressed/Liquefied Natural Gas | C33: 0.040711 | D33: 0.038744 | E33: 0.036801 | F33: 0.035049 | G33: 0.033437 | H33: 0.031726 | I33: 0.030068 | J33: 0.028327 | K33: 0.026554 | L33: 0.024896 | M33: 0.023395 | N33: 0.021886 | O33: 0.020384 | P33: 0.018924 | Q33: 0.017501 | R33: 0.01624 | S33: 0.015091 | T33: 0.014094 | U33: 0.01316 | V33: 0.012222 | W33: 0.01138 | X33: 0.010424 | Y33: 0.00945 | Z33: 0.008636 | AA33: 0.007954 | AB33: 0.007266 | AC33: 0.006568 | AD33: 0.005938 | AE33: 0.005415 | AF33: -0.069514
A34: FTE000:ca_ethanolflex | B34: Ethanol-Flex Fuel | C34: 0.567986 | D34: 0.597828 | E34: 0.637764 | F34: 0.685371 | G34: 0.742963 | H34: 0.808578 | I34: 0.879891 | J34: 0.955174 | K34: 1.036787 | L34: 1.129257 | M34: 1.237243 | N34: 1.355722 | O34: 1.486297 | P34: 1.627784 | Q34: 1.769562 | R34: 1.919661 | S34: 2.070964 | T34: 2.223877 | U34: 2.384504 | V34: 2.545784 | W34: 2.705446 | X34: 2.862837 | Y34: 3.012749 | Z34: 3.155075 | AA34: 3.292932 | AB34: 3.426188 | AC34: 3.547679 | AD34: 3.667386 | AE34: 3.793095 | AF34: 0.070168
A35: FTE000:ca_electric | B35: Electric | C35: 0.004799 | D35: 0.005708 | E35: 0.006401 | F35: 0.006945 | G35: 0.007371 | H35: 0.007662 | I35: 0.007837 | J35: 0.007902 | K35: 0.007887 | L35: 0.007822 | M35: 0.007727 | N35: 0.007575 | O35: 0.007374 | P35: 0.00716 | Q35: 0.006879 | R35: 0.006576 | S35: 0.006319 | T35: 0.006056 | U35: 0.005758 | V35: 0.005468 | W35: 0.005185 | X35: 0.00491 | Y35: 0.004645 | Z35: 0.004391 | AA35: 0.004158 | AB35: 0.003937 | AC35: 0.003723 | AD35: 0.003516 | AE35: 0.003332 | AF35: -0.012949
A36: FTE000:ca_plugindiesel | B36: Plug-in Diesel Hybrid | C36: 0 | D36: 0 | E36: 0.00483 | F36: 0.009332 | G36: 0.013625 | H36: 0.017784 | I36: 0.021821 | J36: 0.025634 | K36: 0.029242 | L36: 0.032781 | M36: 0.03644 | N36: 0.040144 | O36: 0.043931 | P36: 0.047813 | Q36: 0.051763 | R36: 0.055931 | S36: 0.060281 | T36: 0.064887 | U36: 0.06992 | V36: 0.075448 | W36: 0.081417 | X36: 0.087566 | Y36: 0.094056 | Z36: 0.100833 | AA36: 0.108103 | AB36: 0.115766 | AC36: 0.123626 | AD36: 0.131829 | AE36: 0.140711 | AF36: --
A37: FTE000:ca_plugingasolin | B37: Plug-in Gasoline Hybrid | C37: 0 | D37: 0 | E37: 0.004699 | F37: 0.008982 | G37: 0.013004 | H37: 0.016833 | I37: 0.020468 | J37: 0.023865 | K37: 0.027097 | L37: 0.030357 | M37: 0.033845 | N37: 0.037534 | O37: 0.041471 | P37: 0.045675 | Q37: 0.050146 | R37: 0.055067 | S37: 0.060408 | T37: 0.066288 | U37: 0.07291 | V37: 0.080391 | W37: 0.088689 | X37: 0.097593 | Y37: 0.107179 | Z37: 0.117361 | AA37: 0.128284 | AB37: 0.139872 | AC37: 0.151817 | AD37: 0.164304 | AE37: 0.177619 | AF37: --
A38: FTE000:ca_fuelcell | B38: Fuel Cell | C38: 0 | D38: 0 | E38: 0.008078 | F38: 0.015645 | G38: 0.022989 | H38: 0.030179 | I38: 0.037161 | J38: 0.043795 | K38: 0.050102 | L38: 0.056295 | M38: 0.06264 | N38: 0.068956 | O38: 0.075354 | P38: 0.081949 | Q38: 0.088664 | R38: 0.095808 | S38: 0.103379 | T38: 0.111517 | U38: 0.120537 | V38: 0.130567 | W38: 0.141523 | X38: 0.152972 | Y38: 0.165171 | Z38: 0.178007 | AA38: 0.191833 | AB38: 0.206467 | AC38: 0.221546 | AD38: 0.23731 | AE38: 0.254356 | AF38: --
A39: FTE000:ca_MediumSubtota | B39: Medium Subtotal | C39: 59.694576 | D39: 59.232098 | E39: 59.109398 | F39: 59.442654 | G39: 60.168362 | H39: 60.942036 | I39: 61.78616 | J39: 62.527435 | K39: 63.237366 | L39: 64.040108 | M39: 65.104019 | N39: 66.054314 | O39: 66.994217 | P39: 67.990768 | Q39: 68.908279 | R39: 69.951363 | S39: 70.936752 | T39: 71.987885 | U39: 73.103226 | V39: 74.280495 | W39: 75.437996 | X39: 76.598991 | Y39: 77.726692 | Z39: 78.778595 | AA39: 79.907219 | AB39: 81.064888 | AC39: 82.133057 | AD39: 83.250366 | AE39: 84.619041 | AF39: 0.012539
B40: Heavy
A41: FTE000:da_Diesel | B41: Diesel | C41: 184.85648 | D41: 184.3631 | E41: 184.53233 | F41: 185.92311 | G41: 188.09622 | H41: 189.92868 | I41: 191.46675 | J41: 192.31586 | K41: 192.75873 | L41: 193.26146 | M41: 194.18498 | N41: 194.74161 | O41: 195.21269 | P41: 195.78941 | Q41: 196.09772 | R41: 196.64531 | S41: 197.17789 | T41: 197.58701 | U41: 198.11809 | V41: 198.71742 | W41: 199.2968 | X41: 199.71181 | Y41: 199.91617 | Z41: 199.88377 | AA41: 199.97646 | AB41: 200.03841 | AC41: 199.82256 | AD41: 199.67621 | AE41: 200.11252 | AF41: 0.002836
A42: FTE000:da_Gasoline | B42: Motor Gasoline | C42: 0.177811 | D42: 0.177786 | E42: 0.180963 | F42: 0.186843 | G42: 0.196174 | H42: 0.207373 | I42: 0.219367 | J42: 0.231142 | K42: 0.243587 | L42: 0.255892 | M42: 0.268135 | N42: 0.279295 | O42: 0.289438 | P42: 0.298673 | Q42: 0.30595 | R42: 0.31252 | S42: 0.317911 | T42: 0.322673 | U42: 0.327547 | V42: 0.332211 | W42: 0.335203 | X42: 0.337378 | Y42: 0.339952 | Z42: 0.342462 | AA42: 0.345487 | AB42: 0.348537 | AC42: 0.351078 | AD42: 0.353734 | AE42: 0.357393 | AF42: 0.025246
A43: FTE000:da_LiquefiedPetr | B43: Propane | C43: 0.027641 | D43: 0.030197 | E43: 0.032636 | F43: 0.034937 | G43: 0.037206 | H43: 0.039183 | I43: 0.040809 | J43: 0.041921 | K43: 0.042711 | L43: 0.043318 | M43: 0.043885 | N43: 0.044439 | O43: 0.045072 | P43: 0.045765 | Q43: 0.046311 | R43: 0.046866 | S43: 0.047248 | T43: 0.047567 | U43: 0.047885 | V43: 0.048297 | W43: 0.048665 | X43: 0.048979 | Y43: 0.049225 | Z43: 0.049414 | AA43: 0.049661 | AB43: 0.04992 | AC43: 0.050113 | AD43: 0.050276 | AE43: 0.05053 | AF43: 0.021778
A44: FTE000:da_CompressedNat | B44: Compressed/Liquefied Natural Gas | C44: 2.145453 | D44: 2.194808 | E44: 2.238753 | F44: 2.28101 | G44: 2.317616 | H44: 2.333008 | I44: 2.330277 | J44: 2.307991 | K44: 2.27358 | L44: 2.243996 | M44: 2.231564 | N44: 2.234868 | O44: 2.258435 | P44: 2.300837 | Q44: 2.354893 | R44: 2.425728 | S44: 2.508595 | T44: 2.603091 | U44: 2.713572 | V44: 2.839585 | W44: 2.975951 | X44: 3.121336 | Y44: 3.273978 | Z44: 3.43134 | AA44: 3.599105 | AB44: 3.776055 | AC44: 3.954944 | AD44: 4.142594 | AE44: 4.352327 | AF44: 0.025585
A45: FTE000:da_ethanolflex | B45: Ethanol-Flex Fuel | C45: 0 | D45: 0 | E45: 0 | F45: 0 | G45: 0 | H45: 0 | I45: 0 | J45: 0 | K45: 0 | L45: 0 | M45: 0 | N45: 0 | O45: 0 | P45: 0 | Q45: 0 | R45: 0 | S45: 0 | T45: 0 | U45: 0 | V45: 0 | W45: 0 | X45: 0 | Y45: 0 | Z45: 0 | AA45: 0 | AB45: 0 | AC45: 0 | AD45: 0 | AE45: 0 | AF45: --
A46: FTE000:da_electric | B46: Electric | C46: 0.004264 | D46: 0.004962 | E46: 0.005559 | F46: 0.006088 | G46: 0.006551 | H46: 0.006912 | I46: 0.007172 | J46: 0.007324 | K46: 0.007383 | L46: 0.007367 | M46: 0.007284 | N46: 0.007108 | O46: 0.006863 | P46: 0.006574 | Q46: 0.006244 | R46: 0.005922 | S46: 0.005604 | T46: 0.005244 | U46: 0.004876 | V46: 0.00456 | W46: 0.004299 | X46: 0.00403 | Y46: 0.003785 | Z46: 0.00356 | AA46: 0.003357 | AB46: 0.00317 | AC46: 0.002991 | AD46: 0.002826 | AE46: 0.002681 | AF46: -0.016431
A47: FTE000:da_plugindiesel | B47: Plug-in Diesel Hybrid | C47: 0 | D47: 0 | E47: 0.001246 | F47: 0.00243 | G47: 0.0036 | H47: 0.004779 | I47: 0.00597 | J47: 0.007146 | K47: 0.00831 | L47: 0.009483 | M47: 0.010697 | N47: 0.011908 | O47: 0.013111 | P47: 0.014297 | Q47: 0.015442 | R47: 0.016583 | S47: 0.017702 | T47: 0.018821 | U47: 0.019993 | V47: 0.021249 | W47: 0.022599 | X47: 0.024009 | Y47: 0.025467 | Z47: 0.027013 | AA47: 0.028766 | AB47: 0.030682 | AC47: 0.032723 | AD47: 0.034948 | AE47: 0.037459 | AF47: --
A48: FTE000:da_plugingasolin | B48: Plug-in Gasoline Hybrid | C48: 0 | D48: 0 | E48: 0.002763 | F48: 0.005341 | G48: 0.007861 | H48: 0.010367 | I48: 0.012849 | J48: 0.015255 | K48: 0.017602 | L48: 0.01995 | M48: 0.02235 | N48: 0.02471 | O48: 0.027016 | P48: 0.029253 | Q48: 0.031359 | R48: 0.033412 | S48: 0.035376 | T48: 0.037299 | U48: 0.039282 | V48: 0.041389 | W48: 0.043634 | X48: 0.045939 | Y48: 0.048251 | Z48: 0.050642 | AA48: 0.053319 | AB48: 0.056164 | AC48: 0.05907 | AD48: 0.06213 | AE48: 0.065482 | AF48: --
A49: FTE000:da_fuelcell | B49: Fuel Cell | C49: 0 | D49: 0 | E49: 0.00678 | F49: 0.013259 | G49: 0.019751 | H49: 0.026344 | I49: 0.03299 | J49: 0.039546 | K49: 0.045989 | L49: 0.052423 | M49: 0.058965 | N49: 0.065316 | O49: 0.071456 | P49: 0.07736 | Q49: 0.082834 | R49: 0.088063 | S49: 0.092967 | T49: 0.097629 | U49: 0.102295 | V49: 0.107098 | W49: 0.112072 | X49: 0.117018 | Y49: 0.121867 | Z49: 0.126833 | AA49: 0.132515 | AB49: 0.138672 | AC49: 0.145142 | AD49: 0.152234 | AE49: 0.160418 | AF49: --
A50: FTE000:da_HeavySubtotal | B50: Heavy Subtotal | C50: 187.21161 | D50: 186.77066 | E50: 187.00078 | F50: 188.45283 | G50: 190.68486 | H50: 192.55638 | I50: 194.11635 | J50: 194.96588 | K50: 195.39752 | L50: 195.89365 | M50: 196.82713 | N50: 197.40904 | O50: 197.92372 | P50: 198.56163 | Q50: 198.94003 | R50: 199.57364 | S50: 200.20254 | T50: 200.71848 | U50: 201.37273 | V50: 202.11119 | W50: 202.83833 | X50: 203.40926 | Y50: 203.7776 | Z50: 203.91367 | AA50: 204.18713 | AB50: 204.44009 | AC50: 204.41753 | AD50: 204.47378 | AE50: 205.13785 | AF50: 0.003271
A51: FTE000:da_TotalVehicleM | B51: Total Vehicle Miles Traveled | C51: 321.95383 | D51: 320.71957 | E51: 321.15537 | F51: 324.03748 | G51: 328.44952 | H51: 332.31747 | I51: 335.87714 | J51: 338.61987 | K51: 341.15076 | L51: 344.15997 | M51: 348.16452 | N51: 351.53851 | O51: 354.82727 | P51: 358.34311 | Q51: 361.3916 | R51: 364.92499 | S51: 368.37805 | T51: 371.80917 | U51: 375.58542 | V51: 379.58304 | W51: 383.51111 | X51: 387.20508 | Y51: 390.63013 | Z51: 393.8345 | AA51: 397.53842 | AB51: 401.35025 | AC51: 404.65439 | AD51: 408.2189 | AE51: 413.07754 | AF51: 0.008941
B53: Consumption (trillion Btu)
B54: Light Medium
A55: FTE000:lm_use_stk_Dies | B55: Diesel | C55: 503.23831 | D55: 484.80926 | E55: 470.10184 | F55: 459.78449 | G55: 451.87814 | H55: 443.24606 | I55: 435.43274 | J55: 428.57593 | K55: 424.18491 | L55: 422.56686 | M55: 423.05704 | N55: 423.25711 | O55: 424.28409 | P55: 426.25699 | Q55: 428.07437 | R55: 430.74142 | S55: 433.84168 | T55: 437.7146 | U55: 442.6882 | V55: 448.15237 | W55: 453.8429 | X55: 459.89023 | Y55: 466.2998 | Z55: 473.53125 | AA55: 482.34018 | AB55: 491.8963 | AC55: 501.23676 | AD55: 511.31162 | AE55: 523.31238 | AF55: 0.001398
A56: FTE000:lm_use_stk_Gas | B56: Motor Gasoline | C56: 196.41988 | D56: 201.42117 | E56: 206.93259 | F56: 213.4828 | G56: 220.53224 | H56: 226.21765 | I56: 231.3105 | J56: 235.95909 | K56: 241.0206 | L56: 246.62308 | M56: 253.2693 | N56: 259.5228 | O56: 265.59988 | P56: 271.63849 | Q56: 277.3645 | R56: 283.4436 | S56: 289.37485 | T56: 295.02786 | U56: 300.90585 | V56: 307.12256 | W56: 313.00485 | X56: 318.11237 | Y56: 322.94775 | Z56: 327.87622 | AA56: 333.5806 | AB56: 339.54462 | AC56: 345.05283 | AD56: 350.95578 | AE56: 358.22073 | AF56: 0.021693
A57: FTE000:lm_use_stk_Liq | B57: Propane | C57: 0.008824 | D57: 0.079078 | E57: 0.148368 | F57: 0.211796 | G57: 0.27223 | H57: 0.328085 | I57: 0.380416 | J57: 0.429704 | K57: 0.477469 | L57: 0.525701 | M57: 0.575181 | N57: 0.623545 | O57: 0.671896 | P57: 0.722093 | Q57: 0.774258 | R57: 0.831293 | S57: 0.893031 | T57: 0.960705 | U57: 1.036213 | V57: 1.11984 | W57: 1.210605 | X57: 1.308586 | Y57: 1.412456 | Z57: 1.525402 | AA57: 1.65115 | AB57: 1.786922 | AC57: 1.928594 | AD57: 2.079436 | AE57: 2.244543 | AF57: 0.218738
A58: FTE000:lm_use_stk_NGas | B58: Compressed/Liquefied Natural Gas | C58: 0.192116 | D58: 0.174257 | E58: 0.158799 | F58: 0.145806 | G58: 0.134438 | H58: 0.123654 | I58: 0.113679 | J58: 0.104485 | K58: 0.096244 | L58: 0.088943 | M58: 0.082427 | N58: 0.075773 | O58: 0.068822 | P58: 0.061432 | Q58: 0.053884 | R58: 0.045974 | S58: 0.038685 | T58: 0.032133 | U58: 0.025619 | V58: 0.020525 | W58: 0.016807 | X58: 0.014122 | Y58: 0.012398 | Z58: 0.011208 | AA58: 0.010267 | AB58: 0.009607 | AC58: 0.008735 | AD58: 0.007734 | AE58: 0.00649 | AF58: -0.113962
A59: FTE000:lm_use_stk_flex | B59: Ethanol-Flex Fuel | C59: 45.964245 | D59: 44.611794 | E59: 43.499821 | F59: 42.670467 | G59: 42.056103 | H59: 41.41785 | I59: 40.858673 | J59: 40.401375 | K59: 40.094643 | L59: 39.995682 | M59: 40.077168 | N59: 40.08778 | O59: 39.881618 | P59: 39.530632 | Q59: 38.979153 | R59: 38.427227 | S59: 37.705452 | T59: 37.000896 | U59: 36.440113 | V59: 36.08366 | W59: 35.872028 | X59: 35.852295 | Y59: 36.018429 | Z59: 36.285957 | AA59: 36.676159 | AB59: 37.130253 | AC59: 37.561069 | AD59: 38.004097 | AE59: 38.549274 | AF59: -0.006263
A60: FTE000:lm_use_stk_elect | B60: Electric | C60: 0.004618 | D60: 0.004177 | E60: 0.003821 | F60: 0.003554 | G60: 0.003357 | H60: 0.0032 | I60: 0.003084 | J60: 0.002899 | K60: 0.002664 | L60: 0.002446 | M60: 0.002253 | N60: 0.001897 | O60: 0.001495 | P60: 0.001176 | Q60: 0.000923 | R60: 0.000724 | S60: 0.000568 | T60: 0.000444 | U60: 0.000396 | V60: 0.000387 | W60: 0.000378 | X60: 0.000368 | Y60: 0.000298 | Z60: 0.000209 | AA60: 0.000147 | AB60: 0.000103 | AC60: 7.3e-05 | AD60: 5.1e-05 | AE60: 3.6e-05 | AF60: -0.159099
A61: FTE000:lm_use_stk_plugd | B61: Plug-in Diesel Hybrid | C61: 0 | D61: 0.034697 | E61: 0.06879 | F61: 0.10379 | G61: 0.139219 | H61: 0.173667 | I61: 0.207235 | J61: 0.239813 | K61: 0.272039 | L61: 0.304685 | M61: 0.338422 | N61: 0.372229 | O61: 0.407349 | P61: 0.444994 | Q61: 0.485266 | R61: 0.530182 | S61: 0.580241 | T61: 0.636407 | U61: 0.700343 | V61: 0.772136 | W61: 0.85035 | X61: 0.933939 | Y61: 1.022764 | Z61: 1.117797 | AA61: 1.219284 | AB61: 1.324989 | AC61: 1.431711 | AD61: 1.542152 | AE61: 1.659889 | AF61: --
A62: FTE000:lm_use_stk_plugg | B62: Plug-in Gasoline Hybrid | C62: 0 | D62: 0.039742 | E62: 0.079436 | F62: 0.119691 | G62: 0.160329 | H62: 0.199692 | I62: 0.237663 | J62: 0.27446 | K62: 0.311191 | L62: 0.349268 | M62: 0.389597 | N62: 0.431086 | O62: 0.475127 | P62: 0.523366 | Q62: 0.575913 | R62: 0.635429 | S62: 0.702605 | T62: 0.7789 | U62: 0.866414 | V62: 0.965463 | W62: 1.074376 | X62: 1.192066 | Y62: 1.317839 | Z62: 1.452814 | AA62: 1.596785 | AB62: 1.746942 | AC62: 1.89845 | AD62: 2.054983 | AE62: 2.220644 | AF62: --
A63: FTE000:lm_use_stk_sell | B63: Fuel Cell | C63: 0 | D63: 0 | E63: 1.4e-05 | F63: 3e-05 | G63: 4.7e-05 | H63: 6.3e-05 | I63: 8e-05 | J63: 9.5e-05 | K63: 0.00011 | L63: 0.000125 | M63: 0.00014 | N63: 0.000153 | O63: 0.000166 | P63: 0.000177 | Q63: 0.000188 | R63: 0.000197 | S63: 0.000206 | T63: 0.000215 | U63: 0.000222 | V63: 0.000229 | W63: 0.000235 | X63: 0.000239 | Y63: 0.000241 | Z63: 0.000243 | AA63: 0.000243 | AB63: 0.000241 | AC63: 0.000238 | AD63: 0.000232 | AE63: 0.000226 | AF63: --
A64: FTE000:lm_use_stk_total | B64: Light Medium Subtotal | C64: 745.828 | D64: 731.17419 | E64: 720.99335 | F64: 716.5227 | G64: 715.17602 | H64: 711.70978 | I64: 708.54401 | J64: 705.98767 | K64: 706.45978 | L64: 710.45648 | M64: 717.79108 | N64: 724.37238 | O64: 731.39026 | P64: 739.17914 | Q64: 746.30835 | R64: 754.65625 | S64: 763.13678 | T64: 772.15192 | U64: 782.66351 | V64: 794.237 | W64: 805.87268 | X64: 817.30414 | Y64: 829.03204 | Z64: 841.80078 | AA64: 857.07452 | AB64: 873.44 | AC64: 889.11823 | AD64: 905.95587 | AE64: 926.21387 | AF64: 0.007766
B65: Medium
A66: FTE000:ea_Diesel | B66: Diesel | C66: 596.79718 | D66: 582.57031 | E66: 570.54584 | F66: 562.60992 | G66: 557.47638 | H66: 552.10059 | I66: 547.56726 | J66: 541.8349 | K66: 535.99304 | L66: 531.10577 | M66: 528.55798 | N66: 525.62 | O66: 523.05524 | P66: 521.63513 | Q66: 520.47327 | R66: 520.68817 | S66: 521.26672 | T66: 522.35956 | U66: 524.42358 | V66: 527.08154 | W66: 529.90253 | X66: 533.3006 | Y66: 536.98975 | Z66: 540.51788 | AA66: 544.76953 | AB66: 549.50623 | AC66: 553.8952 | AD66: 558.68854 | AE66: 565.29273 | AF66: -0.001935
A67: FTE000:ea_Gasoline | B67: Motor Gasoline | C67: 361.09714 | D67: 352.45267 | E67: 345.87949 | F67: 341.19531 | G67: 338.49741 | H67: 335.44928 | I67: 333.12943 | J67: 330.41745 | K67: 327.60516 | L67: 325.20841 | M67: 324.38138 | N67: 322.96948 | O67: 321.80856 | P67: 321.0246 | Q67: 319.85523 | R67: 319.80576 | S67: 319.18863 | T67: 319.81021 | U67: 320.5246 | V67: 321.91736 | W67: 323.47983 | X67: 325.35474 | Y67: 327.38092 | Z67: 329.19855 | AA67: 331.44745 | AB67: 333.82504 | AC67: 335.92966 | AD67: 338.38473 | AE67: 341.7948 | AF67: -0.00196
A68: FTE000:ea_LiquefiedPetr | B68: Propane | C68: 0.665595 | D68: 0.682733 | E68: 0.700859 | F68: 0.720756 | G68: 0.744488 | H68: 0.767789 | I68: 0.792564 | J68: 0.815042 | K68: 0.838861 | L68: 0.866507 | M68: 0.902205 | N68: 0.944946 | O68: 0.993298 | P68: 1.040652 | Q68: 1.091984 | R68: 1.151901 | S68: 1.219368 | T68: 1.295874 | U68: 1.383652 | V68: 1.483504 | W68: 1.590991 | X68: 1.705203 | Y68: 1.823792 | Z68: 1.944942 | AA68: 2.071958 | AB68: 2.202169 | AC68: 2.33111 | AD68: 2.451528 | AE68: 2.581014 | AF68: 0.049592
A69: FTE000:ea_CompressedNat | B69: Compressed/Liquefied Natural Gas | C69: 0.761944 | D69: 0.718699 | E69: 0.676321 | F69: 0.637992 | G69: 0.602869 | H69: 0.56657 | I69: 0.532462 | J69: 0.497576 | K69: 0.462788 | L69: 0.430828 | M69: 0.402386 | N69: 0.374433 | O69: 0.346945 | P69: 0.320598 | Q69: 0.295219 | R69: 0.273016 | S69: 0.253025 | T69: 0.235997 | U69: 0.220233 | V69: 0.204292 | W69: 0.190149 | X69: 0.173557 | Y69: 0.156469 | Z69: 0.142422 | AA69: 0.130806 | AB69: 0.118887 | AC69: 0.106766 | AD69: 0.095869 | AE69: 0.086903 | AF69: -0.074609
A70: FTE000:ea_ethanolflex | B70: Ethanol-Flex Fuel | C70: 10.331885 | D70: 10.758182 | E70: 11.321586 | F70: 11.975374 | G70: 12.744726 | H70: 13.587193 | I70: 14.506134 | J70: 15.44483 | K70: 16.450348 | L70: 17.581884 | M70: 18.915562 | N70: 20.372982 | O70: 22.01041 | P70: 23.794563 | Q70: 25.57753 | R70: 27.489719 | S70: 29.423685 | T70: 31.3827 | U70: 33.47094 | V70: 35.564487 | W70: 37.641945 | X70: 39.69342 | Y70: 41.6465 | Z70: 43.501041 | AA70: 45.296207 | AB70: 47.027523 | AC70: 48.595695 | AD70: 50.145443 | AE70: 51.783787 | AF70: 0.059255
A71: FTE000:ea_electric | B71: Electric | C71: 0.038242 | D71: 0.045435 | E71: 0.050754 | F71: 0.054753 | G71: 0.057684 | H71: 0.059468 | I71: 0.060365 | J71: 0.060383 | K71: 0.05979 | L71: 0.058834 | M71: 0.057679 | N71: 0.056149 | O71: 0.054414 | P71: 0.052583 | Q71: 0.050235 | R71: 0.047787 | S71: 0.045778 | T71: 0.043761 | U71: 0.041476 | V71: 0.03928 | W71: 0.037174 | X71: 0.035144 | Y71: 0.033201 | Z71: 0.031363 | AA71: 0.029679 | AB71: 0.02809 | AC71: 0.026553 | AD71: 0.025127 | AE71: 0.02381 | AF71: -0.01678
A72: FTE000:ea_plugindiesel | B72: Plug-in Diesel Hybrid | C72: 0 | D72: 0 | E72: 0.046031 | F72: 0.087364 | G72: 0.125998 | H72: 0.162359 | I72: 0.196929 | J72: 0.228566 | K72: 0.257603 | L72: 0.285156 | M72: 0.312729 | N72: 0.339615 | O72: 0.36633 | P72: 0.393577 | Q72: 0.420733 | R72: 0.449286 | S72: 0.47926 | T72: 0.511257 | U72: 0.546639 | V72: 0.585939 | W72: 0.62877 | X72: 0.672651 | Y72: 0.719311 | Z72: 0.768308 | AA72: 0.821181 | AB72: 0.877112 | AC72: 0.934619 | AD72: 0.994792 | AE72: 1.060159 | AF72: --
A73: FTE000:ea_plugingasolin | B73: Plug-in Gasoline Hybrid | C73: 0 | D73: 0 | E73: 0.055973 | F73: 0.105385 | G73: 0.151093 | H73: 0.193687 | I73: 0.233462 | J73: 0.26947 | K73: 0.302646 | L73: 0.335016 | M73: 0.368535 | N73: 0.40277 | O73: 0.438283 | P73: 0.476151 | Q73: 0.515752 | R73: 0.559245 | S73: 0.606796 | T73: 0.659627 | U73: 0.719741 | V73: 0.788289 | W73: 0.864886 | X73: 0.946915 | Y73: 1.035699 | Z73: 1.130374 | AA73: 1.23231 | AB73: 1.340697 | AC73: 1.452583 | AD73: 1.569724 | AE73: 1.695413 | AF73: --
A74: FTE000:ea_fuelcell | B74: Fuel Cell | C74: 0 | D74: 0 | E74: 0.097282 | F74: 0.188421 | G74: 0.276858 | H74: 0.363454 | I74: 0.447537 | J74: 0.527429 | K74: 0.603393 | L74: 0.677971 | M74: 0.75438 | N74: 0.830451 | O74: 0.907503 | P74: 0.98692 | Q74: 1.067797 | R74: 1.153837 | S74: 1.245005 | T74: 1.34302 | U74: 1.451644 | V74: 1.572443 | W74: 1.704381 | X74: 1.842259 | Y74: 1.989176 | Z74: 2.143766 | AA74: 2.310273 | AB74: 2.48651 | AC74: 2.668105 | AD74: 2.857946 | AE74: 3.063244 | AF74: --
A75: FTE000:ea_MediumSubtota | B75: Medium Subtotal | C75: 969.6922 | D75: 947.2279 | E75: 929.3739 | F75: 917.57489 | G75: 910.67767 | H75: 903.25073 | I75: 897.46606 | J75: 890.09558 | K75: 882.57385 | L75: 876.55035 | M75: 874.65283 | N75: 871.91071 | O75: 869.9809 | P75: 869.72479 | Q75: 869.34753 | R75: 871.61847 | S75: 873.72821 | T75: 877.64209 | U75: 882.78265 | V75: 889.23706 | W75: 896.04047 | X75: 903.72449 | Y75: 911.77454 | Z75: 919.37824 | AA75: 928.10968 | AB75: 937.41242 | AC75: 945.94019 | AD75: 955.21375 | AE75: 967.38214 | AF75: -8.5e-05
B76: Heavy
A77: FTE000:fa_Diesel | B77: Diesel | C77: 4152.2949 | D77: 4082.8315 | E77: 4021.4512 | F77: 3982.2764 | G77: 3955.9531 | H77: 3919.7483 | I77: 3881.1033 | J77: 3831.7788 | K77: 3778.5308 | L77: 3730.3296 | M77: 3694.2207 | N77: 3656.8643 | O77: 3623.7571 | P77: 3598.0146 | Q77: 3572.1406 | R77: 3555.0132 | S77: 3541.657 | T77: 3529.0093 | U77: 3520.9712 | V77: 3515.9072 | W77: 3513.189 | X77: 3509.6179 | Y77: 3504.0908 | Z77: 3495.7058 | AA77: 3490.0081 | AB77: 3484.0903 | AC77: 3473.502 | AD77: 3463.9399 | AE77: 3464.1235 | AF77: -0.006451
A78: FTE000:fa_Gasoline | B78: Motor Gasoline | C78: 3.967448 | D78: 3.91121 | E78: 3.927975 | F78: 4.003333 | G78: 4.154909 | H78: 4.346583 | I78: 4.555941 | J78: 4.758452 | K78: 4.97601 | L78: 5.18817 | M78: 5.395782 | N78: 5.579236 | O78: 5.743181 | P78: 5.890036 | Q78: 5.998426 | R78: 6.094069 | S78: 6.16721 | T78: 6.22837 | U78: 6.292622 | V78: 6.356681 | W78: 6.389575 | X78: 6.407103 | Y78: 6.434031 | Z78: 6.465653 | AA78: 6.509548 | AB78: 6.555473 | AC78: 6.592998 | AD78: 6.633256 | AE78: 6.692633 | AF78: 0.01885
A79: FTE000:fa_LiquefiedPetr | B79: Propane | C79: 0.570847 | D79: 0.624367 | E79: 0.675653 | F79: 0.723456 | G79: 0.769549 | H79: 0.807832 | I79: 0.837598 | J79: 0.854943 | K79: 0.864169 | L79: 0.868258 | M79: 0.870423 | N79: 0.871982 | O79: 0.876027 | P79: 0.882238 | Q79: 0.886164 | R79: 0.890656 | S79: 0.892193 | T79: 0.893006 | U79: 0.894043 | V79: 0.897259 | W79: 0.900476 | X79: 0.903219 | Y79: 0.905168 | Z79: 0.906542 | AA79: 0.909339 | AB79: 0.912656 | AC79: 0.914926 | AD79: 0.916513 | AE79: 0.919479 | AF79: 0.01717
A80: FTE000:fa_CompressedNat | B80: Compressed/Liquefied Natural Gas | C80: 50.390869 | D80: 50.880238 | E80: 51.130661 | F80: 51.278004 | G80: 51.2663 | H80: 50.76376 | I80: 49.941105 | J80: 48.755848 | K80: 47.376194 | L80: 46.136257 | M80: 45.289948 | N80: 44.81562 | O80: 44.797993 | P80: 45.188122 | Q80: 45.832714 | R80: 46.829082 | S80: 48.081806 | T80: 49.582222 | U80: 51.412018 | V80: 53.560184 | W80: 55.921677 | X80: 58.465366 | Y80: 61.153961 | Z80: 63.935596 | AA80: 66.919731 | AB80: 70.06723 | AC80: 73.232262 | AD80: 76.543907 | AE80: 80.243095 | AF80: 0.016755
A81: FTE000:fa_ethanolflex | B81: Ethanol-Flex Fuel | C81: 0 | D81: 0 | E81: 0 | F81: 0 | G81: 0 | H81: 0 | I81: 0 | J81: 0 | K81: 0 | L81: 0 | M81: 0 | N81: 0 | O81: 0 | P81: 0 | Q81: 0 | R81: 0 | S81: 0 | T81: 0 | U81: 0 | V81: 0 | W81: 0 | X81: 0 | Y81: 0 | Z81: 0 | AA81: 0 | AB81: 0 | AC81: 0 | AD81: 0 | AE81: 0 | AF81: --
A82: FTE000:fa_electric | B82: Electric | C82: 0.047272 | D82: 0.056366 | E82: 0.064063 | F82: 0.070822 | G82: 0.076726 | H82: 0.081383 | I82: 0.08483 | J82: 0.086958 | K82: 0.087952 | L82: 0.088013 | M82: 0.08725 | N82: 0.085333 | O82: 0.082536 | P82: 0.079114 | Q82: 0.075204 | R82: 0.071353 | S82: 0.067467 | T82: 0.063056 | U82: 0.058637 | V82: 0.054799 | W82: 0.051537 | X82: 0.048206 | Y82: 0.045224 | Z82: 0.042496 | AA82: 0.040057 | AB82: 0.037804 | AC82: 0.035659 | AD82: 0.033694 | AE82: 0.031963 | AF82: -0.013879
A83: FTE000:fa_plugindiesel | B83: Plug-in Diesel Hybrid | C83: 0 | D83: 0 | E83: 0.111749 | F83: 0.126518 | G83: 0.142694 | H83: 0.15934 | I83: 0.176213 | J83: 0.192228 | K83: 0.207245 | L83: 0.221401 | M83: 0.234888 | N83: 0.246569 | O83: 0.256597 | P83: 0.265207 | Q83: 0.272052 | R83: 0.278225 | S83: 0.283998 | T83: 0.29018 | U83: 0.298065 | V83: 0.30863 | W83: 0.322564 | X83: 0.334818 | Y83: 0.346776 | Z83: 0.362276 | AA83: 0.384801 | AB83: 0.407429 | AC83: 0.431705 | AD83: 0.458424 | AE83: 0.488884 | AF83: --
A84: FTE000:fa_plugingasolin | B84: Plug-in Gasoline Hybrid | C84: 0 | D84: 0 | E84: 0.234144 | F84: 0.262736 | G84: 0.294181 | H84: 0.326345 | I84: 0.358361 | J84: 0.388214 | K84: 0.415743 | L84: 0.441347 | M84: 0.465224 | N84: 0.485016 | O84: 0.500979 | P84: 0.513628 | Q84: 0.522262 | R84: 0.52909 | S84: 0.534693 | T84: 0.540743 | U84: 0.549724 | V84: 0.563565 | W84: 0.583643 | X84: 0.599231 | Y84: 0.613008 | Z84: 0.632858 | AA84: 0.665276 | AB84: 0.695484 | AC84: 0.726562 | AD84: 0.759665 | AE84: 0.796416 | AF84: --
A85: FTE000:fa_fuelcell | B85: Fuel Cell | C85: 0 | D85: 0 | E85: 0.132431 | F85: 0.258802 | G85: 0.385407 | H85: 0.513998 | I85: 0.643633 | J85: 0.771512 | K85: 0.897175 | L85: 1.022669 | M85: 1.150256 | N85: 1.274112 | O85: 1.393794 | P85: 1.508843 | Q85: 1.615412 | R85: 1.717117 | S85: 1.812324 | T85: 1.902677 | U85: 1.992978 | V85: 2.085901 | W85: 2.182155 | X85: 2.277899 | Y85: 2.371854 | Z85: 2.468158 | AA85: 2.57848 | AB85: 2.69808 | AC85: 2.823772 | AD85: 2.961604 | AE85: 3.12061 | AF85: --
A86: FTE000:fa_HeavySubtotal | B86: Heavy Subtotal | C86: 4207.2734 | D86: 4138.3027 | E86: 4077.7275 | F86: 4039.0002 | G86: 4013.043 | H86: 3976.7485 | I86: 3937.7007 | J86: 3887.5862 | K86: 3833.3564 | L86: 3784.2959 | M86: 3747.7146 | N86: 3710.2214 | O86: 3677.4077 | P86: 3652.3428 | Q86: 3627.3423 | R86: 3611.4219 | S86: 3599.4954 | T86: 3588.5098 | U86: 3582.4688 | V86: 3579.7346 | W86: 3579.541 | X86: 3578.6531 | Y86: 3575.9612 | Z86: 3570.5195 | AA86: 3568.0159 | AB86: 3565.4648 | AC86: 3558.2588 | AD86: 3552.2461 | AE86: 3556.4155 | AF86: -0.005984
B87: Light Medium, Medium, and Heavy Total
A88: FTE000:ga_Diesel | B88: Diesel | C88: 5252.3306 | D88: 5150.2109 | E88: 5062.0986 | F88: 5004.6709 | G88: 4965.3076 | H88: 4915.0947 | I88: 4864.1035 | J88: 4802.1895 | K88: 4738.709 | L88: 4684.002 | M88: 4645.8359 | N88: 4605.7412 | O88: 4571.0967 | P88: 4545.9067 | Q88: 4520.6885 | R88: 4506.4429 | S88: 4496.7656 | T88: 4489.0835 | U88: 4488.083 | V88: 4491.1411 | W88: 4496.9346 | X88: 4502.8086 | Y88: 4507.3804 | Z88: 4509.7549 | AA88: 4517.1177 | AB88: 4525.4932 | AC88: 4528.6338 | AD88: 4533.9399 | AE88: 4552.7285 | AF88: -0.005092
A89: FTE000:ga_Gasoline | B89: Motor Gasoline | C89: 561.4845 | D89: 557.78503 | E89: 556.74005 | F89: 558.68146 | G89: 563.18457 | H89: 566.01349 | I89: 568.99591 | J89: 571.13495 | K89: 573.60175 | L89: 577.01965 | M89: 583.04651 | N89: 588.07153 | O89: 593.15161 | P89: 598.5531 | Q89: 603.21814 | R89: 609.34344 | S89: 614.73071 | T89: 621.06647 | U89: 627.72302 | V89: 635.39661 | W89: 642.87427 | X89: 649.87421 | Y89: 656.7627 | Z89: 663.5404 | AA89: 671.5376 | AB89: 679.92511 | AC89: 687.5755 | AD89: 695.97375 | AE89: 706.70813 | AF89: 0.008249
A90: FTE000:ga_LiquefiedPetr | B90: Propane | C90: 1.245265 | D90: 1.386178 | E90: 1.52488 | F90: 1.656008 | G90: 1.786266 | H90: 1.903707 | I90: 2.010578 | J90: 2.099688 | K90: 2.180499 | L90: 2.260466 | M90: 2.347808 | N90: 2.440473 | O90: 2.541221 | P90: 2.644983 | Q90: 2.752405 | R90: 2.873849 | S90: 3.004591 | T90: 3.149585 | U90: 3.313908 | V90: 3.500602 | W90: 3.702072 | X90: 3.917007 | Y90: 4.141415 | Z90: 4.376886 | AA90: 4.632447 | AB90: 4.901746 | AC90: 5.174631 | AD90: 5.447477 | AE90: 5.745036 | AF90: 0.056125
A91: FTE000:ga_CompressedNat | B91: Compressed/Liquefied Natural Gas | C91: 51.344929 | D91: 51.773193 | E91: 51.965782 | F91: 52.061802 | G91: 52.003609 | H91: 51.453983 | I91: 50.587246 | J91: 49.35791 | K91: 47.935226 | L91: 46.656029 | M91: 45.774761 | N91: 45.265827 | O91: 45.21376 | P91: 45.570152 | Q91: 46.181816 | R91: 47.148071 | S91: 48.373516 | T91: 49.850353 | U91: 51.657871 | V91: 53.785004 | W91: 56.128632 | X91: 58.653046 | Y91: 61.32283 | Z91: 64.089226 | AA91: 67.060806 | AB91: 70.195724 | AC91: 73.347763 | AD91: 76.647514 | AE91: 80.336487 | AF91: 0.016116
A92: FTE000:ga_ethanolflex | B92: Ethanol-Flex Fuel | C92: 56.296131 | D92: 55.369976 | E92: 54.821407 | F92: 54.645844 | G92: 54.800827 | H92: 55.005043 | I92: 55.364807 | J92: 55.846207 | K92: 56.544991 | L92: 57.577568 | M92: 58.992729 | N92: 60.460762 | O92: 61.892029 | P92: 63.325195 | Q92: 64.556686 | R92: 65.916946 | S92: 67.129135 | T92: 68.383598 | U92: 69.911057 | V92: 71.648148 | W92: 73.513977 | X92: 75.545715 | Y92: 77.664932 | Z92: 79.787003 | AA92: 81.972366 | AB92: 84.157776 | AC92: 86.156769 | AD92: 88.149536 | AE92: 90.333061 | AF92: 0.017032
A93: FTE000:ga_electric | B93: Electric | C93: 0.090132 | D93: 0.105979 | E93: 0.118638 | F93: 0.129129 | G93: 0.137766 | H93: 0.144051 | I93: 0.148279 | J93: 0.15024 | K93: 0.150405 | L93: 0.149294 | M93: 0.147183 | N93: 0.143379 | O93: 0.138445 | P93: 0.132873 | Q93: 0.126362 | R93: 0.119864 | S93: 0.113812 | T93: 0.107261 | U93: 0.100509 | V93: 0.094466 | W93: 0.089089 | X93: 0.083718 | Y93: 0.078723 | Z93: 0.074068 | AA93: 0.069883 | AB93: 0.065998 | AC93: 0.062285 | AD93: 0.058872 | AE93: 0.055809 | AF93: -0.016974
A94: FTE000:ga_plugindiesel | B94: Plug-in Diesel Hybrid | C94: 0 | D94: 0.034697 | E94: 0.22657 | F94: 0.317672 | G94: 0.40791 | H94: 0.495367 | I94: 0.580377 | J94: 0.660607 | K94: 0.736886 | L94: 0.811243 | M94: 0.886039 | N94: 0.958413 | O94: 1.030276 | P94: 1.103778 | Q94: 1.178052 | R94: 1.257694 | S94: 1.343499 | T94: 1.437844 | U94: 1.545047 | V94: 1.666705 | W94: 1.801683 | X94: 1.941409 | Y94: 2.088851 | Z94: 2.248381 | AA94: 2.425267 | AB94: 2.60953 | AC94: 2.798035 | AD94: 2.995368 | AE94: 3.208932 | AF94: --
A95: FTE000:ga_plugingasolin | B95: Plug-in Gasoline Hybrid | C95: 0 | D95: 0.039742 | E95: 0.369553 | F95: 0.487812 | G95: 0.605603 | H95: 0.719725 | I95: 0.829486 | J95: 0.932144 | K95: 1.02958 | L95: 1.12563 | M95: 1.223357 | N95: 1.318871 | O95: 1.414389 | P95: 1.513145 | Q95: 1.613927 | R95: 1.723764 | S95: 1.844094 | T95: 1.979271 | U95: 2.13588 | V95: 2.317318 | W95: 2.522904 | X95: 2.738211 | Y95: 2.966547 | Z95: 3.216047 | AA95: 3.49437 | AB95: 3.783123 | AC95: 4.077595 | AD95: 4.384372 | AE95: 4.712472 | AF95: --
A96: FTE000:ga_fuelcell | B96: Fuel Cell | C96: 0 | D96: 0 | E96: 0.229727 | F96: 0.447252 | G96: 0.662312 | H96: 0.877515 | I96: 1.09125 | J96: 1.299036 | K96: 1.500679 | L96: 1.700765 | M96: 1.904776 | N96: 2.104716 | O96: 2.301462 | P96: 2.49594 | Q96: 2.683397 | R96: 2.871152 | S96: 3.057536 | T96: 3.245911 | U96: 3.444844 | V96: 3.658573 | W96: 3.886771 | X96: 4.120397 | Y96: 4.361271 | Z96: 4.612166 | AA96: 4.888996 | AB96: 5.184831 | AC96: 5.492115 | AD96: 5.819783 | AE96: 6.18408 | AF96: --
A97: FTE000:ga_Total | B97: Total Consumption | C97: 5922.7944 | D97: 5816.7051 | E97: 5728.0957 | F97: 5673.0986 | G97: 5638.8975 | H97: 5591.7061 | I97: 5543.71 | J97: 5483.6724 | K97: 5422.3882 | L97: 5371.3042 | M97: 5340.1577 | N97: 5306.5059 | O97: 5278.7812 | P97: 5261.2451 | Q97: 5243.0034 | R97: 5237.6968 | S97: 5236.3604 | T97: 5238.3047 | U97: 5247.9136 | V97: 5263.2056 | W97: 5281.4531 | X97: 5299.6841 | Y97: 5316.7676 | Z97: 5331.7002 | AA97: 5353.1963 | AB97: 5376.3159 | AC97: 5393.3193 | AD97: 5413.417 | AE97: 5450.0137 | AF97: -0.002967
B99: Fuel Efficiency (miles per gallon)
B100: Light Medium
A101: FTE000:lm_mpg_stk_Dies | B101: Diesel | C101: 14.991418 | D101: 15.216496 | E101: 15.498507 | F101: 15.831193 | G101: 16.182243 | H101: 16.538082 | I101: 16.880116 | J101: 17.209087 | K101: 17.515287 | L101: 17.796841 | M101: 18.05801 | N101: 18.298815 | O101: 18.515478 | P101: 18.711391 | Q101: 18.891172 | R101: 19.054907 | S101: 19.202492 | T101: 19.329569 | U101: 19.439314 | V101: 19.535429 | W101: 19.61628 | X101: 19.678816 | Y101: 19.72633 | Z101: 19.762045 | AA101: 19.788633 | AB101: 19.806604 | AC101: 19.813744 | AD101: 19.817585 | AE101: 19.819794 | AF101: 0.010021
A102: FTE000:lm_mpg_stk_Gas | B102: Motor Gasoline | C102: 10.726876 | D102: 11.029115 | E102: 11.340722 | F102: 11.658097 | G102: 11.957341 | H102: 12.246843 | I102: 12.511288 | J102: 12.761357 | K102: 12.989336 | L102: 13.199086 | M102: 13.38113 | N102: 13.546596 | O102: 13.699472 | P102: 13.842229 | Q102: 13.973739 | R102: 14.095364 | S102: 14.210415 | T102: 14.321558 | U102: 14.425992 | V102: 14.520219 | W102: 14.608215 | X102: 14.692059 | Y102: 14.763736 | Z102: 14.827796 | AA102: 14.883237 | AB102: 14.930063 | AC102: 14.969678 | AD102: 15.003341 | AE102: 15.030684 | AF102: 0.012121
A103: FTE000:lm_mpg_stk_Liq | B103: Propane | C103: 8.287116 | D103: 12.070017 | E103: 12.378905 | F103: 12.533067 | G103: 12.633637 | H103: 12.727521 | I103: 12.811732 | J103: 12.9071 | K103: 13.019794 | L103: 13.144209 | M103: 13.276356 | N103: 13.407525 | O103: 13.532327 | P103: 13.644149 | Q103: 13.742635 | R103: 13.828311 | S103: 13.902666 | T103: 13.967391 | U103: 14.023659 | V103: 14.072396 | W103: 14.11443 | X103: 14.150719 | Y103: 14.184551 | Z103: 14.215186 | AA103: 14.241229 | AB103: 14.26371 | AC103: 14.282851 | AD103: 14.299067 | AE103: 14.312678 | AF103: 0.019708
A104: FTE000:lm_mpg_stk_NGas | B104: Compressed/Liquefied Natural Gas | C104: 10.037065 | D104: 10.03825 | E104: 10.039481 | F104: 10.04076 | G104: 10.04208 | H104: 10.043437 | I104: 10.044827 | J104: 10.046251 | K104: 10.047701 | L104: 10.049176 | M104: 10.050672 | N104: 10.057157 | O104: 10.073521 | P104: 10.105247 | Q104: 10.140972 | R104: 10.185604 | S104: 10.231821 | T104: 10.265868 | U104: 10.275093 | V104: 10.25789 | W104: 10.216537 | X104: 10.1613 | Y104: 10.092754 | Z104: 10.027177 | AA104: 9.99404 | AB104: 10.014455 | AC104: 10.061934 | AD104: 10.114001 | AE104: 10.188727 | AF104: 0.000536
A105: FTE000:lm_mpg_stk_fleck | B105: Ethanol-Flex Fuel | C105: 10.321225 | D105: 10.468386 | E105: 10.641707 | F105: 10.829888 | G105: 11.019979 | H105: 11.213248 | I105: 11.394366 | J105: 11.570538 | K105: 11.740291 | L105: 11.905053 | M105: 12.059313 | N105: 12.21348 | O105: 12.379014 | P105: 12.555837 | Q105: 12.744346 | R105: 12.939108 | S105: 13.149075 | T105: 13.363464 | U105: 13.576193 | V105: 13.772496 | W105: 13.949099 | X105: 14.098662 | Y105: 14.220824 | Z105: 14.323482 | AA105: 14.410444 | AB105: 14.483241 | AC105: 14.544046 | AD105: 14.60201 | AE105: 14.655778 | AF105: 0.012601
A106: FTE000:lm_mpg_stk_eleck | B106: Electric | C106: 24.120544 | D106: 24.120651 | E106: 24.120832 | F106: 24.121077 | G106: 24.121357 | H106: 24.121647 | I106: 24.121906 | J106: 24.1206 | K106: 24.120342 | L106: 24.120312 | M106: 24.120283 | N106: 24.116169 | O106: 24.116142 | P106: 24.116114 | Q106: 24.116087 | R106: 24.116058 | S106: 24.11603 | T106: 24.116003 | U106: 24.12192 | V106: 24.121895 | W106: 24.121872 | X106: 24.121847 | Y106: 24.121847 | Z106: 24.121847 | AA106: 24.121847 | AB106: 24.121847 | AC106: 24.121847 | AD106: 24.121847 | AE106: 24.121849 | AF106: 2e-06
A107: FTE000:lm_mpg_stk_diehy | B107: Plug-in Diesel Hybrid | C107: 0 | D107: 23.149469 | E107: 23.472181 | F107: 23.713379 | G107: 23.934065 | H107: 24.180559 | I107: 24.434351 | J107: 24.733727 | K107: 25.076927 | L107: 25.458097 | M107: 25.866047 | N107: 26.26355 | O107: 26.63553 | P107: 26.97172 | Q107: 27.273853 | R107: 27.540438 | S107: 27.771664 | T107: 27.968973 | U107: 28.134949 | V107: 28.272074 | W107: 28.389307 | X107: 28.489752 | Y107: 28.575668 | Z107: 28.649502 | AA107: 28.719357 | AB107: 28.78302 | AC107: 28.839659 | AD107: 28.888365 | AE107: 28.930431 | AF107: --
A108: FTE000:lm_mpg_stk_gashy | B108: Plug-in Gasoline Hybrid | C108: 0 | D108: 18.959843 | E108: 19.097799 | F108: 19.221861 | G108: 19.306705 | H108: 19.394665 | I108: 19.477266 | J108: 19.57037 | K108: 19.676134 | L108: 19.793497 | M108: 19.919716 | N108: 20.047338 | O108: 20.172951 | P108: 20.289747 | Q108: 20.399185 | R108: 20.498297 | S108: 20.584267 | T108: 20.657764 | U108: 20.719555 | V108: 20.770308 | W108: 20.813774 | X108: 20.851307 | Y108: 20.877443 | Z108: 20.902786 | AA108: 20.928736 | AB108: 20.955839 | AC108: 20.984339 | AD108: 21.01486 | AE108: 21.047607 | AF108: --
...

Sheet ICCT MDV HDV Data
A1: ICCT Data
B2: 2021 | C2: 2022 | D2: 2023 | E2: 2024 | F2: 2025 | G2: 2026 | H2: 2027 | I2: 2028 | J2: 2029 | K2: 2030 | L2: 2031 | M2: 2032 | N2: 2033 | O2: 2034 | P2: 2035
A3: BET cost
A4: Rigid truck, 4-5 | C4: 123014.03 | D4: 116891.1 | E4: 110861.02 | F4: 105086.28 | G4: 99480.617 | H4: 94041.792 | I4: 88699.548 | J4: 83590.764 | K4: 78642.067 | L4: 77971.136 | M4: 77306.303 | N4: 76647.568 | O4: 75994.931 | P4: 75348.394
A5: Rigid truck, 6-7 | C5: 159207.81 | D5: 150762.98 | E5: 142465.29 | F5: 134523.43 | G5: 126825.62 | H5: 119368.46 | I5: 112062.61 | J5: 105080.85 | K5: 98329.492 | L5: 97356.118 | M5: 96392.003 | N5: 95437.148 | O5: 94491.551 | P5: 93555.214
A6: Rigid truck, 8 | C6: 270108.76 | D6: 255656.81 | E6: 241481.06 | F6: 227934.4 | G6: 214826.43 | H6: 202150.52 | I6: 189754.52 | J6: 177930.1 | K6: 166517.74 | L6: 164752.89 | M6: 163006.1 | N6: 161277.37 | O6: 159566.71 | P6: 157874.1
A7: Tractor truck, short-haul | C7: 279260.19 | D7: 263473.36 | E7: 248012.42 | F7: 233239.74 | G7: 218958.37 | H7: 205160.76 | I7: 191692.38 | J7: 178847.74 | K7: 166464.11 | L7: 164483.98 | M7: 162524.39 | N7: 160585.35 | O7: 158666.85 | P7: 156768.9
A8: Tractor truck, long-haul | C8: 514693.03 | D8: 478374.45 | E8: 443236.4 | F8: 409916.58 | G8: 378042.57 | H8: 347585.9 | I8: 318274.01 | J8: 290584.83 | K8: 264226.96 | L8: 259041.24 | M8: 253933.16 | N8: 248902.74 | O8: 243949.97 | P8: 239074.84
A9: Refuse truck | C9: 352345.79 | D9: 336920.4 | E9: 321714.5 | F9: 307197.76 | G9: 293121.27 | H9: 279478.32 | I9: 266058.17 | J9: 253269.42 | K9: 240893.94 | L9: 239120.83 | M9: 237366 | N9: 235629.47 | O9: 233911.22 | P9: 232211.26
A10: Overall HDT | C10: 254244.3 | D10: 238190.03 | E10: 222651.14 | F10: 207942.32 | G10: 193798.83 | H10: 180291.8 | I10: 167274.25 | J10: 154992.18 | K10: 143291.09 | L10: 141012.55 | M10: 138777.42 | N10: 136585.21 | O10: 134435.41 | P10: 132327.55
A11: Small bus, 4-5 | C11: 122214.21 | D11: 117413.98 | E11: 112666.52 | F11: 108136.27 | G11: 103736.84 | H11: 99466.246 | I11: 95249.445 | J11: 91232.696 | K11: 87338.772 | L11: 86812.205 | M11: 86291.056 | N11: 85775.323 | O11: 85265.007 | P11: 84760.108
A12: Transit bus, 6-8 | C12: 450892.87 | D12: 434385.77 | E12: 418045.41 | F12: 402480.97 | G12: 387372.71 | H12: 372713.17 | I12: 358220.19 | J12: 344442.81 | K12: 331091.65 | L12: 329239.35 | M12: 327407.37 | N12: 325595.72 | O12: 323804.38 | P12: 322033.37
A13: School bus, 6-8 | C13: 189784.88 | D13: 182723.32 | E13: 175696.32 | F13: 168961.49 | G13: 162385.75 | H13: 155967.4 | I13: 149590.02 | J13: 143484.57 | K13: 137531.35 | L13: 136760.2 | M13: 135995.26 | N13: 135236.51 | O13: 134483.96 | P13: 133737.6
A14: Other bus, 6-8 | C14: 824534.66 | D14: 800245.73 | E14: 775788.08 | F14: 752300.28 | G14: 729205.34 | H14: 706501.55 | I14: 683662.91 | J14: 661746.4 | K14: 640215.89 | L14: 637719.43 | M14: 635235.36 | N14: 632763.68 | O14: 630304.4 | P14: 627857.52
A15: Overall Bus | C15: 402865.47 | D15: 389825.19 | E15: 376772.31 | F15: 364259.16 | G15: 352003.05 | H15: 340001.82 | I15: 328001.63 | J15: 316508.87 | K15: 305264.04 | L15: 303882.4 | M15: 302510.17 | N15: 301147.36 | O15: 299793.96 | P15: 298449.98
A18: Average Battery Pack Size | B18: 2020 | C18: 2021 | D18: 2022 | E18: 2023 | F18: 2024 | G18: 2025 | H18: 2026 | I18: 2027 | J18: 2028 | K18: 2029 | L18: 2030 | M18: 2031 | N18: 2032 | O18: 2033 | P18: 2034 | Q18: 2035 | R18: 2036 | S18: 2037 | T18: 2038 | U18: 2039 | V18: 2040 | W18: 2041 | X18: 2042 | Y18: 2043 | Z18: 2044 | AA18: 2045 | AB18: 2046 | AC18: 2047 | AD18: 2048 | AE18: 2049 | AF18: 2050
A19: Rigid truck, 4-5 | B19: 140.5 | C19: 137.75 | D19: 135 | E19: 132.25 | F19: 129.5 | G19: 126.75 | H19: 124 | I19: 121.25 | J19: 118.5 | K19: 115.75 | L19: 113 | M19: 113 | N19: 113 | O19: 113 | P19: 113 | Q19: 113 | R19: 113 | S19: 113 | T19: 113 | U19: 113 | V19: 113 | W19: 113 | X19: 113 | Y19: 113 | Z19: 113 | AA19: 113 | AB19: 113 | AC19: 113 | AD19: 113 | AE19: 113 | AF19: 113
A20: Rigid truck, 6-7 | B20: 213.5 | C20: 209.25 | D20: 205 | E20: 200.75 | F20: 196.5 | G20: 192.25 | H20: 188 | I20: 183.75 | J20: 179.5 | K20: 175.25 | L20: 171 | M20: 171 | N20: 171 | O20: 171 | P20: 171 | Q20: 171 | R20: 171 | S20: 171 | T20: 171 | U20: 171 | V20: 171 | W20: 171 | X20: 171 | Y20: 171 | Z20: 171 | AA20: 171 | AB20: 171 | AC20: 171 | AD20: 171 | AE20: 171 | AF20: 171
A21: Rigid truck, 8 | B21: 425 | C21: 412.5 | D21: 400 | E21: 387.5 | F21: 375 | G21: 362.5 | H21: 350 | I21: 337.5 | J21: 325 | K21: 312.5 | L21: 300 | M21: 300 | N21: 300 | O21: 300 | P21: 300 | Q21: 300 | R21: 300 | S21: 300 | T21: 300 | U21: 300 | V21: 300 | W21: 300 | X21: 300 | Y21: 300 | Z21: 300 | AA21: 300 | AB21: 300 | AC21: 300 | AD21: 300 | AE21: 300 | AF21: 300
A22: Tractor truck, short-haul | B22: 485.5 | C22: 470.25 | D22: 455 | E22: 439.75 | F22: 424.5 | G22: 409.25 | H22: 394 | I22: 378.75 | J22: 363.5 | K22: 348.25 | L22: 333 | M22: 333 | N22: 333 | O22: 333 | P22: 333 | Q22: 333 | R22: 333 | S22: 333 | T22: 333 | U22: 333 | V22: 333 | W22: 333 | X22: 333 | Y22: 333 | Z22: 333 | AA22: 333 | AB22: 333 | AC22: 333 | AD22: 333 | AE22: 333 | AF22: 333
A23: Tractor truck, long-haul | B23: 984.25 | C23: 952.125 | D23: 920 | E23: 887.875 | F23: 855.75 | G23: 823.625 | H23: 791.5 | I23: 759.375 | J23: 727.25 | K23: 695.125 | L23: 663 | M23: 663 | N23: 663 | O23: 663 | P23: 663 | Q23: 663 | R23: 663 | S23: 663 | T23: 663 | U23: 663 | V23: 663 | W23: 663 | X23: 663 | Y23: 663 | Z23: 663 | AA23: 663 | AB23: 663 | AC23: 663 | AD23: 663 | AE23: 663 | AF23: 663
A24: Refuse truck | B24: 428.25 | C24: 416.625 | D24: 405 | E24: 393.375 | F24: 381.75 | G24: 370.125 | H24: 358.5 | I24: 346.875 | J24: 335.25 | K24: 323.625 | L24: 312 | M24: 312 | N24: 312 | O24: 312 | P24: 312 | Q24: 312 | R24: 312 | S24: 312 | T24: 312 | U24: 312 | V24: 312 | W24: 312 | X24: 312 | Y24: 312 | Z24: 312 | AA24: 312 | AB24: 312 | AC24: 312 | AD24: 312 | AE24: 312 | AF24: 312
A25: Small bus, 4-5 | B25: 121.25 | C25: 120.625 | D25: 120 | E25: 119.375 | F25: 118.75 | G25: 118.125 | H25: 117.5 | I25: 116.875 | J25: 116.25 | K25: 115.625 | L25: 115 | M25: 115 | N25: 115 | O25: 115 | P25: 115 | Q25: 115 | R25: 115 | S25: 115 | T25: 115 | U25: 115 | V25: 115 | W25: 115 | X25: 115 | Y25: 115 | Z25: 115 | AA25: 115 | AB25: 115 | AC25: 115 | AD25: 115 | AE25: 115 | AF25: 115
A26: Transit bus, 6-8 | B26: 455 | C26: 452.5 | D26: 450 | E26: 447.5 | F26: 445 | G26: 442.5 | H26: 440 | I26: 437.5 | J26: 435 | K26: 432.5 | L26: 430 | M26: 430 | N26: 430 | O26: 430 | P26: 430 | Q26: 430 | R26: 430 | S26: 430 | T26: 430 | U26: 430 | V26: 430 | W26: 430 | X26: 430 | Y26: 430 | Z26: 430 | AA26: 430 | AB26: 430 | AC26: 430 | AD26: 430 | AE26: 430 | AF26: 430
A27: School bus, 6-8 | B27: 182 | C27: 181 | D27: 180 | E27: 179 | F27: 178 | G27: 177 | H27: 176 | I27: 175 | J27: 174 | K27: 173 | L27: 172 | M27: 172 | N27: 172 | O27: 172 | P27: 172 | Q27: 172 | R27: 172 | S27: 172 | T27: 172 | U27: 172 | V27: 172 | W27: 172 | X27: 172 | Y27: 172 | Z27: 172 | AA27: 172 | AB27: 172 | AC27: 172 | AD27: 172 | AE27: 172 | AF27: 172
A28: Other bus, 6-8 | B28: 683.5 | C28: 679.75 | D28: 676 | E28: 672.25 | F28: 668.5 | G28: 664.75 | H28: 661 | I28: 657.25 | J28: 653.5 | K28: 649.75 | L28: 646 | M28: 646 | N28: 646 | O28: 646 | P28: 646 | Q28: 646 | R28: 646 | S28: 646 | T28: 646 | U28: 646 | V28: 646 | W28: 646 | X28: 646 | Y28: 646 | Z28: 646 | AA28: 646 | AB28: 646 | AC28: 646 | AD28: 646 | AE28: 646 | AF28: 646
A31: Total vehicle sales - historical data and projections
B32: 2020 | C32: 2021 | D32: 2022 | E32: 2023 | F32: 2024 | G32: 2025 | H32: 2026 | I32: 2027 | J32: 2028 | K32: 2029 | L32: 2030 | M32: 2031 | N32: 2032 | O32: 2033 | P32: 2034 | Q32: 2035 | R32: 2036 | S32: 2037 | T32: 2038 | U32: 2039 | V32: 2040 | W32: 2041 | X32: 2042 | Y32: 2043 | Z32: 2044 | AA32: 2045 | AB32: 2046 | AC32: 2047 | AD32: 2048 | AE32: 2049 | AF32: 2050 | AG32: 2051 | AH32: 2052 | AI32: 2053 | AJ32: EPS Category
A33: Annual sales
A34: Rigid truck, 4-5 | B34: 116537.59 | C34: 117344.41 | D34: 118151.24 | E34: 118958.06 | F34: 119764.89 | G34: 120571.71 | H34: 122325.78 | I34: 124079.86 | J34: 125833.93 | K34: 127588.01 | L34: 129342.08 | M34: 132498.09 | N34: 135654.1 | O34: 138810.12 | P34: 141966.13 | Q34: 145122.14 | R34: 148198.99 | S34: 151275.84 | T34: 154352.7 | U34: 157429.55 | V34: 160506.4 | W34: 163688.8 | X34: 166799.23 | Y34: 169909.67 | Z34: 173020.1 | AA34: 176130.54 | AB34: 179240.97 | AC34: 182351.41 | AD34: 185461.84 | AE34: 188572.28 | AF34: 191682.71 | AG34: 194793.15 | AH34: 197903.58 | AI34: 201014.02 | AJ34: Freight LDV
A35: Rigid truck, 6-7 | B35: 118399.01 | C35: 119218.7 | D35: 120038.39 | E35: 120858.07 | F35: 121677.76 | G35: 122497.45 | H35: 124279.49 | I35: 126061.52 | J35: 127843.56 | K35: 129625.6 | L35: 131407.63 | M35: 134614.11 | N35: 137820.6 | O35: 141027.08 | P35: 144233.56 | Q35: 147440.04 | R35: 150566.05 | S35: 153692.05 | T35: 156818.06 | U35: 159944.06 | V35: 163070.07 | W35: 166303.38 | X35: 169463.52 | Y35: 172623.67 | Z35: 175783.82 | AA35: 178943.97 | AB35: 182104.11 | AC35: 185264.26 | AD35: 188424.41 | AE35: 191584.55 | AF35: 194744.7 | AG35: 197904.85 | AH35: 201064.99 | AI35: 204225.14 | AJ35: Freight LDV
A36: Rigid truck, 8 | B36: 95647.28 | C36: 96309.492 | D36: 96971.704 | E36: 97633.915 | F36: 98296.127 | G36: 98958.339 | H36: 100397.96 | I36: 101837.59 | J36: 103277.21 | K36: 104716.83 | L36: 106156.46 | M36: 108746.77 | N36: 111337.08 | O36: 113927.39 | P36: 116517.71 | Q36: 119108.02 | R36: 121633.36 | S36: 124158.69 | T36: 126684.03 | U36: 129209.37 | V36: 131734.7 | W36: 134346.68 | X36: 136899.58 | Y36: 139452.48 | Z36: 142005.38 | AA36: 144558.29 | AB36: 147111.19 | AC36: 149664.09 | AD36: 152216.99 | AE36: 154769.9 | AF36: 157322.8 | AG36: 159875.7 | AH36: 162428.6 | AI36: 164981.51 | AJ36: Freight HDV
A37: Tractor truck, short-haul | B37: 55945.25 | C37: 55322.91 | D37: 54700.57 | E37: 54078.23 | F37: 53455.89 | G37: 52833.55 | H37: 52462.84 | I37: 52092.13 | J37: 51721.42 | K37: 51350.71 | L37: 50980 | M37: 51194.304 | N37: 51408.608 | O37: 51622.912 | P37: 51837.216 | Q37: 52051.52 | R37: 52259.394 | S37: 52467.268 | T37: 52675.142 | U37: 52883.016 | V37: 53090.89 | W37: 53307.337 | X37: 53517.939 | Y37: 53728.541 | Z37: 53939.143 | AA37: 54149.745 | AB37: 54360.347 | AC37: 54570.949 | AD37: 54781.55 | AE37: 54992.152 | AF37: 55202.754 | AG37: 55413.356 | AH37: 55623.958 | AI37: 55834.56 | AJ37: Freight HDV
A38: Tractor truck, long-haul | B38: 92843.9 | C38: 91811.12 | D38: 90778.34 | E38: 89745.56 | F38: 88712.78 | G38: 87680 | H38: 87064.76 | I38: 86449.52 | J38: 85834.28 | K38: 85219.04 | L38: 84603.8 | M38: 84959.44 | N38: 85315.08 | O38: 85670.72 | P38: 86026.36 | Q38: 86382 | R38: 86726.98 | S38: 87071.96 | T38: 87416.94 | U38: 87761.92 | V38: 88106.9 | W38: 88466.093 | X38: 88815.596 | Y38: 89165.098 | Z38: 89514.601 | AA38: 89864.103 | AB38: 90213.605 | AC38: 90563.108 | AD38: 90912.61 | AE38: 91262.113 | AF38: 91611.615 | AG38: 91961.118 | AH38: 92310.62 | AI38: 92660.122 | AJ38: Freight HDV
A39: Refuse truck | B39: 3614 | C39: 3639 | D39: 3664 | E39: 3689 | F39: 3714 | G39: 3739 | H39: 3793.4 | I39: 3847.8 | J39: 3902.2 | K39: 3956.6 | L39: 4011 | M39: 4108.8 | N39: 4206.6 | O39: 4304.4 | P39: 4402.2 | Q39: 4500 | R39: 4595.4 | S39: 4690.8 | T39: 4786.2 | U39: 4881.6 | V39: 4977 | W39: 5075.6 | X39: 5172.0182 | Y39: 5268.4364 | Z39: 5364.8545 | AA39: 5461.2727 | AB39: 5557.6909 | AC39: 5654.1091 | AD39: 5750.5273 | AE39: 5846.9455 | AF39: 5943.3636 | AG39: 6039.7818 | AH39: 6136.2 | AI39: 6232.6182 | AJ39: Freight HDV
A40: Overall HDT | B40: 482987.03 | G40: 486280.05 | L40: 506500.97 | Q40: 554603.72 | V40: 601485.96
A41: Small bus, 4-5 | B41: 4754.011 | C41: 4754.1696 | D41: 4754.3282 | E41: 4754.4868 | F41: 4754.6454 | G41: 4754.804 | H41: 4784.2998 | I41: 4813.7956 | J41: 4843.2914 | K41: 4872.7872 | L41: 4902.283 | M41: 4986.5684 | N41: 5070.8538 | O41: 5155.1392 | P41: 5239.4246 | Q41: 5323.71 | R41: 5405.7774 | S41: 5487.8448 | T41: 5569.9122 | U41: 5651.9796 | V41: 5734.047 | W41: 5819.0717 | X41: 5902.0801 | Y41: 5985.0885 | Z41: 6068.0968 | AA41: 6151.1052 | AB41: 6234.1136 | AC41: 6317.122 | AD41: 6400.1303 | AE41: 6483.1387 | AF41: 6566.1471 | AG41: 6649.1554 | AH41: 6732.1638 | AI41: 6815.1722 | AJ41: Passenger HDV
A42: Transit bus, 6-8 | B42: 5282.984 | C42: 5283.158 | D42: 5283.332 | E42: 5283.506 | F42: 5283.68 | G42: 5283.854 | H42: 5316.6318 | I42: 5349.4096 | J42: 5382.1874 | K42: 5414.9652 | L42: 5447.743 | M42: 5541.4026 | N42: 5635.0622 | O42: 5728.7218 | P42: 5822.3814 | Q42: 5916.041 | R42: 6007.242 | S42: 6098.443 | T42: 6189.644 | U42: 6280.845 | V42: 6372.046 | W42: 6466.5251 | X42: 6558.7692 | Y42: 6651.0132 | Z42: 6743.2573 | AA42: 6835.5013 | AB42: 6927.7453 | AC42: 7019.9894 | AD42: 7112.2334 | AE42: 7204.4775 | AF42: 7296.7215 | AG42: 7388.9656 | AH42: 7481.2096 | AI42: 7573.4536 | AJ42: Passenger HDV
A43: School bus, 6-8 | B43: 27044.907 | C43: 27045.802 | D43: 27046.698 | E43: 27047.593 | F43: 27048.489 | G43: 27049.384 | H43: 27217.202 | I43: 27385.02 | J43: 27552.837 | K43: 27720.655 | L43: 27888.473 | M43: 28367.96 | N43: 28847.447 | O43: 29326.934 | P43: 29806.421 | Q43: 30285.908 | R43: 30752.794 | S43: 31219.68 | T43: 31686.566 | U43: 32153.452 | V43: 32620.338 | W43: 33104.025 | X43: 33576.257 | Y43: 34048.489 | Z43: 34520.721 | AA43: 34992.953 | AB43: 35465.185 | AC43: 35937.417 | AD43: 36409.648 | AE43: 36881.88 | AF43: 37354.112 | AG43: 37826.344 | AH43: 38298.576 | AI43: 38770.808 | AJ43: Passenger HDV
A44: Other bus, 6-8 | B44: 16228.913 | C44: 16229.455 | D44: 16229.997 | E44: 16230.539 | F44: 16231.081 | G44: 16231.623 | H44: 16332.309 | I44: 16432.996 | J44: 16533.682 | K44: 16634.369 | L44: 16735.055 | M44: 17022.792 | N44: 17310.528 | O44: 17598.265 | P44: 17886.001 | Q44: 18173.738 | R44: 18453.896 | S44: 18734.054 | T44: 19014.212 | U44: 19294.37 | V44: 19574.528 | W44: 19864.791 | X44: 20148.164 | Y44: 20431.537 | Z44: 20714.91 | AA44: 20998.283 | AB44: 21281.657 | AC44: 21565.03 | AD44: 21848.403 | AE44: 22131.776 | AF44: 22415.149 | AG44: 22698.522 | AH44: 22981.896 | AI44: 23265.269 | AJ44: Passenger HDV
A45: Overall Bus | B45: 53310.815 | G45: 53319.665 | L45: 54973.554 | Q45: 59699.397 | V45: 64300.959
B48: VKT per vehicle
B49: Average of VKTpVeh
B50: Row Labels | C50: 2020 | D50: 2021 | E50: 2022 | F50: 2023 | G50: 2024 | H50: 2025 | I50: 2026 | J50: 2027 | K50: 2028 | L50: 2029 | M50: 2030 | N50: 2031 | O50: 2032 | P50: 2033 | Q50: 2034 | R50: 2035 | S50: 2036 | T50: 2037 | U50: 2038 | V50: 2039 | W50: 2040 | X50: 2041 | Y50: 2042 | Z50: 2043 | AA50: 2044 | AB50: 2045 | AC50: 2046 | AD50: 2047 | AE50: 2048 | AF50: 2049 | AG50: 2050 | AH50: 2051 | AI50: 2052 | AJ50: 2053 | AK50: 2054 | AL50: 2055 | AM50: 2056 | AN50: 2057 | AO50: 2058 | AP50: 2059 | AQ50: 2060 | AR50: 2061 | AS50: 2062 | AT50: 2063 | AU50: 2064 | AV50: 2065 | AW50: 2066 | AX50: 2067 | AY50: 2068 | AZ50: 2069 | BA50: 2070
A51: bus | B51: Motor Home_4_5 | C51: 7282.1417 | D51: 7350.0019 | E51: 7417.8622 | F51: 7485.7225 | G51: 7553.5827 | H51: 7621.443 | I51: 7849.9524 | J51: 8078.4619 | K51: 8306.9713 | L51: 8535.4807 | M51: 8763.9902 | N51: 8847.3833 | O51: 8930.7764 | P51: 9014.1695 | Q51: 9097.5626 | R51: 9180.9557 | S51: 9222.1208 | T51: 9263.2859 | U51: 9304.451 | V51: 9345.6161 | W51: 9386.7812 | X51: 9369.1215 | Y51: 9351.4619 | Z51: 9333.8022 | AA51: 9316.1426 | AB51: 9298.4829 | AC51: 9319.9004 | AD51: 9341.3179 | AE51: 9362.7354 | AF51: 9384.1529 | AG51: 9405.5704 | AH51: 9452.4188 | AI51: 9499.2673 | AJ51: 9546.1157 | AK51: 9592.9642 | AL51: 9639.8126 | AM51: 9681.9088 | AN51: 9724.0049 | AO51: 9766.1011 | AP51: 9808.1972 | AQ51: 9850.2934 | AR51: 9850.2934 | AS51: 9850.2934 | AT51: 9850.2934 | AU51: 9850.2934 | AV51: 9850.2934 | AW51: 9850.2934 | AX51: 9850.2934 | AY51: 9850.2934 | AZ51: 9850.2934 | BA51: 9850.2934
A52: bus | B52: Motor Home_6_7 | C52: 8136.7393 | D52: 8129.8981 | E52: 8123.057 | F52: 8116.2159 | G52: 8109.3747 | H52: 8102.5336 | I52: 8172.6773 | J52: 8242.821 | K52: 8312.9647 | L52: 8383.1085 | M52: 8453.2522 | N52: 8557.9387 | O52: 8662.6252 | P52: 8767.3116 | Q52: 8871.9981 | R52: 8976.6846 | S52: 9033.8404 | T52: 9090.9962 | U52: 9148.1519 | V52: 9205.3077 | W52: 9262.4635 | X52: 9269.6668 | Y52: 9276.8702 | Z52: 9284.0736 | AA52: 9291.2769 | AB52: 9298.4803 | AC52: 9319.8974 | AD52: 9341.3146 | AE52: 9362.7317 | AF52: 9384.1488 | AG52: 9405.5659 | AH52: 9452.4154 | AI52: 9499.2649 | AJ52: 9546.1145 | AK52: 9592.964 | AL52: 9639.8135 | AM52: 9681.9107 | AN52: 9724.0079 | AO52: 9766.1051 | AP52: 9808.2023 | AQ52: 9850.2995 | AR52: 9850.2995 | AS52: 9850.2995 | AT52: 9850.2995 | AU52: 9850.2995 | AV52: 9850.2995 | AW52: 9850.2995 | AX52: 9850.2995 | AY52: 9850.2995 | AZ52: 9850.2995 | BA52: 9850.2995
A53: bus | B53: Motor Home_8 | C53: 8719.9367 | D53: 8710.9262 | E53: 8701.9157 | F53: 8692.9052 | G53: 8683.8947 | H53: 8674.8843 | I53: 8710.6316 | J53: 8746.3789 | K53: 8782.1261 | L53: 8817.8734 | M53: 8853.6207 | N53: 8903.4736 | O53: 8953.3264 | P53: 9003.1792 | Q53: 9053.032 | R53: 9102.8849 | S53: 9139.2061 | T53: 9175.5272 | U53: 9211.8484 | V53: 9248.1696 | W53: 9284.4908 | X53: 9287.2934 | Y53: 9290.0959 | Z53: 9292.8985 | AA53: 9295.701 | AB53: 9298.5036 | AC53: 9319.9193 | AD53: 9341.335 | AE53: 9362.7507 | AF53: 9384.1664 | AG53: 9405.582 | AH53: 9452.4314 | AI53: 9499.2808 | AJ53: 9546.1301 | AK53: 9592.9795 | AL53: 9639.8288 | AM53: 9681.927 | AN53: 9724.0251 | AO53: 9766.1233 | AP53: 9808.2214 | AQ53: 9850.3195 | AR53: 9850.3195 | AS53: 9850.3195 | AT53: 9850.3195 | AU53: 9850.3195 | AV53: 9850.3195 | AW53: 9850.3195 | AX53: 9850.3195 | AY53: 9850.3195 | AZ53: 9850.3195 | BA53: 9850.3195
A54: bus | B54: Other Buses_4_5 | C54: 47403.343 | D54: 47370.819 | E54: 47338.296 | F54: 47305.773 | G54: 47273.25 | H54: 47240.726 | I54: 47313.685 | J54: 47386.644 | K54: 47459.602 | L54: 47532.561 | M54: 47605.52 | N54: 47813.84 | O54: 48022.161 | P54: 48230.482 | Q54: 48438.802 | R54: 48647.123 | S54: 49000.983 | T54: 49354.842 | U54: 49708.702 | V54: 50062.561 | W54: 50416.421 | X54: 50436.532 | Y54: 50456.643 | Z54: 50476.753 | AA54: 50496.864 | AB54: 50516.975 | AC54: 50482.109 | AD54: 50447.243 | AE54: 50412.377 | AF54: 50377.511 | AG54: 50342.645 | AH54: 50354.082 | AI54: 50365.519 | AJ54: 50376.956 | AK54: 50388.393 | AL54: 50399.83 | AM54: 50409.758 | AN54: 50419.687 | AO54: 50429.615 | AP54: 50439.543 | AQ54: 50449.472 | AR54: 50449.472 | AS54: 50449.472 | AT54: 50449.472 | AU54: 50449.472 | AV54: 50449.472 | AW54: 50449.472 | AX54: 50449.472 | AY54: 50449.472 | AZ54: 50449.472 | BA54: 50449.472
A55: Other bus, 6-8 | B55: Other Buses_6_7 | C55: 46342.195 | D55: 46524.8 | E55: 46707.405 | F55: 46890.011 | G55: 47072.616 | H55: 47255.221 | I55: 47488.017 | J55: 47720.814 | K55: 47953.61 | L55: 48186.406 | M55: 48419.202 | N55: 48697.121 | O55: 48975.039 | P55: 49252.958 | Q55: 49530.877 | R55: 49808.796 | S55: 50037.092 | T55: 50265.388 | U55: 50493.684 | V55: 50721.98 | W55: 50950.276 | X55: 50863.641 | Y55: 50777.005 | Z55: 50690.369 | AA55: 50603.734 | AB55: 50517.098 | AC55: 50482.235 | AD55: 50447.372 | AE55: 50412.509 | AF55: 50377.646 | AG55: 50342.783 | AH55: 50354.218 | AI55: 50365.652 | AJ55: 50377.086 | AK55: 50388.521 | AL55: 50399.955 | AM55: 50409.891 | AN55: 50419.827 | AO55: 50429.764 | AP55: 50439.7 | AQ55: 50449.636 | AR55: 50449.636 | AS55: 50449.636 | AT55: 50449.636 | AU55: 50449.636 | AV55: 50449.636 | AW55: 50449.636 | AX55: 50449.636 | AY55: 50449.636 | AZ55: 50449.636 | BA55: 50449.636
A56: Other bus, 6-8 | B56: Other Buses_8 | C56: 47278.158 | D56: 47569.074 | E56: 47859.99 | F56: 48150.905 | G56: 48441.821 | H56: 48732.737 | I56: 48956.527 | J56: 49180.316 | K56: 49404.106 | L56: 49627.896 | M56: 49851.686 | N56: 49992.598 | O56: 50133.51 | P56: 50274.421 | Q56: 50415.333 | R56: 50556.245 | S56: 50632.373 | T56: 50708.5 | U56: 50784.627 | V56: 50860.755 | W56: 50936.882 | X56: 50852.921 | Y56: 50768.96 | Z56: 50684.999 | AA56: 50601.038 | AB56: 50517.077 | AC56: 50482.206 | AD56: 50447.336 | AE56: 50412.466 | AF56: 50377.595 | AG56: 50342.725 | AH56: 50354.163 | AI56: 50365.601 | AJ56: 50377.038 | AK56: 50388.476 | AL56: 50399.914 | AM56: 50409.856 | AN56: 50419.798 | AO56: 50429.739 | AP56: 50439.681 | AQ56: 50449.623 | AR56: 50449.623 | AS56: 50449.623 | AT56: 50449.623 | AU56: 50449.623 | AV56: 50449.623 | AW56: 50449.623 | AX56: 50449.623 | AY56: 50449.623 | AZ56: 50449.623 | BA56: 50449.623
A57: Small bus, 4-5 | B57: School Bus_4_5 | C57: 16553.996 | D57: 16490.021 | E57: 16426.045 | F57: 16362.07 | G57: 16298.094 | H57: 16234.119 | I57: 16231.142 | J57: 16228.165 | K57: 16225.188 | L57: 16222.21 | M57: 16219.233 | N57: 16279.774 | O57: 16340.315 | P57: 16400.857 | Q57: 16461.398 | R57: 16521.939 | S57: 16649.081 | T57: 16776.224 | U57: 16903.366 | V57: 17030.509 | W57: 17157.652 | X57: 17212.593 | Y57: 17267.535 | Z57: 17322.477 | AA57: 17377.419 | AB57: 17432.361 | AC57: 17419.188 | AD57: 17406.014 | AE57: 17392.841 | AF57: 17379.668 | AG57: 17366.495 | AH57: 17369.149 | AI57: 17371.803 | AJ57: 17374.456 | AK57: 17377.11 | AL57: 17379.764 | AM57: 17382.863 | AN57: 17385.963 | AO57: 17389.062 | AP57: 17392.161 | AQ57: 17395.26 | AR57: 17395.26 | AS57: 17395.26 | AT57: 17395.26 | AU57: 17395.26 | AV57: 17395.26 | AW57: 17395.26 | AX57: 17395.26 | AY57: 17395.26 | AZ57: 17395.26 | BA57: 17395.26
A58: School bus, 6-8 | B58: School Bus_6_7 | C58: 16570.755 | D58: 16622.415 | E58: 16674.076 | F58: 16725.737 | G58: 16777.397 | H58: 16829.058 | I58: 16868.764 | J58: 16908.47 | K58: 16948.176 | L58: 16987.882 | M58: 17027.588 | N58: 17080.18 | O58: 17132.772 | P58: 17185.364 | Q58: 17237.957 | R58: 17290.549 | S58: 17338.471 | T58: 17386.392 | U58: 17434.314 | V58: 17482.236 | W58: 17530.157 | X58: 17510.594 | Y58: 17491.03 | Z58: 17471.466 | AA58: 17451.902 | AB58: 17432.339 | AC58: 17419.165 | AD58: 17405.992 | AE58: 17392.818 | AF58: 17379.645 | AG58: 17366.472 | AH58: 17369.128 | AI58: 17371.784 | AJ58: 17374.441 | AK58: 17377.097 | AL58: 17379.754 | AM58: 17382.852 | AN58: 17385.951 | AO58: 17389.049 | AP58: 17392.148 | AQ58: 17395.246 | AR58: 17395.246 | AS58: 17395.246 | AT58: 17395.246 | AU58: 17395.246 | AV58: 17395.246 | AW58: 17395.246 | AX58: 17395.246 | AY58: 17395.246 | AZ58: 17395.246 | BA58: 17395.246
A59: School bus, 6-8 | B59: School Bus_8 | C59: 16704.542 | D59: 16744.325 | E59: 16784.109 | F59: 16823.892 | G59: 16863.675 | H59: 16903.458 | I59: 16930.018 | J59: 16956.578 | K59: 16983.137 | L59: 17009.697 | M59: 17036.256 | N59: 17092.803 | O59: 17149.349 | P59: 17205.895 | Q59: 17262.441 | R59: 17318.987 | S59: 17364.258 | T59: 17409.529 | U59: 17454.8 | V59: 17500.072 | W59: 17545.343 | X59: 17522.743 | Y59: 17500.144 | Z59: 17477.544 | AA59: 17454.944 | AB59: 17432.345 | AC59: 17419.171 | AD59: 17405.996 | AE59: 17392.822 | AF59: 17379.648 | AG59: 17366.474 | AH59: 17369.128 | AI59: 17371.782 | AJ59: 17374.436 | AK59: 17377.091 | AL59: 17379.745 | AM59: 17382.843 | AN59: 17385.941 | AO59: 17389.038 | AP59: 17392.136 | AQ59: 17395.234 | AR59: 17395.234 | AS59: 17395.234 | AT59: 17395.234 | AU59: 17395.234 | AV59: 17395.234 | AW59: 17395.234 | AX59: 17395.234 | AY59: 17395.234 | AZ59: 17395.234 | BA59: 17395.234
A60: Small bus, 4-5 | B60: Transit Bus_4_5 | C60: 48680.059 | D60: 48531.565 | E60: 48383.072 | F60: 48234.578 | G60: 48086.084 | H60: 47937.59 | I60: 47927.116 | J60: 47916.641 | K60: 47906.167 | L60: 47895.692 | M60: 47885.217 | N60: 47968.701 | O60: 48052.184 | P60: 48135.667 | Q60: 48219.151 | R60: 48302.634 | S60: 48572.494 | T60: 48842.354 | U60: 49112.213 | V60: 49382.073 | W60: 49651.933 | X60: 49714.263 | Y60: 49776.593 | Z60: 49838.923 | AA60: 49901.253 | AB60: 49963.584 | AC60: 49892.911 | AD60: 49822.238 | AE60: 49751.565 | AF60: 49680.892 | AG60: 49610.219 | AH60: 49619.684 | AI60: 49629.149 | AJ60: 49638.614 | AK60: 49648.078 | AL60: 49657.543 | AM60: 49669.802 | AN60: 49682.062 | AO60: 49694.321 | AP60: 49706.58 | AQ60: 49718.84 | AR60: 49718.84 | AS60: 49718.84 | AT60: 49718.84 | AU60: 49718.84 | AV60: 49718.84 | AW60: 49718.84 | AX60: 49718.84 | AY60: 49718.84 | AZ60: 49718.84 | BA60: 49718.84
A61: Transit bus, 6-8 | B61: Transit Bus_6_7 | C61: 48928.255 | D61: 48905.951 | E61: 48883.647 | F61: 48861.343 | G61: 48839.039 | H61: 48816.735 | I61: 48853.19 | J61: 48889.644 | K61: 48926.098 | L61: 48962.553 | M61: 48999.007 | N61: 49142.052 | O61: 49285.097 | P61: 49428.142 | Q61: 49571.187 | R61: 49714.232 | S61: 49870.382 | T61: 50026.531 | U61: 50182.68 | V61: 50338.829 | W61: 50494.979 | X61: 50388.725 | Y61: 50282.472 | Z61: 50176.219 | AA61: 50069.966 | AB61: 49963.713 | AC61: 49893.036 | AD61: 49822.36 | AE61: 49751.684 | AF61: 49681.007 | AG61: 49610.331 | AH61: 49619.804 | AI61: 49629.276 | AJ61: 49638.749 | AK61: 49648.222 | AL61: 49657.695 | AM61: 49669.953 | AN61: 49682.211 | AO61: 49694.469 | AP61: 49706.726 | AQ61: 49718.984 | AR61: 49718.984 | AS61: 49718.984 | AT61: 49718.984 | AU61: 49718.984 | AV61: 49718.984 | AW61: 49718.984 | AX61: 49718.984 | AY61: 49718.984 | AZ61: 49718.984 | BA61: 49718.984
A62: Transit bus, 6-8 | B62: Transit Bus_8 | C62: 41840.804 | D62: 40833.384 | E62: 39825.965 | F62: 38818.545 | G62: 37811.126 | H62: 36803.706 | I62: 35882.536 | J62: 34961.366 | K62: 34040.196 | L62: 33119.026 | M62: 32197.856 | N62: 31358.835 | O62: 30519.814 | P62: 29680.793 | Q62: 28841.773 | R62: 28002.752 | S62: 28002.752 | T62: 28002.752 | U62: 28002.752 | V62: 28002.752 | W62: 28002.752 | X62: 28002.752 | Y62: 28002.752 | Z62: 28002.752 | AA62: 28002.752 | AB62: 28002.752 | AC62: 28002.752 | AD62: 28002.752 | AE62: 28002.752 | AF62: 28002.752 | AG62: 28002.752 | AH62: 28002.752 | AI62: 28002.752 | AJ62: 28002.752 | AK62: 28002.752 | AL62: 28002.752 | AM62: 28002.752 | AN62: 28002.752 | AO62: 28002.752 | AP62: 28002.752 | AQ62: 28002.752 | AR62: 28002.752 | AS62: 28002.752 | AT62: 28002.752 | AU62: 28002.752 | AV62: 28002.752 | AW62: 28002.752 | AX62: 28002.752 | AY62: 28002.752 | AZ62: 28002.752 | BA62: 28002.752
... A88: Rigid truck, 8 | B88: Single Unit Short-haul Truck_8 | C88: 22089.612 | D88: 22254.831 | E88: 22420.049 | F88: 22585.267 | G88: 22750.485 | H88: 22915.703 | I88: 22961.06 | J88: 23006.417 | K88: 23051.774 | L88: 23097.132 | M88: 23142.489 | N88: 23237.179 | O88: 23331.869 | P88: 23426.559 | Q88: 23521.249 | R88: 23615.939 | S88: 23667.042 | T88: 23718.146 | U88: 23769.249 | V88: 23820.353 | W88: 23871.456 | X88: 23825.96 | Y88: 23780.463 | Z88: 23734.966 | AA88: 23689.47 | AB88: 23643.973 | AC88: 23696.146 | AD88: 23748.318 | AE88: 23800.49 | AF88: 23852.663 | AG88: 23904.835 | AH88: 23991.658 | AI88: 24078.481 | AJ88: 24165.304 | AK88: 24252.126 | AL88: 24338.949 | AM88: 24427.753 | AN88: 24516.557 | AO88: 24605.361 | AP88: 24694.164 | AQ88: 24782.968 | AR88: 24782.968 | AS88: 24782.968 | AT88: 24782.968 | AU88: 24782.968 | AV88: 24782.968 | AW88: 24782.968 | AX88: 24782.968 | AY88: 24782.968 | AZ88: 24782.968 | BA88: 24782.968
B89: (blank)
B90: Grand Total | C90: 36212.918 | D90: 35995.436 | E90: 35777.955 | F90: 35560.474 | G90: 35342.993 | H90: 35125.512 | I90: 35092.616 | J90: 35059.721 | K90: 35026.826 | L90: 34993.93 | M90: 34961.035 | N90: 35044.534 | O90: 35128.033 | P90: 35211.532 | Q90: 35295.032 | R90: 35378.531 | S90: 35519.507 | T90: 35660.484 | U90: 35801.46 | V90: 35942.437 | W90: 36083.413 | X90: 36110.468 | Y90: 36137.523 | Z90: 36164.578 | AA90: 36191.633 | AB90: 36218.688 | AC90: 36304.421 | AD90: 36390.153 | AE90: 36475.886 | AF90: 36561.618 | AG90: 36647.351 | AH90: 36746.835 | AI90: 36846.32 | AJ90: 36945.804 | AK90: 37045.289 | AL90: 37144.773 | AM90: 37248.896 | AN90: 37353.018 | AO90: 37457.141 | AP90: 37561.263 | AQ90: 37665.385 | AR90: 37665.385 | AS90: 37665.385 | AT90: 37665.385 | AU90: 37665.385 | AV90: 37665.385 | AW90: 37665.385 | AX90: 37665.385 | AY90: 37665.385 | AZ90: 37665.385 | BA90: 37665.385
A93: Total Vehicle Kilometers by Vehicle Type | B93: EPS Vehicle Type | C93: 2020 | D93: 2021 | E93: 2022 | F93: 2023 | G93: 2024 | H93: 2025 | I93: 2026 | J93: 2027 | K93: 2028 | L93: 2029 | M93: 2030 | N93: 2031 | O93: 2032 | P93: 2033 | Q93: 2034 | R93: 2035 | S93: 2036 | T93: 2037 | U93: 2038 | V93: 2039 | W93: 2040 | X93: 2041 | Y93: 2042 | Z93: 2043 | AA93: 2044 | AB93: 2045 | AC93: 2046 | AD93: 2047 | AE93: 2048 | AF93: 2049 | AG93: 2050
A94: Rigid truck, 4-5 | B94: Freight LDV | C94: 28710.322 | D94: 28740.361 | E94: 28770.64 | F94: 28801.159 | G94: 28831.917 | H94: 28862.915 | I94: 28717.2 | J94: 28573.838 | K94: 28432.843 | L94: 28294.231 | M94: 28158.017 | N94: 28447.915 | O94: 28737.821 | P94: 29027.734 | Q94: 29317.655 | R94: 29607.583 | S94: 29766.429 | T94: 29925.278 | U94: 30084.13 | V94: 30242.986 | W94: 30401.845 | X94: 30515.02 | Y94: 30628.195 | Z94: 30741.371 | AA94: 30854.547 | AB94: 30967.723 | AC94: 31031.244 | AD94: 31094.766 | AE94: 31158.287 | AF94: 31221.81 | AG94: 31285.333
A95: Rigid truck, 6-7 | B95: Freight LDV | C95: 28744.398 | D95: 28676.968 | E95: 28610.936 | F95: 28546.303 | G95: 28483.071 | H95: 28421.24 | I95: 28580.672 | J95: 28740.916 | K95: 28901.96 | L95: 29063.796 | M95: 29226.414 | N95: 29411.355 | O95: 29596.323 | P95: 29781.317 | Q95: 29966.336 | R95: 30151.379 | S95: 30333.797 | T95: 30516.215 | U95: 30698.633 | V95: 30881.05 | W95: 31063.468 | X95: 31044.308 | Y95: 31025.154 | Z95: 31006.006 | AA95: 30986.865 | AB95: 30967.73 | AC95: 31031.246 | AD95: 31094.762 | AE95: 31158.28 | AF95: 31221.797 | AG95: 31285.315
A96: Rigid truck, 8 | B96: Freight HDV | C96: 29842.882 | D96: 29958.388 | E96: 30074.143 | F96: 30190.144 | G96: 30306.388 | H96: 30422.871 | I96: 30408.455 | J96: 30394.163 | K96: 30379.997 | L96: 30365.955 | M96: 30352.037 | N96: 30440.447 | O96: 30528.886 | P96: 30617.354 | Q96: 30705.852 | R96: 30794.377 | S96: 30870.004 | T96: 30945.633 | U96: 31021.264 | V96: 31096.896 | W96: 31172.531 | X96: 31131.559 | Y96: 31090.595 | Z96: 31049.638 | AA96: 31008.69 | AB96: 30967.749 | AC96: 31031.268 | AD96: 31094.788 | AE96: 31158.309 | AF96: 31221.83 | AG96: 31285.351
A97: Tractor truck, short-haul | B97: Freight HDV | C97: 75846.447 | D97: 74745.588 | E97: 73758.185 | F97: 72884.635 | G97: 72125.337 | H97: 71480.694 | I97: 70922.611 | J97: 70413.121 | K97: 69952.752 | L97: 69542.044 | M97: 69181.542 | N97: 69180.132 | O97: 69188.97 | P97: 69208.044 | Q97: 69237.339 | R97: 69276.842 | S97: 69538.576 | T97: 69803.277 | U97: 70070.914 | V97: 70341.454 | W97: 70614.868 | X97: 70686.212 | Y97: 70757.843 | Z97: 70829.762 | AA97: 70901.967 | AB97: 70974.457 | AC97: 71303.864 | AD97: 71633.818 | AE97: 71964.31 | AF97: 72295.332 | AG97: 72626.878
A98: Tractor truck, long-haul | B98: Freight HDV | C98: 157391.05 | D98: 155345.29 | E98: 153379.8 | F98: 151498.63 | G98: 149706.09 | H98: 148006.79 | I98: 146843.95 | J98: 145721.67 | K98: 144640.79 | L98: 143602.16 | M98: 142606.69 | N98: 142731.55 | O98: 142868.66 | P98: 143018.04 | Q98: 143179.69 | R98: 143353.62 | S98: 143836.64 | T98: 144324.96 | U98: 144818.54 | V98: 145317.34 | W98: 145821.3 | X98: 146102.18 | Y98: 146383.3 | Z98: 146664.65 | AA98: 146946.22 | AB98: 147228.03 | AC98: 148034.16 | AD98: 148841.8 | AE98: 149650.93 | AF98: 150461.53 | AG98: 151273.58
A99: Refuse truck | B99: Freight HDV | C99: 26260.099 | D99: 26546.403 | E99: 26863.984 | F99: 27213.576 | G99: 27595.935 | H99: 28011.843 | I99: 28396.124 | J99: 28780.696 | K99: 29165.549 | L99: 29550.672 | M99: 29936.057 | N99: 30431.206 | O99: 30928.207 | P99: 31426.98 | Q99: 31927.45 | R99: 32429.547 | S99: 32687.596 | T99: 32946.044 | U99: 33204.885 | V99: 33464.109 | W99: 33723.708 | X99: 33736.014 | Y99: 33748.57 | Z99: 33761.377 | AA99: 33774.435 | AB99: 33787.743 | AC99: 33844.171 | AD99: 33900.601 | AE99: 33957.034 | AF99: 34013.468 | AG99: 34069.905
A100: Small bus, 4-5 | B100: Passenger HDV | C100: 40527.65 | D100: 40405.56 | E100: 40283.477 | F100: 40161.4 | G100: 40039.33 | H100: 39917.266 | I100: 39908.478 | J100: 39899.689 | K100: 39890.901 | L100: 39882.113 | M100: 39873.324 | N100: 39939.116 | O100: 40004.943 | P100: 40070.807 | Q100: 40136.705 | R100: 40202.639 | S100: 40423.419 | T100: 40644.24 | U100: 40865.1 | V100: 41086 | W100: 41306.939 | X100: 41355.316 | Y100: 41403.73 | Z100: 41452.18 | AA100: 41500.667 | AB100: 41549.19 | AC100: 41489.282 | AD100: 41429.379 | AE100: 41369.48 | AF100: 41309.585 | AG100: 41249.695
A101: Transit bus, 6-8 | B101: Passenger HDV | C101: 45661.232 | D101: 45232.755 | E101: 44817.223 | F101: 44415.092 | G101: 44026.841 | H101: 43652.969 | I101: 43360.584 | J101: 43082.3 | K101: 42818.57 | L101: 42569.862 | M101: 42336.668 | N101: 42214.663 | O101: 42108.685 | P101: 42019.156 | Q101: 41946.516 | R101: 41891.216 | S101: 42006.902 | T101: 42122.749 | U101: 42238.757 | V101: 42354.926 | W101: 42471.253 | X101: 42392.08 | Y101: 42312.98 | Z101: 42233.954 | AA101: 42155.002 | AB101: 42076.125 | AC101: 42023.699 | AD101: 41971.307 | AE101: 41918.948 | AF101: 41866.622 | AG101: 41814.33
A102: School bus, 6-8 | B102: Passenger HDV | C102: 16637.917 | D102: 16683.593 | E102: 16729.273 | F102: 16774.958 | G102: 16820.647 | H102: 16866.34 | I102: 16899.446 | J102: 16932.558 | K102: 16965.674 | L102: 16998.796 | M102: 17031.923 | N102: 17086.494 | O102: 17141.064 | P102: 17195.636 | Q102: 17250.207 | R102: 17304.779 | S102: 17351.374 | T102: 17397.968 | U102: 17444.563 | V102: 17491.158 | W102: 17537.753 | X102: 17516.67 | Y102: 17495.588 | Z102: 17474.506 | AA102: 17453.424 | AB102: 17432.342 | AC102: 17419.168 | AD102: 17405.994 | AE102: 17392.82 | AF102: 17379.646 | AG102: 17366.473
A103: Other bus, 6-8 | B103: Passenger HDV | C103: 46814.855 | D103: 47052.732 | E103: 47290.721 | F103: 47528.822 | G103: 47767.032 | H103: 48005.351 | I103: 48233.452 | J103: 48461.556 | K103: 48689.663 | L103: 48917.772 | M103: 49145.884 | N103: 49353.362 | O103: 49561.045 | P103: 49768.932 | Q103: 49977.019 | R103: 50185.304 | S103: 50336.492 | T103: 50487.916 | U103: 50639.574 | V103: 50791.462 | W103: 50943.58 | X103: 50858.281 | Y103: 50772.983 | Z103: 50687.684 | AA103: 50602.386 | AB103: 50517.088 | AC103: 50482.221 | AD103: 50447.354 | AE103: 50412.488 | AF103: 50377.621 | AG103: 50342.754
A105: Total New Vehicle Miles | B105: EPS Vehicle Type | C105: 2020 | D105: 2021 | E105: 2022 | F105: 2023 | G105: 2024 | H105: 2025 | I105: 2026 | J105: 2027 | K105: 2028 | L105: 2029 | M105: 2030 | N105: 2031 | O105: 2032 | P105: 2033 | Q105: 2034 | R105: 2035 | S105: 2036 | T105: 2037 | U105: 2038 | V105: 2039 | W105: 2040 | X105: 2041 | Y105: 2042 | Z105: 2043 | AA105: 2044 | AB105: 2045 | AC105: 2046 | AD105: 2047 | AE105: 2048 | AF105: 2049 | AG105: 2050
... A139: Other bus, 6-8 | B139: Passenger HDV | C139: 315.94377 | D139: 315.37492 | E139: 314.77737 | F139: 314.15083 | G139: 313.49503 | H139: 312.80965 | I139: 311.95558 | J139: 311.07392 | K139: 310.16452 | L139: 309.22719 | M139: 308.26176 | N139: 308.73 | O139: 309.18077 | P139: 309.61374 | Q139: 310.02856 | R139: 310.42485 | S139: 310.37578 | T139: 310.32759 | U139: 310.28026 | V139: 310.23377 | W139: 310.18811 | X139: 310.05475 | Y139: 309.92082 | Z139: 309.78645 | AA139: 309.65164 | AB139: 309.51639 | AC139: 309.57125 | AD139: 309.62616 | AE139: 309.68113 | AF139: 309.73616 | AG139: 309.79126
A141: New BEV Battery Size by EPS Vehicle Type | C141: 2020 | D141: 2021 | E141: 2022 | F141: 2023 | G141: 2024 | H141: 2025 | I141: 2026 | J141: 2027 | K141: 2028 | L141: 2029 | M141: 2030 | N141: 2031 | O141: 2032 | P141: 2033 | Q141: 2034 | R141: 2035 | S141: 2036 | T141: 2037 | U141: 2038 | V141: 2039 | W141: 2040 | X141: 2041 | Y141: 2042 | Z141: 2043 | AA141: 2044 | AB141: 2045 | AC141: 2046 | AD141: 2047 | AE141: 2048 | AF141: 2049 | AG141: 2050
A142: Freight LDV | C142: 177.31084 | D142: 173.74378 | E142: 170.17989 | F142: 166.61915 | G142: 163.06152 | H142: 159.50696 | I142: 156.17727 | J142: 152.83866 | K142: 149.49114 | L142: 146.13476 | M142: 142.76954 | N142: 142.71253 | O142: 142.65646 | P142: 142.60129 | Q142: 142.54702 | R142: 142.49362 | S142: 142.50349 | T142: 142.51326 | U142: 142.52291 | V142: 142.53245 | W142: 142.54188 | X142: 142.47908 | Y142: 142.41647 | Z142: 142.35405 | AA142: 142.29182 | AB142: 142.22978 | AC142: 142.22978 | AD142: 142.22978 | AE142: 142.22978 | AF142: 142.22978 | AG142: 142.22978
A143: Freight HDV | C143: 811.56733 | D143: 783.67722 | E143: 755.82259 | F143: 728.01646 | G143: 700.27211 | H143: 672.60296 | I143: 645.38599 | J143: 618.26561 | K143: 591.24666 | L143: 564.33387 | M143: 537.53185 | N143: 536.62096 | O143: 535.72116 | P143: 534.8325 | Q143: 533.95502 | R143: 533.08875 | S143: 532.34084 | T143: 531.60615 | U143: 530.88444 | V143: 530.17546 | W143: 529.47899 | X143: 528.92797 | Y143: 528.40465 | Z143: 527.89287 | AA143: 527.39236 | AB143: 526.90286 | AC143: 526.43452 | AD143: 525.97611 | AE143: 525.52739 | AF143: 525.08811 | AG143: 524.658
A144: Passenger HDV | C144: 446.7612 | D144: 444.77135 | E144: 442.77571 | F144: 440.77425 | G144: 438.76692 | H144: 436.75369 | I144: 434.6628 | J144: 432.56659 | K144: 430.46504 | L144: 428.35813 | M144: 426.24584 | N144: 426.40399 | O144: 426.56186 | P144: 426.71944 | Q144: 426.87669 | R144: 427.03359 | S144: 426.96898 | T144: 426.90524 | U144: 426.84235 | V144: 426.78029 | W144: 426.71907 | X144: 426.5846 | Y144: 426.44969 | Z144: 426.31442 | AA144: 426.17877 | AB144: 426.04276 | AC144: 426.07408 | AD144: 426.10545 | AE144: 426.13688 | AF144: 426.16835 | AG144: 426.19988
A146: Annual Percent Improvement in Battery Size by Vehicle Type | C146: 2020 | D146: 2021 | E146: 2022 | F146: 2023 | G146: 2024 | H146: 2025 | I146: 2026 | J146: 2027 | K146: 2028 | L146: 2029 | M146: 2030 | N146: 2031 | O146: 2032 | P146: 2033 | Q146: 2034 | R146: 2035 | S146: 2036 | T146: 2037 | U146: 2038 | V146: 2039 | W146: 2040 | X146: 2041 | Y146: 2042 | Z146: 2043 | AA146: 2044 | AB146: 2045 | AC146: 2046 | AD146: 2047 | AE146: 2048 | AF146: 2049 | AG146: 2050
A147: Freight LDV | C147: 0 | D147: 0.020117557 | E147: 0.020512302 | F147: 0.020923403 | G147: 0.021351893 | H147: 0.021798896 | I147: 0.020874853 | J147: 0.02137708 | K147: 0.021902281 | L147: 0.02245206 | M147: 0.02302817 | N147: 0.00039931429 | O147: 0.00039292195 | P147: 0.00038668056 | Q147: 0.00038058545 | R147: 0.00037463211 | S147: -6.9298791e-05 | T147: -6.8499473e-05 | U147: -6.7713885e-05 | V147: -6.6941715e-05 | W147: -6.6182657e-05 | X147: 0.00044056024 | Y147: 0.00043943563 | Z147: 0.00043828592 | AA147: 0.00043714043 | AB147: 0.00043599914 | AC147: 3.4780812e-10 | AD147: 8.0378948e-10 | AE147: 1.2339005e-09 | AF147: 1.6398758e-09 | AG147: 2.0233043e-09
A148: Freight HDV | C148: 0 | D148: 0.034365738 | E148: 0.035543496 | F148: 0.036789228 | G148: 0.038109516 | H148: 0.039512 | I148: 0.040465129 | J148: 0.042021957 | K148: 0.043701203 | L148: 0.045518707 | M148: 0.047493199 | N148: 0.0016945919 | O148: 0.0016767841 | P148: 0.0016588048 | Q148: 0.0016406635 | R148: 0.0016223699 | S148: 0.0014029682 | T148: 0.001380108 | U148: 0.0013576087 | V148: 0.0013354655 | W148: 0.0013136735 | X148: 0.0010406696 | Y148: 0.00098941149 | Z148: 0.00096853729 | AA148: 0.00094811995 | AB148: 0.00092814645 | AC148: 0.00088886636 | AD148: 0.00087076864 | AE148: 0.0008531183 | AF148: 0.00083590185 | AG148: 0.00081910634
A149: Passenger HDV | C149: 0 | D149: 0.004453946 | E149: 0.0044868858 | F149: 0.004520266 | G149: 0.0045540956 | H149: 0.0045883837 | I149: 0.0047873348 | J149: 0.0048226108 | K149: 0.0048583291 | L149: 0.0048944986 | M149: 0.0049311286 | N149: -0.00037102334 | O149: -0.00037024093 | P149: -0.00036940457 | Q149: -0.00036851378 | R149: -0.00036756807 | S149: 0.00015129823 | T149: 0.00014929771 | U149: 0.00014732301 | V149: 0.00014537379 | W149: 0.0001434497 | X149: 0.00031513167 | Y149: 0.0003162491 | Z149: 0.00031721381 | AA149: 0.00031818192 | AB149: 0.00031915345 | AC149: -7.3521429e-05 | AD149: -7.3635433e-05 | AE149: -7.3749687e-05 | AF149: -7.3864188e-05 | AG149: -7.3978938e-05

Sheet AEO by Class
A1: Total VMT by Class
B2: 2021 | C2: 2022 | D2: 2023 | E2: 2024 | F2: 2025 | G2: 2026 | H2: 2027 | I2: 2028 | J2: 2029 | K2: 2030 | L2: 2031 | M2: 2032 | N2: 2033 | O2: 2034 | P2: 2035 | Q2: 2036 | R2: 2037 | S2: 2038 | T2: 2039 | U2: 2040 | V2: 2041 | W2: 2042 | X2: 2043 | Y2: 2044 | Z2: 2045 | AA2: 2046 | AB2: 2047 | AC2: 2048 | AD2: 2049 | AE2: 2050
A3: 2b | B3: =SUMIFS($E$22:$E$372,$B$22:$B$372,B$2)+SUMIFS($F$22:$F$372,$B$22:$B$372,B$2) -> 89367047258 | C3: =SUMIFS($E$22:$E$372,$B$22:$B$372,C$2)+SUMIFS($F$22:$F$372,$B$22:$B$372,C$2) -> 95977015103 | D3: =SUMIFS($E$22:$E$372,$B$22:$B$372,D$2)+SUMIFS($F$22:$F$372,$B$22:$B$372,D$2) -> 98812825093 | E3: =SUMIFS($E$22:$E$372,$B$22:$B$372,E$2)+SUMIFS($F$22:$F$372,$B$22:$B$372,E$2) -> 100094998262 | F3: =SUMIFS($E$22:$E$372,$B$22:$B$372,F$2)+SUMIFS($F$22:$F$372,$B$22:$B$372,F$2) -> 100480428369 | G3: =SUMIFS($E$22:$E$372,$B$22:$B$372,G$2)+SUMIFS($F$22:$F$372,$B$22:$B$372,G$2) -> 101424489851 | H3: =SUMIFS($E$22:$E$372,$B$22:$B$372,H$2)+SUMIFS($F$22:$F$372,$B$22:$B$372,H$2) -> 102816579379 | I3: =SUMIFS($E$22:$E$372,$B$22:$B$372,I$2)+SUMIFS($F$22:$F$372,$B$22:$B$372,I$2) -> 104230371474 | ... AE3: =SUMIFS($E$22:$E$372,$B$22:$B$372,AE$2)+SUMIFS($F$22:$F$372,$B$22:$B$372,AE$2) -> 130641797616
A4: 3 | B4: =SUMIFS($G$22:$G$372,$B$22:$B$372,B$2)+SUMIFS($H$22:$H$372,$B$22:$B$372,B$2) -> 73491209528 | C4: =SUMIFS($G$22:$G$372,$B$22:$B$372,C$2)+SUMIFS($H$22:$H$372,$B$22:$B$372,C$2) -> 75058850216 | D4: =SUMIFS($G$22:$G$372,$B$22:$B$372,D$2)+SUMIFS($H$22:$H$372,$B$22:$B$372,D$2) -> 74732068170 | E4: =SUMIFS($G$22:$G$372,$B$22:$B$372,E$2)+SUMIFS($H$22:$H$372,$B$22:$B$372,E$2) -> 75056362035 | F4: =SUMIFS($G$22:$G$372,$B$22:$B$372,F$2)+SUMIFS($H$22:$H$372,$B$22:$B$372,F$2) -> 76161660589 | G4: =SUMIFS($G$22:$G$372,$B$22:$B$372,G$2)+SUMIFS($H$22:$H$372,$B$22:$B$372,G$2) -> 77621935152 | H4: =SUMIFS($G$22:$G$372,$B$22:$B$372,H$2)+SUMIFS($H$22:$H$372,$B$22:$B$372,H$2) -> 78824143867 | I4: =SUMIFS($G$22:$G$372,$B$22:$B$372,I$2)+SUMIFS($H$22:$H$372,$B$22:$B$372,I$2) -> 79954302377 | ... AE4: =SUMIFS($G$22:$G$372,$B$22:$B$372,AE$2)+SUMIFS($H$22:$H$372,$B$22:$B$372,AE$2) -> 123324758518
A5: 4 | B5: =SUMIFS($I$22:$I$372,$B$22:$B$372,B$2) -> 16520378018 | C5: =SUMIFS($I$22:$I$372,$B$22:$B$372,C$2) -> 16751666086 | D5: =SUMIFS($I$22:$I$372,$B$22:$B$372,D$2) -> 16583323470 | E5: =SUMIFS($I$22:$I$372,$B$22:$B$372,E$2) -> 16511942220 | F5: =SUMIFS($I$22:$I$372,$B$22:$B$372,F$2) -> 16557685158 | G5: =SUMIFS($I$22:$I$372,$B$22:$B$372,G$2) -> 16722257362 | H5: =SUMIFS($I$22:$I$372,$B$22:$B$372,H$2) -> 16890767928 | I5: =SUMIFS($I$22:$I$372,$B$22:$B$372,I$2) -> 17088339593 | ... AE5: =SUMIFS($I$22:$I$372,$B$22:$B$372,AE$2) -> 22481978241
A6: 5 | B6: =SUMIFS($J$22:$J$372,$B$22:$B$372,B$2) -> 21162307201 | C6: =SUMIFS($J$22:$J$372,$B$22:$B$372,C$2) -> 21781207474 | D6: =SUMIFS($J$22:$J$372,$B$22:$B$372,D$2) -> 21876699449 | E6: =SUMIFS($J$22:$J$372,$B$22:$B$372,E$2) -> 22056979412 | F6: =SUMIFS($J$22:$J$372,$B$22:$B$372,F$2) -> 22392723421 | G6: =SUMIFS($J$22:$J$372,$B$22:$B$372,G$2) -> 22851304902 | H6: =SUMIFS($J$22:$J$372,$B$22:$B$372,H$2) -> 23305101083 | I6: =SUMIFS($J$22:$J$372,$B$22:$B$372,I$2) -> 23762269052 | ... AE6: =SUMIFS($J$22:$J$372,$B$22:$B$372,AE$2) -> 34590984593
A7: 6 | B7: =SUMIFS($K$22:$K$372,$B$22:$B$372,B$2) -> 21091781567 | C7: =SUMIFS($K$22:$K$372,$B$22:$B$372,C$2) -> 21163519149 | D7: =SUMIFS($K$22:$K$372,$B$22:$B$372,D$2) -> 20772978430 | E7: =SUMIFS($K$22:$K$372,$B$22:$B$372,E$2) -> 20535995156 | F7: =SUMIFS($K$22:$K$372,$B$22:$B$372,F$2) -> 20494574836 | G7: =SUMIFS($K$22:$K$372,$B$22:$B$372,G$2) -> 20605713318 | H7: =SUMIFS($K$22:$K$372,$B$22:$B$372,H$2) -> 20747433204 | I7: =SUMIFS($K$22:$K$372,$B$22:$B$372,I$2) -> 20918246976 | ... AE7: =SUMIFS($K$22:$K$372,$B$22:$B$372,AE$2) -> 27570635908
A8: 7 rigid | B8: =SUMIFS($M$22:$M$372,$B$22:$B$372,B$2) -> 1569335340 | C8: =SUMIFS($M$22:$M$372,$B$22:$B$372,C$2) -> 1569523818 | D8: =SUMIFS($M$22:$M$372,$B$22:$B$372,D$2) -> 1537467462 | E8: =SUMIFS($M$22:$M$372,$B$22:$B$372,E$2) -> 1516936979 | F8: =SUMIFS($M$22:$M$372,$B$22:$B$372,F$2) -> 1511397950 | G8: =SUMIFS($M$22:$M$372,$B$22:$B$372,G$2) -> 1515308124 | H8: =SUMIFS($M$22:$M$372,$B$22:$B$372,H$2) -> 1517673891 | I8: =SUMIFS($M$22:$M$372,$B$22:$B$372,I$2) -> 1518660649 | ... AE8: =SUMIFS($M$22:$M$372,$B$22:$B$372,AE$2) -> 1526169152
A9: 7 tractor | B9: =SUMIFS($N$22:$N$372,$B$22:$B$372,B$2)+SUMIFS($O$22:$O$372,$B$22:$B$372,B$2)+SUMIFS($L$22:$L$372,$B$22:$B$372,B$2) -> 19938335776 | C9: =SUMIFS($N$22:$N$372,$B$22:$B$372,C$2)+SUMIFS($O$22:$O$372,$B$22:$B$372,C$2)+SUMIFS($L$22:$L$372,$B$22:$B$372,C$2) -> 19788451950 | D9: =SUMIFS($N$22:$N$372,$B$22:$B$372,D$2)+SUMIFS($O$22:$O$372,$B$22:$B$372,D$2)+SUMIFS($L$22:$L$372,$B$22:$B$372,D$2) -> 19245591105 | E9: =SUMIFS($N$22:$N$372,$B$22:$B$372,E$2)+SUMIFS($O$22:$O$372,$B$22:$B$372,E$2)+SUMIFS($L$22:$L$372,$B$22:$B$372,E$2) -> 18857702606 | F9: =SUMIFS($N$22:$N$372,$B$22:$B$372,F$2)+SUMIFS($O$22:$O$372,$B$22:$B$372,F$2)+SUMIFS($L$22:$L$372,$B$22:$B$372,F$2) -> 18670142101 | G9: =SUMIFS($N$22:$N$372,$B$22:$B$372,G$2)+SUMIFS($O$22:$O$372,$B$22:$B$372,G$2)+SUMIFS($L$22:$L$372,$B$22:$B$372,G$2) -> 18618312052 | H9: =SUMIFS($N$22:$N$372,$B$22:$B$372,H$2)+SUMIFS($O$22:$O$372,$B$22:$B$372,H$2)+SUMIFS($L$22:$L$372,$B$22:$B$372,H$2) -> 18569432995 | I9: =SUMIFS($N$22:$N$372,$B$22:$B$372,I$2)+SUMIFS($O$22:$O$372,$B$22:$B$372,I$2)+SUMIFS($L$22:$L$372,$B$22:$B$372,I$2) -> 18519975259 | ... AE9: =SUMIFS($N$22:$N$372,$B$22:$B$372,AE$2)+SUMIFS($O$22:$O$372,$B$22:$B$372,AE$2)+SUMIFS($L$22:$L$372,$B$22:$B$372,AE$2) -> 17948633464
