Workbook

Sheet About
A1: BGDPbES BAU Guaranteed Dispatch Percentage by Electricity Source | B1: North Dakota | C1: 46226 | K1: Alabama | L1: AL
A2: Active state: cell B1 (full state name). B2 resolves the abbreviation used by the calc tabs. | B2: =INDEX(L1:L48,MATCH(B1,K1:K48,0)) -> ND | K2: Arizona | L2: AZ
K3: Arkansas | L3: AR
A4: Purpose: | B4: Guarantee a portion of coal dispatch. EPS under-dispatches coal ~-27% nationally vs EIA-923 2025 (gas +3.4%) because annual-average least-cost dispatch cannot represent the non-price factors that kept the real coal fleet at ~50% CF (seasonal gas price spikes hidden by the annual average, utility self-scheduling, coal supply contracts, minimum-run and pipeline constraints). The BFPaT electricity-sector fuel prices were audited 2026-07-22 and are correct (EIA EPA 7.17/7.20 2024 anchors x CPI-U 2012$ deflator, STEO Jun-2026 2025 step of gas x1.41 / coal x0.98), so the calibration lever is guaranteed dispatch, not prices. | K4: California | L4: CA
A5: Mechanism: | B5: Guaranteed dispatch = capacity x expected hourly CF x BGDPbES, per hour (proportionally scaled back only if hourly demand is exceeded); the remaining capacity still bids into RPS and least-cost dispatch, up to the full expected CF. Because HYECFCA anchors start-year expected CFs to 2025 observed CFs, BGDPbES[coal]=X floors start-year coal generation at X x (2025 observed generation) while leaving (1-X) to economics. | K5: Colorado | L5: CO
A6: Values: | B6: hard coal + lignite and NGCC + gas steam rows take the PER-STATE tuned guarantees on the Tuned tab (2026-07-22 calibration fleet: secant search per state so 2025 coal AND gas generation land within 3% of proportional targets r x observed, r = achievable coal+gas residual; the tuned coal guarantee varies ~0.58-0.85 inversely with coal's economic share, and g_gas is usually 0 because conservation lands gas once coal is on target). Keys coal_guarantee is only a fallback for states missing a Tuned row. ALL other techs keep their current per-state values (Current_BGDPbES tab), except WA hydro = 0 (Keys hydro_zero_state): WA is at the $80 HOC cap and still over-dispatches, so its hydro guarantee is removed and hydro becomes the least-cost residual behind the tuned coal/gas floors. | K6: Connecticut | L6: CT
A7: Expected impact: | B7: At 0.90 with the current -2.8% demand anchor: national coal rises from ~531 to a >=657 TWh floor (-10% vs 923ER instead of -27%); displaced generation comes mostly out of gas (~+3.4% -> ~-4%). After the November SEDS 2025 demand re-anchor restores ~119 TWh of demand, least-cost refills gas toward actuals. | K7: Delaware | L7: DE
A8: CAVEAT - policy runs: | B8: BGDPbES applies in ALL scenarios, not just BAU. A coal floor mutes price-driven coal redispatch (e.g. carbon tax) until capacity actually retires: policy can still retire coal (guaranteed MWh fall with capacity) but cannot dispatch surviving coal below the floor. Same trade-off already accepted for nuclear (1.0), hydro (0.9), peakers (1.0) and documented for HYECFCA. Staff decision on the fraction; set Keys coal_guarantee to taste (0 restores pure least-cost). | K8: Florida | L8: FL
A9: Caveats - data: | B9: Floor quality inherits HYECFCA/SYSHECF quality: 2025 observed coal CFs include 2025-specific outages and the thin-demand year. States where coal is already economic in EPS (MO, KY, WY: coal beats gas on fuel cost) are unaffected in practice -- least-cost already dispatches above the floor there. Verify against primary sources (EIA-923/860, EPA 7.17/7.20) before adopting; draft for staff review. | K9: Georgia | L9: GA
A10: Rebuild: | B10: python outputs/BGDPbES/_build_bgdpbes_workbook.py | K10: Idaho | L10: ID
K11: Illinois | L11: IL
K12: Indiana | L12: IN
K13: Iowa | L13: IA
K14: Kansas | L14: KS
K15: Kentucky | L15: KY
K16: Louisiana | L16: LA
K17: Maine | L17: ME
K18: Maryland | L18: MD
K19: Massachusetts | L19: MA
K20: Michigan | L20: MI
K21: Minnesota | L21: MN
K22: Mississippi | L22: MS
... K48: Wyoming | L48: WY

Sheet Keys
A1: category | B1: key | C1: value | D1: description
A2: gate | B2: coal_guarantee | C2: 0.9 | D2: FALLBACK guaranteed-dispatch fraction for coal techs, used only if the active state has no row on the Tuned tab. Tuned per-state values take precedence.
A3: tech | B3: coal_tech_1 | C3: hard coal | D3: First tech row driven by the tuned coal guarantee
A4: tech | B4: coal_tech_2 | C4: lignite | D4: Second tech row driven by the tuned coal guarantee
A5: gate | B5: hydro_zero_state | C5: WA | D5: State whose hydro guarantee is removed entirely (staff 2026-07-22): WA hydro is at the $80 HOC cap and still over-dispatching, so hydro becomes the pure least-cost residual while tuned coal/gas floors reclaim their share.
A6: gate | B6: hydro_zero_value | C6: 0 | D6: Hydro guarantee applied when the active state equals hydro_zero_state

Sheet Current_BGDPbES
A1: state | B1: tech | C1: current_value | D1: key (state|tech)
A2: AL | B2: hard coal | C2: 0 | D2: AL|hard coal
A3: AL | B3: natural gas steam turbine | C3: 0 | D3: AL|natural gas steam turbine
A4: AL | B4: natural gas combined cycle | C4: 0 | D4: AL|natural gas combined cycle
A5: AL | B5: nuclear | C5: 1 | D5: AL|nuclear
A6: AL | B6: hydro | C6: 0.9 | D6: AL|hydro
A7: AL | B7: onshore wind | C7: 0 | D7: AL|onshore wind
A8: AL | B8: solar PV | C8: 0 | D8: AL|solar PV
A9: AL | B9: solar thermal | C9: 0 | D9: AL|solar thermal
A10: AL | B10: biomass | C10: 1 | D10: AL|biomass
A11: AL | B11: geothermal | C11: 1 | D11: AL|geothermal
A12: AL | B12: petroleum | C12: 1 | D12: AL|petroleum
A13: AL | B13: natural gas peaker | C13: 1 | D13: AL|natural gas peaker
... A1153: WY | B1153: hydrogen combined cycle | C1153: 1 | D1153: WY|hydrogen combined cycle

Sheet Tuned
A1: state | B1: g_coal | C1: g_gas | D1: runs | E1: coal_err_vs_target | F1: gas_err_vs_target | G1: note
A2: AL | B2: 0.6025 | C2: 0 | D2: 3 | E2: 0.0009 | F2: 0.0132 | G2: tuned
A3: AR | B3: 0.2612 | C3: 0 | D3: 3 | E3: 0.011 | F3: -0.0052 | G3: tuned
A4: AZ | B4: 0.7921 | C4: 0 | D4: 2 | E4: 0.0072 | F4: 0.0023 | G4: tuned
A5: CA | B5: 0 | C5: 0 | D5: 0 | E5: 0 | F5: 0 | G5: no coal fleet
A6: CO | B6: 0 | C6: 0 | D6: 0 | E6: 0.1111 | F6: 0.0606 | G6: coal already >= target at deployed g=0.00; unchanged
A7: CT | B7: 0 | C7: 0 | D7: 0 | E7: 0 | F7: 0.0017 | G7: no coal fleet
A8: DE | B8: 0 | C8: 0 | D8: 3 | E8: -1 | F8: 0.0714 | G8: floor zeroed: EPS carries no DE coal capacity in 2025 (BCRbQ retirement timing; 923ER shows 0.25 TWh actual) -- see capacity review group 1, not a dispatch issue
A9: FL | B9: 0.4949 | C9: 0 | D9: 3 | E9: 0.001 | F9: -0.0001 | G9: tuned
A10: GA | B10: 0.5147 | C10: 0 | D10: 3 | E10: 0.0019 | F10: 0.0016 | G10: tuned
A11: IA | B11: 0.174 | C11: 0 | D11: 3 | E11: 0.0172 | F11: 0.0678 | G11: tuned
A12: ID | B12: 0 | C12: 0 | D12: 0 | E12: 0 | F12: -0.0144 | G12: no coal fleet
A13: IL | B13: 0.4054 | C13: 0 | D13: 3 | E13: 0.0171 | F13: -0.0176 | G13: tuned
... A49: WY | B49: 0 | C49: 0.5692 | D49: 3 | E49: 0.0016 | F49: 0.0018 | G49: coal already >= target at deployed g=0.00; unchanged

Sheet BGDPbES
A1: BAU Guaranteed Dispatch (dimensionless) | B1: 2021 | C1: 2022 | D1: 2023 | E1: 2024 | F1: 2025 | G1: 2026 | H1: 2027 | I1: 2028 | J1: 2029 | K1: 2030 | L1: 2031 | M1: 2032 | N1: 2033 | O1: 2034 | P1: 2035 | Q1: 2036 | R1: 2037 | S1: 2038 | T1: 2039 | U1: 2040 | V1: 2041 | W1: 2042 | X1: 2043 | Y1: 2044 | Z1: 2045 | AA1: 2046 | AB1: 2047 | AC1: 2048 | AD1: 2049 | AE1: 2050
A2: hard coal | B2: =IFERROR(INDEX(Tuned!$B$2:$B$49,MATCH(About!$B$2,Tuned!$A$2:$A$49,0)),Keys!$C$2) -> 0.6273 | C2: =$B2 -> 0.6273 | D2: =$B2 -> 0.6273 | E2: =$B2 -> 0.6273 | F2: =$B2 -> 0.6273 | G2: =$B2 -> 0.6273 | H2: =$B2 -> 0.6273 | I2: =$B2 -> 0.6273 | J2: =$B2 -> 0.6273 | ... AE2: =$B2 -> 0.6273
A3: natural gas steam turbine | B3: =IFERROR(INDEX(Tuned!$C$2:$C$49,MATCH(About!$B$2,Tuned!$A$2:$A$49,0)),INDEX(Current_BGDPbES!$C$2:$C$1153,MATCH(About!$B$2&"|"&$A3,Current_BGDPbES!$D$2:$D$1153,0))) -> 0 | C3: =$B3 -> 0 | D3: =$B3 -> 0 | E3: =$B3 -> 0 | F3: =$B3 -> 0 | G3: =$B3 -> 0 | H3: =$B3 -> 0 | I3: =$B3 -> 0 | J3: =$B3 -> 0 | ... AE3: =$B3 -> 0
A4: natural gas combined cycle | B4: =IFERROR(INDEX(Tuned!$C$2:$C$49,MATCH(About!$B$2,Tuned!$A$2:$A$49,0)),INDEX(Current_BGDPbES!$C$2:$C$1153,MATCH(About!$B$2&"|"&$A4,Current_BGDPbES!$D$2:$D$1153,0))) -> 0 | C4: =$B4 -> 0 | D4: =$B4 -> 0 | E4: =$B4 -> 0 | F4: =$B4 -> 0 | G4: =$B4 -> 0 | H4: =$B4 -> 0 | I4: =$B4 -> 0 | J4: =$B4 -> 0 | ... AE4: =$B4 -> 0
A5: nuclear | B5: =INDEX(Current_BGDPbES!$C$2:$C$1153,MATCH(About!$B$2&"|"&$A5,Current_BGDPbES!$D$2:$D$1153,0)) -> 1 | C5: =$B5 -> 1 | D5: =$B5 -> 1 | E5: =$B5 -> 1 | F5: =$B5 -> 1 | G5: =$B5 -> 1 | H5: =$B5 -> 1 | I5: =$B5 -> 1 | J5: =$B5 -> 1 | ... AE5: =$B5 -> 1
A6: hydro | B6: =IF(About!$B$2=Keys!$C$5,Keys!$C$6,INDEX(Current_BGDPbES!$C$2:$C$1153,MATCH(About!$B$2&"|"&$A6,Current_BGDPbES!$D$2:$D$1153,0))) -> 0.9 | C6: =$B6 -> 0.9 | D6: =$B6 -> 0.9 | E6: =$B6 -> 0.9 | F6: =$B6 -> 0.9 | G6: =$B6 -> 0.9 | H6: =$B6 -> 0.9 | I6: =$B6 -> 0.9 | J6: =$B6 -> 0.9 | ... AE6: =$B6 -> 0.9
A7: onshore wind | B7: =INDEX(Current_BGDPbES!$C$2:$C$1153,MATCH(About!$B$2&"|"&$A7,Current_BGDPbES!$D$2:$D$1153,0)) -> 0 | C7: =$B7 -> 0 | D7: =$B7 -> 0 | E7: =$B7 -> 0 | F7: =$B7 -> 0 | G7: =$B7 -> 0 | H7: =$B7 -> 0 | I7: =$B7 -> 0 | J7: =$B7 -> 0 | ... AE7: =$B7 -> 0
A8: solar PV | B8: =INDEX(Current_BGDPbES!$C$2:$C$1153,MATCH(About!$B$2&"|"&$A8,Current_BGDPbES!$D$2:$D$1153,0)) -> 0 | C8: =$B8 -> 0 | D8: =$B8 -> 0 | E8: =$B8 -> 0 | F8: =$B8 -> 0 | G8: =$B8 -> 0 | H8: =$B8 -> 0 | I8: =$B8 -> 0 | J8: =$B8 -> 0 | ... AE8: =$B8 -> 0
A9: solar thermal | B9: =INDEX(Current_BGDPbES!$C$2:$C$1153,MATCH(About!$B$2&"|"&$A9,Current_BGDPbES!$D$2:$D$1153,0)) -> 0 | C9: =$B9 -> 0 | D9: =$B9 -> 0 | E9: =$B9 -> 0 | F9: =$B9 -> 0 | G9: =$B9 -> 0 | H9: =$B9 -> 0 | I9: =$B9 -> 0 | J9: =$B9 -> 0 | ... AE9: =$B9 -> 0
A10: biomass | B10: =INDEX(Current_BGDPbES!$C$2:$C$1153,MATCH(About!$B$2&"|"&$A10,Current_BGDPbES!$D$2:$D$1153,0)) -> 1 | C10: =$B10 -> 1 | D10: =$B10 -> 1 | E10: =$B10 -> 1 | F10: =$B10 -> 1 | G10: =$B10 -> 1 | H10: =$B10 -> 1 | I10: =$B10 -> 1 | J10: =$B10 -> 1 | ... AE10: =$B10 -> 1
A11: geothermal | B11: =INDEX(Current_BGDPbES!$C$2:$C$1153,MATCH(About!$B$2&"|"&$A11,Current_BGDPbES!$D$2:$D$1153,0)) -> 1 | C11: =$B11 -> 1 | D11: =$B11 -> 1 | E11: =$B11 -> 1 | F11: =$B11 -> 1 | G11: =$B11 -> 1 | H11: =$B11 -> 1 | I11: =$B11 -> 1 | J11: =$B11 -> 1 | ... AE11: =$B11 -> 1
A12: petroleum | B12: =INDEX(Current_BGDPbES!$C$2:$C$1153,MATCH(About!$B$2&"|"&$A12,Current_BGDPbES!$D$2:$D$1153,0)) -> 1 | C12: =$B12 -> 1 | D12: =$B12 -> 1 | E12: =$B12 -> 1 | F12: =$B12 -> 1 | G12: =$B12 -> 1 | H12: =$B12 -> 1 | I12: =$B12 -> 1 | J12: =$B12 -> 1 | ... AE12: =$B12 -> 1
A13: natural gas peaker | B13: =INDEX(Current_BGDPbES!$C$2:$C$1153,MATCH(About!$B$2&"|"&$A13,Current_BGDPbES!$D$2:$D$1153,0)) -> 1 | C13: =$B13 -> 1 | D13: =$B13 -> 1 | E13: =$B13 -> 1 | F13: =$B13 -> 1 | G13: =$B13 -> 1 | H13: =$B13 -> 1 | I13: =$B13 -> 1 | J13: =$B13 -> 1 | ... AE13: =$B13 -> 1
A14: lignite | B14: =IFERROR(INDEX(Tuned!$B$2:$B$49,MATCH(About!$B$2,Tuned!$A$2:$A$49,0)),Keys!$C$2) -> 0.6273 | C14: =$B14 -> 0.6273 | D14: =$B14 -> 0.6273 | E14: =$B14 -> 0.6273 | F14: =$B14 -> 0.6273 | G14: =$B14 -> 0.6273 | H14: =$B14 -> 0.6273 | I14: =$B14 -> 0.6273 | J14: =$B14 -> 0.6273 | ... AE14: =$B14 -> 0.6273
A15: offshore wind | B15: =INDEX(Current_BGDPbES!$C$2:$C$1153,MATCH(About!$B$2&"|"&$A15,Current_BGDPbES!$D$2:$D$1153,0)) -> 0 | C15: =$B15 -> 0 | D15: =$B15 -> 0 | E15: =$B15 -> 0 | F15: =$B15 -> 0 | G15: =$B15 -> 0 | H15: =$B15 -> 0 | I15: =$B15 -> 0 | J15: =$B15 -> 0 | ... AE15: =$B15 -> 0
A16: crude oil | B16: =INDEX(Current_BGDPbES!$C$2:$C$1153,MATCH(About!$B$2&"|"&$A16,Current_BGDPbES!$D$2:$D$1153,0)) -> 1 | C16: =$B16 -> 1 | D16: =$B16 -> 1 | E16: =$B16 -> 1 | F16: =$B16 -> 1 | G16: =$B16 -> 1 | H16: =$B16 -> 1 | I16: =$B16 -> 1 | J16: =$B16 -> 1 | ... AE16: =$B16 -> 1
A17: heavy or residual fuel oil | B17: =INDEX(Current_BGDPbES!$C$2:$C$1153,MATCH(About!$B$2&"|"&$A17,Current_BGDPbES!$D$2:$D$1153,0)) -> 0 | C17: =$B17 -> 0 | D17: =$B17 -> 0 | E17: =$B17 -> 0 | F17: =$B17 -> 0 | G17: =$B17 -> 0 | H17: =$B17 -> 0 | I17: =$B17 -> 0 | J17: =$B17 -> 0 | ... AE17: =$B17 -> 0
A18: municipal solid waste | B18: =INDEX(Current_BGDPbES!$C$2:$C$1153,MATCH(About!$B$2&"|"&$A18,Current_BGDPbES!$D$2:$D$1153,0)) -> 0 | C18: =$B18 -> 0 | D18: =$B18 -> 0 | E18: =$B18 -> 0 | F18: =$B18 -> 0 | G18: =$B18 -> 0 | H18: =$B18 -> 0 | I18: =$B18 -> 0 | J18: =$B18 -> 0 | ... AE18: =$B18 -> 0
A19: hard coal w CCS | B19: =INDEX(Current_BGDPbES!$C$2:$C$1153,MATCH(About!$B$2&"|"&$A19,Current_BGDPbES!$D$2:$D$1153,0)) -> 0.15 | C19: =$B19 -> 0.15 | D19: =$B19 -> 0.15 | E19: =$B19 -> 0.15 | F19: =$B19 -> 0.15 | G19: =$B19 -> 0.15 | H19: =$B19 -> 0.15 | I19: =$B19 -> 0.15 | J19: =$B19 -> 0.15 | ... AE19: =$B19 -> 0.15
A20: natural gas combined cycle w CCS | B20: =INDEX(Current_BGDPbES!$C$2:$C$1153,MATCH(About!$B$2&"|"&$A20,Current_BGDPbES!$D$2:$D$1153,0)) -> 0.15 | C20: =$B20 -> 0.15 | D20: =$B20 -> 0.15 | E20: =$B20 -> 0.15 | F20: =$B20 -> 0.15 | G20: =$B20 -> 0.15 | H20: =$B20 -> 0.15 | I20: =$B20 -> 0.15 | J20: =$B20 -> 0.15 | ... AE20: =$B20 -> 0.15
A21: biomass w CCS | B21: =INDEX(Current_BGDPbES!$C$2:$C$1153,MATCH(About!$B$2&"|"&$A21,Current_BGDPbES!$D$2:$D$1153,0)) -> 1 | C21: =$B21 -> 1 | D21: =$B21 -> 1 | E21: =$B21 -> 1 | F21: =$B21 -> 1 | G21: =$B21 -> 1 | H21: =$B21 -> 1 | I21: =$B21 -> 1 | J21: =$B21 -> 1 | ... AE21: =$B21 -> 1
A22: lignite w CCS | B22: =INDEX(Current_BGDPbES!$C$2:$C$1153,MATCH(About!$B$2&"|"&$A22,Current_BGDPbES!$D$2:$D$1153,0)) -> 1 | C22: =$B22 -> 1 | D22: =$B22 -> 1 | E22: =$B22 -> 1 | F22: =$B22 -> 1 | G22: =$B22 -> 1 | H22: =$B22 -> 1 | I22: =$B22 -> 1 | J22: =$B22 -> 1 | ... AE22: =$B22 -> 1
A23: small modular reactor | B23: =INDEX(Current_BGDPbES!$C$2:$C$1153,MATCH(About!$B$2&"|"&$A23,Current_BGDPbES!$D$2:$D$1153,0)) -> 0 | C23: =$B23 -> 0 | D23: =$B23 -> 0 | E23: =$B23 -> 0 | F23: =$B23 -> 0 | G23: =$B23 -> 0 | H23: =$B23 -> 0 | I23: =$B23 -> 0 | J23: =$B23 -> 0 | ... AE23: =$B23 -> 0
A24: hydrogen combustion turbine | B24: =INDEX(Current_BGDPbES!$C$2:$C$1153,MATCH(About!$B$2&"|"&$A24,Current_BGDPbES!$D$2:$D$1153,0)) -> 1 | C24: =$B24 -> 1 | D24: =$B24 -> 1 | E24: =$B24 -> 1 | F24: =$B24 -> 1 | G24: =$B24 -> 1 | H24: =$B24 -> 1 | I24: =$B24 -> 1 | J24: =$B24 -> 1 | ... AE24: =$B24 -> 1
A25: hydrogen combined cycle | B25: =INDEX(Current_BGDPbES!$C$2:$C$1153,MATCH(About!$B$2&"|"&$A25,Current_BGDPbES!$D$2:$D$1153,0)) -> 1 | C25: =$B25 -> 1 | D25: =$B25 -> 1 | E25: =$B25 -> 1 | F25: =$B25 -> 1 | G25: =$B25 -> 1 | H25: =$B25 -> 1 | I25: =$B25 -> 1 | J25: =$B25 -> 1 | ... AE25: =$B25 -> 1
